// 
// Decompiled by Procyon v0.5.30
// 

package z;

final class aY implements Runnable
{
    public String a;
    public String b;
    public boolean c;
    private boolean d;
    private final aT e;
    private static /* synthetic */ boolean f;
    private /* synthetic */ aT g;
    
    public aY(final aT g, final aT e) {
        this.g = g;
        this.c = false;
        this.d = false;
        this.e = e;
    }
    
    public final void a() {
        this.d = true;
    }
    
    public final void run() {
        // 
        // This method could not be decompiled.
        // 
        // Original Bytecode:
        // 
        //     0: getstatic       z/aY.f:Z
        //     3: ifne            21
        //     6: aload_0        
        //     7: getfield        z/aY.c:Z
        //    10: ifne            21
        //    13: new             Ljava/lang/AssertionError;
        //    16: dup            
        //    17: invokespecial   java/lang/AssertionError.<init>:()V
        //    20: athrow         
        //    21: aload_0        
        //    22: getfield        z/aY.g:Lz/aT;
        //    25: invokestatic    z/aT.a:(Lz/aT;)Ljavax/swing/JPanel;
        //    28: invokevirtual   javax/swing/JPanel.removeAll:()V
        //    31: aload_0        
        //    32: getfield        z/aY.g:Lz/aT;
        //    35: invokestatic    z/aT.a:(Lz/aT;)Ljavax/swing/JPanel;
        //    38: invokevirtual   javax/swing/JPanel.validate:()V
        //    41: aload_0        
        //    42: getfield        z/aY.g:Lz/aT;
        //    45: invokestatic    z/aT.a:(Lz/aT;)Ljavax/swing/JPanel;
        //    48: invokevirtual   javax/swing/JPanel.repaint:()V
        //    51: aload_0        
        //    52: getfield        z/aY.a:Ljava/lang/String;
        //    55: aload_0        
        //    56: getfield        z/aY.b:Ljava/lang/String;
        //    59: invokevirtual   java/lang/String.equals:(Ljava/lang/Object;)Z
        //    62: ifeq            79
        //    65: aload_0        
        //    66: getfield        z/aY.g:Lz/aT;
        //    69: invokestatic    z/aT.b:(Lz/aT;)Lz/f;
        //    72: invokevirtual   z/f.b:()Ljava/util/ArrayList;
        //    75: astore_1       
        //    76: goto            293
        //    79: new             Ljava/util/ArrayList;
        //    82: dup            
        //    83: invokespecial   java/util/ArrayList.<init>:()V
        //    86: astore_1       
        //    87: new             Ljava/io/File;
        //    90: dup            
        //    91: aload_0        
        //    92: getfield        z/aY.a:Ljava/lang/String;
        //    95: invokespecial   java/io/File.<init>:(Ljava/lang/String;)V
        //    98: dup            
        //    99: astore_2       
        //   100: invokevirtual   java/io/File.exists:()Z
        //   103: ifne            138
        //   106: getstatic       java/lang/System.out:Ljava/io/PrintStream;
        //   109: new             Ljava/lang/StringBuilder;
        //   112: dup            
        //   113: invokespecial   java/lang/StringBuilder.<init>:()V
        //   116: ldc             "Can't find path: "
        //   118: invokevirtual   java/lang/StringBuilder.append:(Ljava/lang/String;)Ljava/lang/StringBuilder;
        //   121: aload_0        
        //   122: getfield        z/aY.a:Ljava/lang/String;
        //   125: invokevirtual   java/lang/StringBuilder.append:(Ljava/lang/String;)Ljava/lang/StringBuilder;
        //   128: invokevirtual   java/lang/StringBuilder.toString:()Ljava/lang/String;
        //   131: invokevirtual   java/io/PrintStream.println:(Ljava/lang/String;)V
        //   134: jsr             743
        //   137: return         
        //   138: aload_2        
        //   139: invokevirtual   java/io/File.isDirectory:()Z
        //   142: ifne            177
        //   145: getstatic       java/lang/System.out:Ljava/io/PrintStream;
        //   148: new             Ljava/lang/StringBuilder;
        //   151: dup            
        //   152: invokespecial   java/lang/StringBuilder.<init>:()V
        //   155: ldc             "Not a directory: "
        //   157: invokevirtual   java/lang/StringBuilder.append:(Ljava/lang/String;)Ljava/lang/StringBuilder;
        //   160: aload_0        
        //   161: getfield        z/aY.a:Ljava/lang/String;
        //   164: invokevirtual   java/lang/StringBuilder.append:(Ljava/lang/String;)Ljava/lang/StringBuilder;
        //   167: invokevirtual   java/lang/StringBuilder.toString:()Ljava/lang/String;
        //   170: invokevirtual   java/io/PrintStream.println:(Ljava/lang/String;)V
        //   173: jsr             743
        //   176: return         
        //   177: aload_2        
        //   178: aload_0        
        //   179: getfield        z/aY.g:Lz/aT;
        //   182: invokestatic    z/aT.c:(Lz/aT;)Ljava/io/FileFilter;
        //   185: invokevirtual   java/io/File.listFiles:(Ljava/io/FileFilter;)[Ljava/io/File;
        //   188: dup            
        //   189: astore_3       
        //   190: ifnonnull       197
        //   193: jsr             743
        //   196: return         
        //   197: aload_3        
        //   198: dup            
        //   199: astore          4
        //   201: arraylength    
        //   202: istore          5
        //   204: iconst_0       
        //   205: istore          6
        //   207: iload           6
        //   209: iload           5
        //   211: if_icmpge       241
        //   214: aload           4
        //   216: iload           6
        //   218: aaload         
        //   219: dup            
        //   220: astore          7
        //   222: invokevirtual   java/io/File.isDirectory:()Z
        //   225: ifeq            235
        //   228: aload_1        
        //   229: aload           7
        //   231: invokevirtual   java/util/ArrayList.add:(Ljava/lang/Object;)Z
        //   234: pop            
        //   235: iinc            6, 1
        //   238: goto            207
        //   241: aload_3        
        //   242: dup            
        //   243: astore          4
        //   245: arraylength    
        //   246: istore          5
        //   248: iconst_0       
        //   249: istore          6
        //   251: iload           6
        //   253: iload           5
        //   255: if_icmpge       293
        //   258: aload           4
        //   260: iload           6
        //   262: aaload         
        //   263: dup            
        //   264: astore          7
        //   266: invokevirtual   java/io/File.isDirectory:()Z
        //   269: ifne            287
        //   272: aload           7
        //   274: invokevirtual   java/io/File.isHidden:()Z
        //   277: ifne            287
        //   280: aload_1        
        //   281: aload           7
        //   283: invokevirtual   java/util/ArrayList.add:(Ljava/lang/Object;)Z
        //   286: pop            
        //   287: iinc            6, 1
        //   290: goto            251
        //   293: aload_0        
        //   294: getfield        z/aY.g:Lz/aT;
        //   297: invokestatic    z/aT.d:(Lz/aT;)Lz/w;
        //   300: aload_0        
        //   301: getfield        z/aY.a:Ljava/lang/String;
        //   304: invokevirtual   z/w.j:(Ljava/lang/String;)V
        //   307: aload_1        
        //   308: invokevirtual   java/util/ArrayList.iterator:()Ljava/util/Iterator;
        //   311: astore_2       
        //   312: aload_2        
        //   313: invokeinterface java/util/Iterator.hasNext:()Z
        //   318: ifeq            719
        //   321: aload_2        
        //   322: invokeinterface java/util/Iterator.next:()Ljava/lang/Object;
        //   327: checkcast       Ljava/io/File;
        //   330: astore_3       
        //   331: iconst_0       
        //   332: istore          4
        //   334: aload_0        
        //   335: getfield        z/aY.d:Z
        //   338: ifeq            345
        //   341: jsr             743
        //   344: return         
        //   345: aload_3        
        //   346: invokevirtual   java/io/File.isDirectory:()Z
        //   349: ifne            363
        //   352: aload_3        
        //   353: invokevirtual   java/io/File.isFile:()Z
        //   356: ifne            363
        //   359: iconst_1       
        //   360: goto            364
        //   363: iconst_0       
        //   364: istore          7
        //   366: aload_3        
        //   367: invokevirtual   java/io/File.isDirectory:()Z
        //   370: ifne            378
        //   373: iload           7
        //   375: ifeq            395
        //   378: aload_0        
        //   379: getfield        z/aY.g:Lz/aT;
        //   382: invokestatic    z/aT.e:(Lz/aT;)Ljavax/swing/ImageIcon;
        //   385: astore          5
        //   387: getstatic       z/aW.a:Lz/aW;
        //   390: astore          6
        //   392: goto            484
        //   395: aload_3        
        //   396: invokevirtual   java/io/File.getPath:()Ljava/lang/String;
        //   399: invokestatic    z/au.h:(Ljava/lang/String;)Z
        //   402: ifeq            422
        //   405: aload_0        
        //   406: getfield        z/aY.g:Lz/aT;
        //   409: invokestatic    z/aT.f:(Lz/aT;)Ljavax/swing/ImageIcon;
        //   412: astore          5
        //   414: getstatic       z/aW.b:Lz/aW;
        //   417: astore          6
        //   419: goto            484
        //   422: aload_0        
        //   423: getfield        z/aY.g:Lz/aT;
        //   426: invokestatic    z/aT.d:(Lz/aT;)Lz/w;
        //   429: aload_3        
        //   430: invokevirtual   java/io/File.getPath:()Ljava/lang/String;
        //   433: invokevirtual   z/w.k:(Ljava/lang/String;)Ljavax/swing/ImageIcon;
        //   436: astore          5
        //   438: getstatic       z/aW.b:Lz/aW;
        //   441: astore          6
        //   443: aload_3        
        //   444: invokevirtual   java/io/File.length:()J
        //   447: ldc2_w          1024
        //   450: ldiv           
        //   451: dup2           
        //   452: lstore          8
        //   454: ldc2_w          2147483647
        //   457: lcmp           
        //   458: ifge            477
        //   461: lload           8
        //   463: l2i            
        //   464: aload_0        
        //   465: getfield        z/aY.g:Lz/aT;
        //   468: getfield        z/aT.a:Lcom/photochannel/easyUploader/AppletParams;
        //   471: invokevirtual   com/photochannel/easyUploader/AppletParams.b:()I
        //   474: if_icmplt       481
        //   477: iconst_1       
        //   478: goto            482
        //   481: iconst_0       
        //   482: istore          4
        //   484: aload_0        
        //   485: getfield        z/aY.g:Lz/aT;
        //   488: invokestatic    z/aT.a:(Lz/aT;)Ljavax/swing/JPanel;
        //   491: invokevirtual   javax/swing/JPanel.getComponentCount:()I
        //   494: istore          8
        //   496: new             Lz/d;
        //   499: dup            
        //   500: aload_0        
        //   501: getfield        z/aY.g:Lz/aT;
        //   504: invokestatic    z/aT.g:(Lz/aT;)Lz/bg;
        //   507: ldc             "cell"
        //   509: invokevirtual   z/bg.f:(Ljava/lang/String;)Lz/bg;
        //   512: aload_3        
        //   513: invokevirtual   java/io/File.getPath:()Ljava/lang/String;
        //   516: aload           5
        //   518: aload           6
        //   520: iload           8
        //   522: iload           4
        //   524: invokespecial   z/d.<init>:(Lz/bg;Ljava/lang/String;Ljavax/swing/ImageIcon;Lz/aW;IZ)V
        //   527: astore          9
        //   529: aload_0        
        //   530: getfield        z/aY.g:Lz/aT;
        //   533: invokestatic    z/aT.h:(Lz/aT;)Ljava/util/List;
        //   536: dup            
        //   537: astore          4
        //   539: monitorenter   
        //   540: aload_0        
        //   541: getfield        z/aY.g:Lz/aT;
        //   544: invokestatic    z/aT.h:(Lz/aT;)Ljava/util/List;
        //   547: aload_3        
        //   548: invokevirtual   java/io/File.getPath:()Ljava/lang/String;
        //   551: invokeinterface java/util/List.contains:(Ljava/lang/Object;)Z
        //   556: istore_1       
        //   557: aload           4
        //   559: monitorexit    
        //   560: goto            569
        //   563: astore_1       
        //   564: aload           4
        //   566: monitorexit    
        //   567: aload_1        
        //   568: athrow         
        //   569: iload_1        
        //   570: ifeq            579
        //   573: aload           9
        //   575: iconst_1       
        //   576: invokevirtual   z/d.a:(Z)V
        //   579: aload_0        
        //   580: getfield        z/aY.g:Lz/aT;
        //   583: invokestatic    z/aT.i:(Lz/aT;)Ljava/util/Hashtable;
        //   586: dup            
        //   587: astore_1       
        //   588: monitorenter   
        //   589: aload_0        
        //   590: getfield        z/aY.g:Lz/aT;
        //   593: invokestatic    z/aT.i:(Lz/aT;)Ljava/util/Hashtable;
        //   596: aload_3        
        //   597: invokevirtual   java/io/File.getPath:()Ljava/lang/String;
        //   600: invokevirtual   java/util/Hashtable.remove:(Ljava/lang/Object;)Ljava/lang/Object;
        //   603: checkcast       Ljava/lang/String;
        //   606: astore          4
        //   608: aload_1        
        //   609: monitorexit    
        //   610: goto            618
        //   613: astore_2       
        //   614: aload_1        
        //   615: monitorexit    
        //   616: aload_2        
        //   617: athrow         
        //   618: aload           4
        //   620: ifnonnull       639
        //   623: aload_3        
        //   624: invokevirtual   java/io/File.isDirectory:()Z
        //   627: ifne            639
        //   630: aload_3        
        //   631: invokevirtual   java/io/File.getPath:()Ljava/lang/String;
        //   634: invokestatic    z/au.a:(Ljava/lang/String;)Ljava/lang/String;
        //   637: astore          4
        //   639: aload           9
        //   641: aload           4
        //   643: invokevirtual   z/d.setToolTipText:(Ljava/lang/String;)V
        //   646: aload_0        
        //   647: getfield        z/aY.g:Lz/aT;
        //   650: invokestatic    z/aT.a:(Lz/aT;)Ljavax/swing/JPanel;
        //   653: aload           9
        //   655: invokevirtual   javax/swing/JPanel.add:(Ljava/awt/Component;)Ljava/awt/Component;
        //   658: pop            
        //   659: aload           9
        //   661: aload_0        
        //   662: getfield        z/aY.e:Lz/aT;
        //   665: invokevirtual   z/d.a:(Lz/I;)V
        //   668: aload_0        
        //   669: getfield        z/aY.g:Lz/aT;
        //   672: invokestatic    z/aT.j:(Lz/aT;)Ljava/util/Hashtable;
        //   675: ifnonnull       686
        //   678: aload_0        
        //   679: iconst_1       
        //   680: putfield        z/aY.d:Z
        //   683: goto            713
        //   686: aload_0        
        //   687: getfield        z/aY.g:Lz/aT;
        //   690: invokestatic    z/aT.j:(Lz/aT;)Ljava/util/Hashtable;
        //   693: aload_3        
        //   694: invokevirtual   java/io/File.getPath:()Ljava/lang/String;
        //   697: aload           9
        //   699: invokevirtual   java/util/Hashtable.put:(Ljava/lang/Object;Ljava/lang/Object;)Ljava/lang/Object;
        //   702: pop            
        //   703: aload_0        
        //   704: getfield        z/aY.g:Lz/aT;
        //   707: invokestatic    z/aT.a:(Lz/aT;)Ljavax/swing/JPanel;
        //   710: invokevirtual   javax/swing/JPanel.validate:()V
        //   713: invokestatic    java/lang/Thread.yield:()V
        //   716: goto            312
        //   719: jsr             743
        //   722: return         
        //   723: astore_1       
        //   724: getstatic       java/lang/System.out:Ljava/io/PrintStream;
        //   727: aload_1        
        //   728: invokevirtual   java/io/PrintStream.println:(Ljava/lang/Object;)V
        //   731: jsr             743
        //   734: return         
        //   735: astore          10
        //   737: jsr             743
        //   740: aload           10
        //   742: athrow         
        //   743: astore_1       
        //   744: aload_0        
        //   745: iconst_0       
        //   746: putfield        z/aY.c:Z
        //   749: aload_0        
        //   750: dup            
        //   751: astore_2       
        //   752: monitorenter   
        //   753: aload_0        
        //   754: invokevirtual   java/lang/Object.notify:()V
        //   757: aload_2        
        //   758: monitorexit    
        //   759: goto            767
        //   762: astore_0       
        //   763: aload_2        
        //   764: monitorexit    
        //   765: aload_0        
        //   766: athrow         
        //   767: ret             1
        //    Exceptions:
        //  Try           Handler
        //  Start  End    Start  End    Type                            
        //  -----  -----  -----  -----  --------------------------------
        //  540    560    563    569    Any
        //  563    567    563    569    Any
        //  589    610    613    618    Any
        //  613    616    613    618    Any
        //  0      137    723    735    Ljava/lang/NullPointerException;
        //  138    176    723    735    Ljava/lang/NullPointerException;
        //  177    196    723    735    Ljava/lang/NullPointerException;
        //  197    344    723    735    Ljava/lang/NullPointerException;
        //  345    719    723    735    Ljava/lang/NullPointerException;
        //  0      137    735    743    Any
        //  138    176    735    743    Any
        //  177    196    735    743    Any
        //  197    344    735    743    Any
        //  345    722    735    743    Any
        //  723    734    735    743    Any
        //  753    759    762    767    Any
        //  762    765    762    767    Any
        // 
        // The error that occurred was:
        // 
        // java.lang.NullPointerException
        //     at com.strobel.decompiler.ast.AstBuilder.convertLocalVariables(AstBuilder.java:2985)
        //     at com.strobel.decompiler.ast.AstBuilder.performStackAnalysis(AstBuilder.java:2445)
        //     at com.strobel.decompiler.ast.AstBuilder.build(AstBuilder.java:108)
        //     at com.strobel.decompiler.languages.java.ast.AstMethodBodyBuilder.createMethodBody(AstMethodBodyBuilder.java:210)
        //     at com.strobel.decompiler.languages.java.ast.AstMethodBodyBuilder.createMethodBody(AstMethodBodyBuilder.java:99)
        //     at com.strobel.decompiler.languages.java.ast.AstBuilder.createMethodBody(AstBuilder.java:757)
        //     at com.strobel.decompiler.languages.java.ast.AstBuilder.createMethod(AstBuilder.java:655)
        //     at com.strobel.decompiler.languages.java.ast.AstBuilder.addTypeMembers(AstBuilder.java:532)
        //     at com.strobel.decompiler.languages.java.ast.AstBuilder.createTypeCore(AstBuilder.java:499)
        //     at com.strobel.decompiler.languages.java.ast.AstBuilder.createTypeNoCache(AstBuilder.java:141)
        //     at com.strobel.decompiler.languages.java.ast.AstBuilder.createType(AstBuilder.java:130)
        //     at com.strobel.decompiler.languages.java.ast.AstBuilder.addType(AstBuilder.java:105)
        //     at com.strobel.decompiler.languages.java.JavaLanguage.buildAst(JavaLanguage.java:71)
        //     at com.strobel.decompiler.languages.java.JavaLanguage.decompileType(JavaLanguage.java:59)
        //     at com.strobel.decompiler.DecompilerDriver.decompileType(DecompilerDriver.java:317)
        //     at com.strobel.decompiler.DecompilerDriver.decompileJar(DecompilerDriver.java:238)
        //     at com.strobel.decompiler.DecompilerDriver.main(DecompilerDriver.java:138)
        // 
        throw new IllegalStateException("An error occurred while decompiling this method.");
    }
    
    static {
        aY.f = !aT.class.desiredAssertionStatus();
    }
}
