// 
// Decompiled by Procyon v0.5.30
// 

package a;

import java.awt.Image;
import java.awt.Canvas;

public class aD implements ba
{
    public co q;
    
    public aD() {
    }
    
    public static Canvas q(final String s, final String s2, final String s3, final co co, final int n, final int n2) {
        aA q;
        if (!aS.w.j() || s == null) {
            ((M)(q = new M(n, n2))).q(co.q(s3, false));
        }
        else {
            final Image r = co.r(s + s2 + "_button_up.gif", true);
            final Image r2 = co.r(s + s2 + "_button_dn.gif", true);
            final Image r3 = co.r(s + s2 + "_button_disabled.gif", true);
            if (r == null || r2 == null) {
                ((M)(q = new M(n, n2))).q(co.q(s3, false));
            }
            else {
                q = w.q(r, r2, r3);
            }
        }
        return (M)q;
    }
    
    public static Canvas q(final String s, final String s2, final String s3, final co co) {
        return q(s, s2, s3, co, 25, 25);
    }
    
    public aD(final co q) {
        this.q = q;
    }
    
    public void q(final cp p0) {
        // 
        // This method could not be decompiled.
        // 
        // Original Bytecode:
        // 
        //     0: aload_1        
        //     1: invokevirtual   a/cp.q:()I
        //     4: ldc             66310
        //     6: if_icmpeq       10
        //     9: return         
        //    10: aload_1        
        //    11: iconst_0       
        //    12: iconst_0       
        //    13: invokevirtual   a/cp.q:(II)I
        //    16: istore_2       
        //    17: aload_1        
        //    18: iconst_0       
        //    19: iconst_1       
        //    20: invokevirtual   a/cp.q:(II)I
        //    23: istore_3       
        //    24: aload_1        
        //    25: iconst_0       
        //    26: iconst_2       
        //    27: invokevirtual   a/cp.q:(II)I
        //    30: istore          4
        //    32: aload_1        
        //    33: iconst_0       
        //    34: iconst_3       
        //    35: invokevirtual   a/cp.q:(II)I
        //    38: istore          5
        //    40: aload_1        
        //    41: iconst_0       
        //    42: iconst_0       
        //    43: invokevirtual   a/cp.q:(II)Ljava/lang/String;
        //    46: astore_1       
        //    47: aload_0        
        //    48: getfield        a/aD.q:La/co;
        //    51: getfield        a/co.f:La/A;
        //    54: dup            
        //    55: astore          7
        //    57: monitorenter   
        //    58: aload_0        
        //    59: getfield        a/aD.q:La/co;
        //    62: getfield        a/co.f:La/A;
        //    65: iload_2        
        //    66: invokevirtual   a/A.w:(I)Ljava/lang/Object;
        //    69: checkcast       La/aO;
        //    72: astore          6
        //    74: aload           7
        //    76: monitorexit    
        //    77: goto            86
        //    80: astore_3       
        //    81: aload           7
        //    83: monitorexit    
        //    84: aload_3        
        //    85: athrow         
        //    86: iload_3        
        //    87: tableswitch {
        //                0: 306
        //                1: 409
        //                2: 423
        //                3: 197
        //                4: 124
        //                5: 437
        //          default: 459
        //        }
        //   124: new             La/aO;
        //   127: dup            
        //   128: aload_0        
        //   129: getfield        a/aD.q:La/co;
        //   132: checkcast       La/W;
        //   135: aload_0        
        //   136: getfield        a/aD.q:La/co;
        //   139: dup            
        //   140: astore_1       
        //   141: getfield        a/aJ.s:I
        //   144: new             La/bY;
        //   147: dup            
        //   148: aload_0        
        //   149: getfield        a/aD.q:La/co;
        //   152: iconst_0       
        //   153: invokespecial   a/bY.<init>:(La/co;Z)V
        //   156: iload_2        
        //   157: invokespecial   a/aO.<init>:(La/W;ILa/aF;I)V
        //   160: astore          7
        //   162: aload_0        
        //   163: getfield        a/aD.q:La/co;
        //   166: getfield        a/co.f:La/A;
        //   169: dup            
        //   170: astore_3       
        //   171: monitorenter   
        //   172: aload_0        
        //   173: getfield        a/aD.q:La/co;
        //   176: getfield        a/co.f:La/A;
        //   179: aload           7
        //   181: invokevirtual   a/A.q:(La/bV;)I
        //   184: pop            
        //   185: aload_3        
        //   186: monitorexit    
        //   187: goto            459
        //   190: astore          7
        //   192: aload_3        
        //   193: monitorexit    
        //   194: aload           7
        //   196: athrow         
        //   197: aload_0        
        //   198: getfield        a/aD.q:La/co;
        //   201: getfield        a/co.e:La/A;
        //   204: iload           4
        //   206: invokevirtual   a/A.w:(I)Ljava/lang/Object;
        //   209: checkcast       La/l;
        //   212: dup            
        //   213: astore_3       
        //   214: ifnonnull       233
        //   217: aload_0        
        //   218: getfield        a/aD.q:La/co;
        //   221: getfield        a/co.r:La/A;
        //   224: iload           4
        //   226: invokevirtual   a/A.w:(I)Ljava/lang/Object;
        //   229: checkcast       La/l;
        //   232: astore_3       
        //   233: aload_3        
        //   234: getfield        a/l.e:I
        //   237: istore          7
        //   239: aload_0        
        //   240: getfield        a/aD.q:La/co;
        //   243: getfield        a/co.w:La/A;
        //   246: iload           7
        //   248: invokevirtual   a/A.w:(I)Ljava/lang/Object;
        //   251: checkcast       La/av;
        //   254: astore          5
        //   256: new             La/r;
        //   259: dup            
        //   260: aload_0        
        //   261: getfield        a/aD.q:La/co;
        //   264: aload_1        
        //   265: invokevirtual   a/co.w:(Ljava/lang/String;)Ljava/lang/String;
        //   268: aload_3        
        //   269: iconst_0       
        //   270: iconst_1       
        //   271: aload           5
        //   273: aload_0        
        //   274: getfield        a/aD.q:La/co;
        //   277: invokespecial   a/r.<init>:(Ljava/lang/String;La/l;ZZLa/av;La/bp;)V
        //   280: dup            
        //   281: astore_1       
        //   282: iload_2        
        //   283: putfield        a/r.d:I
        //   286: aload_1        
        //   287: iload           4
        //   289: putfield        a/r.f:I
        //   292: aload_0        
        //   293: getfield        a/aD.q:La/co;
        //   296: getfield        a/co.q:La/am;
        //   299: aload_1        
        //   300: invokeinterface a/am.q:(La/r;)V
        //   305: return         
        //   306: aload           6
        //   308: ifnonnull       312
        //   311: return         
        //   312: aload_0        
        //   313: getfield        a/aD.q:La/co;
        //   316: getfield        a/co.e:La/A;
        //   319: iload           4
        //   321: invokevirtual   a/A.w:(I)Ljava/lang/Object;
        //   324: checkcast       La/l;
        //   327: dup            
        //   328: astore_3       
        //   329: ifnonnull       348
        //   332: aload_0        
        //   333: getfield        a/aD.q:La/co;
        //   336: getfield        a/co.r:La/A;
        //   339: iload           4
        //   341: invokevirtual   a/A.w:(I)Ljava/lang/Object;
        //   344: checkcast       La/l;
        //   347: astore_3       
        //   348: aload_3        
        //   349: getfield        a/l.e:I
        //   352: istore          7
        //   354: aload_3        
        //   355: iload           5
        //   357: invokevirtual   a/l.i:(I)V
        //   360: aload_0        
        //   361: getfield        a/aD.q:La/co;
        //   364: getfield        a/co.w:La/A;
        //   367: iload           7
        //   369: invokevirtual   a/A.w:(I)Ljava/lang/Object;
        //   372: checkcast       La/av;
        //   375: astore          5
        //   377: new             La/r;
        //   380: dup            
        //   381: aload_0        
        //   382: getfield        a/aD.q:La/co;
        //   385: aload_1        
        //   386: invokevirtual   a/co.w:(Ljava/lang/String;)Ljava/lang/String;
        //   389: aload_3        
        //   390: iconst_0       
        //   391: iconst_1       
        //   392: aload           5
        //   394: aload_0        
        //   395: getfield        a/aD.q:La/co;
        //   398: invokespecial   a/r.<init>:(Ljava/lang/String;La/l;ZZLa/av;La/bp;)V
        //   401: astore_1       
        //   402: aload           6
        //   404: aload_1        
        //   405: invokevirtual   a/aO.q:(La/r;)V
        //   408: return         
        //   409: aload           6
        //   411: ifnonnull       415
        //   414: return         
        //   415: aload           6
        //   417: iload           4
        //   419: invokevirtual   a/aO.q:(I)V
        //   422: return         
        //   423: aload           6
        //   425: ifnonnull       429
        //   428: return         
        //   429: aload           6
        //   431: iload           4
        //   433: invokevirtual   a/aO.w:(I)V
        //   436: return         
        //   437: aload           6
        //   439: ifnonnull       443
        //   442: return         
        //   443: aload           6
        //   445: dup            
        //   446: astore_1       
        //   447: getfield        a/aO.q:Z
        //   450: ifeq            454
        //   453: return         
        //   454: aload           6
        //   456: invokevirtual   a/aO.dispose:()V
        //   459: return         
        //    Exceptions:
        //  Try           Handler
        //  Start  End    Start  End    Type
        //  -----  -----  -----  -----  ----
        //  58     77     80     86     Any
        //  80     84     80     86     Any
        //  172    187    190    197    Any
        //  190    194    190    197    Any
        // 
        // The error that occurred was:
        // 
        // java.lang.NullPointerException
        //     at com.strobel.decompiler.ast.AstBuilder.convertLocalVariables(AstBuilder.java:2985)
        //     at com.strobel.decompiler.ast.AstBuilder.performStackAnalysis(AstBuilder.java:2445)
        //     at com.strobel.decompiler.ast.AstBuilder.build(AstBuilder.java:108)
        //     at com.strobel.decompiler.languages.java.ast.AstMethodBodyBuilder.createMethodBody(AstMethodBodyBuilder.java:210)
        //     at com.strobel.decompiler.languages.java.ast.AstMethodBodyBuilder.createMethodBody(AstMethodBodyBuilder.java:99)
        //     at com.strobel.decompiler.languages.java.ast.AstBuilder.createMethodBody(AstBuilder.java:757)
        //     at com.strobel.decompiler.languages.java.ast.AstBuilder.createMethod(AstBuilder.java:655)
        //     at com.strobel.decompiler.languages.java.ast.AstBuilder.addTypeMembers(AstBuilder.java:532)
        //     at com.strobel.decompiler.languages.java.ast.AstBuilder.createTypeCore(AstBuilder.java:499)
        //     at com.strobel.decompiler.languages.java.ast.AstBuilder.createTypeNoCache(AstBuilder.java:141)
        //     at com.strobel.decompiler.languages.java.ast.AstBuilder.createType(AstBuilder.java:130)
        //     at com.strobel.decompiler.languages.java.ast.AstBuilder.addType(AstBuilder.java:105)
        //     at com.strobel.decompiler.languages.java.JavaLanguage.buildAst(JavaLanguage.java:71)
        //     at com.strobel.decompiler.languages.java.JavaLanguage.decompileType(JavaLanguage.java:59)
        //     at com.strobel.decompiler.DecompilerDriver.decompileType(DecompilerDriver.java:317)
        //     at com.strobel.decompiler.DecompilerDriver.decompileJar(DecompilerDriver.java:238)
        //     at com.strobel.decompiler.DecompilerDriver.main(DecompilerDriver.java:138)
        // 
        throw new IllegalStateException("An error occurred while decompiling this method.");
    }
}
