// 
// Decompiled by Procyon v0.5.30
// 

package a;

import java.awt.Image;
import java.awt.Canvas;

public class cc implements cd
{
    private bH q;
    
    public cc(final bH q) {
        this.q = q;
    }
    
    public final void x(final cJ p0) {
        // 
        // This method could not be decompiled.
        // 
        // Original Bytecode:
        // 
        //     0: aload_1        
        //     1: invokevirtual   a/cJ.q:()I
        //     4: ldc             66310
        //     6: if_icmpeq       10
        //     9: return         
        //    10: aload_1        
        //    11: iconst_0       
        //    12: iconst_0       
        //    13: invokevirtual   a/cJ.q:(II)I
        //    16: istore_2       
        //    17: aload_1        
        //    18: iconst_0       
        //    19: iconst_1       
        //    20: invokevirtual   a/cJ.q:(II)I
        //    23: istore_3       
        //    24: aload_1        
        //    25: iconst_0       
        //    26: iconst_2       
        //    27: invokevirtual   a/cJ.q:(II)I
        //    30: istore          4
        //    32: aload_1        
        //    33: iconst_0       
        //    34: iconst_3       
        //    35: invokevirtual   a/cJ.q:(II)I
        //    38: istore          5
        //    40: aload_1        
        //    41: iconst_0       
        //    42: iconst_0       
        //    43: invokevirtual   a/cJ.q:(II)Ljava/lang/String;
        //    46: astore_1       
        //    47: aload_0        
        //    48: getfield        a/cc.q:La/bH;
        //    51: getfield        a/bH.f:La/cq;
        //    54: dup            
        //    55: astore          7
        //    57: monitorenter   
        //    58: aload_0        
        //    59: getfield        a/cc.q:La/bH;
        //    62: getfield        a/bH.f:La/cq;
        //    65: iload_2        
        //    66: invokevirtual   a/cq.w:(I)Ljava/lang/Object;
        //    69: checkcast       La/J;
        //    72: astore          6
        //    74: aload           7
        //    76: monitorexit    
        //    77: goto            86
        //    80: astore_3       
        //    81: aload           7
        //    83: monitorexit    
        //    84: aload_3        
        //    85: athrow         
        //    86: iload_3        
        //    87: tableswitch {
        //                0: 304
        //                1: 417
        //                2: 431
        //                3: 195
        //                4: 124
        //                5: 445
        //          default: 465
        //        }
        //   124: new             La/J;
        //   127: dup            
        //   128: aload_0        
        //   129: getfield        a/cc.q:La/bH;
        //   132: checkcast       La/bI;
        //   135: aload_0        
        //   136: getfield        a/cc.q:La/bH;
        //   139: invokevirtual   a/bH.q:()I
        //   142: new             La/bv;
        //   145: dup            
        //   146: aload_0        
        //   147: getfield        a/cc.q:La/bH;
        //   150: iconst_0       
        //   151: invokespecial   a/bv.<init>:(La/bH;Z)V
        //   154: iload_2        
        //   155: invokespecial   a/J.<init>:(La/bI;ILa/bC;I)V
        //   158: astore          7
        //   160: aload_0        
        //   161: getfield        a/cc.q:La/bH;
        //   164: getfield        a/bH.f:La/cq;
        //   167: dup            
        //   168: astore_3       
        //   169: monitorenter   
        //   170: aload_0        
        //   171: getfield        a/cc.q:La/bH;
        //   174: getfield        a/bH.f:La/cq;
        //   177: aload           7
        //   179: invokevirtual   a/cq.q:(La/cG;)I
        //   182: pop            
        //   183: aload_3        
        //   184: monitorexit    
        //   185: goto            465
        //   188: astore          7
        //   190: aload_3        
        //   191: monitorexit    
        //   192: aload           7
        //   194: athrow         
        //   195: aload_0        
        //   196: getfield        a/cc.q:La/bH;
        //   199: getfield        a/bH.e:La/cq;
        //   202: iload           4
        //   204: invokevirtual   a/cq.w:(I)Ljava/lang/Object;
        //   207: checkcast       La/bp;
        //   210: dup            
        //   211: astore_3       
        //   212: ifnonnull       231
        //   215: aload_0        
        //   216: getfield        a/cc.q:La/bH;
        //   219: getfield        a/bH.r:La/cq;
        //   222: iload           4
        //   224: invokevirtual   a/cq.w:(I)Ljava/lang/Object;
        //   227: checkcast       La/bp;
        //   230: astore_3       
        //   231: aload_3        
        //   232: getfield        a/bp.u:I
        //   235: istore          7
        //   237: aload_0        
        //   238: getfield        a/cc.q:La/bH;
        //   241: getfield        a/bH.w:La/cq;
        //   244: iload           7
        //   246: invokevirtual   a/cq.w:(I)Ljava/lang/Object;
        //   249: checkcast       La/bj;
        //   252: astore          7
        //   254: new             La/bF;
        //   257: dup            
        //   258: aload_0        
        //   259: getfield        a/cc.q:La/bH;
        //   262: aload_1        
        //   263: invokevirtual   a/bH.w:(Ljava/lang/String;)Ljava/lang/String;
        //   266: aload_3        
        //   267: iconst_0       
        //   268: iconst_1       
        //   269: aload           7
        //   271: aload_0        
        //   272: getfield        a/cc.q:La/bH;
        //   275: invokespecial   a/bF.<init>:(Ljava/lang/String;La/bp;ZZLa/bj;La/bz;)V
        //   278: dup            
        //   279: astore_1       
        //   280: iload_2        
        //   281: putfield        a/bF.d:I
        //   284: aload_1        
        //   285: iload           4
        //   287: putfield        a/bF.f:I
        //   290: aload_0        
        //   291: getfield        a/cc.q:La/bH;
        //   294: getfield        a/bH.q:La/ce;
        //   297: aload_1        
        //   298: invokeinterface a/ce.q:(La/bF;)V
        //   303: return         
        //   304: aload           6
        //   306: ifnonnull       310
        //   309: return         
        //   310: aload_0        
        //   311: getfield        a/cc.q:La/bH;
        //   314: getfield        a/bH.e:La/cq;
        //   317: iload           4
        //   319: invokevirtual   a/cq.w:(I)Ljava/lang/Object;
        //   322: checkcast       La/bp;
        //   325: dup            
        //   326: astore_3       
        //   327: ifnonnull       346
        //   330: aload_0        
        //   331: getfield        a/cc.q:La/bH;
        //   334: getfield        a/bH.r:La/cq;
        //   337: iload           4
        //   339: invokevirtual   a/cq.w:(I)Ljava/lang/Object;
        //   342: checkcast       La/bp;
        //   345: astore_3       
        //   346: aload_3        
        //   347: getfield        a/bp.u:I
        //   350: istore          7
        //   352: aload_3        
        //   353: iload           5
        //   355: invokevirtual   a/bp.b_:(I)V
        //   358: aload_0        
        //   359: getfield        a/cc.q:La/bH;
        //   362: getfield        a/bH.w:La/cq;
        //   365: iload           7
        //   367: invokevirtual   a/cq.w:(I)Ljava/lang/Object;
        //   370: checkcast       La/bj;
        //   373: astore          7
        //   375: new             La/bF;
        //   378: dup            
        //   379: aload_0        
        //   380: getfield        a/cc.q:La/bH;
        //   383: aload_1        
        //   384: invokevirtual   a/bH.w:(Ljava/lang/String;)Ljava/lang/String;
        //   387: aload_3        
        //   388: iconst_0       
        //   389: iconst_1       
        //   390: aload           7
        //   392: aload_0        
        //   393: getfield        a/cc.q:La/bH;
        //   396: invokespecial   a/bF.<init>:(Ljava/lang/String;La/bp;ZZLa/bj;La/bz;)V
        //   399: dup            
        //   400: astore_1       
        //   401: iload           5
        //   403: istore_3       
        //   404: dup            
        //   405: astore_2       
        //   406: iload_3        
        //   407: putfield        a/bF.o:I
        //   410: aload           6
        //   412: aload_1        
        //   413: invokevirtual   a/J.q:(La/bF;)V
        //   416: return         
        //   417: aload           6
        //   419: ifnonnull       423
        //   422: return         
        //   423: aload           6
        //   425: iload           4
        //   427: invokevirtual   a/J.q:(I)V
        //   430: return         
        //   431: aload           6
        //   433: ifnonnull       437
        //   436: return         
        //   437: aload           6
        //   439: iload           4
        //   441: invokevirtual   a/J.w:(I)V
        //   444: return         
        //   445: aload           6
        //   447: ifnonnull       451
        //   450: return         
        //   451: aload           6
        //   453: invokevirtual   a/J.q:()Z
        //   456: ifeq            460
        //   459: return         
        //   460: aload           6
        //   462: invokevirtual   a/J.dispose:()V
        //   465: return         
        //    Exceptions:
        //  Try           Handler
        //  Start  End    Start  End    Type
        //  -----  -----  -----  -----  ----
        //  58     77     80     86     Any
        //  170    185    188    195    Any
        // 
        // The error that occurred was:
        // 
        // java.lang.NullPointerException
        //     at com.strobel.decompiler.ast.AstBuilder.convertLocalVariables(AstBuilder.java:2985)
        //     at com.strobel.decompiler.ast.AstBuilder.performStackAnalysis(AstBuilder.java:2445)
        //     at com.strobel.decompiler.ast.AstBuilder.build(AstBuilder.java:108)
        //     at com.strobel.decompiler.languages.java.ast.AstMethodBodyBuilder.createMethodBody(AstMethodBodyBuilder.java:210)
        //     at com.strobel.decompiler.languages.java.ast.AstMethodBodyBuilder.createMethodBody(AstMethodBodyBuilder.java:99)
        //     at com.strobel.decompiler.languages.java.ast.AstBuilder.createMethodBody(AstBuilder.java:757)
        //     at com.strobel.decompiler.languages.java.ast.AstBuilder.createMethod(AstBuilder.java:655)
        //     at com.strobel.decompiler.languages.java.ast.AstBuilder.addTypeMembers(AstBuilder.java:532)
        //     at com.strobel.decompiler.languages.java.ast.AstBuilder.createTypeCore(AstBuilder.java:499)
        //     at com.strobel.decompiler.languages.java.ast.AstBuilder.createTypeNoCache(AstBuilder.java:141)
        //     at com.strobel.decompiler.languages.java.ast.AstBuilder.createType(AstBuilder.java:130)
        //     at com.strobel.decompiler.languages.java.ast.AstBuilder.addType(AstBuilder.java:105)
        //     at com.strobel.decompiler.languages.java.JavaLanguage.buildAst(JavaLanguage.java:71)
        //     at com.strobel.decompiler.languages.java.JavaLanguage.decompileType(JavaLanguage.java:59)
        //     at com.strobel.decompiler.DecompilerDriver.decompileType(DecompilerDriver.java:317)
        //     at com.strobel.decompiler.DecompilerDriver.decompileJar(DecompilerDriver.java:238)
        //     at com.strobel.decompiler.DecompilerDriver.main(DecompilerDriver.java:138)
        // 
        throw new IllegalStateException("An error occurred while decompiling this method.");
    }
    
    public cc() {
    }
    
    public static Canvas q(final String s, final String s2, final String s3, final bH bh, final int n, final int n2) {
        cn q;
        if (!be.w.h() || s == null) {
            ((e)(q = new e(n, n2))).q(bh.w(s3, false));
        }
        else {
            final Image q2 = bh.q(s + s2 + "_button_up.gif", true);
            final Image q3 = bh.q(s + s2 + "_button_dn.gif", true);
            final Image q4 = bh.q(s + s2 + "_button_disabled.gif", true);
            if (q2 == null || q3 == null) {
                ((e)(q = new e(n, n2))).q(bh.w(s3, false));
            }
            else {
                q = n.q(q2, q3, q4);
            }
        }
        return (e)q;
    }
    
    public static Canvas q(final String s, final String s2, final String s3, final bH bh) {
        return q(s, s2, s3, bh, 25, 25);
    }
}
