// 
// Decompiled by Procyon v0.5.30
// 

package ruby.jit;

import org.jruby.Ruby;
import org.jruby.RubyInstanceConfig;
import org.jruby.runtime.Arity;
import org.jruby.javasupport.util.RuntimeHelpers;
import org.jruby.anno.JRubyMethod;
import org.jruby.runtime.Block;
import org.jruby.runtime.builtin.IRubyObject;
import org.jruby.ast.executable.RuntimeCache;
import org.jruby.runtime.ThreadContext;
import org.jruby.ast.executable.AbstractScript;

public class FILE_DD0CDC2E771D8F64111D2A35BD604FE29D54BBC7 extends AbstractScript
{
    public FILE_DD0CDC2E771D8F64111D2A35BD604FE29D54BBC7() {
        this.filename = "./lib//lister/measurements/wlan_scan.rb";
        super.runtimeCache = new RuntimeCache();
        this.initFromDescriptor("require\uffffF\uffffversion\uffffF\uffffold_versions\uffffF\uffffdescribe\uffffF\uffffdescribe\uffffF\uffffdescribe\uffffF\uffffdescribe\uffffF\uffffreport\uffffF\uffffdescribe\uffffF\uffffdescribe\uffffF\uffffreport\uffffF\uffffdescribe\uffffF\uffffdescribe\uffffF\uffffreport\uffffF\uffffdescribe\uffffF\uffffdescribe\uffffF\uffffreport\uffffF\uffffdescribe\uffffF\uffffdescribe\uffffF\uffffreport\uffffF\uffffdescribe\uffffF\uffffdescribe\uffffF\uffffreport\uffffF\uffffdescribe\uffffF\uffffdescribe\uffffF\uffffreport\uffffF\uffffdescribe\uffffF\uffffdescribe\uffffF\uffffreport\uffffF\uffffdescribe\uffffF\uffffdescribe\uffffF\uffff\u0003\b\u0000\u0000\u0001\u0000\u0000\u0000\u0000\b\u0000\u0000\u001e\u0001");
        this.setEncoding(0, "ASCII-8BIT");
        this.setByteList(16, "The number of APs (unique bssids) in the neighbouring", this.getEncoding0());
        this.setByteList(28, "The command leading to the WiFi scan, or 'library' or 'legacy' on Windows with/without a WiFi library", this.getEncoding0());
        this.setByteList(2, "dev", this.getEncoding0());
        this.setByteList(0, "lister/measurement", this.getEncoding0());
        this.setByteList(22, "The channels of the WiFi APs", this.getEncoding0());
        this.setByteList(27, "Le SHA1 de l'ESSID du r\uffc3\uffa9seau WiFi activ\uffc3\uffa9 (si applicable)", this.getEncoding0());
        this.setByteList(7, "Number of neighboring WiFi networks", this.getEncoding0());
        this.setByteList(8, "Nombre de r\uffc3\uffa9seaux WiFi dans le voisinage", this.getEncoding0());
        this.setByteList(25, "La liste des r\uffc3\uffa9seaux avec le SHA1 de leur ESSID", this.getEncoding0());
        this.setByteList(10, "<p>This module counts the visible WiFi networks. A large number\nof neighbouring WiFi may explain poor wireless performance.  We anonymize the\nnames of WiFi networks before collection.\n      </p>", this.getEncoding0());
        this.setByteList(18, "The number of APs (unique essids) in the neighbouring", this.getEncoding0());
        this.setByteList(17, "Le nombre de BSSIDs uniques alentours", this.getEncoding0());
        this.setByteList(14, "The number of APs (unique (essids;bssid)) in the neighbouring", this.getEncoding0());
        this.setByteList(1, "0.1.1", this.getEncoding0());
        this.setByteList(21, "La puissance des signaux WiFi re\uffc3\uffa7us", this.getEncoding0());
        this.setByteList(6, "0.1.0", this.getEncoding0());
        this.setByteList(15, "Le nombre de points d'acc\uffc3\uffa8s alentours", this.getEncoding0());
        this.setByteList(12, "<p>Ce module scanne les WiFi dans le voisinage. S'il y a beaucoup de\npoints d'acc\uffc3\uffa8s WiFi en concurrence, cela pourrait expliquer des probl\uffc3\uffa8mes de\nperformance. Nous ne gardons pas les noms des r\uffc3\uffa9seaux WiFi, mais seulement un\nidentifiant anonyme.\n      </p>", this.getEncoding0());
        this.setByteList(11, "English-HTML", this.getEncoding0());
        this.setByteList(19, "Le nombre d'ESSIDs uniques alentours", this.getEncoding0());
        this.setByteList(29, "La commande donnant le scan WiFi, ou 'library' ou 'legacy' pour Windows avec/sans biblioth\uffc3\uffa8que WiFi", this.getEncoding0());
        this.setByteList(9, "Fran\uffc3\uffa7ais", this.getEncoding0());
        this.setByteList(26, "Current ESSID's SHA1 (if there is a current one)", this.getEncoding0());
        this.setByteList(3, "0.0.1", this.getEncoding0());
        this.setByteList(24, "The list of networks with their ESSID's SHA1", this.getEncoding0());
        this.setByteList(5, "0.0.3", this.getEncoding0());
        this.setByteList(4, "0.0.2", this.getEncoding0());
        this.setByteList(20, "The received signal strength", this.getEncoding0());
        this.setByteList(23, "Les canaux des r\uffc3\uffa9seaux WiFi alentours", this.getEncoding0());
        this.setByteList(13, "Fran\uffc3\uffa7ais-HTML", this.getEncoding0());
    }
    
    @JRubyMethod(name = "__file__", frame = true, required = 0, optional = 0, rest = -2)
    public static IRubyObject __file__(final FILE_DD0CDC2E771D8F64111D2A35BD604FE29D54BBC7 file_DD0CDC2E771D8F64111D2A35BD604FE29D54BBC7, final ThreadContext threadContext, final IRubyObject rubyObject, final IRubyObject[] array, final Block block) {
        file_DD0CDC2E771D8F64111D2A35BD604FE29D54BBC7.getCallSite0().call(threadContext, rubyObject, rubyObject, file_DD0CDC2E771D8F64111D2A35BD604FE29D54BBC7.getString0(threadContext.runtime, 32));
        return module__0$RUBY$Lister(file_DD0CDC2E771D8F64111D2A35BD604FE29D54BBC7, threadContext, rubyObject, IRubyObject.NULL_ARRAY, Block.NULL_BLOCK);
    }
    
    @Override
    public IRubyObject __file__(final ThreadContext threadContext, final IRubyObject rubyObject, final IRubyObject[] array, final Block block) {
        return __file__(this, threadContext, rubyObject, array, block);
    }
    
    public static IRubyObject module__0$RUBY$Lister(final FILE_DD0CDC2E771D8F64111D2A35BD604FE29D54BBC7 p0, final ThreadContext p1, final IRubyObject p2, final Block p3) {
        // 
        // This method could not be decompiled.
        // 
        // Original Bytecode:
        // 
        //     0: aload_1        
        //     1: aload_1        
        //     2: getfield        org/jruby/runtime/ThreadContext.nil:Lorg/jruby/runtime/builtin/IRubyObject;
        //     5: invokestatic    org/jruby/javasupport/util/RuntimeHelpers.prepareClassNamespace:(Lorg/jruby/runtime/ThreadContext;Lorg/jruby/runtime/builtin/IRubyObject;)Lorg/jruby/RubyModule;
        //     8: ldc             "Lister"
        //    10: invokevirtual   org/jruby/RubyModule.defineOrGetModuleUnder:(Ljava/lang/String;)Lorg/jruby/RubyModule;
        //    13: dup            
        //    14: astore_2       
        //    15: aload_1        
        //    16: swap           
        //    17: aload_0        
        //    18: aload_1        
        //    19: ldc             ",0,0,-1"
        //    21: invokevirtual   ruby/jit/FILE_DD0CDC2E771D8F64111D2A35BD604FE29D54BBC7.getScope0:(Lorg/jruby/runtime/ThreadContext;Ljava/lang/String;)Lorg/jruby/parser/StaticScope;
        //    24: invokevirtual   org/jruby/runtime/ThreadContext.preCompiledClassDummyScope:(Lorg/jruby/RubyModule;Lorg/jruby/parser/StaticScope;)V
        //    27: aload_0        
        //    28: aload_1        
        //    29: aload_2        
        //    30: getstatic       org/jruby/runtime/builtin/IRubyObject.NULL_ARRAY:[Lorg/jruby/runtime/builtin/IRubyObject;
        //    33: getstatic       org/jruby/runtime/Block.NULL_BLOCK:Lorg/jruby/runtime/Block;
        //    36: invokestatic    ruby/jit/FILE_DD0CDC2E771D8F64111D2A35BD604FE29D54BBC7.module__1$RUBY$Measurements:(Lruby/jit/FILE_DD0CDC2E771D8F64111D2A35BD604FE29D54BBC7;Lorg/jruby/runtime/ThreadContext;Lorg/jruby/runtime/builtin/IRubyObject;[Lorg/jruby/runtime/builtin/IRubyObject;Lorg/jruby/runtime/Block;)Lorg/jruby/runtime/builtin/IRubyObject;
        //    39: aload_1        
        //    40: getfield        org/jruby/runtime/ThreadContext.nil:Lorg/jruby/runtime/builtin/IRubyObject;
        //    43: goto            51
        //    46: aload_1        
        //    47: invokevirtual   org/jruby/runtime/ThreadContext.postCompiledClass:()V
        //    50: athrow         
        //    51: aload_1        
        //    52: invokevirtual   org/jruby/runtime/ThreadContext.postCompiledClass:()V
        //    55: areturn        
        //    Exceptions:
        //  Try           Handler
        //  Start  End    Start  End    Type
        //  -----  -----  -----  -----  ----
        //  27     43     46     51     Any
        // 
        // The error that occurred was:
        // 
        // java.lang.ArrayIndexOutOfBoundsException
        // 
        throw new IllegalStateException("An error occurred while decompiling this method.");
    }
    
    public static IRubyObject module__1$RUBY$Measurements(final FILE_DD0CDC2E771D8F64111D2A35BD604FE29D54BBC7 p0, final ThreadContext p1, final IRubyObject p2, final Block p3) {
        // 
        // This method could not be decompiled.
        // 
        // Original Bytecode:
        // 
        //     0: aload_1        
        //     1: aload_1        
        //     2: getfield        org/jruby/runtime/ThreadContext.nil:Lorg/jruby/runtime/builtin/IRubyObject;
        //     5: invokestatic    org/jruby/javasupport/util/RuntimeHelpers.prepareClassNamespace:(Lorg/jruby/runtime/ThreadContext;Lorg/jruby/runtime/builtin/IRubyObject;)Lorg/jruby/RubyModule;
        //     8: ldc             "Measurements"
        //    10: invokevirtual   org/jruby/RubyModule.defineOrGetModuleUnder:(Ljava/lang/String;)Lorg/jruby/RubyModule;
        //    13: dup            
        //    14: astore_2       
        //    15: aload_1        
        //    16: swap           
        //    17: aload_0        
        //    18: aload_1        
        //    19: ldc             ",0,0,-1"
        //    21: invokevirtual   ruby/jit/FILE_DD0CDC2E771D8F64111D2A35BD604FE29D54BBC7.getScope1:(Lorg/jruby/runtime/ThreadContext;Ljava/lang/String;)Lorg/jruby/parser/StaticScope;
        //    24: invokevirtual   org/jruby/runtime/ThreadContext.preCompiledClassDummyScope:(Lorg/jruby/RubyModule;Lorg/jruby/parser/StaticScope;)V
        //    27: aload_0        
        //    28: aload_1        
        //    29: aload_0        
        //    30: aload_1        
        //    31: ldc_w           "Measurement"
        //    34: invokevirtual   ruby/jit/FILE_DD0CDC2E771D8F64111D2A35BD604FE29D54BBC7.getConstant0:(Lorg/jruby/runtime/ThreadContext;Ljava/lang/String;)Lorg/jruby/runtime/builtin/IRubyObject;
        //    37: getstatic       org/jruby/runtime/Block.NULL_BLOCK:Lorg/jruby/runtime/Block;
        //    40: invokestatic    ruby/jit/FILE_DD0CDC2E771D8F64111D2A35BD604FE29D54BBC7.class_2$RUBY$WlanScan:(Lruby/jit/FILE_DD0CDC2E771D8F64111D2A35BD604FE29D54BBC7;Lorg/jruby/runtime/ThreadContext;Lorg/jruby/runtime/builtin/IRubyObject;Lorg/jruby/runtime/Block;)Lorg/jruby/runtime/builtin/IRubyObject;
        //    43: aload_1        
        //    44: getfield        org/jruby/runtime/ThreadContext.nil:Lorg/jruby/runtime/builtin/IRubyObject;
        //    47: goto            55
        //    50: aload_1        
        //    51: invokevirtual   org/jruby/runtime/ThreadContext.postCompiledClass:()V
        //    54: athrow         
        //    55: aload_1        
        //    56: invokevirtual   org/jruby/runtime/ThreadContext.postCompiledClass:()V
        //    59: areturn        
        //    Exceptions:
        //  Try           Handler
        //  Start  End    Start  End    Type
        //  -----  -----  -----  -----  ----
        //  27     47     50     55     Any
        // 
        // The error that occurred was:
        // 
        // java.lang.ArrayIndexOutOfBoundsException
        // 
        throw new IllegalStateException("An error occurred while decompiling this method.");
    }
    
    public static IRubyObject class_2$RUBY$WlanScan(final FILE_DD0CDC2E771D8F64111D2A35BD604FE29D54BBC7 p0, final ThreadContext p1, final IRubyObject p2, final Block p3) {
        // 
        // This method could not be decompiled.
        // 
        // Original Bytecode:
        // 
        //     0: aload_1        
        //     1: invokevirtual   org/jruby/runtime/ThreadContext.getCurrentScope:()Lorg/jruby/runtime/DynamicScope;
        //     4: dup            
        //     5: astore          4
        //     7: invokevirtual   org/jruby/runtime/DynamicScope.getValues:()[Lorg/jruby/runtime/builtin/IRubyObject;
        //    10: astore          5
        //    12: aload_1        
        //    13: getfield        org/jruby/runtime/ThreadContext.runtime:Lorg/jruby/Ruby;
        //    16: aload_2        
        //    17: invokestatic    org/jruby/javasupport/util/RuntimeHelpers.prepareSuperClass:(Lorg/jruby/Ruby;Lorg/jruby/runtime/builtin/IRubyObject;)Lorg/jruby/RubyClass;
        //    20: aload_1        
        //    21: aload_1        
        //    22: getfield        org/jruby/runtime/ThreadContext.nil:Lorg/jruby/runtime/builtin/IRubyObject;
        //    25: invokestatic    org/jruby/javasupport/util/RuntimeHelpers.prepareClassNamespace:(Lorg/jruby/runtime/ThreadContext;Lorg/jruby/runtime/builtin/IRubyObject;)Lorg/jruby/RubyModule;
        //    28: swap           
        //    29: ldc             "WlanScan"
        //    31: swap           
        //    32: invokevirtual   org/jruby/RubyModule.defineOrGetClassUnder:(Ljava/lang/String;Lorg/jruby/RubyClass;)Lorg/jruby/RubyClass;
        //    35: dup            
        //    36: astore_2       
        //    37: aload_1        
        //    38: swap           
        //    39: aload_0        
        //    40: aload_1        
        //    41: ldc             ",0,0,-1"
        //    43: invokevirtual   ruby/jit/FILE_DD0CDC2E771D8F64111D2A35BD604FE29D54BBC7.getScope2:(Lorg/jruby/runtime/ThreadContext;Ljava/lang/String;)Lorg/jruby/parser/StaticScope;
        //    46: invokevirtual   org/jruby/runtime/ThreadContext.preCompiledClass:(Lorg/jruby/RubyModule;Lorg/jruby/parser/StaticScope;)V
        //    49: aload_1        
        //    50: invokevirtual   org/jruby/runtime/ThreadContext.getCurrentScope:()Lorg/jruby/runtime/DynamicScope;
        //    53: astore          locals
        //    55: aload_0        
        //    56: invokevirtual   ruby/jit/FILE_DD0CDC2E771D8F64111D2A35BD604FE29D54BBC7.getCallSite1:()Lorg/jruby/runtime/CallSite;
        //    59: aload_1        
        //    60: aload_2        
        //    61: aload_2        
        //    62: aload_0        
        //    63: aload_1        
        //    64: getfield        org/jruby/runtime/ThreadContext.runtime:Lorg/jruby/Ruby;
        //    67: bipush          32
        //    69: invokevirtual   ruby/jit/FILE_DD0CDC2E771D8F64111D2A35BD604FE29D54BBC7.getString1:(Lorg/jruby/Ruby;I)Lorg/jruby/RubyString;
        //    72: invokevirtual   org/jruby/runtime/CallSite.call:(Lorg/jruby/runtime/ThreadContext;Lorg/jruby/runtime/builtin/IRubyObject;Lorg/jruby/runtime/builtin/IRubyObject;Lorg/jruby/runtime/builtin/IRubyObject;)Lorg/jruby/runtime/builtin/IRubyObject;
        //    75: pop            
        //    76: aload_0        
        //    77: invokevirtual   ruby/jit/FILE_DD0CDC2E771D8F64111D2A35BD604FE29D54BBC7.getCallSite2:()Lorg/jruby/runtime/CallSite;
        //    80: aload_1        
        //    81: aload_2        
        //    82: aload_2        
        //    83: aload_0        
        //    84: aload_1        
        //    85: getfield        org/jruby/runtime/ThreadContext.runtime:Lorg/jruby/Ruby;
        //    88: bipush          32
        //    90: invokevirtual   ruby/jit/FILE_DD0CDC2E771D8F64111D2A35BD604FE29D54BBC7.getString2:(Lorg/jruby/Ruby;I)Lorg/jruby/RubyString;
        //    93: aload_0        
        //    94: aload_1        
        //    95: getfield        org/jruby/runtime/ThreadContext.runtime:Lorg/jruby/Ruby;
        //    98: bipush          32
        //   100: invokevirtual   ruby/jit/FILE_DD0CDC2E771D8F64111D2A35BD604FE29D54BBC7.getString3:(Lorg/jruby/Ruby;I)Lorg/jruby/RubyString;
        //   103: aload_0        
        //   104: aload_1        
        //   105: getfield        org/jruby/runtime/ThreadContext.runtime:Lorg/jruby/Ruby;
        //   108: bipush          32
        //   110: invokevirtual   ruby/jit/FILE_DD0CDC2E771D8F64111D2A35BD604FE29D54BBC7.getString4:(Lorg/jruby/Ruby;I)Lorg/jruby/RubyString;
        //   113: aload_0        
        //   114: aload_1        
        //   115: getfield        org/jruby/runtime/ThreadContext.runtime:Lorg/jruby/Ruby;
        //   118: bipush          32
        //   120: invokevirtual   ruby/jit/FILE_DD0CDC2E771D8F64111D2A35BD604FE29D54BBC7.getString5:(Lorg/jruby/Ruby;I)Lorg/jruby/RubyString;
        //   123: aload_0        
        //   124: aload_1        
        //   125: getfield        org/jruby/runtime/ThreadContext.runtime:Lorg/jruby/Ruby;
        //   128: bipush          32
        //   130: invokevirtual   ruby/jit/FILE_DD0CDC2E771D8F64111D2A35BD604FE29D54BBC7.getString6:(Lorg/jruby/Ruby;I)Lorg/jruby/RubyString;
        //   133: invokestatic    org/jruby/javasupport/util/RuntimeHelpers.constructObjectArray:(Lorg/jruby/runtime/builtin/IRubyObject;Lorg/jruby/runtime/builtin/IRubyObject;Lorg/jruby/runtime/builtin/IRubyObject;Lorg/jruby/runtime/builtin/IRubyObject;Lorg/jruby/runtime/builtin/IRubyObject;)[Lorg/jruby/runtime/builtin/IRubyObject;
        //   136: invokevirtual   org/jruby/runtime/CallSite.call:(Lorg/jruby/runtime/ThreadContext;Lorg/jruby/runtime/builtin/IRubyObject;Lorg/jruby/runtime/builtin/IRubyObject;[Lorg/jruby/runtime/builtin/IRubyObject;)Lorg/jruby/runtime/builtin/IRubyObject;
        //   139: pop            
        //   140: aload_0        
        //   141: invokevirtual   ruby/jit/FILE_DD0CDC2E771D8F64111D2A35BD604FE29D54BBC7.getCallSite3:()Lorg/jruby/runtime/CallSite;
        //   144: aload_1        
        //   145: aload_2        
        //   146: aload_2        
        //   147: aload_0        
        //   148: aload_1        
        //   149: getfield        org/jruby/runtime/ThreadContext.runtime:Lorg/jruby/Ruby;
        //   152: bipush          32
        //   154: invokevirtual   ruby/jit/FILE_DD0CDC2E771D8F64111D2A35BD604FE29D54BBC7.getString7:(Lorg/jruby/Ruby;I)Lorg/jruby/RubyString;
        //   157: invokevirtual   org/jruby/runtime/CallSite.call:(Lorg/jruby/runtime/ThreadContext;Lorg/jruby/runtime/builtin/IRubyObject;Lorg/jruby/runtime/builtin/IRubyObject;Lorg/jruby/runtime/builtin/IRubyObject;)Lorg/jruby/runtime/builtin/IRubyObject;
        //   160: pop            
        //   161: aload_0        
        //   162: invokevirtual   ruby/jit/FILE_DD0CDC2E771D8F64111D2A35BD604FE29D54BBC7.getCallSite4:()Lorg/jruby/runtime/CallSite;
        //   165: aload_1        
        //   166: aload_2        
        //   167: aload_2        
        //   168: aload_0        
        //   169: aload_1        
        //   170: getfield        org/jruby/runtime/ThreadContext.runtime:Lorg/jruby/Ruby;
        //   173: bipush          64
        //   175: invokevirtual   ruby/jit/FILE_DD0CDC2E771D8F64111D2A35BD604FE29D54BBC7.getString8:(Lorg/jruby/Ruby;I)Lorg/jruby/RubyString;
        //   178: aload_0        
        //   179: aload_1        
        //   180: getfield        org/jruby/runtime/ThreadContext.runtime:Lorg/jruby/Ruby;
        //   183: bipush          64
        //   185: invokevirtual   ruby/jit/FILE_DD0CDC2E771D8F64111D2A35BD604FE29D54BBC7.getString9:(Lorg/jruby/Ruby;I)Lorg/jruby/RubyString;
        //   188: invokevirtual   org/jruby/runtime/CallSite.call:(Lorg/jruby/runtime/ThreadContext;Lorg/jruby/runtime/builtin/IRubyObject;Lorg/jruby/runtime/builtin/IRubyObject;Lorg/jruby/runtime/builtin/IRubyObject;Lorg/jruby/runtime/builtin/IRubyObject;)Lorg/jruby/runtime/builtin/IRubyObject;
        //   191: pop            
        //   192: aload_0        
        //   193: invokevirtual   ruby/jit/FILE_DD0CDC2E771D8F64111D2A35BD604FE29D54BBC7.getCallSite5:()Lorg/jruby/runtime/CallSite;
        //   196: aload_1        
        //   197: aload_2        
        //   198: aload_2        
        //   199: aload_0        
        //   200: aload_1        
        //   201: getfield        org/jruby/runtime/ThreadContext.runtime:Lorg/jruby/Ruby;
        //   204: bipush          10
        //   206: bipush          32
        //   208: invokevirtual   ruby/jit/FILE_DD0CDC2E771D8F64111D2A35BD604FE29D54BBC7.getString:(Lorg/jruby/Ruby;II)Lorg/jruby/RubyString;
        //   211: aload_0        
        //   212: aload_1        
        //   213: getfield        org/jruby/runtime/ThreadContext.runtime:Lorg/jruby/Ruby;
        //   216: bipush          11
        //   218: bipush          32
        //   220: invokevirtual   ruby/jit/FILE_DD0CDC2E771D8F64111D2A35BD604FE29D54BBC7.getString:(Lorg/jruby/Ruby;II)Lorg/jruby/RubyString;
        //   223: invokevirtual   org/jruby/runtime/CallSite.call:(Lorg/jruby/runtime/ThreadContext;Lorg/jruby/runtime/builtin/IRubyObject;Lorg/jruby/runtime/builtin/IRubyObject;Lorg/jruby/runtime/builtin/IRubyObject;Lorg/jruby/runtime/builtin/IRubyObject;)Lorg/jruby/runtime/builtin/IRubyObject;
        //   226: pop            
        //   227: aload_0        
        //   228: invokevirtual   ruby/jit/FILE_DD0CDC2E771D8F64111D2A35BD604FE29D54BBC7.getCallSite6:()Lorg/jruby/runtime/CallSite;
        //   231: aload_1        
        //   232: aload_2        
        //   233: aload_2        
        //   234: aload_0        
        //   235: aload_1        
        //   236: getfield        org/jruby/runtime/ThreadContext.runtime:Lorg/jruby/Ruby;
        //   239: bipush          12
        //   241: bipush          64
        //   243: invokevirtual   ruby/jit/FILE_DD0CDC2E771D8F64111D2A35BD604FE29D54BBC7.getString:(Lorg/jruby/Ruby;II)Lorg/jruby/RubyString;
        //   246: aload_0        
        //   247: aload_1        
        //   248: getfield        org/jruby/runtime/ThreadContext.runtime:Lorg/jruby/Ruby;
        //   251: bipush          13
        //   253: bipush          64
        //   255: invokevirtual   ruby/jit/FILE_DD0CDC2E771D8F64111D2A35BD604FE29D54BBC7.getString:(Lorg/jruby/Ruby;II)Lorg/jruby/RubyString;
        //   258: invokevirtual   org/jruby/runtime/CallSite.call:(Lorg/jruby/runtime/ThreadContext;Lorg/jruby/runtime/builtin/IRubyObject;Lorg/jruby/runtime/builtin/IRubyObject;Lorg/jruby/runtime/builtin/IRubyObject;Lorg/jruby/runtime/builtin/IRubyObject;)Lorg/jruby/runtime/builtin/IRubyObject;
        //   261: pop            
        //   262: aload_0        
        //   263: invokevirtual   ruby/jit/FILE_DD0CDC2E771D8F64111D2A35BD604FE29D54BBC7.getCallSite7:()Lorg/jruby/runtime/CallSite;
        //   266: aload_1        
        //   267: aload_2        
        //   268: aload_2        
        //   269: aload_0        
        //   270: aload_1        
        //   271: getfield        org/jruby/runtime/ThreadContext.runtime:Lorg/jruby/Ruby;
        //   274: ldc             "count"
        //   276: invokevirtual   ruby/jit/FILE_DD0CDC2E771D8F64111D2A35BD604FE29D54BBC7.getSymbol0:(Lorg/jruby/Ruby;Ljava/lang/String;)Lorg/jruby/RubySymbol;
        //   279: aload_1        
        //   280: aload_2        
        //   281: aload_0        
        //   282: aload_1        
        //   283: ldc             "block_0$RUBY$WlanScan,-1,,false,0,./lib//lister/measurements/wlan_scan.rb,25,true"
        //   285: invokevirtual   ruby/jit/FILE_DD0CDC2E771D8F64111D2A35BD604FE29D54BBC7.getBlockBody0:(Lorg/jruby/runtime/ThreadContext;Ljava/lang/String;)Lorg/jruby/runtime/BlockBody;
        //   288: invokestatic    org/jruby/javasupport/util/RuntimeHelpers.createBlock:(Lorg/jruby/runtime/ThreadContext;Lorg/jruby/runtime/builtin/IRubyObject;Lorg/jruby/runtime/BlockBody;)Lorg/jruby/runtime/Block;
        //   291: invokevirtual   org/jruby/runtime/CallSite.callIter:(Lorg/jruby/runtime/ThreadContext;Lorg/jruby/runtime/builtin/IRubyObject;Lorg/jruby/runtime/builtin/IRubyObject;Lorg/jruby/runtime/builtin/IRubyObject;Lorg/jruby/runtime/Block;)Lorg/jruby/runtime/builtin/IRubyObject;
        //   294: pop            
        //   295: aload_0        
        //   296: bipush          10
        //   298: invokevirtual   ruby/jit/FILE_DD0CDC2E771D8F64111D2A35BD604FE29D54BBC7.getCallSite:(I)Lorg/jruby/runtime/CallSite;
        //   301: aload_1        
        //   302: aload_2        
        //   303: aload_2        
        //   304: aload_0        
        //   305: aload_1        
        //   306: getfield        org/jruby/runtime/ThreadContext.runtime:Lorg/jruby/Ruby;
        //   309: ldc             "count_bssid"
        //   311: invokevirtual   ruby/jit/FILE_DD0CDC2E771D8F64111D2A35BD604FE29D54BBC7.getSymbol1:(Lorg/jruby/Ruby;Ljava/lang/String;)Lorg/jruby/RubySymbol;
        //   314: aload_1        
        //   315: aload_2        
        //   316: aload_0        
        //   317: aload_1        
        //   318: ldc             "block_1$RUBY$WlanScan,-1,,false,0,./lib//lister/measurements/wlan_scan.rb,31,true"
        //   320: invokevirtual   ruby/jit/FILE_DD0CDC2E771D8F64111D2A35BD604FE29D54BBC7.getBlockBody1:(Lorg/jruby/runtime/ThreadContext;Ljava/lang/String;)Lorg/jruby/runtime/BlockBody;
        //   323: invokestatic    org/jruby/javasupport/util/RuntimeHelpers.createBlock:(Lorg/jruby/runtime/ThreadContext;Lorg/jruby/runtime/builtin/IRubyObject;Lorg/jruby/runtime/BlockBody;)Lorg/jruby/runtime/Block;
        //   326: invokevirtual   org/jruby/runtime/CallSite.callIter:(Lorg/jruby/runtime/ThreadContext;Lorg/jruby/runtime/builtin/IRubyObject;Lorg/jruby/runtime/builtin/IRubyObject;Lorg/jruby/runtime/builtin/IRubyObject;Lorg/jruby/runtime/Block;)Lorg/jruby/runtime/builtin/IRubyObject;
        //   329: pop            
        //   330: aload_0        
        //   331: bipush          13
        //   333: invokevirtual   ruby/jit/FILE_DD0CDC2E771D8F64111D2A35BD604FE29D54BBC7.getCallSite:(I)Lorg/jruby/runtime/CallSite;
        //   336: aload_1        
        //   337: aload_2        
        //   338: aload_2        
        //   339: aload_0        
        //   340: aload_1        
        //   341: getfield        org/jruby/runtime/ThreadContext.runtime:Lorg/jruby/Ruby;
        //   344: ldc             "count_essid"
        //   346: invokevirtual   ruby/jit/FILE_DD0CDC2E771D8F64111D2A35BD604FE29D54BBC7.getSymbol2:(Lorg/jruby/Ruby;Ljava/lang/String;)Lorg/jruby/RubySymbol;
        //   349: aload_1        
        //   350: aload_2        
        //   351: aload_0        
        //   352: aload_1        
        //   353: ldc             "block_2$RUBY$WlanScan,-1,,false,0,./lib//lister/measurements/wlan_scan.rb,37,true"
        //   355: invokevirtual   ruby/jit/FILE_DD0CDC2E771D8F64111D2A35BD604FE29D54BBC7.getBlockBody2:(Lorg/jruby/runtime/ThreadContext;Ljava/lang/String;)Lorg/jruby/runtime/BlockBody;
        //   358: invokestatic    org/jruby/javasupport/util/RuntimeHelpers.createBlock:(Lorg/jruby/runtime/ThreadContext;Lorg/jruby/runtime/builtin/IRubyObject;Lorg/jruby/runtime/BlockBody;)Lorg/jruby/runtime/Block;
        //   361: invokevirtual   org/jruby/runtime/CallSite.callIter:(Lorg/jruby/runtime/ThreadContext;Lorg/jruby/runtime/builtin/IRubyObject;Lorg/jruby/runtime/builtin/IRubyObject;Lorg/jruby/runtime/builtin/IRubyObject;Lorg/jruby/runtime/Block;)Lorg/jruby/runtime/builtin/IRubyObject;
        //   364: pop            
        //   365: aload_0        
        //   366: bipush          16
        //   368: invokevirtual   ruby/jit/FILE_DD0CDC2E771D8F64111D2A35BD604FE29D54BBC7.getCallSite:(I)Lorg/jruby/runtime/CallSite;
        //   371: aload_1        
        //   372: aload_2        
        //   373: aload_2        
        //   374: aload_0        
        //   375: aload_1        
        //   376: getfield        org/jruby/runtime/ThreadContext.runtime:Lorg/jruby/Ruby;
        //   379: ldc             "rssis"
        //   381: invokevirtual   ruby/jit/FILE_DD0CDC2E771D8F64111D2A35BD604FE29D54BBC7.getSymbol3:(Lorg/jruby/Ruby;Ljava/lang/String;)Lorg/jruby/RubySymbol;
        //   384: aload_1        
        //   385: aload_2        
        //   386: aload_0        
        //   387: aload_1        
        //   388: ldc             "block_3$RUBY$WlanScan,-1,,false,0,./lib//lister/measurements/wlan_scan.rb,43,true"
        //   390: invokevirtual   ruby/jit/FILE_DD0CDC2E771D8F64111D2A35BD604FE29D54BBC7.getBlockBody3:(Lorg/jruby/runtime/ThreadContext;Ljava/lang/String;)Lorg/jruby/runtime/BlockBody;
        //   393: invokestatic    org/jruby/javasupport/util/RuntimeHelpers.createBlock:(Lorg/jruby/runtime/ThreadContext;Lorg/jruby/runtime/builtin/IRubyObject;Lorg/jruby/runtime/BlockBody;)Lorg/jruby/runtime/Block;
        //   396: invokevirtual   org/jruby/runtime/CallSite.callIter:(Lorg/jruby/runtime/ThreadContext;Lorg/jruby/runtime/builtin/IRubyObject;Lorg/jruby/runtime/builtin/IRubyObject;Lorg/jruby/runtime/builtin/IRubyObject;Lorg/jruby/runtime/Block;)Lorg/jruby/runtime/builtin/IRubyObject;
        //   399: pop            
        //   400: aload_0        
        //   401: bipush          19
        //   403: invokevirtual   ruby/jit/FILE_DD0CDC2E771D8F64111D2A35BD604FE29D54BBC7.getCallSite:(I)Lorg/jruby/runtime/CallSite;
        //   406: aload_1        
        //   407: aload_2        
        //   408: aload_2        
        //   409: aload_0        
        //   410: aload_1        
        //   411: getfield        org/jruby/runtime/ThreadContext.runtime:Lorg/jruby/Ruby;
        //   414: ldc             "channels"
        //   416: invokevirtual   ruby/jit/FILE_DD0CDC2E771D8F64111D2A35BD604FE29D54BBC7.getSymbol4:(Lorg/jruby/Ruby;Ljava/lang/String;)Lorg/jruby/RubySymbol;
        //   419: aload_1        
        //   420: aload_2        
        //   421: aload_0        
        //   422: aload_1        
        //   423: ldc             "block_4$RUBY$WlanScan,-1,,false,0,./lib//lister/measurements/wlan_scan.rb,49,true"
        //   425: invokevirtual   ruby/jit/FILE_DD0CDC2E771D8F64111D2A35BD604FE29D54BBC7.getBlockBody4:(Lorg/jruby/runtime/ThreadContext;Ljava/lang/String;)Lorg/jruby/runtime/BlockBody;
        //   428: invokestatic    org/jruby/javasupport/util/RuntimeHelpers.createBlock:(Lorg/jruby/runtime/ThreadContext;Lorg/jruby/runtime/builtin/IRubyObject;Lorg/jruby/runtime/BlockBody;)Lorg/jruby/runtime/Block;
        //   431: invokevirtual   org/jruby/runtime/CallSite.callIter:(Lorg/jruby/runtime/ThreadContext;Lorg/jruby/runtime/builtin/IRubyObject;Lorg/jruby/runtime/builtin/IRubyObject;Lorg/jruby/runtime/builtin/IRubyObject;Lorg/jruby/runtime/Block;)Lorg/jruby/runtime/builtin/IRubyObject;
        //   434: pop            
        //   435: aload_0        
        //   436: bipush          22
        //   438: invokevirtual   ruby/jit/FILE_DD0CDC2E771D8F64111D2A35BD604FE29D54BBC7.getCallSite:(I)Lorg/jruby/runtime/CallSite;
        //   441: aload_1        
        //   442: aload_2        
        //   443: aload_2        
        //   444: aload_0        
        //   445: aload_1        
        //   446: getfield        org/jruby/runtime/ThreadContext.runtime:Lorg/jruby/Ruby;
        //   449: ldc             "networks"
        //   451: invokevirtual   ruby/jit/FILE_DD0CDC2E771D8F64111D2A35BD604FE29D54BBC7.getSymbol5:(Lorg/jruby/Ruby;Ljava/lang/String;)Lorg/jruby/RubySymbol;
        //   454: aload_1        
        //   455: aload_2        
        //   456: aload_0        
        //   457: aload_1        
        //   458: ldc_w           "block_5$RUBY$WlanScan,-1,,false,0,./lib//lister/measurements/wlan_scan.rb,55,true"
        //   461: invokevirtual   ruby/jit/FILE_DD0CDC2E771D8F64111D2A35BD604FE29D54BBC7.getBlockBody5:(Lorg/jruby/runtime/ThreadContext;Ljava/lang/String;)Lorg/jruby/runtime/BlockBody;
        //   464: invokestatic    org/jruby/javasupport/util/RuntimeHelpers.createBlock:(Lorg/jruby/runtime/ThreadContext;Lorg/jruby/runtime/builtin/IRubyObject;Lorg/jruby/runtime/BlockBody;)Lorg/jruby/runtime/Block;
        //   467: invokevirtual   org/jruby/runtime/CallSite.callIter:(Lorg/jruby/runtime/ThreadContext;Lorg/jruby/runtime/builtin/IRubyObject;Lorg/jruby/runtime/builtin/IRubyObject;Lorg/jruby/runtime/builtin/IRubyObject;Lorg/jruby/runtime/Block;)Lorg/jruby/runtime/builtin/IRubyObject;
        //   470: pop            
        //   471: aload_0        
        //   472: bipush          25
        //   474: invokevirtual   ruby/jit/FILE_DD0CDC2E771D8F64111D2A35BD604FE29D54BBC7.getCallSite:(I)Lorg/jruby/runtime/CallSite;
        //   477: aload_1        
        //   478: aload_2        
        //   479: aload_2        
        //   480: aload_0        
        //   481: aload_1        
        //   482: getfield        org/jruby/runtime/ThreadContext.runtime:Lorg/jruby/Ruby;
        //   485: ldc_w           "current"
        //   488: invokevirtual   ruby/jit/FILE_DD0CDC2E771D8F64111D2A35BD604FE29D54BBC7.getSymbol6:(Lorg/jruby/Ruby;Ljava/lang/String;)Lorg/jruby/RubySymbol;
        //   491: aload_1        
        //   492: aload_2        
        //   493: aload_0        
        //   494: aload_1        
        //   495: ldc_w           "block_6$RUBY$WlanScan,-1,,false,0,./lib//lister/measurements/wlan_scan.rb,61,true"
        //   498: invokevirtual   ruby/jit/FILE_DD0CDC2E771D8F64111D2A35BD604FE29D54BBC7.getBlockBody6:(Lorg/jruby/runtime/ThreadContext;Ljava/lang/String;)Lorg/jruby/runtime/BlockBody;
        //   501: invokestatic    org/jruby/javasupport/util/RuntimeHelpers.createBlock:(Lorg/jruby/runtime/ThreadContext;Lorg/jruby/runtime/builtin/IRubyObject;Lorg/jruby/runtime/BlockBody;)Lorg/jruby/runtime/Block;
        //   504: invokevirtual   org/jruby/runtime/CallSite.callIter:(Lorg/jruby/runtime/ThreadContext;Lorg/jruby/runtime/builtin/IRubyObject;Lorg/jruby/runtime/builtin/IRubyObject;Lorg/jruby/runtime/builtin/IRubyObject;Lorg/jruby/runtime/Block;)Lorg/jruby/runtime/builtin/IRubyObject;
        //   507: pop            
        //   508: aload_0        
        //   509: bipush          28
        //   511: invokevirtual   ruby/jit/FILE_DD0CDC2E771D8F64111D2A35BD604FE29D54BBC7.getCallSite:(I)Lorg/jruby/runtime/CallSite;
        //   514: aload_1        
        //   515: aload_2        
        //   516: aload_2        
        //   517: aload_0        
        //   518: aload_1        
        //   519: getfield        org/jruby/runtime/ThreadContext.runtime:Lorg/jruby/Ruby;
        //   522: ldc_w           "scan_command"
        //   525: invokevirtual   ruby/jit/FILE_DD0CDC2E771D8F64111D2A35BD604FE29D54BBC7.getSymbol7:(Lorg/jruby/Ruby;Ljava/lang/String;)Lorg/jruby/RubySymbol;
        //   528: aload_1        
        //   529: aload_2        
        //   530: aload_0        
        //   531: aload_1        
        //   532: ldc_w           "block_7$RUBY$WlanScan,-1,,false,0,./lib//lister/measurements/wlan_scan.rb,67,true"
        //   535: invokevirtual   ruby/jit/FILE_DD0CDC2E771D8F64111D2A35BD604FE29D54BBC7.getBlockBody7:(Lorg/jruby/runtime/ThreadContext;Ljava/lang/String;)Lorg/jruby/runtime/BlockBody;
        //   538: invokestatic    org/jruby/javasupport/util/RuntimeHelpers.createBlock:(Lorg/jruby/runtime/ThreadContext;Lorg/jruby/runtime/builtin/IRubyObject;Lorg/jruby/runtime/BlockBody;)Lorg/jruby/runtime/Block;
        //   541: invokevirtual   org/jruby/runtime/CallSite.callIter:(Lorg/jruby/runtime/ThreadContext;Lorg/jruby/runtime/builtin/IRubyObject;Lorg/jruby/runtime/builtin/IRubyObject;Lorg/jruby/runtime/builtin/IRubyObject;Lorg/jruby/runtime/Block;)Lorg/jruby/runtime/builtin/IRubyObject;
        //   544: aload_1        
        //   545: invokevirtual   org/jruby/runtime/ThreadContext.postCompiledClass:()V
        //   548: goto            556
        //   551: aload_1        
        //   552: invokevirtual   org/jruby/runtime/ThreadContext.postCompiledClass:()V
        //   555: athrow         
        //   556: areturn        
        //    LocalVariableTable:
        //  Start  Length  Slot  Name    Signature
        //  -----  ------  ----  ------  --------------------------------
        //  55     502     4     locals  Lorg/jruby/runtime/DynamicScope;
        //    Exceptions:
        //  Try           Handler
        //  Start  End    Start  End    Type
        //  -----  -----  -----  -----  ----
        //  55     544    551    556    Any
        // 
        // The error that occurred was:
        // 
        // java.lang.ArrayIndexOutOfBoundsException
        // 
        throw new IllegalStateException("An error occurred while decompiling this method.");
    }
    
    public static IRubyObject block_0$RUBY$WlanScan(final FILE_DD0CDC2E771D8F64111D2A35BD604FE29D54BBC7 file_DD0CDC2E771D8F64111D2A35BD604FE29D54BBC7, final ThreadContext threadContext, final IRubyObject rubyObject, final IRubyObject rubyObject2, final Block block) {
        threadContext.getCurrentScope();
        RuntimeHelpers.processBlockArgument(threadContext.runtime, block);
        file_DD0CDC2E771D8F64111D2A35BD604FE29D54BBC7.getCallSite8().call(threadContext, rubyObject, rubyObject, file_DD0CDC2E771D8F64111D2A35BD604FE29D54BBC7.getString(threadContext.runtime, 14, 32));
        return file_DD0CDC2E771D8F64111D2A35BD604FE29D54BBC7.getCallSite9().call(threadContext, rubyObject, rubyObject, file_DD0CDC2E771D8F64111D2A35BD604FE29D54BBC7.getString(threadContext.runtime, 15, 64), file_DD0CDC2E771D8F64111D2A35BD604FE29D54BBC7.getString9(threadContext.runtime, 64));
    }
    
    public static IRubyObject block_1$RUBY$WlanScan(final FILE_DD0CDC2E771D8F64111D2A35BD604FE29D54BBC7 file_DD0CDC2E771D8F64111D2A35BD604FE29D54BBC7, final ThreadContext threadContext, final IRubyObject rubyObject, final IRubyObject rubyObject2, final Block block) {
        threadContext.getCurrentScope();
        RuntimeHelpers.processBlockArgument(threadContext.runtime, block);
        file_DD0CDC2E771D8F64111D2A35BD604FE29D54BBC7.getCallSite(11).call(threadContext, rubyObject, rubyObject, file_DD0CDC2E771D8F64111D2A35BD604FE29D54BBC7.getString(threadContext.runtime, 16, 32));
        return file_DD0CDC2E771D8F64111D2A35BD604FE29D54BBC7.getCallSite(12).call(threadContext, rubyObject, rubyObject, file_DD0CDC2E771D8F64111D2A35BD604FE29D54BBC7.getString(threadContext.runtime, 17, 32), file_DD0CDC2E771D8F64111D2A35BD604FE29D54BBC7.getString9(threadContext.runtime, 64));
    }
    
    public static IRubyObject block_2$RUBY$WlanScan(final FILE_DD0CDC2E771D8F64111D2A35BD604FE29D54BBC7 file_DD0CDC2E771D8F64111D2A35BD604FE29D54BBC7, final ThreadContext threadContext, final IRubyObject rubyObject, final IRubyObject rubyObject2, final Block block) {
        threadContext.getCurrentScope();
        RuntimeHelpers.processBlockArgument(threadContext.runtime, block);
        file_DD0CDC2E771D8F64111D2A35BD604FE29D54BBC7.getCallSite(14).call(threadContext, rubyObject, rubyObject, file_DD0CDC2E771D8F64111D2A35BD604FE29D54BBC7.getString(threadContext.runtime, 18, 32));
        return file_DD0CDC2E771D8F64111D2A35BD604FE29D54BBC7.getCallSite(15).call(threadContext, rubyObject, rubyObject, file_DD0CDC2E771D8F64111D2A35BD604FE29D54BBC7.getString(threadContext.runtime, 19, 32), file_DD0CDC2E771D8F64111D2A35BD604FE29D54BBC7.getString9(threadContext.runtime, 64));
    }
    
    public static IRubyObject block_3$RUBY$WlanScan(final FILE_DD0CDC2E771D8F64111D2A35BD604FE29D54BBC7 file_DD0CDC2E771D8F64111D2A35BD604FE29D54BBC7, final ThreadContext threadContext, final IRubyObject rubyObject, final IRubyObject rubyObject2, final Block block) {
        threadContext.getCurrentScope();
        RuntimeHelpers.processBlockArgument(threadContext.runtime, block);
        file_DD0CDC2E771D8F64111D2A35BD604FE29D54BBC7.getCallSite(17).call(threadContext, rubyObject, rubyObject, file_DD0CDC2E771D8F64111D2A35BD604FE29D54BBC7.getString(threadContext.runtime, 20, 32));
        return file_DD0CDC2E771D8F64111D2A35BD604FE29D54BBC7.getCallSite(18).call(threadContext, rubyObject, rubyObject, file_DD0CDC2E771D8F64111D2A35BD604FE29D54BBC7.getString(threadContext.runtime, 21, 64), file_DD0CDC2E771D8F64111D2A35BD604FE29D54BBC7.getString9(threadContext.runtime, 64));
    }
    
    public static IRubyObject block_4$RUBY$WlanScan(final FILE_DD0CDC2E771D8F64111D2A35BD604FE29D54BBC7 file_DD0CDC2E771D8F64111D2A35BD604FE29D54BBC7, final ThreadContext threadContext, final IRubyObject rubyObject, final IRubyObject rubyObject2, final Block block) {
        threadContext.getCurrentScope();
        RuntimeHelpers.processBlockArgument(threadContext.runtime, block);
        file_DD0CDC2E771D8F64111D2A35BD604FE29D54BBC7.getCallSite(20).call(threadContext, rubyObject, rubyObject, file_DD0CDC2E771D8F64111D2A35BD604FE29D54BBC7.getString(threadContext.runtime, 22, 32));
        return file_DD0CDC2E771D8F64111D2A35BD604FE29D54BBC7.getCallSite(21).call(threadContext, rubyObject, rubyObject, file_DD0CDC2E771D8F64111D2A35BD604FE29D54BBC7.getString(threadContext.runtime, 23, 64), file_DD0CDC2E771D8F64111D2A35BD604FE29D54BBC7.getString9(threadContext.runtime, 64));
    }
    
    public static IRubyObject block_5$RUBY$WlanScan(final FILE_DD0CDC2E771D8F64111D2A35BD604FE29D54BBC7 file_DD0CDC2E771D8F64111D2A35BD604FE29D54BBC7, final ThreadContext threadContext, final IRubyObject rubyObject, final IRubyObject rubyObject2, final Block block) {
        threadContext.getCurrentScope();
        RuntimeHelpers.processBlockArgument(threadContext.runtime, block);
        file_DD0CDC2E771D8F64111D2A35BD604FE29D54BBC7.getCallSite(23).call(threadContext, rubyObject, rubyObject, file_DD0CDC2E771D8F64111D2A35BD604FE29D54BBC7.getString(threadContext.runtime, 24, 32));
        return file_DD0CDC2E771D8F64111D2A35BD604FE29D54BBC7.getCallSite(24).call(threadContext, rubyObject, rubyObject, file_DD0CDC2E771D8F64111D2A35BD604FE29D54BBC7.getString(threadContext.runtime, 25, 64), file_DD0CDC2E771D8F64111D2A35BD604FE29D54BBC7.getString9(threadContext.runtime, 64));
    }
    
    public static IRubyObject block_6$RUBY$WlanScan(final FILE_DD0CDC2E771D8F64111D2A35BD604FE29D54BBC7 file_DD0CDC2E771D8F64111D2A35BD604FE29D54BBC7, final ThreadContext threadContext, final IRubyObject rubyObject, final IRubyObject rubyObject2, final Block block) {
        threadContext.getCurrentScope();
        RuntimeHelpers.processBlockArgument(threadContext.runtime, block);
        file_DD0CDC2E771D8F64111D2A35BD604FE29D54BBC7.getCallSite(26).call(threadContext, rubyObject, rubyObject, file_DD0CDC2E771D8F64111D2A35BD604FE29D54BBC7.getString(threadContext.runtime, 26, 32));
        return file_DD0CDC2E771D8F64111D2A35BD604FE29D54BBC7.getCallSite(27).call(threadContext, rubyObject, rubyObject, file_DD0CDC2E771D8F64111D2A35BD604FE29D54BBC7.getString(threadContext.runtime, 27, 64), file_DD0CDC2E771D8F64111D2A35BD604FE29D54BBC7.getString9(threadContext.runtime, 64));
    }
    
    public static IRubyObject block_7$RUBY$WlanScan(final FILE_DD0CDC2E771D8F64111D2A35BD604FE29D54BBC7 file_DD0CDC2E771D8F64111D2A35BD604FE29D54BBC7, final ThreadContext threadContext, final IRubyObject rubyObject, final IRubyObject rubyObject2, final Block block) {
        threadContext.getCurrentScope();
        RuntimeHelpers.processBlockArgument(threadContext.runtime, block);
        file_DD0CDC2E771D8F64111D2A35BD604FE29D54BBC7.getCallSite(29).call(threadContext, rubyObject, rubyObject, file_DD0CDC2E771D8F64111D2A35BD604FE29D54BBC7.getString(threadContext.runtime, 28, 32));
        return file_DD0CDC2E771D8F64111D2A35BD604FE29D54BBC7.getCallSite(30).call(threadContext, rubyObject, rubyObject, file_DD0CDC2E771D8F64111D2A35BD604FE29D54BBC7.getString(threadContext.runtime, 29, 64), file_DD0CDC2E771D8F64111D2A35BD604FE29D54BBC7.getString9(threadContext.runtime, 64));
    }
    
    public static IRubyObject class_2$RUBY$WlanScan(final FILE_DD0CDC2E771D8F64111D2A35BD604FE29D54BBC7 file_DD0CDC2E771D8F64111D2A35BD604FE29D54BBC7, final ThreadContext threadContext, final IRubyObject rubyObject, final IRubyObject[] args, final Block block) {
        Arity.checkArgumentCount(threadContext.getRuntime(), args, 0, 0);
        return class_2$RUBY$WlanScan(file_DD0CDC2E771D8F64111D2A35BD604FE29D54BBC7, threadContext, rubyObject, block);
    }
    
    public static IRubyObject module__1$RUBY$Measurements(final FILE_DD0CDC2E771D8F64111D2A35BD604FE29D54BBC7 file_DD0CDC2E771D8F64111D2A35BD604FE29D54BBC7, final ThreadContext threadContext, final IRubyObject rubyObject, final IRubyObject[] args, final Block block) {
        Arity.checkArgumentCount(threadContext.getRuntime(), args, 0, 0);
        return module__1$RUBY$Measurements(file_DD0CDC2E771D8F64111D2A35BD604FE29D54BBC7, threadContext, rubyObject, block);
    }
    
    public static IRubyObject module__0$RUBY$Lister(final FILE_DD0CDC2E771D8F64111D2A35BD604FE29D54BBC7 file_DD0CDC2E771D8F64111D2A35BD604FE29D54BBC7, final ThreadContext threadContext, final IRubyObject rubyObject, final IRubyObject[] args, final Block block) {
        Arity.checkArgumentCount(threadContext.getRuntime(), args, 0, 0);
        return module__0$RUBY$Lister(file_DD0CDC2E771D8F64111D2A35BD604FE29D54BBC7, threadContext, rubyObject, block);
    }
    
    @Override
    public IRubyObject load(final ThreadContext context, final IRubyObject rubyObject, final IRubyObject[] array, final Block block) {
        try {
            RuntimeHelpers.preLoad(context, ",0,0,-2");
            final IRubyObject _file__ = __file__(this, context, rubyObject, array, block);
            RuntimeHelpers.postLoad(context);
            return _file__;
        }
        finally {
            RuntimeHelpers.postLoad(context);
        }
    }
    
    public static void main(final String[] argv) {
        final FILE_DD0CDC2E771D8F64111D2A35BD604FE29D54BBC7 file_DD0CDC2E771D8F64111D2A35BD604FE29D54BBC7 = new FILE_DD0CDC2E771D8F64111D2A35BD604FE29D54BBC7();
        final String string = FILE_DD0CDC2E771D8F64111D2A35BD604FE29D54BBC7.class.getClassLoader().getResource("ruby/jit/FILE_DD0CDC2E771D8F64111D2A35BD604FE29D54BBC7.class").toString();
        file_DD0CDC2E771D8F64111D2A35BD604FE29D54BBC7.setFilename(string);
        final RubyInstanceConfig config = new RubyInstanceConfig();
        config.setArgv(argv);
        config.setScriptFileName(string);
        final Ruby instance = Ruby.newInstance(config);
        file_DD0CDC2E771D8F64111D2A35BD604FE29D54BBC7.load(instance.getCurrentContext(), instance.getTopSelf(), IRubyObject.NULL_ARRAY, Block.NULL_BLOCK);
    }
}
