// 
// Decompiled by Procyon v0.5.30
// 

package ruby.jit;

import org.jruby.Ruby;
import org.jruby.RubyInstanceConfig;
import org.jruby.runtime.Arity;
import org.jruby.javasupport.util.RuntimeHelpers;
import org.jruby.anno.JRubyMethod;
import org.jruby.runtime.Block;
import org.jruby.runtime.builtin.IRubyObject;
import org.jruby.ast.executable.RuntimeCache;
import org.jruby.runtime.ThreadContext;
import org.jruby.ast.executable.AbstractScript;

public class FILE_D901B762DF4AF11BEFBFDF3F5AE47863FA2F62D5 extends AbstractScript
{
    public FILE_D901B762DF4AF11BEFBFDF3F5AE47863FA2F62D5() {
        this.filename = "./lib//lister/measurements/configuration.rb";
        super.runtimeCache = new RuntimeCache();
        this.initFromDescriptor("require\uffffF\uffffversion\uffffF\uffffold_versions\uffffF\uffffdescribe\uffffF\uffffdescribe\uffffF\uffffdescribe\uffffF\uffffdescribe\uffffF\uffffreport\uffffF\uffffdescribe\uffffF\uffffdescribe\uffffF\uffffreport\uffffF\uffffdescribe\uffffF\uffffdescribe\uffffF\uffffreport\uffffF\uffffdescribe\uffffF\uffffdescribe\uffffF\uffffreport\uffffF\uffffdescribe\uffffF\uffffdescribe\uffffF\uffffattr_accessor\uffffF\uffffreport\uffffF\uffffdescribe\uffffF\uffffdescribe\uffffF\uffff\u0003\u0005\u0000\u0000\u0001\u0000\u0000\u0000\u0000\u0005\u0000\u0000\u0017\u0001");
        this.setEncoding(0, "ASCII-8BIT");
        this.setByteList(17, "The dump of the network configuration (via sysconfig on Mac and Linux, ad-hoc methods on Windows)", this.getEncoding0());
        this.setByteList(20, "La liste des interfaces r\uffc3\uffa9seaux de l'ordinateur", this.getEncoding0());
        this.setByteList(1, "0.1.0", this.getEncoding0());
        this.setByteList(2, "dev", this.getEncoding0());
        this.setByteList(0, "lister/measurement", this.getEncoding0());
        this.setByteList(7, "Version du syst\uffc3\uffa8me d'exploitation et configuration r\uffc3\uffa9seau", this.getEncoding0());
        this.setByteList(15, "The OS version of this computer.", this.getEncoding0());
        this.setByteList(10, "English-HTML", this.getEncoding0());
        this.setByteList(14, "Le syst\uffc3\uffa8me d'exploitation de cet ordinateur, selon la platerforme Java", this.getEncoding0());
        this.setByteList(18, "Une sorte de dump de la configuration r\uffc3\uffa9seau", this.getEncoding0());
        this.setByteList(16, "La version du syst\uffc3\uffa8me d'exploitation de cet ordinateur", this.getEncoding0());
        this.setByteList(8, "Fran\uffc3\uffa7ais", this.getEncoding0());
        this.setByteList(3, "0.0.1", this.getEncoding0());
        this.setByteList(6, "Operating system version and network configuration", this.getEncoding0());
        this.setByteList(9, "<p>This module gets information about the computer where HomeNet Profiler runs.\n      We collect: the name and the version of the OS, the list of the IP adresses of the computer (an anonymized list of the local IP addresses), and a dump of the network configuration (such as TCP parameters).\n      </p>", this.getEncoding0());
        this.setByteList(19, "A list of network interfaces on the computer running HomeNet Profiler", this.getEncoding0());
        this.setByteList(13, "The Operating System of this computer, according to the Java platform", this.getEncoding0());
        this.setByteList(5, "0.0.3", this.getEncoding0());
        this.setByteList(4, "0.0.2", this.getEncoding0());
        this.setByteList(11, "Ce module mesure des donn\uffc3\uffa9es sur l'ordinateur lui-m\uffc3\uffaame: le type\net la version du syst\uffc3\uffa8me d'exploitation et comment le r\uffc3\uffa9seau est param\uffc3\uffa9tr\uffc3\uffa9.\n      Nous aimerions comprendre comment ces facteurs influent sur les performances.", this.getEncoding0());
        this.setByteList(12, "Fran\uffc3\uffa7ais-HTML", this.getEncoding0());
        this.setByteList(21, "The list of network interfaces and, with their vendor-id, and their IP if it is private", this.getEncoding0());
        this.setByteList(22, "La liste des interfaces r\uffc3\uffa9seaux, avec leurs identifiant-vendeur, et leur adresse IP si elle est priv\uffc3\uffa9e", this.getEncoding0());
    }
    
    @JRubyMethod(name = "__file__", frame = true, required = 0, optional = 0, rest = -2)
    public static IRubyObject __file__(final FILE_D901B762DF4AF11BEFBFDF3F5AE47863FA2F62D5 file_D901B762DF4AF11BEFBFDF3F5AE47863FA2F62D5, final ThreadContext threadContext, final IRubyObject rubyObject, final IRubyObject[] array, final Block block) {
        file_D901B762DF4AF11BEFBFDF3F5AE47863FA2F62D5.getCallSite0().call(threadContext, rubyObject, rubyObject, file_D901B762DF4AF11BEFBFDF3F5AE47863FA2F62D5.getString0(threadContext.runtime, 32));
        return module__0$RUBY$Lister(file_D901B762DF4AF11BEFBFDF3F5AE47863FA2F62D5, threadContext, rubyObject, IRubyObject.NULL_ARRAY, Block.NULL_BLOCK);
    }
    
    @Override
    public IRubyObject __file__(final ThreadContext threadContext, final IRubyObject rubyObject, final IRubyObject[] array, final Block block) {
        return __file__(this, threadContext, rubyObject, array, block);
    }
    
    public static IRubyObject module__0$RUBY$Lister(final FILE_D901B762DF4AF11BEFBFDF3F5AE47863FA2F62D5 p0, final ThreadContext p1, final IRubyObject p2, final Block p3) {
        // 
        // This method could not be decompiled.
        // 
        // Original Bytecode:
        // 
        //     0: aload_1        
        //     1: aload_1        
        //     2: getfield        org/jruby/runtime/ThreadContext.nil:Lorg/jruby/runtime/builtin/IRubyObject;
        //     5: invokestatic    org/jruby/javasupport/util/RuntimeHelpers.prepareClassNamespace:(Lorg/jruby/runtime/ThreadContext;Lorg/jruby/runtime/builtin/IRubyObject;)Lorg/jruby/RubyModule;
        //     8: ldc             "Lister"
        //    10: invokevirtual   org/jruby/RubyModule.defineOrGetModuleUnder:(Ljava/lang/String;)Lorg/jruby/RubyModule;
        //    13: dup            
        //    14: astore_2       
        //    15: aload_1        
        //    16: swap           
        //    17: aload_0        
        //    18: aload_1        
        //    19: ldc             ",0,0,-1"
        //    21: invokevirtual   ruby/jit/FILE_D901B762DF4AF11BEFBFDF3F5AE47863FA2F62D5.getScope0:(Lorg/jruby/runtime/ThreadContext;Ljava/lang/String;)Lorg/jruby/parser/StaticScope;
        //    24: invokevirtual   org/jruby/runtime/ThreadContext.preCompiledClassDummyScope:(Lorg/jruby/RubyModule;Lorg/jruby/parser/StaticScope;)V
        //    27: aload_0        
        //    28: aload_1        
        //    29: aload_2        
        //    30: getstatic       org/jruby/runtime/builtin/IRubyObject.NULL_ARRAY:[Lorg/jruby/runtime/builtin/IRubyObject;
        //    33: getstatic       org/jruby/runtime/Block.NULL_BLOCK:Lorg/jruby/runtime/Block;
        //    36: invokestatic    ruby/jit/FILE_D901B762DF4AF11BEFBFDF3F5AE47863FA2F62D5.module__1$RUBY$Measurements:(Lruby/jit/FILE_D901B762DF4AF11BEFBFDF3F5AE47863FA2F62D5;Lorg/jruby/runtime/ThreadContext;Lorg/jruby/runtime/builtin/IRubyObject;[Lorg/jruby/runtime/builtin/IRubyObject;Lorg/jruby/runtime/Block;)Lorg/jruby/runtime/builtin/IRubyObject;
        //    39: aload_1        
        //    40: getfield        org/jruby/runtime/ThreadContext.nil:Lorg/jruby/runtime/builtin/IRubyObject;
        //    43: goto            51
        //    46: aload_1        
        //    47: invokevirtual   org/jruby/runtime/ThreadContext.postCompiledClass:()V
        //    50: athrow         
        //    51: aload_1        
        //    52: invokevirtual   org/jruby/runtime/ThreadContext.postCompiledClass:()V
        //    55: areturn        
        //    Exceptions:
        //  Try           Handler
        //  Start  End    Start  End    Type
        //  -----  -----  -----  -----  ----
        //  27     43     46     51     Any
        // 
        // The error that occurred was:
        // 
        // java.lang.ArrayIndexOutOfBoundsException
        // 
        throw new IllegalStateException("An error occurred while decompiling this method.");
    }
    
    public static IRubyObject module__1$RUBY$Measurements(final FILE_D901B762DF4AF11BEFBFDF3F5AE47863FA2F62D5 p0, final ThreadContext p1, final IRubyObject p2, final Block p3) {
        // 
        // This method could not be decompiled.
        // 
        // Original Bytecode:
        // 
        //     0: aload_1        
        //     1: aload_1        
        //     2: getfield        org/jruby/runtime/ThreadContext.nil:Lorg/jruby/runtime/builtin/IRubyObject;
        //     5: invokestatic    org/jruby/javasupport/util/RuntimeHelpers.prepareClassNamespace:(Lorg/jruby/runtime/ThreadContext;Lorg/jruby/runtime/builtin/IRubyObject;)Lorg/jruby/RubyModule;
        //     8: ldc             "Measurements"
        //    10: invokevirtual   org/jruby/RubyModule.defineOrGetModuleUnder:(Ljava/lang/String;)Lorg/jruby/RubyModule;
        //    13: dup            
        //    14: astore_2       
        //    15: aload_1        
        //    16: swap           
        //    17: aload_0        
        //    18: aload_1        
        //    19: ldc             ",0,0,-1"
        //    21: invokevirtual   ruby/jit/FILE_D901B762DF4AF11BEFBFDF3F5AE47863FA2F62D5.getScope1:(Lorg/jruby/runtime/ThreadContext;Ljava/lang/String;)Lorg/jruby/parser/StaticScope;
        //    24: invokevirtual   org/jruby/runtime/ThreadContext.preCompiledClassDummyScope:(Lorg/jruby/RubyModule;Lorg/jruby/parser/StaticScope;)V
        //    27: aload_0        
        //    28: aload_1        
        //    29: aload_0        
        //    30: aload_1        
        //    31: ldc_w           "Measurement"
        //    34: invokevirtual   ruby/jit/FILE_D901B762DF4AF11BEFBFDF3F5AE47863FA2F62D5.getConstant0:(Lorg/jruby/runtime/ThreadContext;Ljava/lang/String;)Lorg/jruby/runtime/builtin/IRubyObject;
        //    37: getstatic       org/jruby/runtime/Block.NULL_BLOCK:Lorg/jruby/runtime/Block;
        //    40: invokestatic    ruby/jit/FILE_D901B762DF4AF11BEFBFDF3F5AE47863FA2F62D5.class_2$RUBY$Configuration:(Lruby/jit/FILE_D901B762DF4AF11BEFBFDF3F5AE47863FA2F62D5;Lorg/jruby/runtime/ThreadContext;Lorg/jruby/runtime/builtin/IRubyObject;Lorg/jruby/runtime/Block;)Lorg/jruby/runtime/builtin/IRubyObject;
        //    43: aload_1        
        //    44: getfield        org/jruby/runtime/ThreadContext.nil:Lorg/jruby/runtime/builtin/IRubyObject;
        //    47: goto            55
        //    50: aload_1        
        //    51: invokevirtual   org/jruby/runtime/ThreadContext.postCompiledClass:()V
        //    54: athrow         
        //    55: aload_1        
        //    56: invokevirtual   org/jruby/runtime/ThreadContext.postCompiledClass:()V
        //    59: areturn        
        //    Exceptions:
        //  Try           Handler
        //  Start  End    Start  End    Type
        //  -----  -----  -----  -----  ----
        //  27     47     50     55     Any
        // 
        // The error that occurred was:
        // 
        // java.lang.ArrayIndexOutOfBoundsException
        // 
        throw new IllegalStateException("An error occurred while decompiling this method.");
    }
    
    public static IRubyObject class_2$RUBY$Configuration(final FILE_D901B762DF4AF11BEFBFDF3F5AE47863FA2F62D5 p0, final ThreadContext p1, final IRubyObject p2, final Block p3) {
        // 
        // This method could not be decompiled.
        // 
        // Original Bytecode:
        // 
        //     0: aload_1        
        //     1: invokevirtual   org/jruby/runtime/ThreadContext.getCurrentScope:()Lorg/jruby/runtime/DynamicScope;
        //     4: dup            
        //     5: astore          4
        //     7: invokevirtual   org/jruby/runtime/DynamicScope.getValues:()[Lorg/jruby/runtime/builtin/IRubyObject;
        //    10: astore          5
        //    12: aload_1        
        //    13: getfield        org/jruby/runtime/ThreadContext.runtime:Lorg/jruby/Ruby;
        //    16: aload_2        
        //    17: invokestatic    org/jruby/javasupport/util/RuntimeHelpers.prepareSuperClass:(Lorg/jruby/Ruby;Lorg/jruby/runtime/builtin/IRubyObject;)Lorg/jruby/RubyClass;
        //    20: aload_1        
        //    21: aload_1        
        //    22: getfield        org/jruby/runtime/ThreadContext.nil:Lorg/jruby/runtime/builtin/IRubyObject;
        //    25: invokestatic    org/jruby/javasupport/util/RuntimeHelpers.prepareClassNamespace:(Lorg/jruby/runtime/ThreadContext;Lorg/jruby/runtime/builtin/IRubyObject;)Lorg/jruby/RubyModule;
        //    28: swap           
        //    29: ldc             "Configuration"
        //    31: swap           
        //    32: invokevirtual   org/jruby/RubyModule.defineOrGetClassUnder:(Ljava/lang/String;Lorg/jruby/RubyClass;)Lorg/jruby/RubyClass;
        //    35: dup            
        //    36: astore_2       
        //    37: aload_1        
        //    38: swap           
        //    39: aload_0        
        //    40: aload_1        
        //    41: ldc             ",0,0,-1"
        //    43: invokevirtual   ruby/jit/FILE_D901B762DF4AF11BEFBFDF3F5AE47863FA2F62D5.getScope2:(Lorg/jruby/runtime/ThreadContext;Ljava/lang/String;)Lorg/jruby/parser/StaticScope;
        //    46: invokevirtual   org/jruby/runtime/ThreadContext.preCompiledClass:(Lorg/jruby/RubyModule;Lorg/jruby/parser/StaticScope;)V
        //    49: aload_1        
        //    50: invokevirtual   org/jruby/runtime/ThreadContext.getCurrentScope:()Lorg/jruby/runtime/DynamicScope;
        //    53: astore          locals
        //    55: aload_0        
        //    56: invokevirtual   ruby/jit/FILE_D901B762DF4AF11BEFBFDF3F5AE47863FA2F62D5.getCallSite1:()Lorg/jruby/runtime/CallSite;
        //    59: aload_1        
        //    60: aload_2        
        //    61: aload_2        
        //    62: aload_0        
        //    63: aload_1        
        //    64: getfield        org/jruby/runtime/ThreadContext.runtime:Lorg/jruby/Ruby;
        //    67: bipush          32
        //    69: invokevirtual   ruby/jit/FILE_D901B762DF4AF11BEFBFDF3F5AE47863FA2F62D5.getString1:(Lorg/jruby/Ruby;I)Lorg/jruby/RubyString;
        //    72: invokevirtual   org/jruby/runtime/CallSite.call:(Lorg/jruby/runtime/ThreadContext;Lorg/jruby/runtime/builtin/IRubyObject;Lorg/jruby/runtime/builtin/IRubyObject;Lorg/jruby/runtime/builtin/IRubyObject;)Lorg/jruby/runtime/builtin/IRubyObject;
        //    75: pop            
        //    76: aload_0        
        //    77: invokevirtual   ruby/jit/FILE_D901B762DF4AF11BEFBFDF3F5AE47863FA2F62D5.getCallSite2:()Lorg/jruby/runtime/CallSite;
        //    80: aload_1        
        //    81: aload_2        
        //    82: aload_2        
        //    83: aload_0        
        //    84: aload_1        
        //    85: getfield        org/jruby/runtime/ThreadContext.runtime:Lorg/jruby/Ruby;
        //    88: bipush          32
        //    90: invokevirtual   ruby/jit/FILE_D901B762DF4AF11BEFBFDF3F5AE47863FA2F62D5.getString2:(Lorg/jruby/Ruby;I)Lorg/jruby/RubyString;
        //    93: aload_0        
        //    94: aload_1        
        //    95: getfield        org/jruby/runtime/ThreadContext.runtime:Lorg/jruby/Ruby;
        //    98: bipush          32
        //   100: invokevirtual   ruby/jit/FILE_D901B762DF4AF11BEFBFDF3F5AE47863FA2F62D5.getString3:(Lorg/jruby/Ruby;I)Lorg/jruby/RubyString;
        //   103: aload_0        
        //   104: aload_1        
        //   105: getfield        org/jruby/runtime/ThreadContext.runtime:Lorg/jruby/Ruby;
        //   108: bipush          32
        //   110: invokevirtual   ruby/jit/FILE_D901B762DF4AF11BEFBFDF3F5AE47863FA2F62D5.getString4:(Lorg/jruby/Ruby;I)Lorg/jruby/RubyString;
        //   113: aload_0        
        //   114: aload_1        
        //   115: getfield        org/jruby/runtime/ThreadContext.runtime:Lorg/jruby/Ruby;
        //   118: bipush          32
        //   120: invokevirtual   ruby/jit/FILE_D901B762DF4AF11BEFBFDF3F5AE47863FA2F62D5.getString5:(Lorg/jruby/Ruby;I)Lorg/jruby/RubyString;
        //   123: invokestatic    org/jruby/javasupport/util/RuntimeHelpers.constructObjectArray:(Lorg/jruby/runtime/builtin/IRubyObject;Lorg/jruby/runtime/builtin/IRubyObject;Lorg/jruby/runtime/builtin/IRubyObject;Lorg/jruby/runtime/builtin/IRubyObject;)[Lorg/jruby/runtime/builtin/IRubyObject;
        //   126: invokevirtual   org/jruby/runtime/CallSite.call:(Lorg/jruby/runtime/ThreadContext;Lorg/jruby/runtime/builtin/IRubyObject;Lorg/jruby/runtime/builtin/IRubyObject;[Lorg/jruby/runtime/builtin/IRubyObject;)Lorg/jruby/runtime/builtin/IRubyObject;
        //   129: pop            
        //   130: aload_0        
        //   131: invokevirtual   ruby/jit/FILE_D901B762DF4AF11BEFBFDF3F5AE47863FA2F62D5.getCallSite3:()Lorg/jruby/runtime/CallSite;
        //   134: aload_1        
        //   135: aload_2        
        //   136: aload_2        
        //   137: aload_0        
        //   138: aload_1        
        //   139: getfield        org/jruby/runtime/ThreadContext.runtime:Lorg/jruby/Ruby;
        //   142: bipush          32
        //   144: invokevirtual   ruby/jit/FILE_D901B762DF4AF11BEFBFDF3F5AE47863FA2F62D5.getString6:(Lorg/jruby/Ruby;I)Lorg/jruby/RubyString;
        //   147: invokevirtual   org/jruby/runtime/CallSite.call:(Lorg/jruby/runtime/ThreadContext;Lorg/jruby/runtime/builtin/IRubyObject;Lorg/jruby/runtime/builtin/IRubyObject;Lorg/jruby/runtime/builtin/IRubyObject;)Lorg/jruby/runtime/builtin/IRubyObject;
        //   150: pop            
        //   151: aload_0        
        //   152: invokevirtual   ruby/jit/FILE_D901B762DF4AF11BEFBFDF3F5AE47863FA2F62D5.getCallSite4:()Lorg/jruby/runtime/CallSite;
        //   155: aload_1        
        //   156: aload_2        
        //   157: aload_2        
        //   158: aload_0        
        //   159: aload_1        
        //   160: getfield        org/jruby/runtime/ThreadContext.runtime:Lorg/jruby/Ruby;
        //   163: bipush          64
        //   165: invokevirtual   ruby/jit/FILE_D901B762DF4AF11BEFBFDF3F5AE47863FA2F62D5.getString7:(Lorg/jruby/Ruby;I)Lorg/jruby/RubyString;
        //   168: aload_0        
        //   169: aload_1        
        //   170: getfield        org/jruby/runtime/ThreadContext.runtime:Lorg/jruby/Ruby;
        //   173: bipush          64
        //   175: invokevirtual   ruby/jit/FILE_D901B762DF4AF11BEFBFDF3F5AE47863FA2F62D5.getString8:(Lorg/jruby/Ruby;I)Lorg/jruby/RubyString;
        //   178: invokevirtual   org/jruby/runtime/CallSite.call:(Lorg/jruby/runtime/ThreadContext;Lorg/jruby/runtime/builtin/IRubyObject;Lorg/jruby/runtime/builtin/IRubyObject;Lorg/jruby/runtime/builtin/IRubyObject;Lorg/jruby/runtime/builtin/IRubyObject;)Lorg/jruby/runtime/builtin/IRubyObject;
        //   181: pop            
        //   182: aload_0        
        //   183: invokevirtual   ruby/jit/FILE_D901B762DF4AF11BEFBFDF3F5AE47863FA2F62D5.getCallSite5:()Lorg/jruby/runtime/CallSite;
        //   186: aload_1        
        //   187: aload_2        
        //   188: aload_2        
        //   189: aload_0        
        //   190: aload_1        
        //   191: getfield        org/jruby/runtime/ThreadContext.runtime:Lorg/jruby/Ruby;
        //   194: bipush          32
        //   196: invokevirtual   ruby/jit/FILE_D901B762DF4AF11BEFBFDF3F5AE47863FA2F62D5.getString9:(Lorg/jruby/Ruby;I)Lorg/jruby/RubyString;
        //   199: aload_0        
        //   200: aload_1        
        //   201: getfield        org/jruby/runtime/ThreadContext.runtime:Lorg/jruby/Ruby;
        //   204: bipush          10
        //   206: bipush          32
        //   208: invokevirtual   ruby/jit/FILE_D901B762DF4AF11BEFBFDF3F5AE47863FA2F62D5.getString:(Lorg/jruby/Ruby;II)Lorg/jruby/RubyString;
        //   211: invokevirtual   org/jruby/runtime/CallSite.call:(Lorg/jruby/runtime/ThreadContext;Lorg/jruby/runtime/builtin/IRubyObject;Lorg/jruby/runtime/builtin/IRubyObject;Lorg/jruby/runtime/builtin/IRubyObject;Lorg/jruby/runtime/builtin/IRubyObject;)Lorg/jruby/runtime/builtin/IRubyObject;
        //   214: pop            
        //   215: aload_0        
        //   216: invokevirtual   ruby/jit/FILE_D901B762DF4AF11BEFBFDF3F5AE47863FA2F62D5.getCallSite6:()Lorg/jruby/runtime/CallSite;
        //   219: aload_1        
        //   220: aload_2        
        //   221: aload_2        
        //   222: aload_0        
        //   223: aload_1        
        //   224: getfield        org/jruby/runtime/ThreadContext.runtime:Lorg/jruby/Ruby;
        //   227: bipush          11
        //   229: bipush          64
        //   231: invokevirtual   ruby/jit/FILE_D901B762DF4AF11BEFBFDF3F5AE47863FA2F62D5.getString:(Lorg/jruby/Ruby;II)Lorg/jruby/RubyString;
        //   234: aload_0        
        //   235: aload_1        
        //   236: getfield        org/jruby/runtime/ThreadContext.runtime:Lorg/jruby/Ruby;
        //   239: bipush          12
        //   241: bipush          64
        //   243: invokevirtual   ruby/jit/FILE_D901B762DF4AF11BEFBFDF3F5AE47863FA2F62D5.getString:(Lorg/jruby/Ruby;II)Lorg/jruby/RubyString;
        //   246: invokevirtual   org/jruby/runtime/CallSite.call:(Lorg/jruby/runtime/ThreadContext;Lorg/jruby/runtime/builtin/IRubyObject;Lorg/jruby/runtime/builtin/IRubyObject;Lorg/jruby/runtime/builtin/IRubyObject;Lorg/jruby/runtime/builtin/IRubyObject;)Lorg/jruby/runtime/builtin/IRubyObject;
        //   249: pop            
        //   250: aload_0        
        //   251: invokevirtual   ruby/jit/FILE_D901B762DF4AF11BEFBFDF3F5AE47863FA2F62D5.getCallSite7:()Lorg/jruby/runtime/CallSite;
        //   254: aload_1        
        //   255: aload_2        
        //   256: aload_2        
        //   257: aload_0        
        //   258: aload_1        
        //   259: getfield        org/jruby/runtime/ThreadContext.runtime:Lorg/jruby/Ruby;
        //   262: ldc             "java_os"
        //   264: invokevirtual   ruby/jit/FILE_D901B762DF4AF11BEFBFDF3F5AE47863FA2F62D5.getSymbol0:(Lorg/jruby/Ruby;Ljava/lang/String;)Lorg/jruby/RubySymbol;
        //   267: aload_1        
        //   268: aload_2        
        //   269: aload_0        
        //   270: aload_1        
        //   271: ldc             "block_0$RUBY$Configuration,-1,,false,0,./lib//lister/measurements/configuration.rb,23,true"
        //   273: invokevirtual   ruby/jit/FILE_D901B762DF4AF11BEFBFDF3F5AE47863FA2F62D5.getBlockBody0:(Lorg/jruby/runtime/ThreadContext;Ljava/lang/String;)Lorg/jruby/runtime/BlockBody;
        //   276: invokestatic    org/jruby/javasupport/util/RuntimeHelpers.createBlock:(Lorg/jruby/runtime/ThreadContext;Lorg/jruby/runtime/builtin/IRubyObject;Lorg/jruby/runtime/BlockBody;)Lorg/jruby/runtime/Block;
        //   279: invokevirtual   org/jruby/runtime/CallSite.callIter:(Lorg/jruby/runtime/ThreadContext;Lorg/jruby/runtime/builtin/IRubyObject;Lorg/jruby/runtime/builtin/IRubyObject;Lorg/jruby/runtime/builtin/IRubyObject;Lorg/jruby/runtime/Block;)Lorg/jruby/runtime/builtin/IRubyObject;
        //   282: pop            
        //   283: aload_0        
        //   284: bipush          10
        //   286: invokevirtual   ruby/jit/FILE_D901B762DF4AF11BEFBFDF3F5AE47863FA2F62D5.getCallSite:(I)Lorg/jruby/runtime/CallSite;
        //   289: aload_1        
        //   290: aload_2        
        //   291: aload_2        
        //   292: aload_0        
        //   293: aload_1        
        //   294: getfield        org/jruby/runtime/ThreadContext.runtime:Lorg/jruby/Ruby;
        //   297: ldc             "os"
        //   299: invokevirtual   ruby/jit/FILE_D901B762DF4AF11BEFBFDF3F5AE47863FA2F62D5.getSymbol1:(Lorg/jruby/Ruby;Ljava/lang/String;)Lorg/jruby/RubySymbol;
        //   302: aload_1        
        //   303: aload_2        
        //   304: aload_0        
        //   305: aload_1        
        //   306: ldc             "block_1$RUBY$Configuration,-1,,false,0,./lib//lister/measurements/configuration.rb,29,true"
        //   308: invokevirtual   ruby/jit/FILE_D901B762DF4AF11BEFBFDF3F5AE47863FA2F62D5.getBlockBody1:(Lorg/jruby/runtime/ThreadContext;Ljava/lang/String;)Lorg/jruby/runtime/BlockBody;
        //   311: invokestatic    org/jruby/javasupport/util/RuntimeHelpers.createBlock:(Lorg/jruby/runtime/ThreadContext;Lorg/jruby/runtime/builtin/IRubyObject;Lorg/jruby/runtime/BlockBody;)Lorg/jruby/runtime/Block;
        //   314: invokevirtual   org/jruby/runtime/CallSite.callIter:(Lorg/jruby/runtime/ThreadContext;Lorg/jruby/runtime/builtin/IRubyObject;Lorg/jruby/runtime/builtin/IRubyObject;Lorg/jruby/runtime/builtin/IRubyObject;Lorg/jruby/runtime/Block;)Lorg/jruby/runtime/builtin/IRubyObject;
        //   317: pop            
        //   318: aload_0        
        //   319: bipush          13
        //   321: invokevirtual   ruby/jit/FILE_D901B762DF4AF11BEFBFDF3F5AE47863FA2F62D5.getCallSite:(I)Lorg/jruby/runtime/CallSite;
        //   324: aload_1        
        //   325: aload_2        
        //   326: aload_2        
        //   327: aload_0        
        //   328: aload_1        
        //   329: getfield        org/jruby/runtime/ThreadContext.runtime:Lorg/jruby/Ruby;
        //   332: ldc             "net_config"
        //   334: invokevirtual   ruby/jit/FILE_D901B762DF4AF11BEFBFDF3F5AE47863FA2F62D5.getSymbol2:(Lorg/jruby/Ruby;Ljava/lang/String;)Lorg/jruby/RubySymbol;
        //   337: aload_1        
        //   338: aload_2        
        //   339: aload_0        
        //   340: aload_1        
        //   341: ldc             "block_2$RUBY$Configuration,-1,,false,0,./lib//lister/measurements/configuration.rb,35,true"
        //   343: invokevirtual   ruby/jit/FILE_D901B762DF4AF11BEFBFDF3F5AE47863FA2F62D5.getBlockBody2:(Lorg/jruby/runtime/ThreadContext;Ljava/lang/String;)Lorg/jruby/runtime/BlockBody;
        //   346: invokestatic    org/jruby/javasupport/util/RuntimeHelpers.createBlock:(Lorg/jruby/runtime/ThreadContext;Lorg/jruby/runtime/builtin/IRubyObject;Lorg/jruby/runtime/BlockBody;)Lorg/jruby/runtime/Block;
        //   349: invokevirtual   org/jruby/runtime/CallSite.callIter:(Lorg/jruby/runtime/ThreadContext;Lorg/jruby/runtime/builtin/IRubyObject;Lorg/jruby/runtime/builtin/IRubyObject;Lorg/jruby/runtime/builtin/IRubyObject;Lorg/jruby/runtime/Block;)Lorg/jruby/runtime/builtin/IRubyObject;
        //   352: pop            
        //   353: aload_0        
        //   354: bipush          16
        //   356: invokevirtual   ruby/jit/FILE_D901B762DF4AF11BEFBFDF3F5AE47863FA2F62D5.getCallSite:(I)Lorg/jruby/runtime/CallSite;
        //   359: aload_1        
        //   360: aload_2        
        //   361: aload_2        
        //   362: aload_0        
        //   363: aload_1        
        //   364: getfield        org/jruby/runtime/ThreadContext.runtime:Lorg/jruby/Ruby;
        //   367: ldc             "interfaces"
        //   369: invokevirtual   ruby/jit/FILE_D901B762DF4AF11BEFBFDF3F5AE47863FA2F62D5.getSymbol3:(Lorg/jruby/Ruby;Ljava/lang/String;)Lorg/jruby/RubySymbol;
        //   372: aload_1        
        //   373: aload_2        
        //   374: aload_0        
        //   375: aload_1        
        //   376: ldc             "block_3$RUBY$Configuration,-1,,false,0,./lib//lister/measurements/configuration.rb,41,true"
        //   378: invokevirtual   ruby/jit/FILE_D901B762DF4AF11BEFBFDF3F5AE47863FA2F62D5.getBlockBody3:(Lorg/jruby/runtime/ThreadContext;Ljava/lang/String;)Lorg/jruby/runtime/BlockBody;
        //   381: invokestatic    org/jruby/javasupport/util/RuntimeHelpers.createBlock:(Lorg/jruby/runtime/ThreadContext;Lorg/jruby/runtime/builtin/IRubyObject;Lorg/jruby/runtime/BlockBody;)Lorg/jruby/runtime/Block;
        //   384: invokevirtual   org/jruby/runtime/CallSite.callIter:(Lorg/jruby/runtime/ThreadContext;Lorg/jruby/runtime/builtin/IRubyObject;Lorg/jruby/runtime/builtin/IRubyObject;Lorg/jruby/runtime/builtin/IRubyObject;Lorg/jruby/runtime/Block;)Lorg/jruby/runtime/builtin/IRubyObject;
        //   387: pop            
        //   388: aload_0        
        //   389: bipush          19
        //   391: invokevirtual   ruby/jit/FILE_D901B762DF4AF11BEFBFDF3F5AE47863FA2F62D5.getCallSite:(I)Lorg/jruby/runtime/CallSite;
        //   394: aload_1        
        //   395: aload_2        
        //   396: aload_2        
        //   397: aload_0        
        //   398: aload_1        
        //   399: getfield        org/jruby/runtime/ThreadContext.runtime:Lorg/jruby/Ruby;
        //   402: ldc             "os"
        //   404: invokevirtual   ruby/jit/FILE_D901B762DF4AF11BEFBFDF3F5AE47863FA2F62D5.getSymbol1:(Lorg/jruby/Ruby;Ljava/lang/String;)Lorg/jruby/RubySymbol;
        //   407: aload_0        
        //   408: aload_1        
        //   409: getfield        org/jruby/runtime/ThreadContext.runtime:Lorg/jruby/Ruby;
        //   412: ldc             "net_config"
        //   414: invokevirtual   ruby/jit/FILE_D901B762DF4AF11BEFBFDF3F5AE47863FA2F62D5.getSymbol2:(Lorg/jruby/Ruby;Ljava/lang/String;)Lorg/jruby/RubySymbol;
        //   417: aload_0        
        //   418: aload_1        
        //   419: getfield        org/jruby/runtime/ThreadContext.runtime:Lorg/jruby/Ruby;
        //   422: ldc             "interfaces"
        //   424: invokevirtual   ruby/jit/FILE_D901B762DF4AF11BEFBFDF3F5AE47863FA2F62D5.getSymbol3:(Lorg/jruby/Ruby;Ljava/lang/String;)Lorg/jruby/RubySymbol;
        //   427: invokevirtual   org/jruby/runtime/CallSite.call:(Lorg/jruby/runtime/ThreadContext;Lorg/jruby/runtime/builtin/IRubyObject;Lorg/jruby/runtime/builtin/IRubyObject;Lorg/jruby/runtime/builtin/IRubyObject;Lorg/jruby/runtime/builtin/IRubyObject;Lorg/jruby/runtime/builtin/IRubyObject;)Lorg/jruby/runtime/builtin/IRubyObject;
        //   430: pop            
        //   431: aload_0        
        //   432: bipush          20
        //   434: invokevirtual   ruby/jit/FILE_D901B762DF4AF11BEFBFDF3F5AE47863FA2F62D5.getCallSite:(I)Lorg/jruby/runtime/CallSite;
        //   437: aload_1        
        //   438: aload_2        
        //   439: aload_2        
        //   440: aload_0        
        //   441: aload_1        
        //   442: getfield        org/jruby/runtime/ThreadContext.runtime:Lorg/jruby/Ruby;
        //   445: ldc             "interfaces_details"
        //   447: invokevirtual   ruby/jit/FILE_D901B762DF4AF11BEFBFDF3F5AE47863FA2F62D5.getSymbol4:(Lorg/jruby/Ruby;Ljava/lang/String;)Lorg/jruby/RubySymbol;
        //   450: aload_1        
        //   451: aload_2        
        //   452: aload_0        
        //   453: aload_1        
        //   454: ldc             "block_4$RUBY$Configuration,-1,,false,0,./lib//lister/measurements/configuration.rb,49,true"
        //   456: invokevirtual   ruby/jit/FILE_D901B762DF4AF11BEFBFDF3F5AE47863FA2F62D5.getBlockBody4:(Lorg/jruby/runtime/ThreadContext;Ljava/lang/String;)Lorg/jruby/runtime/BlockBody;
        //   459: invokestatic    org/jruby/javasupport/util/RuntimeHelpers.createBlock:(Lorg/jruby/runtime/ThreadContext;Lorg/jruby/runtime/builtin/IRubyObject;Lorg/jruby/runtime/BlockBody;)Lorg/jruby/runtime/Block;
        //   462: invokevirtual   org/jruby/runtime/CallSite.callIter:(Lorg/jruby/runtime/ThreadContext;Lorg/jruby/runtime/builtin/IRubyObject;Lorg/jruby/runtime/builtin/IRubyObject;Lorg/jruby/runtime/builtin/IRubyObject;Lorg/jruby/runtime/Block;)Lorg/jruby/runtime/builtin/IRubyObject;
        //   465: aload_1        
        //   466: invokevirtual   org/jruby/runtime/ThreadContext.postCompiledClass:()V
        //   469: goto            477
        //   472: aload_1        
        //   473: invokevirtual   org/jruby/runtime/ThreadContext.postCompiledClass:()V
        //   476: athrow         
        //   477: areturn        
        //    LocalVariableTable:
        //  Start  Length  Slot  Name    Signature
        //  -----  ------  ----  ------  --------------------------------
        //  55     423     4     locals  Lorg/jruby/runtime/DynamicScope;
        //    Exceptions:
        //  Try           Handler
        //  Start  End    Start  End    Type
        //  -----  -----  -----  -----  ----
        //  55     465    472    477    Any
        // 
        // The error that occurred was:
        // 
        // java.lang.ArrayIndexOutOfBoundsException
        // 
        throw new IllegalStateException("An error occurred while decompiling this method.");
    }
    
    public static IRubyObject block_0$RUBY$Configuration(final FILE_D901B762DF4AF11BEFBFDF3F5AE47863FA2F62D5 file_D901B762DF4AF11BEFBFDF3F5AE47863FA2F62D5, final ThreadContext threadContext, final IRubyObject rubyObject, final IRubyObject rubyObject2, final Block block) {
        threadContext.getCurrentScope();
        RuntimeHelpers.processBlockArgument(threadContext.runtime, block);
        file_D901B762DF4AF11BEFBFDF3F5AE47863FA2F62D5.getCallSite8().call(threadContext, rubyObject, rubyObject, file_D901B762DF4AF11BEFBFDF3F5AE47863FA2F62D5.getString(threadContext.runtime, 13, 32));
        return file_D901B762DF4AF11BEFBFDF3F5AE47863FA2F62D5.getCallSite9().call(threadContext, rubyObject, rubyObject, file_D901B762DF4AF11BEFBFDF3F5AE47863FA2F62D5.getString(threadContext.runtime, 14, 64), file_D901B762DF4AF11BEFBFDF3F5AE47863FA2F62D5.getString8(threadContext.runtime, 64));
    }
    
    public static IRubyObject block_1$RUBY$Configuration(final FILE_D901B762DF4AF11BEFBFDF3F5AE47863FA2F62D5 file_D901B762DF4AF11BEFBFDF3F5AE47863FA2F62D5, final ThreadContext threadContext, final IRubyObject rubyObject, final IRubyObject rubyObject2, final Block block) {
        threadContext.getCurrentScope();
        RuntimeHelpers.processBlockArgument(threadContext.runtime, block);
        file_D901B762DF4AF11BEFBFDF3F5AE47863FA2F62D5.getCallSite(11).call(threadContext, rubyObject, rubyObject, file_D901B762DF4AF11BEFBFDF3F5AE47863FA2F62D5.getString(threadContext.runtime, 15, 32));
        return file_D901B762DF4AF11BEFBFDF3F5AE47863FA2F62D5.getCallSite(12).call(threadContext, rubyObject, rubyObject, file_D901B762DF4AF11BEFBFDF3F5AE47863FA2F62D5.getString(threadContext.runtime, 16, 64), file_D901B762DF4AF11BEFBFDF3F5AE47863FA2F62D5.getString8(threadContext.runtime, 64));
    }
    
    public static IRubyObject block_2$RUBY$Configuration(final FILE_D901B762DF4AF11BEFBFDF3F5AE47863FA2F62D5 file_D901B762DF4AF11BEFBFDF3F5AE47863FA2F62D5, final ThreadContext threadContext, final IRubyObject rubyObject, final IRubyObject rubyObject2, final Block block) {
        threadContext.getCurrentScope();
        RuntimeHelpers.processBlockArgument(threadContext.runtime, block);
        file_D901B762DF4AF11BEFBFDF3F5AE47863FA2F62D5.getCallSite(14).call(threadContext, rubyObject, rubyObject, file_D901B762DF4AF11BEFBFDF3F5AE47863FA2F62D5.getString(threadContext.runtime, 17, 32));
        return file_D901B762DF4AF11BEFBFDF3F5AE47863FA2F62D5.getCallSite(15).call(threadContext, rubyObject, rubyObject, file_D901B762DF4AF11BEFBFDF3F5AE47863FA2F62D5.getString(threadContext.runtime, 18, 64), file_D901B762DF4AF11BEFBFDF3F5AE47863FA2F62D5.getString8(threadContext.runtime, 64));
    }
    
    public static IRubyObject block_3$RUBY$Configuration(final FILE_D901B762DF4AF11BEFBFDF3F5AE47863FA2F62D5 file_D901B762DF4AF11BEFBFDF3F5AE47863FA2F62D5, final ThreadContext threadContext, final IRubyObject rubyObject, final IRubyObject rubyObject2, final Block block) {
        threadContext.getCurrentScope();
        RuntimeHelpers.processBlockArgument(threadContext.runtime, block);
        file_D901B762DF4AF11BEFBFDF3F5AE47863FA2F62D5.getCallSite(17).call(threadContext, rubyObject, rubyObject, file_D901B762DF4AF11BEFBFDF3F5AE47863FA2F62D5.getString(threadContext.runtime, 19, 32));
        return file_D901B762DF4AF11BEFBFDF3F5AE47863FA2F62D5.getCallSite(18).call(threadContext, rubyObject, rubyObject, file_D901B762DF4AF11BEFBFDF3F5AE47863FA2F62D5.getString(threadContext.runtime, 20, 64), file_D901B762DF4AF11BEFBFDF3F5AE47863FA2F62D5.getString8(threadContext.runtime, 64));
    }
    
    public static IRubyObject block_4$RUBY$Configuration(final FILE_D901B762DF4AF11BEFBFDF3F5AE47863FA2F62D5 file_D901B762DF4AF11BEFBFDF3F5AE47863FA2F62D5, final ThreadContext threadContext, final IRubyObject rubyObject, final IRubyObject rubyObject2, final Block block) {
        threadContext.getCurrentScope();
        RuntimeHelpers.processBlockArgument(threadContext.runtime, block);
        file_D901B762DF4AF11BEFBFDF3F5AE47863FA2F62D5.getCallSite(21).call(threadContext, rubyObject, rubyObject, file_D901B762DF4AF11BEFBFDF3F5AE47863FA2F62D5.getString(threadContext.runtime, 21, 32));
        return file_D901B762DF4AF11BEFBFDF3F5AE47863FA2F62D5.getCallSite(22).call(threadContext, rubyObject, rubyObject, file_D901B762DF4AF11BEFBFDF3F5AE47863FA2F62D5.getString(threadContext.runtime, 22, 64), file_D901B762DF4AF11BEFBFDF3F5AE47863FA2F62D5.getString8(threadContext.runtime, 64));
    }
    
    public static IRubyObject class_2$RUBY$Configuration(final FILE_D901B762DF4AF11BEFBFDF3F5AE47863FA2F62D5 file_D901B762DF4AF11BEFBFDF3F5AE47863FA2F62D5, final ThreadContext threadContext, final IRubyObject rubyObject, final IRubyObject[] args, final Block block) {
        Arity.checkArgumentCount(threadContext.getRuntime(), args, 0, 0);
        return class_2$RUBY$Configuration(file_D901B762DF4AF11BEFBFDF3F5AE47863FA2F62D5, threadContext, rubyObject, block);
    }
    
    public static IRubyObject module__1$RUBY$Measurements(final FILE_D901B762DF4AF11BEFBFDF3F5AE47863FA2F62D5 file_D901B762DF4AF11BEFBFDF3F5AE47863FA2F62D5, final ThreadContext threadContext, final IRubyObject rubyObject, final IRubyObject[] args, final Block block) {
        Arity.checkArgumentCount(threadContext.getRuntime(), args, 0, 0);
        return module__1$RUBY$Measurements(file_D901B762DF4AF11BEFBFDF3F5AE47863FA2F62D5, threadContext, rubyObject, block);
    }
    
    public static IRubyObject module__0$RUBY$Lister(final FILE_D901B762DF4AF11BEFBFDF3F5AE47863FA2F62D5 file_D901B762DF4AF11BEFBFDF3F5AE47863FA2F62D5, final ThreadContext threadContext, final IRubyObject rubyObject, final IRubyObject[] args, final Block block) {
        Arity.checkArgumentCount(threadContext.getRuntime(), args, 0, 0);
        return module__0$RUBY$Lister(file_D901B762DF4AF11BEFBFDF3F5AE47863FA2F62D5, threadContext, rubyObject, block);
    }
    
    @Override
    public IRubyObject load(final ThreadContext context, final IRubyObject rubyObject, final IRubyObject[] array, final Block block) {
        try {
            RuntimeHelpers.preLoad(context, ",0,0,-2");
            final IRubyObject _file__ = __file__(this, context, rubyObject, array, block);
            RuntimeHelpers.postLoad(context);
            return _file__;
        }
        finally {
            RuntimeHelpers.postLoad(context);
        }
    }
    
    public static void main(final String[] argv) {
        final FILE_D901B762DF4AF11BEFBFDF3F5AE47863FA2F62D5 file_D901B762DF4AF11BEFBFDF3F5AE47863FA2F62D5 = new FILE_D901B762DF4AF11BEFBFDF3F5AE47863FA2F62D5();
        final String string = FILE_D901B762DF4AF11BEFBFDF3F5AE47863FA2F62D5.class.getClassLoader().getResource("ruby/jit/FILE_D901B762DF4AF11BEFBFDF3F5AE47863FA2F62D5.class").toString();
        file_D901B762DF4AF11BEFBFDF3F5AE47863FA2F62D5.setFilename(string);
        final RubyInstanceConfig config = new RubyInstanceConfig();
        config.setArgv(argv);
        config.setScriptFileName(string);
        final Ruby instance = Ruby.newInstance(config);
        file_D901B762DF4AF11BEFBFDF3F5AE47863FA2F62D5.load(instance.getCurrentContext(), instance.getTopSelf(), IRubyObject.NULL_ARRAY, Block.NULL_BLOCK);
    }
}
