// 
// Decompiled by Procyon v0.5.30
// 

package ruby.jit;

import org.jruby.Ruby;
import org.jruby.RubyInstanceConfig;
import org.jruby.ast.util.ArgsUtil;
import org.jruby.RubyBoolean;
import org.jruby.runtime.Arity;
import org.jruby.javasupport.util.RuntimeHelpers;
import org.jruby.anno.JRubyMethod;
import org.jruby.runtime.Block;
import org.jruby.runtime.builtin.IRubyObject;
import org.jruby.ast.executable.RuntimeCache;
import org.jruby.runtime.ThreadContext;
import org.jruby.ast.executable.AbstractScript;

public class FILE_585EF64F5F783DD4B3D9294B482D429011640F7A extends AbstractScript
{
    public FILE_585EF64F5F783DD4B3D9294B482D429011640F7A() {
        this.filename = "./lib//lister/runner/questionnaire/question_table_model.rb";
        super.runtimeCache = new RuntimeCache();
        this.initFromDescriptor("require\uffffF\uffffnew\uffffN\ufffftext_source=\uffffN\ufffftext_source=\uffffV\uffffdata=\uffffN\uffffdata=\uffffV\uffffattr_accessor\uffffF\uffffString\uffffN\ufffflang\uffffN\uffffjava\uffffV\uffffBoolean\uffffN\ufffflang\uffffN\uffffjava\uffffV\uffffattr_accessor\uffffF\uffffdata_model\uffffN\uffffclass\uffffN\uffffsize\uffffN\ufffffields\uffffN\uffffdata_model\uffffV\uffffsize\uffffN\uffffdata\uffffV\uffff[]\uffffN\uffffdata\uffffV\uffffsend\uffffN\uffffname\uffffN\uffff[]\uffffN\ufffffields\uffffN\uffffdata_model\uffffV\ufffftext_for_field\uffffN\ufffftext_source\uffffV\uffff[]\uffffN\ufffffields\uffffN\uffffdata_model\uffffV\uffffkind\uffffN\uffff[]\uffffN\ufffffields\uffffN\uffffdata_model\uffffV\uffff[]\uffffN\uffff[]\uffffN\uffffdata\uffffV\uffffsend\uffffN\uffffname\uffffN\uffff[]\uffffN\ufffffields\uffffN\uffffdata_model\uffffV\uffffrefresh\uffffV\uffffadd_item\uffffF\uffffnew\uffffN\uffffdata_model\uffffV\uffff<<\uffffN\uffffdata\uffffV\uffffrefresh\uffffV\uffffdup\uffffN\uffffdata\uffffV\uffffdelete_at\uffffN\uffffdata\uffffV\uffffrefresh\uffffV\uffffattr_reader\uffffF\uffffblk\uffffV\uffffcall\uffffN\uffffblk\uffffV\ufffffire_table_data_changed\uffffV\uffffAbstractTableModel\uffffN\ufffftable\uffffN\uffffswing\uffffN\uffffjavax\uffffV\uffff\u0002\u0005\u0000\u0000\u0001\u0000\u0000\u0002\u0003\u0000\u0000\u0000\u0002\u0001");
        this.setEncoding(0, "ASCII-8BIT");
        this.setByteList(0, "java", this.getEncoding0());
        this.setByteList(1, "=", this.getEncoding0());
    }
    
    @JRubyMethod(name = "__file__", frame = true, required = 0, optional = 0, rest = -2)
    public static IRubyObject __file__(final FILE_585EF64F5F783DD4B3D9294B482D429011640F7A file_585EF64F5F783DD4B3D9294B482D429011640F7A, final ThreadContext threadContext, final IRubyObject rubyObject, final IRubyObject[] array, final Block block) {
        file_585EF64F5F783DD4B3D9294B482D429011640F7A.getCallSite0().call(threadContext, rubyObject, rubyObject, file_585EF64F5F783DD4B3D9294B482D429011640F7A.getString0(threadContext.runtime, 32));
        return class_0$RUBY$QuestionTableModel(file_585EF64F5F783DD4B3D9294B482D429011640F7A, threadContext, file_585EF64F5F783DD4B3D9294B482D429011640F7A.getCallSite(62).call(threadContext, rubyObject, file_585EF64F5F783DD4B3D9294B482D429011640F7A.getCallSite(63).call(threadContext, rubyObject, file_585EF64F5F783DD4B3D9294B482D429011640F7A.getCallSite(64).call(threadContext, rubyObject, file_585EF64F5F783DD4B3D9294B482D429011640F7A.getCallSite(65).call(threadContext, rubyObject, rubyObject)))), Block.NULL_BLOCK);
    }
    
    @Override
    public IRubyObject __file__(final ThreadContext threadContext, final IRubyObject rubyObject, final IRubyObject[] array, final Block block) {
        return __file__(this, threadContext, rubyObject, array, block);
    }
    
    public static IRubyObject class_0$RUBY$QuestionTableModel(final FILE_585EF64F5F783DD4B3D9294B482D429011640F7A p0, final ThreadContext p1, final IRubyObject p2, final Block p3) {
        // 
        // This method could not be decompiled.
        // 
        // Original Bytecode:
        // 
        //     0: aload_1        
        //     1: getfield        org/jruby/runtime/ThreadContext.runtime:Lorg/jruby/Ruby;
        //     4: aload_2        
        //     5: invokestatic    org/jruby/javasupport/util/RuntimeHelpers.prepareSuperClass:(Lorg/jruby/Ruby;Lorg/jruby/runtime/builtin/IRubyObject;)Lorg/jruby/RubyClass;
        //     8: aload_1        
        //     9: aload_1        
        //    10: getfield        org/jruby/runtime/ThreadContext.nil:Lorg/jruby/runtime/builtin/IRubyObject;
        //    13: invokestatic    org/jruby/javasupport/util/RuntimeHelpers.prepareClassNamespace:(Lorg/jruby/runtime/ThreadContext;Lorg/jruby/runtime/builtin/IRubyObject;)Lorg/jruby/RubyModule;
        //    16: swap           
        //    17: ldc             "QuestionTableModel"
        //    19: swap           
        //    20: invokevirtual   org/jruby/RubyModule.defineOrGetClassUnder:(Ljava/lang/String;Lorg/jruby/RubyClass;)Lorg/jruby/RubyClass;
        //    23: dup            
        //    24: astore_2       
        //    25: aload_1        
        //    26: swap           
        //    27: aload_0        
        //    28: aload_1        
        //    29: ldc             ",0,0,-1"
        //    31: invokevirtual   ruby/jit/FILE_585EF64F5F783DD4B3D9294B482D429011640F7A.getScope0:(Lorg/jruby/runtime/ThreadContext;Ljava/lang/String;)Lorg/jruby/parser/StaticScope;
        //    34: invokevirtual   org/jruby/runtime/ThreadContext.preCompiledClassDummyScope:(Lorg/jruby/RubyModule;Lorg/jruby/parser/StaticScope;)V
        //    37: aload_0        
        //    38: aload_1        
        //    39: aload_2        
        //    40: getstatic       org/jruby/runtime/Block.NULL_BLOCK:Lorg/jruby/runtime/Block;
        //    43: invokestatic    ruby/jit/FILE_585EF64F5F783DD4B3D9294B482D429011640F7A.sclass_1$RUBY$__singleton__:(Lruby/jit/FILE_585EF64F5F783DD4B3D9294B482D429011640F7A;Lorg/jruby/runtime/ThreadContext;Lorg/jruby/runtime/builtin/IRubyObject;Lorg/jruby/runtime/Block;)Lorg/jruby/runtime/builtin/IRubyObject;
        //    46: pop            
        //    47: aload_0        
        //    48: invokevirtual   ruby/jit/FILE_585EF64F5F783DD4B3D9294B482D429011640F7A.getCallSite6:()Lorg/jruby/runtime/CallSite;
        //    51: aload_1        
        //    52: aload_2        
        //    53: aload_2        
        //    54: aload_0        
        //    55: aload_1        
        //    56: getfield        org/jruby/runtime/ThreadContext.runtime:Lorg/jruby/Ruby;
        //    59: ldc             "text_source"
        //    61: invokevirtual   ruby/jit/FILE_585EF64F5F783DD4B3D9294B482D429011640F7A.getSymbol0:(Lorg/jruby/Ruby;Ljava/lang/String;)Lorg/jruby/RubySymbol;
        //    64: invokevirtual   org/jruby/runtime/CallSite.call:(Lorg/jruby/runtime/ThreadContext;Lorg/jruby/runtime/builtin/IRubyObject;Lorg/jruby/runtime/builtin/IRubyObject;Lorg/jruby/runtime/builtin/IRubyObject;)Lorg/jruby/runtime/builtin/IRubyObject;
        //    67: pop            
        //    68: aload_1        
        //    69: getfield        org/jruby/runtime/ThreadContext.runtime:Lorg/jruby/Ruby;
        //    72: aload_0        
        //    73: aload_1        
        //    74: getfield        org/jruby/runtime/ThreadContext.runtime:Lorg/jruby/Ruby;
        //    77: ldc             "string"
        //    79: invokevirtual   ruby/jit/FILE_585EF64F5F783DD4B3D9294B482D429011640F7A.getSymbol1:(Lorg/jruby/Ruby;Ljava/lang/String;)Lorg/jruby/RubySymbol;
        //    82: aload_0        
        //    83: invokevirtual   ruby/jit/FILE_585EF64F5F783DD4B3D9294B482D429011640F7A.getCallSite7:()Lorg/jruby/runtime/CallSite;
        //    86: aload_1        
        //    87: aload_2        
        //    88: aload_0        
        //    89: invokevirtual   ruby/jit/FILE_585EF64F5F783DD4B3D9294B482D429011640F7A.getCallSite8:()Lorg/jruby/runtime/CallSite;
        //    92: aload_1        
        //    93: aload_2        
        //    94: aload_0        
        //    95: invokevirtual   ruby/jit/FILE_585EF64F5F783DD4B3D9294B482D429011640F7A.getCallSite9:()Lorg/jruby/runtime/CallSite;
        //    98: aload_1        
        //    99: aload_2        
        //   100: aload_2        
        //   101: invokevirtual   org/jruby/runtime/CallSite.call:(Lorg/jruby/runtime/ThreadContext;Lorg/jruby/runtime/builtin/IRubyObject;Lorg/jruby/runtime/builtin/IRubyObject;)Lorg/jruby/runtime/builtin/IRubyObject;
        //   104: invokevirtual   org/jruby/runtime/CallSite.call:(Lorg/jruby/runtime/ThreadContext;Lorg/jruby/runtime/builtin/IRubyObject;Lorg/jruby/runtime/builtin/IRubyObject;)Lorg/jruby/runtime/builtin/IRubyObject;
        //   107: invokevirtual   org/jruby/runtime/CallSite.call:(Lorg/jruby/runtime/ThreadContext;Lorg/jruby/runtime/builtin/IRubyObject;Lorg/jruby/runtime/builtin/IRubyObject;)Lorg/jruby/runtime/builtin/IRubyObject;
        //   110: aload_0        
        //   111: aload_1        
        //   112: getfield        org/jruby/runtime/ThreadContext.runtime:Lorg/jruby/Ruby;
        //   115: ldc             "boolean"
        //   117: invokevirtual   ruby/jit/FILE_585EF64F5F783DD4B3D9294B482D429011640F7A.getSymbol2:(Lorg/jruby/Ruby;Ljava/lang/String;)Lorg/jruby/RubySymbol;
        //   120: aload_0        
        //   121: bipush          10
        //   123: invokevirtual   ruby/jit/FILE_585EF64F5F783DD4B3D9294B482D429011640F7A.getCallSite:(I)Lorg/jruby/runtime/CallSite;
        //   126: aload_1        
        //   127: aload_2        
        //   128: aload_0        
        //   129: bipush          11
        //   131: invokevirtual   ruby/jit/FILE_585EF64F5F783DD4B3D9294B482D429011640F7A.getCallSite:(I)Lorg/jruby/runtime/CallSite;
        //   134: aload_1        
        //   135: aload_2        
        //   136: aload_0        
        //   137: bipush          12
        //   139: invokevirtual   ruby/jit/FILE_585EF64F5F783DD4B3D9294B482D429011640F7A.getCallSite:(I)Lorg/jruby/runtime/CallSite;
        //   142: aload_1        
        //   143: aload_2        
        //   144: aload_2        
        //   145: invokevirtual   org/jruby/runtime/CallSite.call:(Lorg/jruby/runtime/ThreadContext;Lorg/jruby/runtime/builtin/IRubyObject;Lorg/jruby/runtime/builtin/IRubyObject;)Lorg/jruby/runtime/builtin/IRubyObject;
        //   148: invokevirtual   org/jruby/runtime/CallSite.call:(Lorg/jruby/runtime/ThreadContext;Lorg/jruby/runtime/builtin/IRubyObject;Lorg/jruby/runtime/builtin/IRubyObject;)Lorg/jruby/runtime/builtin/IRubyObject;
        //   151: invokevirtual   org/jruby/runtime/CallSite.call:(Lorg/jruby/runtime/ThreadContext;Lorg/jruby/runtime/builtin/IRubyObject;Lorg/jruby/runtime/builtin/IRubyObject;)Lorg/jruby/runtime/builtin/IRubyObject;
        //   154: invokestatic    org/jruby/javasupport/util/RuntimeHelpers.constructHash:(Lorg/jruby/Ruby;Lorg/jruby/runtime/builtin/IRubyObject;Lorg/jruby/runtime/builtin/IRubyObject;Lorg/jruby/runtime/builtin/IRubyObject;Lorg/jruby/runtime/builtin/IRubyObject;)Lorg/jruby/RubyHash;
        //   157: aload_1        
        //   158: ldc_w           "MAPPING"
        //   161: invokestatic    org/jruby/javasupport/util/RuntimeHelpers.setConstantInCurrent:(Lorg/jruby/runtime/builtin/IRubyObject;Lorg/jruby/runtime/ThreadContext;Ljava/lang/String;)Lorg/jruby/runtime/builtin/IRubyObject;
        //   164: pop            
        //   165: aload_0        
        //   166: bipush          13
        //   168: invokevirtual   ruby/jit/FILE_585EF64F5F783DD4B3D9294B482D429011640F7A.getCallSite:(I)Lorg/jruby/runtime/CallSite;
        //   171: aload_1        
        //   172: aload_2        
        //   173: aload_2        
        //   174: aload_0        
        //   175: aload_1        
        //   176: getfield        org/jruby/runtime/ThreadContext.runtime:Lorg/jruby/Ruby;
        //   179: ldc_w           "data"
        //   182: invokevirtual   ruby/jit/FILE_585EF64F5F783DD4B3D9294B482D429011640F7A.getSymbol3:(Lorg/jruby/Ruby;Ljava/lang/String;)Lorg/jruby/RubySymbol;
        //   185: invokevirtual   org/jruby/runtime/CallSite.call:(Lorg/jruby/runtime/ThreadContext;Lorg/jruby/runtime/builtin/IRubyObject;Lorg/jruby/runtime/builtin/IRubyObject;Lorg/jruby/runtime/builtin/IRubyObject;)Lorg/jruby/runtime/builtin/IRubyObject;
        //   188: pop            
        //   189: aload_1        
        //   190: aload_2        
        //   191: aload_0        
        //   192: ldc             "data_model"
        //   194: ldc_w           "method__4$RUBY$data_model"
        //   197: ldc             ",0,0,-1"
        //   199: iconst_0       
        //   200: ldc             "./lib//lister/runner/questionnaire/question_table_model.rb"
        //   202: ldc_w           31
        //   205: getstatic       org/jruby/internal/runtime/methods/CallConfiguration.FrameNoneScopeNone:Lorg/jruby/internal/runtime/methods/CallConfiguration;
        //   208: ldc_w           "NONE"
        //   211: invokestatic    org/jruby/javasupport/util/RuntimeHelpers.def:(Lorg/jruby/runtime/ThreadContext;Lorg/jruby/runtime/builtin/IRubyObject;Ljava/lang/Object;Ljava/lang/String;Ljava/lang/String;Ljava/lang/String;ILjava/lang/String;ILorg/jruby/internal/runtime/methods/CallConfiguration;Ljava/lang/String;)Lorg/jruby/runtime/builtin/IRubyObject;
        //   214: pop            
        //   215: aload_1        
        //   216: aload_2        
        //   217: aload_0        
        //   218: ldc_w           "getColumnCount"
        //   221: ldc_w           "method__5$RUBY$getColumnCount"
        //   224: ldc             ",0,0,-1"
        //   226: iconst_0       
        //   227: ldc             "./lib//lister/runner/questionnaire/question_table_model.rb"
        //   229: ldc_w           37
        //   232: getstatic       org/jruby/internal/runtime/methods/CallConfiguration.FrameNoneScopeNone:Lorg/jruby/internal/runtime/methods/CallConfiguration;
        //   235: ldc_w           "NONE"
        //   238: invokestatic    org/jruby/javasupport/util/RuntimeHelpers.def:(Lorg/jruby/runtime/ThreadContext;Lorg/jruby/runtime/builtin/IRubyObject;Ljava/lang/Object;Ljava/lang/String;Ljava/lang/String;Ljava/lang/String;ILjava/lang/String;ILorg/jruby/internal/runtime/methods/CallConfiguration;Ljava/lang/String;)Lorg/jruby/runtime/builtin/IRubyObject;
        //   241: pop            
        //   242: aload_1        
        //   243: aload_2        
        //   244: aload_0        
        //   245: ldc_w           "getRowCount"
        //   248: ldc_w           "method__6$RUBY$getRowCount"
        //   251: ldc             ",0,0,-1"
        //   253: iconst_0       
        //   254: ldc             "./lib//lister/runner/questionnaire/question_table_model.rb"
        //   256: ldc_w           41
        //   259: getstatic       org/jruby/internal/runtime/methods/CallConfiguration.FrameNoneScopeNone:Lorg/jruby/internal/runtime/methods/CallConfiguration;
        //   262: ldc_w           "NONE"
        //   265: invokestatic    org/jruby/javasupport/util/RuntimeHelpers.def:(Lorg/jruby/runtime/ThreadContext;Lorg/jruby/runtime/builtin/IRubyObject;Ljava/lang/Object;Ljava/lang/String;Ljava/lang/String;Ljava/lang/String;ILjava/lang/String;ILorg/jruby/internal/runtime/methods/CallConfiguration;Ljava/lang/String;)Lorg/jruby/runtime/builtin/IRubyObject;
        //   268: pop            
        //   269: aload_1        
        //   270: aload_2        
        //   271: aload_0        
        //   272: ldc_w           "getValueAt"
        //   275: ldc_w           "method__7$RUBY$getValueAt"
        //   278: ldc_w           "y;x;item,2,0,-1"
        //   281: iconst_2       
        //   282: ldc             "./lib//lister/runner/questionnaire/question_table_model.rb"
        //   284: ldc_w           45
        //   287: getstatic       org/jruby/internal/runtime/methods/CallConfiguration.FrameNoneScopeFull:Lorg/jruby/internal/runtime/methods/CallConfiguration;
        //   290: ldc_w           "qy;qx"
        //   293: invokestatic    org/jruby/javasupport/util/RuntimeHelpers.def:(Lorg/jruby/runtime/ThreadContext;Lorg/jruby/runtime/builtin/IRubyObject;Ljava/lang/Object;Ljava/lang/String;Ljava/lang/String;Ljava/lang/String;ILjava/lang/String;ILorg/jruby/internal/runtime/methods/CallConfiguration;Ljava/lang/String;)Lorg/jruby/runtime/builtin/IRubyObject;
        //   296: pop            
        //   297: aload_1        
        //   298: aload_2        
        //   299: aload_0        
        //   300: ldc_w           "getColumnName"
        //   303: ldc_w           "method__8$RUBY$getColumnName"
        //   306: ldc_w           "x,1,0,-1"
        //   309: iconst_1       
        //   310: ldc             "./lib//lister/runner/questionnaire/question_table_model.rb"
        //   312: ldc_w           50
        //   315: getstatic       org/jruby/internal/runtime/methods/CallConfiguration.FrameNoneScopeFull:Lorg/jruby/internal/runtime/methods/CallConfiguration;
        //   318: ldc_w           "qx"
        //   321: invokestatic    org/jruby/javasupport/util/RuntimeHelpers.def:(Lorg/jruby/runtime/ThreadContext;Lorg/jruby/runtime/builtin/IRubyObject;Ljava/lang/Object;Ljava/lang/String;Ljava/lang/String;Ljava/lang/String;ILjava/lang/String;ILorg/jruby/internal/runtime/methods/CallConfiguration;Ljava/lang/String;)Lorg/jruby/runtime/builtin/IRubyObject;
        //   324: pop            
        //   325: aload_1        
        //   326: aload_2        
        //   327: aload_0        
        //   328: ldc_w           "getColumnClass"
        //   331: ldc_w           "method__9$RUBY$getColumnClass"
        //   334: ldc_w           "x;kind,1,0,-1"
        //   337: iconst_1       
        //   338: ldc             "./lib//lister/runner/questionnaire/question_table_model.rb"
        //   340: ldc_w           54
        //   343: getstatic       org/jruby/internal/runtime/methods/CallConfiguration.FrameNoneScopeFull:Lorg/jruby/internal/runtime/methods/CallConfiguration;
        //   346: ldc_w           "qx"
        //   349: invokestatic    org/jruby/javasupport/util/RuntimeHelpers.def:(Lorg/jruby/runtime/ThreadContext;Lorg/jruby/runtime/builtin/IRubyObject;Ljava/lang/Object;Ljava/lang/String;Ljava/lang/String;Ljava/lang/String;ILjava/lang/String;ILorg/jruby/internal/runtime/methods/CallConfiguration;Ljava/lang/String;)Lorg/jruby/runtime/builtin/IRubyObject;
        //   352: pop            
        //   353: aload_1        
        //   354: aload_2        
        //   355: aload_0        
        //   356: ldc_w           "isCellEditable"
        //   359: ldc_w           "method__10$RUBY$isCellEditable"
        //   362: ldc_w           "y;x,2,0,-1"
        //   365: iconst_2       
        //   366: ldc             "./lib//lister/runner/questionnaire/question_table_model.rb"
        //   368: ldc_w           59
        //   371: getstatic       org/jruby/internal/runtime/methods/CallConfiguration.FrameNoneScopeNone:Lorg/jruby/internal/runtime/methods/CallConfiguration;
        //   374: ldc_w           "qy;qx"
        //   377: invokestatic    org/jruby/javasupport/util/RuntimeHelpers.def:(Lorg/jruby/runtime/ThreadContext;Lorg/jruby/runtime/builtin/IRubyObject;Ljava/lang/Object;Ljava/lang/String;Ljava/lang/String;Ljava/lang/String;ILjava/lang/String;ILorg/jruby/internal/runtime/methods/CallConfiguration;Ljava/lang/String;)Lorg/jruby/runtime/builtin/IRubyObject;
        //   380: pop            
        //   381: aload_1        
        //   382: aload_2        
        //   383: aload_0        
        //   384: ldc_w           "setValueAt"
        //   387: ldc_w           "method__11$RUBY$setValueAt"
        //   390: ldc_w           "val;y;x;item,3,0,-1"
        //   393: iconst_3       
        //   394: ldc             "./lib//lister/runner/questionnaire/question_table_model.rb"
        //   396: ldc_w           63
        //   399: getstatic       org/jruby/internal/runtime/methods/CallConfiguration.FrameNoneScopeFull:Lorg/jruby/internal/runtime/methods/CallConfiguration;
        //   402: ldc_w           "qval;qy;qx"
        //   405: invokestatic    org/jruby/javasupport/util/RuntimeHelpers.def:(Lorg/jruby/runtime/ThreadContext;Lorg/jruby/runtime/builtin/IRubyObject;Ljava/lang/Object;Ljava/lang/String;Ljava/lang/String;Ljava/lang/String;ILjava/lang/String;ILorg/jruby/internal/runtime/methods/CallConfiguration;Ljava/lang/String;)Lorg/jruby/runtime/builtin/IRubyObject;
        //   408: pop            
        //   409: aload_1        
        //   410: aload_2        
        //   411: aload_0        
        //   412: ldc_w           "create_item"
        //   415: ldc_w           "method__12$RUBY$create_item"
        //   418: ldc_w           "args,0,0,0"
        //   421: iconst_m1      
        //   422: ldc             "./lib//lister/runner/questionnaire/question_table_model.rb"
        //   424: ldc_w           71
        //   427: getstatic       org/jruby/internal/runtime/methods/CallConfiguration.FrameNoneScopeNone:Lorg/jruby/internal/runtime/methods/CallConfiguration;
        //   430: ldc_w           "rargs"
        //   433: invokestatic    org/jruby/javasupport/util/RuntimeHelpers.def:(Lorg/jruby/runtime/ThreadContext;Lorg/jruby/runtime/builtin/IRubyObject;Ljava/lang/Object;Ljava/lang/String;Ljava/lang/String;Ljava/lang/String;ILjava/lang/String;ILorg/jruby/internal/runtime/methods/CallConfiguration;Ljava/lang/String;)Lorg/jruby/runtime/builtin/IRubyObject;
        //   436: pop            
        //   437: aload_1        
        //   438: aload_2        
        //   439: aload_0        
        //   440: ldc_w           "add_item"
        //   443: ldc_w           "method__13$RUBY$add_item"
        //   446: ldc_w           "item,1,0,-1"
        //   449: iconst_1       
        //   450: ldc             "./lib//lister/runner/questionnaire/question_table_model.rb"
        //   452: ldc_w           75
        //   455: getstatic       org/jruby/internal/runtime/methods/CallConfiguration.FrameNoneScopeNone:Lorg/jruby/internal/runtime/methods/CallConfiguration;
        //   458: ldc_w           "qitem"
        //   461: invokestatic    org/jruby/javasupport/util/RuntimeHelpers.def:(Lorg/jruby/runtime/ThreadContext;Lorg/jruby/runtime/builtin/IRubyObject;Ljava/lang/Object;Ljava/lang/String;Ljava/lang/String;Ljava/lang/String;ILjava/lang/String;ILorg/jruby/internal/runtime/methods/CallConfiguration;Ljava/lang/String;)Lorg/jruby/runtime/builtin/IRubyObject;
        //   464: pop            
        //   465: aload_1        
        //   466: aload_2        
        //   467: aload_0        
        //   468: ldc_w           "delete_item_at_idx"
        //   471: ldc_w           "method__14$RUBY$delete_item_at_idx"
        //   474: ldc_w           "idx,1,0,-1"
        //   477: iconst_1       
        //   478: ldc             "./lib//lister/runner/questionnaire/question_table_model.rb"
        //   480: ldc_w           80
        //   483: getstatic       org/jruby/internal/runtime/methods/CallConfiguration.FrameNoneScopeNone:Lorg/jruby/internal/runtime/methods/CallConfiguration;
        //   486: ldc_w           "qidx"
        //   489: invokestatic    org/jruby/javasupport/util/RuntimeHelpers.def:(Lorg/jruby/runtime/ThreadContext;Lorg/jruby/runtime/builtin/IRubyObject;Ljava/lang/Object;Ljava/lang/String;Ljava/lang/String;Ljava/lang/String;ILjava/lang/String;ILorg/jruby/internal/runtime/methods/CallConfiguration;Ljava/lang/String;)Lorg/jruby/runtime/builtin/IRubyObject;
        //   492: pop            
        //   493: aload_0        
        //   494: bipush          57
        //   496: invokevirtual   ruby/jit/FILE_585EF64F5F783DD4B3D9294B482D429011640F7A.getCallSite:(I)Lorg/jruby/runtime/CallSite;
        //   499: aload_1        
        //   500: aload_2        
        //   501: aload_2        
        //   502: aload_0        
        //   503: aload_1        
        //   504: getfield        org/jruby/runtime/ThreadContext.runtime:Lorg/jruby/Ruby;
        //   507: ldc_w           "blk"
        //   510: invokevirtual   ruby/jit/FILE_585EF64F5F783DD4B3D9294B482D429011640F7A.getSymbol4:(Lorg/jruby/Ruby;Ljava/lang/String;)Lorg/jruby/RubySymbol;
        //   513: invokevirtual   org/jruby/runtime/CallSite.call:(Lorg/jruby/runtime/ThreadContext;Lorg/jruby/runtime/builtin/IRubyObject;Lorg/jruby/runtime/builtin/IRubyObject;Lorg/jruby/runtime/builtin/IRubyObject;)Lorg/jruby/runtime/builtin/IRubyObject;
        //   516: pop            
        //   517: aload_1        
        //   518: aload_2        
        //   519: aload_0        
        //   520: ldc_w           "refresh"
        //   523: ldc_w           "method__15$RUBY$refresh"
        //   526: ldc             ",0,0,-1"
        //   528: iconst_0       
        //   529: ldc             "./lib//lister/runner/questionnaire/question_table_model.rb"
        //   531: ldc_w           88
        //   534: getstatic       org/jruby/internal/runtime/methods/CallConfiguration.FrameNoneScopeNone:Lorg/jruby/internal/runtime/methods/CallConfiguration;
        //   537: ldc_w           "NONE"
        //   540: invokestatic    org/jruby/javasupport/util/RuntimeHelpers.def:(Lorg/jruby/runtime/ThreadContext;Lorg/jruby/runtime/builtin/IRubyObject;Ljava/lang/Object;Ljava/lang/String;Ljava/lang/String;Ljava/lang/String;ILjava/lang/String;ILorg/jruby/internal/runtime/methods/CallConfiguration;Ljava/lang/String;)Lorg/jruby/runtime/builtin/IRubyObject;
        //   543: pop            
        //   544: aload_1        
        //   545: aload_2        
        //   546: aload_0        
        //   547: ldc_w           "on_data_change"
        //   550: ldc_w           "method__16$RUBY$on_data_change"
        //   553: ldc_w           "blk,0,0,-1"
        //   556: iconst_0       
        //   557: ldc             "./lib//lister/runner/questionnaire/question_table_model.rb"
        //   559: ldc_w           93
        //   562: getstatic       org/jruby/internal/runtime/methods/CallConfiguration.FrameNoneScopeNone:Lorg/jruby/internal/runtime/methods/CallConfiguration;
        //   565: ldc_w           "bblk"
        //   568: invokestatic    org/jruby/javasupport/util/RuntimeHelpers.def:(Lorg/jruby/runtime/ThreadContext;Lorg/jruby/runtime/builtin/IRubyObject;Ljava/lang/Object;Ljava/lang/String;Ljava/lang/String;Ljava/lang/String;ILjava/lang/String;ILorg/jruby/internal/runtime/methods/CallConfiguration;Ljava/lang/String;)Lorg/jruby/runtime/builtin/IRubyObject;
        //   571: aload_1        
        //   572: invokevirtual   org/jruby/runtime/ThreadContext.postCompiledClass:()V
        //   575: goto            583
        //   578: aload_1        
        //   579: invokevirtual   org/jruby/runtime/ThreadContext.postCompiledClass:()V
        //   582: athrow         
        //   583: areturn        
        //    Exceptions:
        //  Try           Handler
        //  Start  End    Start  End    Type
        //  -----  -----  -----  -----  ----
        //  37     571    578    583    Any
        // 
        // The error that occurred was:
        // 
        // java.lang.ArrayIndexOutOfBoundsException
        // 
        throw new IllegalStateException("An error occurred while decompiling this method.");
    }
    
    public static IRubyObject sclass_1$RUBY$__singleton__(final FILE_585EF64F5F783DD4B3D9294B482D429011640F7A p0, final ThreadContext p1, final IRubyObject p2, final Block p3) {
        // 
        // This method could not be decompiled.
        // 
        // Original Bytecode:
        // 
        //     0: aload_1        
        //     1: getfield        org/jruby/runtime/ThreadContext.runtime:Lorg/jruby/Ruby;
        //     4: aload_2        
        //     5: astore          8
        //     7: aload_2        
        //     8: invokestatic    org/jruby/javasupport/util/RuntimeHelpers.getSingletonClass:(Lorg/jruby/Ruby;Lorg/jruby/runtime/builtin/IRubyObject;)Lorg/jruby/RubyClass;
        //    11: dup            
        //    12: astore_2       
        //    13: aload_1        
        //    14: swap           
        //    15: aload_0        
        //    16: aload_1        
        //    17: ldc             ",0,0,-1"
        //    19: invokevirtual   ruby/jit/FILE_585EF64F5F783DD4B3D9294B482D429011640F7A.getScope1:(Lorg/jruby/runtime/ThreadContext;Ljava/lang/String;)Lorg/jruby/parser/StaticScope;
        //    22: invokevirtual   org/jruby/runtime/ThreadContext.preCompiledClassDummyScope:(Lorg/jruby/RubyModule;Lorg/jruby/parser/StaticScope;)V
        //    25: aload_1        
        //    26: aload_2        
        //    27: aload_0        
        //    28: ldc             "data_model"
        //    30: ldc             "method__2$RUBY$data_model"
        //    32: ldc             "val,0,1,-1"
        //    34: iconst_m1      
        //    35: ldc             "./lib//lister/runner/questionnaire/question_table_model.rb"
        //    37: ldc             7
        //    39: getstatic       org/jruby/internal/runtime/methods/CallConfiguration.FrameNoneScopeNone:Lorg/jruby/internal/runtime/methods/CallConfiguration;
        //    42: ldc             "oval"
        //    44: invokestatic    org/jruby/javasupport/util/RuntimeHelpers.def:(Lorg/jruby/runtime/ThreadContext;Lorg/jruby/runtime/builtin/IRubyObject;Ljava/lang/Object;Ljava/lang/String;Ljava/lang/String;Ljava/lang/String;ILjava/lang/String;ILorg/jruby/internal/runtime/methods/CallConfiguration;Ljava/lang/String;)Lorg/jruby/runtime/builtin/IRubyObject;
        //    47: pop            
        //    48: aload_1        
        //    49: aload_2        
        //    50: aload_0        
        //    51: ldc             "create"
        //    53: ldc             "method__3$RUBY$create"
        //    55: ldc             "txt_src;obj,1,0,-1"
        //    57: iconst_1       
        //    58: ldc             "./lib//lister/runner/questionnaire/question_table_model.rb"
        //    60: ldc             15
        //    62: getstatic       org/jruby/internal/runtime/methods/CallConfiguration.FrameFullScopeNone:Lorg/jruby/internal/runtime/methods/CallConfiguration;
        //    65: ldc             "qtxt_src"
        //    67: invokestatic    org/jruby/javasupport/util/RuntimeHelpers.def:(Lorg/jruby/runtime/ThreadContext;Lorg/jruby/runtime/builtin/IRubyObject;Ljava/lang/Object;Ljava/lang/String;Ljava/lang/String;Ljava/lang/String;ILjava/lang/String;ILorg/jruby/internal/runtime/methods/CallConfiguration;Ljava/lang/String;)Lorg/jruby/runtime/builtin/IRubyObject;
        //    70: aload_1        
        //    71: invokevirtual   org/jruby/runtime/ThreadContext.postCompiledClass:()V
        //    74: goto            82
        //    77: aload_1        
        //    78: invokevirtual   org/jruby/runtime/ThreadContext.postCompiledClass:()V
        //    81: athrow         
        //    82: areturn        
        //    Exceptions:
        //  Try           Handler
        //  Start  End    Start  End    Type
        //  -----  -----  -----  -----  ----
        //  25     70     77     82     Any
        // 
        // The error that occurred was:
        // 
        // java.lang.ArrayIndexOutOfBoundsException
        // 
        throw new IllegalStateException("An error occurred while decompiling this method.");
    }
    
    @JRubyMethod(name = "data_model", frame = true, required = 0, optional = 1, rest = -1)
    public static IRubyObject method__2$RUBY$data_model(final FILE_585EF64F5F783DD4B3D9294B482D429011640F7A p0, final ThreadContext p1, final IRubyObject p2, final IRubyObject[] p3, final Block p4) {
        // 
        // This method could not be decompiled.
        // 
        // Original Bytecode:
        // 
        //     0: aload_1        
        //     1: getfield        org/jruby/runtime/ThreadContext.nil:Lorg/jruby/runtime/builtin/IRubyObject;
        //     4: astore          9
        //     6: aload_1        
        //     7: getfield        org/jruby/runtime/ThreadContext.runtime:Lorg/jruby/Ruby;
        //    10: aload_3        
        //    11: iconst_0       
        //    12: iconst_1       
        //    13: invokestatic    org/jruby/runtime/Arity.raiseArgumentError:(Lorg/jruby/Ruby;[Lorg/jruby/runtime/builtin/IRubyObject;II)V
        //    16: aload_3        
        //    17: iconst_0       
        //    18: invokestatic    org/jruby/javasupport/util/RuntimeHelpers.elementOrNull:([Lorg/jruby/runtime/builtin/IRubyObject;I)Lorg/jruby/runtime/builtin/IRubyObject;
        //    21: dup            
        //    22: ifnull          30
        //    25: astore          9
        //    27: goto            37
        //    30: aload_1        
        //    31: getfield        org/jruby/runtime/ThreadContext.nil:Lorg/jruby/runtime/builtin/IRubyObject;
        //    34: astore          9
        //    36: pop            
        //    37: aload           val
        //    39: invokeinterface org/jruby/runtime/builtin/IRubyObject.isTrue:()Z
        //    44: ifeq            63
        //    47: aload_0        
        //    48: aload_1        
        //    49: getfield        org/jruby/runtime/ThreadContext.runtime:Lorg/jruby/Ruby;
        //    52: ldc             "@data_model"
        //    54: aload_2        
        //    55: aload           val
        //    57: invokevirtual   ruby/jit/FILE_585EF64F5F783DD4B3D9294B482D429011640F7A.setVariable0:(Lorg/jruby/Ruby;Ljava/lang/String;Lorg/jruby/runtime/builtin/IRubyObject;Lorg/jruby/runtime/builtin/IRubyObject;)Lorg/jruby/runtime/builtin/IRubyObject;
        //    60: goto            74
        //    63: aload_0        
        //    64: aload_1        
        //    65: getfield        org/jruby/runtime/ThreadContext.runtime:Lorg/jruby/Ruby;
        //    68: ldc             "@data_model"
        //    70: aload_2        
        //    71: invokevirtual   ruby/jit/FILE_585EF64F5F783DD4B3D9294B482D429011640F7A.getVariable0:(Lorg/jruby/Ruby;Ljava/lang/String;Lorg/jruby/runtime/builtin/IRubyObject;)Lorg/jruby/runtime/builtin/IRubyObject;
        //    74: areturn        
        //    LocalVariableTable:
        //  Start  Length  Slot  Name  Signature
        //  -----  ------  ----  ----  ---------------------------------------
        //  37     38      9     val   Lorg/jruby/runtime/builtin/IRubyObject;
        // 
        // The error that occurred was:
        // 
        // java.lang.IndexOutOfBoundsException: Index: 0, Size: 0
        //     at java.util.ArrayList.rangeCheck(ArrayList.java:657)
        //     at java.util.ArrayList.get(ArrayList.java:433)
        //     at com.strobel.decompiler.ast.AstBuilder.convertLocalVariables(AstBuilder.java:3035)
        //     at com.strobel.decompiler.ast.AstBuilder.performStackAnalysis(AstBuilder.java:2445)
        //     at com.strobel.decompiler.ast.AstBuilder.build(AstBuilder.java:108)
        //     at com.strobel.decompiler.languages.java.ast.AstMethodBodyBuilder.createMethodBody(AstMethodBodyBuilder.java:210)
        //     at com.strobel.decompiler.languages.java.ast.AstMethodBodyBuilder.createMethodBody(AstMethodBodyBuilder.java:99)
        //     at com.strobel.decompiler.languages.java.ast.AstBuilder.createMethodBody(AstBuilder.java:757)
        //     at com.strobel.decompiler.languages.java.ast.AstBuilder.createMethod(AstBuilder.java:655)
        //     at com.strobel.decompiler.languages.java.ast.AstBuilder.addTypeMembers(AstBuilder.java:532)
        //     at com.strobel.decompiler.languages.java.ast.AstBuilder.createTypeCore(AstBuilder.java:499)
        //     at com.strobel.decompiler.languages.java.ast.AstBuilder.createTypeNoCache(AstBuilder.java:141)
        //     at com.strobel.decompiler.languages.java.ast.AstBuilder.createType(AstBuilder.java:130)
        //     at com.strobel.decompiler.languages.java.ast.AstBuilder.addType(AstBuilder.java:105)
        //     at com.strobel.decompiler.languages.java.JavaLanguage.buildAst(JavaLanguage.java:71)
        //     at com.strobel.decompiler.languages.java.JavaLanguage.decompileType(JavaLanguage.java:59)
        //     at com.strobel.decompiler.DecompilerDriver.decompileType(DecompilerDriver.java:317)
        //     at com.strobel.decompiler.DecompilerDriver.decompileJar(DecompilerDriver.java:238)
        //     at com.strobel.decompiler.DecompilerDriver.main(DecompilerDriver.java:138)
        // 
        throw new IllegalStateException("An error occurred while decompiling this method.");
    }
    
    @JRubyMethod(name = "create", frame = true, required = 1, optional = 0, rest = -1)
    public static IRubyObject method__3$RUBY$create(final FILE_585EF64F5F783DD4B3D9294B482D429011640F7A file_585EF64F5F783DD4B3D9294B482D429011640F7A, final ThreadContext threadContext, final IRubyObject rubyObject, final IRubyObject value, final Block block) {
        final IRubyObject nil = threadContext.nil;
        final IRubyObject call;
        final IRubyObject obj = call = file_585EF64F5F783DD4B3D9294B482D429011640F7A.getCallSite1().call(threadContext, rubyObject, rubyObject);
        RuntimeHelpers.doAttrAsgn(call, RuntimeHelpers.selectAttrAsgnCallSite(call, rubyObject, file_585EF64F5F783DD4B3D9294B482D429011640F7A.getCallSite2(), file_585EF64F5F783DD4B3D9294B482D429011640F7A.getCallSite3()), value, threadContext, rubyObject);
        final IRubyObject rubyObject2 = obj;
        RuntimeHelpers.doAttrAsgn(rubyObject2, RuntimeHelpers.selectAttrAsgnCallSite(rubyObject2, rubyObject, file_585EF64F5F783DD4B3D9294B482D429011640F7A.getCallSite4(), file_585EF64F5F783DD4B3D9294B482D429011640F7A.getCallSite5()), threadContext.runtime.newArray(), threadContext, rubyObject);
        return obj;
    }
    
    public static IRubyObject sclass_1$RUBY$__singleton__(final FILE_585EF64F5F783DD4B3D9294B482D429011640F7A file_585EF64F5F783DD4B3D9294B482D429011640F7A, final ThreadContext threadContext, final IRubyObject rubyObject, final IRubyObject[] args, final Block block) {
        Arity.checkArgumentCount(threadContext.getRuntime(), args, 0, 0);
        return sclass_1$RUBY$__singleton__(file_585EF64F5F783DD4B3D9294B482D429011640F7A, threadContext, rubyObject, block);
    }
    
    @JRubyMethod(name = "data_model", frame = true, required = 0, optional = 0, rest = -1)
    public static IRubyObject method__4$RUBY$data_model(final FILE_585EF64F5F783DD4B3D9294B482D429011640F7A file_585EF64F5F783DD4B3D9294B482D429011640F7A, final ThreadContext threadContext, final IRubyObject object, final Block block) {
        IRubyObject rubyObject;
        if (!(rubyObject = file_585EF64F5F783DD4B3D9294B482D429011640F7A.getVariable1(threadContext.runtime, "@data_model", object)).isTrue()) {
            rubyObject = file_585EF64F5F783DD4B3D9294B482D429011640F7A.getCallSite(14).call(threadContext, object, file_585EF64F5F783DD4B3D9294B482D429011640F7A.getCallSite(15).call(threadContext, object, object));
        }
        return rubyObject;
    }
    
    @JRubyMethod(name = "getColumnCount", frame = true, required = 0, optional = 0, rest = -1)
    public static IRubyObject method__5$RUBY$getColumnCount(final FILE_585EF64F5F783DD4B3D9294B482D429011640F7A file_585EF64F5F783DD4B3D9294B482D429011640F7A, final ThreadContext threadContext, final IRubyObject rubyObject, final Block block) {
        return file_585EF64F5F783DD4B3D9294B482D429011640F7A.getCallSite(16).call(threadContext, rubyObject, file_585EF64F5F783DD4B3D9294B482D429011640F7A.getCallSite(17).call(threadContext, rubyObject, file_585EF64F5F783DD4B3D9294B482D429011640F7A.getCallSite(18).call(threadContext, rubyObject, rubyObject)));
    }
    
    @JRubyMethod(name = "getRowCount", frame = true, required = 0, optional = 0, rest = -1)
    public static IRubyObject method__6$RUBY$getRowCount(final FILE_585EF64F5F783DD4B3D9294B482D429011640F7A file_585EF64F5F783DD4B3D9294B482D429011640F7A, final ThreadContext threadContext, final IRubyObject rubyObject, final Block block) {
        return file_585EF64F5F783DD4B3D9294B482D429011640F7A.getCallSite(19).call(threadContext, rubyObject, file_585EF64F5F783DD4B3D9294B482D429011640F7A.getCallSite(20).call(threadContext, rubyObject, rubyObject));
    }
    
    @JRubyMethod(name = "getValueAt", frame = true, required = 2, optional = 0, rest = -1)
    public static IRubyObject method__7$RUBY$getValueAt(final FILE_585EF64F5F783DD4B3D9294B482D429011640F7A p0, final ThreadContext p1, final IRubyObject p2, final IRubyObject p3, final IRubyObject p4, final Block p5) {
        // 
        // This method could not be decompiled.
        // 
        // Original Bytecode:
        // 
        //     0: aload_1        
        //     1: invokevirtual   org/jruby/runtime/ThreadContext.getCurrentScope:()Lorg/jruby/runtime/DynamicScope;
        //     4: astore          6
        //     6: aload_3        
        //     7: aload           6
        //     9: swap           
        //    10: invokevirtual   org/jruby/runtime/DynamicScope.setValueZeroDepthZero:(Lorg/jruby/runtime/builtin/IRubyObject;)Lorg/jruby/runtime/builtin/IRubyObject;
        //    13: pop            
        //    14: aload           4
        //    16: aload           6
        //    18: swap           
        //    19: invokevirtual   org/jruby/runtime/DynamicScope.setValueOneDepthZero:(Lorg/jruby/runtime/builtin/IRubyObject;)Lorg/jruby/runtime/builtin/IRubyObject;
        //    22: pop            
        //    23: aload           locals
        //    25: aload_0        
        //    26: bipush          21
        //    28: invokevirtual   ruby/jit/FILE_585EF64F5F783DD4B3D9294B482D429011640F7A.getCallSite:(I)Lorg/jruby/runtime/CallSite;
        //    31: aload_1        
        //    32: aload_2        
        //    33: aload_0        
        //    34: bipush          22
        //    36: invokevirtual   ruby/jit/FILE_585EF64F5F783DD4B3D9294B482D429011640F7A.getCallSite:(I)Lorg/jruby/runtime/CallSite;
        //    39: aload_1        
        //    40: aload_2        
        //    41: aload_2        
        //    42: invokevirtual   org/jruby/runtime/CallSite.call:(Lorg/jruby/runtime/ThreadContext;Lorg/jruby/runtime/builtin/IRubyObject;Lorg/jruby/runtime/builtin/IRubyObject;)Lorg/jruby/runtime/builtin/IRubyObject;
        //    45: aload           locals
        //    47: aload_1        
        //    48: getfield        org/jruby/runtime/ThreadContext.nil:Lorg/jruby/runtime/builtin/IRubyObject;
        //    51: invokevirtual   org/jruby/runtime/DynamicScope.getValueZeroDepthZeroOrNil:(Lorg/jruby/runtime/builtin/IRubyObject;)Lorg/jruby/runtime/builtin/IRubyObject;
        //    54: invokevirtual   org/jruby/runtime/CallSite.call:(Lorg/jruby/runtime/ThreadContext;Lorg/jruby/runtime/builtin/IRubyObject;Lorg/jruby/runtime/builtin/IRubyObject;Lorg/jruby/runtime/builtin/IRubyObject;)Lorg/jruby/runtime/builtin/IRubyObject;
        //    57: invokevirtual   org/jruby/runtime/DynamicScope.setValueTwoDepthZero:(Lorg/jruby/runtime/builtin/IRubyObject;)Lorg/jruby/runtime/builtin/IRubyObject;
        //    60: pop            
        //    61: aload_0        
        //    62: bipush          23
        //    64: invokevirtual   ruby/jit/FILE_585EF64F5F783DD4B3D9294B482D429011640F7A.getCallSite:(I)Lorg/jruby/runtime/CallSite;
        //    67: aload_1        
        //    68: aload_2        
        //    69: aload           locals
        //    71: aload_1        
        //    72: getfield        org/jruby/runtime/ThreadContext.nil:Lorg/jruby/runtime/builtin/IRubyObject;
        //    75: invokevirtual   org/jruby/runtime/DynamicScope.getValueTwoDepthZeroOrNil:(Lorg/jruby/runtime/builtin/IRubyObject;)Lorg/jruby/runtime/builtin/IRubyObject;
        //    78: aload_0        
        //    79: bipush          24
        //    81: invokevirtual   ruby/jit/FILE_585EF64F5F783DD4B3D9294B482D429011640F7A.getCallSite:(I)Lorg/jruby/runtime/CallSite;
        //    84: aload_1        
        //    85: aload_2        
        //    86: aload_0        
        //    87: bipush          25
        //    89: invokevirtual   ruby/jit/FILE_585EF64F5F783DD4B3D9294B482D429011640F7A.getCallSite:(I)Lorg/jruby/runtime/CallSite;
        //    92: aload_1        
        //    93: aload_2        
        //    94: aload_0        
        //    95: bipush          26
        //    97: invokevirtual   ruby/jit/FILE_585EF64F5F783DD4B3D9294B482D429011640F7A.getCallSite:(I)Lorg/jruby/runtime/CallSite;
        //   100: aload_1        
        //   101: aload_2        
        //   102: aload_0        
        //   103: bipush          27
        //   105: invokevirtual   ruby/jit/FILE_585EF64F5F783DD4B3D9294B482D429011640F7A.getCallSite:(I)Lorg/jruby/runtime/CallSite;
        //   108: aload_1        
        //   109: aload_2        
        //   110: aload_2        
        //   111: invokevirtual   org/jruby/runtime/CallSite.call:(Lorg/jruby/runtime/ThreadContext;Lorg/jruby/runtime/builtin/IRubyObject;Lorg/jruby/runtime/builtin/IRubyObject;)Lorg/jruby/runtime/builtin/IRubyObject;
        //   114: invokevirtual   org/jruby/runtime/CallSite.call:(Lorg/jruby/runtime/ThreadContext;Lorg/jruby/runtime/builtin/IRubyObject;Lorg/jruby/runtime/builtin/IRubyObject;)Lorg/jruby/runtime/builtin/IRubyObject;
        //   117: aload           locals
        //   119: aload_1        
        //   120: getfield        org/jruby/runtime/ThreadContext.nil:Lorg/jruby/runtime/builtin/IRubyObject;
        //   123: invokevirtual   org/jruby/runtime/DynamicScope.getValueOneDepthZeroOrNil:(Lorg/jruby/runtime/builtin/IRubyObject;)Lorg/jruby/runtime/builtin/IRubyObject;
        //   126: invokevirtual   org/jruby/runtime/CallSite.call:(Lorg/jruby/runtime/ThreadContext;Lorg/jruby/runtime/builtin/IRubyObject;Lorg/jruby/runtime/builtin/IRubyObject;Lorg/jruby/runtime/builtin/IRubyObject;)Lorg/jruby/runtime/builtin/IRubyObject;
        //   129: invokevirtual   org/jruby/runtime/CallSite.call:(Lorg/jruby/runtime/ThreadContext;Lorg/jruby/runtime/builtin/IRubyObject;Lorg/jruby/runtime/builtin/IRubyObject;)Lorg/jruby/runtime/builtin/IRubyObject;
        //   132: invokevirtual   org/jruby/runtime/CallSite.call:(Lorg/jruby/runtime/ThreadContext;Lorg/jruby/runtime/builtin/IRubyObject;Lorg/jruby/runtime/builtin/IRubyObject;Lorg/jruby/runtime/builtin/IRubyObject;)Lorg/jruby/runtime/builtin/IRubyObject;
        //   135: areturn        
        //    LocalVariableTable:
        //  Start  Length  Slot  Name    Signature
        //  -----  ------  ----  ------  --------------------------------
        //  23     113     6     locals  Lorg/jruby/runtime/DynamicScope;
        // 
        // The error that occurred was:
        // 
        // java.lang.NullPointerException
        // 
        throw new IllegalStateException("An error occurred while decompiling this method.");
    }
    
    @JRubyMethod(name = "getColumnName", frame = true, required = 1, optional = 0, rest = -1)
    public static IRubyObject method__8$RUBY$getColumnName(final FILE_585EF64F5F783DD4B3D9294B482D429011640F7A p0, final ThreadContext p1, final IRubyObject p2, final IRubyObject p3, final Block p4) {
        // 
        // This method could not be decompiled.
        // 
        // Original Bytecode:
        // 
        //     0: aload_1        
        //     1: invokevirtual   org/jruby/runtime/ThreadContext.getCurrentScope:()Lorg/jruby/runtime/DynamicScope;
        //     4: astore          5
        //     6: aload_3        
        //     7: aload           5
        //     9: swap           
        //    10: invokevirtual   org/jruby/runtime/DynamicScope.setValueZeroDepthZero:(Lorg/jruby/runtime/builtin/IRubyObject;)Lorg/jruby/runtime/builtin/IRubyObject;
        //    13: pop            
        //    14: aload_0        
        //    15: bipush          28
        //    17: invokevirtual   ruby/jit/FILE_585EF64F5F783DD4B3D9294B482D429011640F7A.getCallSite:(I)Lorg/jruby/runtime/CallSite;
        //    20: aload_1        
        //    21: aload_2        
        //    22: aload_0        
        //    23: bipush          29
        //    25: invokevirtual   ruby/jit/FILE_585EF64F5F783DD4B3D9294B482D429011640F7A.getCallSite:(I)Lorg/jruby/runtime/CallSite;
        //    28: aload_1        
        //    29: aload_2        
        //    30: aload_2        
        //    31: invokevirtual   org/jruby/runtime/CallSite.call:(Lorg/jruby/runtime/ThreadContext;Lorg/jruby/runtime/builtin/IRubyObject;Lorg/jruby/runtime/builtin/IRubyObject;)Lorg/jruby/runtime/builtin/IRubyObject;
        //    34: aload_0        
        //    35: bipush          30
        //    37: invokevirtual   ruby/jit/FILE_585EF64F5F783DD4B3D9294B482D429011640F7A.getCallSite:(I)Lorg/jruby/runtime/CallSite;
        //    40: aload_1        
        //    41: aload_2        
        //    42: aload_0        
        //    43: bipush          31
        //    45: invokevirtual   ruby/jit/FILE_585EF64F5F783DD4B3D9294B482D429011640F7A.getCallSite:(I)Lorg/jruby/runtime/CallSite;
        //    48: aload_1        
        //    49: aload_2        
        //    50: aload_0        
        //    51: bipush          32
        //    53: invokevirtual   ruby/jit/FILE_585EF64F5F783DD4B3D9294B482D429011640F7A.getCallSite:(I)Lorg/jruby/runtime/CallSite;
        //    56: aload_1        
        //    57: aload_2        
        //    58: aload_2        
        //    59: invokevirtual   org/jruby/runtime/CallSite.call:(Lorg/jruby/runtime/ThreadContext;Lorg/jruby/runtime/builtin/IRubyObject;Lorg/jruby/runtime/builtin/IRubyObject;)Lorg/jruby/runtime/builtin/IRubyObject;
        //    62: invokevirtual   org/jruby/runtime/CallSite.call:(Lorg/jruby/runtime/ThreadContext;Lorg/jruby/runtime/builtin/IRubyObject;Lorg/jruby/runtime/builtin/IRubyObject;)Lorg/jruby/runtime/builtin/IRubyObject;
        //    65: aload           locals
        //    67: aload_1        
        //    68: getfield        org/jruby/runtime/ThreadContext.nil:Lorg/jruby/runtime/builtin/IRubyObject;
        //    71: invokevirtual   org/jruby/runtime/DynamicScope.getValueZeroDepthZeroOrNil:(Lorg/jruby/runtime/builtin/IRubyObject;)Lorg/jruby/runtime/builtin/IRubyObject;
        //    74: invokevirtual   org/jruby/runtime/CallSite.call:(Lorg/jruby/runtime/ThreadContext;Lorg/jruby/runtime/builtin/IRubyObject;Lorg/jruby/runtime/builtin/IRubyObject;Lorg/jruby/runtime/builtin/IRubyObject;)Lorg/jruby/runtime/builtin/IRubyObject;
        //    77: invokevirtual   org/jruby/runtime/CallSite.call:(Lorg/jruby/runtime/ThreadContext;Lorg/jruby/runtime/builtin/IRubyObject;Lorg/jruby/runtime/builtin/IRubyObject;Lorg/jruby/runtime/builtin/IRubyObject;)Lorg/jruby/runtime/builtin/IRubyObject;
        //    80: areturn        
        //    LocalVariableTable:
        //  Start  Length  Slot  Name    Signature
        //  -----  ------  ----  ------  --------------------------------
        //  14     67      5     locals  Lorg/jruby/runtime/DynamicScope;
        // 
        // The error that occurred was:
        // 
        // java.lang.NullPointerException
        // 
        throw new IllegalStateException("An error occurred while decompiling this method.");
    }
    
    @JRubyMethod(name = "getColumnClass", frame = true, required = 1, optional = 0, rest = -1)
    public static IRubyObject method__9$RUBY$getColumnClass(final FILE_585EF64F5F783DD4B3D9294B482D429011640F7A p0, final ThreadContext p1, final IRubyObject p2, final IRubyObject p3, final Block p4) {
        // 
        // This method could not be decompiled.
        // 
        // Original Bytecode:
        // 
        //     0: aload_1        
        //     1: invokevirtual   org/jruby/runtime/ThreadContext.getCurrentScope:()Lorg/jruby/runtime/DynamicScope;
        //     4: astore          5
        //     6: aload_3        
        //     7: aload           5
        //     9: swap           
        //    10: invokevirtual   org/jruby/runtime/DynamicScope.setValueZeroDepthZero:(Lorg/jruby/runtime/builtin/IRubyObject;)Lorg/jruby/runtime/builtin/IRubyObject;
        //    13: pop            
        //    14: aload           locals
        //    16: aload_0        
        //    17: bipush          33
        //    19: invokevirtual   ruby/jit/FILE_585EF64F5F783DD4B3D9294B482D429011640F7A.getCallSite:(I)Lorg/jruby/runtime/CallSite;
        //    22: aload_1        
        //    23: aload_2        
        //    24: aload_0        
        //    25: bipush          34
        //    27: invokevirtual   ruby/jit/FILE_585EF64F5F783DD4B3D9294B482D429011640F7A.getCallSite:(I)Lorg/jruby/runtime/CallSite;
        //    30: aload_1        
        //    31: aload_2        
        //    32: aload_0        
        //    33: bipush          35
        //    35: invokevirtual   ruby/jit/FILE_585EF64F5F783DD4B3D9294B482D429011640F7A.getCallSite:(I)Lorg/jruby/runtime/CallSite;
        //    38: aload_1        
        //    39: aload_2        
        //    40: aload_0        
        //    41: bipush          36
        //    43: invokevirtual   ruby/jit/FILE_585EF64F5F783DD4B3D9294B482D429011640F7A.getCallSite:(I)Lorg/jruby/runtime/CallSite;
        //    46: aload_1        
        //    47: aload_2        
        //    48: aload_2        
        //    49: invokevirtual   org/jruby/runtime/CallSite.call:(Lorg/jruby/runtime/ThreadContext;Lorg/jruby/runtime/builtin/IRubyObject;Lorg/jruby/runtime/builtin/IRubyObject;)Lorg/jruby/runtime/builtin/IRubyObject;
        //    52: invokevirtual   org/jruby/runtime/CallSite.call:(Lorg/jruby/runtime/ThreadContext;Lorg/jruby/runtime/builtin/IRubyObject;Lorg/jruby/runtime/builtin/IRubyObject;)Lorg/jruby/runtime/builtin/IRubyObject;
        //    55: aload           locals
        //    57: aload_1        
        //    58: getfield        org/jruby/runtime/ThreadContext.nil:Lorg/jruby/runtime/builtin/IRubyObject;
        //    61: invokevirtual   org/jruby/runtime/DynamicScope.getValueZeroDepthZeroOrNil:(Lorg/jruby/runtime/builtin/IRubyObject;)Lorg/jruby/runtime/builtin/IRubyObject;
        //    64: invokevirtual   org/jruby/runtime/CallSite.call:(Lorg/jruby/runtime/ThreadContext;Lorg/jruby/runtime/builtin/IRubyObject;Lorg/jruby/runtime/builtin/IRubyObject;Lorg/jruby/runtime/builtin/IRubyObject;)Lorg/jruby/runtime/builtin/IRubyObject;
        //    67: invokevirtual   org/jruby/runtime/CallSite.call:(Lorg/jruby/runtime/ThreadContext;Lorg/jruby/runtime/builtin/IRubyObject;Lorg/jruby/runtime/builtin/IRubyObject;)Lorg/jruby/runtime/builtin/IRubyObject;
        //    70: invokevirtual   org/jruby/runtime/DynamicScope.setValueOneDepthZero:(Lorg/jruby/runtime/builtin/IRubyObject;)Lorg/jruby/runtime/builtin/IRubyObject;
        //    73: pop            
        //    74: aload_0        
        //    75: bipush          37
        //    77: invokevirtual   ruby/jit/FILE_585EF64F5F783DD4B3D9294B482D429011640F7A.getCallSite:(I)Lorg/jruby/runtime/CallSite;
        //    80: aload_1        
        //    81: aload_2        
        //    82: aload_0        
        //    83: aload_1        
        //    84: ldc_w           "MAPPING"
        //    87: invokevirtual   ruby/jit/FILE_585EF64F5F783DD4B3D9294B482D429011640F7A.getConstant0:(Lorg/jruby/runtime/ThreadContext;Ljava/lang/String;)Lorg/jruby/runtime/builtin/IRubyObject;
        //    90: aload           locals
        //    92: aload_1        
        //    93: getfield        org/jruby/runtime/ThreadContext.nil:Lorg/jruby/runtime/builtin/IRubyObject;
        //    96: invokevirtual   org/jruby/runtime/DynamicScope.getValueOneDepthZeroOrNil:(Lorg/jruby/runtime/builtin/IRubyObject;)Lorg/jruby/runtime/builtin/IRubyObject;
        //    99: invokevirtual   org/jruby/runtime/CallSite.call:(Lorg/jruby/runtime/ThreadContext;Lorg/jruby/runtime/builtin/IRubyObject;Lorg/jruby/runtime/builtin/IRubyObject;Lorg/jruby/runtime/builtin/IRubyObject;)Lorg/jruby/runtime/builtin/IRubyObject;
        //   102: areturn        
        //    LocalVariableTable:
        //  Start  Length  Slot  Name    Signature
        //  -----  ------  ----  ------  --------------------------------
        //  14     89      5     locals  Lorg/jruby/runtime/DynamicScope;
        // 
        // The error that occurred was:
        // 
        // java.lang.NullPointerException
        // 
        throw new IllegalStateException("An error occurred while decompiling this method.");
    }
    
    @JRubyMethod(name = "isCellEditable", frame = true, required = 2, optional = 0, rest = -1)
    public static IRubyObject method__10$RUBY$isCellEditable(final FILE_585EF64F5F783DD4B3D9294B482D429011640F7A file_585EF64F5F783DD4B3D9294B482D429011640F7A, final ThreadContext threadContext, final IRubyObject rubyObject, final IRubyObject rubyObject2, final IRubyObject rubyObject3, final Block block) {
        final RubyBoolean true = threadContext.runtime.getTrue();
        threadContext.pollThreadEvents();
        return true;
    }
    
    @JRubyMethod(name = "setValueAt", frame = true, required = 3, optional = 0, rest = -1)
    public static IRubyObject method__11$RUBY$setValueAt(final FILE_585EF64F5F783DD4B3D9294B482D429011640F7A p0, final ThreadContext p1, final IRubyObject p2, final IRubyObject p3, final IRubyObject p4, final IRubyObject p5, final Block p6) {
        // 
        // This method could not be decompiled.
        // 
        // Original Bytecode:
        // 
        //     0: aload_1        
        //     1: invokevirtual   org/jruby/runtime/ThreadContext.getCurrentScope:()Lorg/jruby/runtime/DynamicScope;
        //     4: astore          7
        //     6: aload_3        
        //     7: aload           7
        //     9: swap           
        //    10: invokevirtual   org/jruby/runtime/DynamicScope.setValueZeroDepthZero:(Lorg/jruby/runtime/builtin/IRubyObject;)Lorg/jruby/runtime/builtin/IRubyObject;
        //    13: pop            
        //    14: aload           4
        //    16: aload           7
        //    18: swap           
        //    19: invokevirtual   org/jruby/runtime/DynamicScope.setValueOneDepthZero:(Lorg/jruby/runtime/builtin/IRubyObject;)Lorg/jruby/runtime/builtin/IRubyObject;
        //    22: pop            
        //    23: aload           5
        //    25: aload           7
        //    27: swap           
        //    28: invokevirtual   org/jruby/runtime/DynamicScope.setValueTwoDepthZero:(Lorg/jruby/runtime/builtin/IRubyObject;)Lorg/jruby/runtime/builtin/IRubyObject;
        //    31: pop            
        //    32: aload           locals
        //    34: aload_0        
        //    35: bipush          38
        //    37: invokevirtual   ruby/jit/FILE_585EF64F5F783DD4B3D9294B482D429011640F7A.getCallSite:(I)Lorg/jruby/runtime/CallSite;
        //    40: aload_1        
        //    41: aload_2        
        //    42: aload_0        
        //    43: bipush          39
        //    45: invokevirtual   ruby/jit/FILE_585EF64F5F783DD4B3D9294B482D429011640F7A.getCallSite:(I)Lorg/jruby/runtime/CallSite;
        //    48: aload_1        
        //    49: aload_2        
        //    50: aload_2        
        //    51: invokevirtual   org/jruby/runtime/CallSite.call:(Lorg/jruby/runtime/ThreadContext;Lorg/jruby/runtime/builtin/IRubyObject;Lorg/jruby/runtime/builtin/IRubyObject;)Lorg/jruby/runtime/builtin/IRubyObject;
        //    54: aload           locals
        //    56: aload_1        
        //    57: getfield        org/jruby/runtime/ThreadContext.nil:Lorg/jruby/runtime/builtin/IRubyObject;
        //    60: invokevirtual   org/jruby/runtime/DynamicScope.getValueOneDepthZeroOrNil:(Lorg/jruby/runtime/builtin/IRubyObject;)Lorg/jruby/runtime/builtin/IRubyObject;
        //    63: invokevirtual   org/jruby/runtime/CallSite.call:(Lorg/jruby/runtime/ThreadContext;Lorg/jruby/runtime/builtin/IRubyObject;Lorg/jruby/runtime/builtin/IRubyObject;Lorg/jruby/runtime/builtin/IRubyObject;)Lorg/jruby/runtime/builtin/IRubyObject;
        //    66: invokevirtual   org/jruby/runtime/DynamicScope.setValueThreeDepthZero:(Lorg/jruby/runtime/builtin/IRubyObject;)Lorg/jruby/runtime/builtin/IRubyObject;
        //    69: pop            
        //    70: aload           locals
        //    72: aload_1        
        //    73: getfield        org/jruby/runtime/ThreadContext.nil:Lorg/jruby/runtime/builtin/IRubyObject;
        //    76: invokevirtual   org/jruby/runtime/DynamicScope.getValueThreeDepthZeroOrNil:(Lorg/jruby/runtime/builtin/IRubyObject;)Lorg/jruby/runtime/builtin/IRubyObject;
        //    79: invokeinterface org/jruby/runtime/builtin/IRubyObject.isTrue:()Z
        //    84: ifeq            205
        //    87: aload_0        
        //    88: bipush          40
        //    90: invokevirtual   ruby/jit/FILE_585EF64F5F783DD4B3D9294B482D429011640F7A.getCallSite:(I)Lorg/jruby/runtime/CallSite;
        //    93: aload_1        
        //    94: aload_2        
        //    95: aload           locals
        //    97: aload_1        
        //    98: getfield        org/jruby/runtime/ThreadContext.nil:Lorg/jruby/runtime/builtin/IRubyObject;
        //   101: invokevirtual   org/jruby/runtime/DynamicScope.getValueThreeDepthZeroOrNil:(Lorg/jruby/runtime/builtin/IRubyObject;)Lorg/jruby/runtime/builtin/IRubyObject;
        //   104: aload_1        
        //   105: getfield        org/jruby/runtime/ThreadContext.runtime:Lorg/jruby/Ruby;
        //   108: ldc_w           20
        //   111: invokestatic    org/jruby/RubyString.newStringLight:(Lorg/jruby/Ruby;I)Lorg/jruby/RubyString;
        //   114: aload_0        
        //   115: bipush          41
        //   117: invokevirtual   ruby/jit/FILE_585EF64F5F783DD4B3D9294B482D429011640F7A.getCallSite:(I)Lorg/jruby/runtime/CallSite;
        //   120: aload_1        
        //   121: aload_2        
        //   122: aload_0        
        //   123: bipush          42
        //   125: invokevirtual   ruby/jit/FILE_585EF64F5F783DD4B3D9294B482D429011640F7A.getCallSite:(I)Lorg/jruby/runtime/CallSite;
        //   128: aload_1        
        //   129: aload_2        
        //   130: aload_0        
        //   131: bipush          43
        //   133: invokevirtual   ruby/jit/FILE_585EF64F5F783DD4B3D9294B482D429011640F7A.getCallSite:(I)Lorg/jruby/runtime/CallSite;
        //   136: aload_1        
        //   137: aload_2        
        //   138: aload_0        
        //   139: bipush          44
        //   141: invokevirtual   ruby/jit/FILE_585EF64F5F783DD4B3D9294B482D429011640F7A.getCallSite:(I)Lorg/jruby/runtime/CallSite;
        //   144: aload_1        
        //   145: aload_2        
        //   146: aload_2        
        //   147: invokevirtual   org/jruby/runtime/CallSite.call:(Lorg/jruby/runtime/ThreadContext;Lorg/jruby/runtime/builtin/IRubyObject;Lorg/jruby/runtime/builtin/IRubyObject;)Lorg/jruby/runtime/builtin/IRubyObject;
        //   150: invokevirtual   org/jruby/runtime/CallSite.call:(Lorg/jruby/runtime/ThreadContext;Lorg/jruby/runtime/builtin/IRubyObject;Lorg/jruby/runtime/builtin/IRubyObject;)Lorg/jruby/runtime/builtin/IRubyObject;
        //   153: aload           locals
        //   155: aload_1        
        //   156: getfield        org/jruby/runtime/ThreadContext.nil:Lorg/jruby/runtime/builtin/IRubyObject;
        //   159: invokevirtual   org/jruby/runtime/DynamicScope.getValueTwoDepthZeroOrNil:(Lorg/jruby/runtime/builtin/IRubyObject;)Lorg/jruby/runtime/builtin/IRubyObject;
        //   162: invokevirtual   org/jruby/runtime/CallSite.call:(Lorg/jruby/runtime/ThreadContext;Lorg/jruby/runtime/builtin/IRubyObject;Lorg/jruby/runtime/builtin/IRubyObject;Lorg/jruby/runtime/builtin/IRubyObject;)Lorg/jruby/runtime/builtin/IRubyObject;
        //   165: invokevirtual   org/jruby/runtime/CallSite.call:(Lorg/jruby/runtime/ThreadContext;Lorg/jruby/runtime/builtin/IRubyObject;Lorg/jruby/runtime/builtin/IRubyObject;)Lorg/jruby/runtime/builtin/IRubyObject;
        //   168: invokeinterface org/jruby/runtime/builtin/IRubyObject.asString:()Lorg/jruby/RubyString;
        //   173: invokevirtual   org/jruby/RubyString.append:(Lorg/jruby/runtime/builtin/IRubyObject;)Lorg/jruby/RubyString;
        //   176: aload_0        
        //   177: aload_1        
        //   178: getfield        org/jruby/runtime/ThreadContext.runtime:Lorg/jruby/Ruby;
        //   181: bipush          32
        //   183: invokevirtual   ruby/jit/FILE_585EF64F5F783DD4B3D9294B482D429011640F7A.getString1:(Lorg/jruby/Ruby;I)Lorg/jruby/RubyString;
        //   186: invokevirtual   org/jruby/RubyString.append:(Lorg/jruby/runtime/builtin/IRubyObject;)Lorg/jruby/RubyString;
        //   189: aload           locals
        //   191: aload_1        
        //   192: getfield        org/jruby/runtime/ThreadContext.nil:Lorg/jruby/runtime/builtin/IRubyObject;
        //   195: invokevirtual   org/jruby/runtime/DynamicScope.getValueZeroDepthZeroOrNil:(Lorg/jruby/runtime/builtin/IRubyObject;)Lorg/jruby/runtime/builtin/IRubyObject;
        //   198: invokevirtual   org/jruby/runtime/CallSite.call:(Lorg/jruby/runtime/ThreadContext;Lorg/jruby/runtime/builtin/IRubyObject;Lorg/jruby/runtime/builtin/IRubyObject;Lorg/jruby/runtime/builtin/IRubyObject;Lorg/jruby/runtime/builtin/IRubyObject;)Lorg/jruby/runtime/builtin/IRubyObject;
        //   201: pop            
        //   202: goto            205
        //   205: aload_0        
        //   206: bipush          45
        //   208: invokevirtual   ruby/jit/FILE_585EF64F5F783DD4B3D9294B482D429011640F7A.getCallSite:(I)Lorg/jruby/runtime/CallSite;
        //   211: aload_1        
        //   212: aload_2        
        //   213: aload_2        
        //   214: invokevirtual   org/jruby/runtime/CallSite.call:(Lorg/jruby/runtime/ThreadContext;Lorg/jruby/runtime/builtin/IRubyObject;Lorg/jruby/runtime/builtin/IRubyObject;)Lorg/jruby/runtime/builtin/IRubyObject;
        //   217: areturn        
        //    LocalVariableTable:
        //  Start  Length  Slot  Name    Signature
        //  -----  ------  ----  ------  --------------------------------
        //  32     186     7     locals  Lorg/jruby/runtime/DynamicScope;
        // 
        // The error that occurred was:
        // 
        // java.lang.NullPointerException
        // 
        throw new IllegalStateException("An error occurred while decompiling this method.");
    }
    
    @JRubyMethod(name = "create_item", frame = true, required = 0, optional = 0, rest = 0)
    public static IRubyObject method__12$RUBY$create_item(final FILE_585EF64F5F783DD4B3D9294B482D429011640F7A file_585EF64F5F783DD4B3D9294B482D429011640F7A, final ThreadContext threadContext, final IRubyObject rubyObject, final IRubyObject[] input, final Block block) {
        final IRubyObject nil = threadContext.nil;
        final IRubyObject args = RuntimeHelpers.createSubarray(input, threadContext.runtime, 0);
        return file_585EF64F5F783DD4B3D9294B482D429011640F7A.getCallSite(46).call(threadContext, rubyObject, rubyObject, file_585EF64F5F783DD4B3D9294B482D429011640F7A.getCallSite(47).call(threadContext, rubyObject, file_585EF64F5F783DD4B3D9294B482D429011640F7A.getCallSite(48).call(threadContext, rubyObject, rubyObject), ArgsUtil.convertToJavaArray(RuntimeHelpers.splatValue(args))));
    }
    
    @JRubyMethod(name = "add_item", frame = true, required = 1, optional = 0, rest = -1)
    public static IRubyObject method__13$RUBY$add_item(final FILE_585EF64F5F783DD4B3D9294B482D429011640F7A file_585EF64F5F783DD4B3D9294B482D429011640F7A, final ThreadContext threadContext, final IRubyObject rubyObject, final IRubyObject rubyObject2, final Block block) {
        file_585EF64F5F783DD4B3D9294B482D429011640F7A.getCallSite(49).call(threadContext, rubyObject, file_585EF64F5F783DD4B3D9294B482D429011640F7A.getCallSite(50).call(threadContext, rubyObject, rubyObject), rubyObject2);
        return file_585EF64F5F783DD4B3D9294B482D429011640F7A.getCallSite(51).call(threadContext, rubyObject, rubyObject);
    }
    
    @JRubyMethod(name = "delete_item_at_idx", frame = true, required = 1, optional = 0, rest = -1)
    public static IRubyObject method__14$RUBY$delete_item_at_idx(final FILE_585EF64F5F783DD4B3D9294B482D429011640F7A file_585EF64F5F783DD4B3D9294B482D429011640F7A, final ThreadContext threadContext, final IRubyObject object, final IRubyObject rubyObject, final Block block) {
        file_585EF64F5F783DD4B3D9294B482D429011640F7A.setVariable1(threadContext.runtime, "@data", object, file_585EF64F5F783DD4B3D9294B482D429011640F7A.getCallSite(52).call(threadContext, object, file_585EF64F5F783DD4B3D9294B482D429011640F7A.getCallSite(53).call(threadContext, object, object)));
        file_585EF64F5F783DD4B3D9294B482D429011640F7A.getCallSite(54).call(threadContext, object, file_585EF64F5F783DD4B3D9294B482D429011640F7A.getCallSite(55).call(threadContext, object, object), rubyObject);
        return file_585EF64F5F783DD4B3D9294B482D429011640F7A.getCallSite(56).call(threadContext, object, object);
    }
    
    @JRubyMethod(name = "refresh", frame = true, required = 0, optional = 0, rest = -1)
    public static IRubyObject method__15$RUBY$refresh(final FILE_585EF64F5F783DD4B3D9294B482D429011640F7A file_585EF64F5F783DD4B3D9294B482D429011640F7A, final ThreadContext threadContext, final IRubyObject rubyObject, final Block block) {
        if (file_585EF64F5F783DD4B3D9294B482D429011640F7A.getCallSite(58).call(threadContext, rubyObject, rubyObject).isTrue()) {
            file_585EF64F5F783DD4B3D9294B482D429011640F7A.getCallSite(59).call(threadContext, rubyObject, file_585EF64F5F783DD4B3D9294B482D429011640F7A.getCallSite(60).call(threadContext, rubyObject, rubyObject));
        }
        return file_585EF64F5F783DD4B3D9294B482D429011640F7A.getCallSite(61).call(threadContext, rubyObject, rubyObject);
    }
    
    @JRubyMethod(name = "on_data_change", frame = true, required = 0, optional = 0, rest = -1)
    public static IRubyObject method__16$RUBY$on_data_change(final FILE_585EF64F5F783DD4B3D9294B482D429011640F7A file_585EF64F5F783DD4B3D9294B482D429011640F7A, final ThreadContext threadContext, final IRubyObject object, final Block block) {
        final IRubyObject nil = threadContext.nil;
        final IRubyObject blk = RuntimeHelpers.processBlockArgument(threadContext.runtime, block);
        return file_585EF64F5F783DD4B3D9294B482D429011640F7A.setVariable2(threadContext.runtime, "@blk", object, blk);
    }
    
    public static IRubyObject class_0$RUBY$QuestionTableModel(final FILE_585EF64F5F783DD4B3D9294B482D429011640F7A file_585EF64F5F783DD4B3D9294B482D429011640F7A, final ThreadContext threadContext, final IRubyObject rubyObject, final IRubyObject[] args, final Block block) {
        Arity.checkArgumentCount(threadContext.getRuntime(), args, 0, 0);
        return class_0$RUBY$QuestionTableModel(file_585EF64F5F783DD4B3D9294B482D429011640F7A, threadContext, rubyObject, block);
    }
    
    @Override
    public IRubyObject load(final ThreadContext context, final IRubyObject rubyObject, final IRubyObject[] array, final Block block) {
        try {
            RuntimeHelpers.preLoad(context, ",0,0,-2");
            final IRubyObject _file__ = __file__(this, context, rubyObject, array, block);
            RuntimeHelpers.postLoad(context);
            return _file__;
        }
        finally {
            RuntimeHelpers.postLoad(context);
        }
    }
    
    public static void main(final String[] argv) {
        final FILE_585EF64F5F783DD4B3D9294B482D429011640F7A file_585EF64F5F783DD4B3D9294B482D429011640F7A = new FILE_585EF64F5F783DD4B3D9294B482D429011640F7A();
        final String string = FILE_585EF64F5F783DD4B3D9294B482D429011640F7A.class.getClassLoader().getResource("ruby/jit/FILE_585EF64F5F783DD4B3D9294B482D429011640F7A.class").toString();
        file_585EF64F5F783DD4B3D9294B482D429011640F7A.setFilename(string);
        final RubyInstanceConfig config = new RubyInstanceConfig();
        config.setArgv(argv);
        config.setScriptFileName(string);
        final Ruby instance = Ruby.newInstance(config);
        file_585EF64F5F783DD4B3D9294B482D429011640F7A.load(instance.getCurrentContext(), instance.getTopSelf(), IRubyObject.NULL_ARRAY, Block.NULL_BLOCK);
    }
}
