// 
// Decompiled by Procyon v0.5.30
// 

package ruby.jit;

import org.jruby.Ruby;
import org.jruby.RubyInstanceConfig;
import org.jruby.runtime.Arity;
import org.jruby.RubyBoolean;
import org.jruby.runtime.CallSite;
import org.jruby.javasupport.util.RuntimeHelpers;
import org.jruby.anno.JRubyMethod;
import org.jruby.runtime.Block;
import org.jruby.runtime.builtin.IRubyObject;
import org.jruby.ast.executable.RuntimeCache;
import org.jruby.runtime.ThreadContext;
import org.jruby.ast.executable.AbstractScript;

public class FILE_6685C7BB43146C8423BA5B272AF1FF8007E715FC extends AbstractScript
{
    public FILE_6685C7BB43146C8423BA5B272AF1FF8007E715FC() {
        this.filename = "./lib//lister/runner/measurements/ask_email.rb";
        super.runtimeCache = new RuntimeCache();
        this.initFromDescriptor("require\uffffF\uffffrequire\uffffF\uffffrequire\uffffF\uffffrequire\uffffF\uffffinclude_class\uffffF\uffffinclude_class\uffffF\uffffinclude_class\uffffF\uffffinclude\uffffF\uffffattr_reader\uffffF\uffffemail_question\uffffN\uffffnew\uffffN\uffffurl\uffffN\uffffrunner\uffffV\uffffeditable=\uffffN\uffffeditable=\uffffV\ufffffont\uffffN\ufffffont=\uffffN\ufffffont=\uffffV\uffffnew\uffffN\uffffname\uffffN\uffff+\uffffN\uffffsize\uffffN\uffffquestion_for_description\uffffN\uffffdescription\uffffV\uffffinterpret\uffffN\uffffrunner\uffffV\uffffadd\uffffN\uffffurl_area\uffffV\uffffquestion\uffffV\uffffnew\uffffN\uffffquestions\uffffV\uffffinterpret\uffffN\uffffrunner\uffffV\uffffstart\uffffN\uffffquestionnaire\uffffV\uffffadd\uffffN\uffffpoll_panel\uffffN\uffffrunner\uffffV\uffffquestionnaire\uffffV\uffffframe\uffffN\uffffrunner\uffffV\uffffvisible=\uffffN\uffffvisible=\uffffV\uffffwait_questionnaire\uffffN\uffffquestionnaire\uffffV\uffffquestionnaire\uffffV\uffffvisible=\uffffN\uffffvisible=\uffffV\uffffremove\uffffN\uffffframe\uffffN\uffffrunner\uffffV\uffffquestionnaire\uffffV\uffffresults\uffffN\uffffquestionnaire\uffffV\uffff\u0003\u0001\u0000\u0000\u0010\u0000\u0000\u0000\u0001\u0000\u0000\u0000\u0007\u0001");
        this.setEncoding(0, "ASCII-8BIT");
        this.setByteList(4, "javax.swing.JTextArea", this.getEncoding0());
        this.setByteList(5, "java.awt.BorderLayout", this.getEncoding0());
        this.setByteList(1, "lister/questions_list", this.getEncoding0());
        this.setByteList(3, "lister/runner/questionnaire/questionnaire", this.getEncoding0());
        this.setByteList(0, "lister/measurements/ask_email", this.getEncoding0());
        this.setByteList(6, "java.awt.Font", this.getEncoding0());
        this.setByteList(2, "lister/runner/questionnaire/workflow", this.getEncoding0());
    }
    
    @JRubyMethod(name = "__file__", frame = true, required = 0, optional = 0, rest = -2)
    public static IRubyObject __file__(final FILE_6685C7BB43146C8423BA5B272AF1FF8007E715FC file_6685C7BB43146C8423BA5B272AF1FF8007E715FC, final ThreadContext threadContext, final IRubyObject rubyObject, final IRubyObject[] array, final Block block) {
        file_6685C7BB43146C8423BA5B272AF1FF8007E715FC.getCallSite0().call(threadContext, rubyObject, rubyObject, file_6685C7BB43146C8423BA5B272AF1FF8007E715FC.getString0(threadContext.runtime, 32));
        file_6685C7BB43146C8423BA5B272AF1FF8007E715FC.getCallSite1().call(threadContext, rubyObject, rubyObject, file_6685C7BB43146C8423BA5B272AF1FF8007E715FC.getString1(threadContext.runtime, 32));
        file_6685C7BB43146C8423BA5B272AF1FF8007E715FC.getCallSite2().call(threadContext, rubyObject, rubyObject, file_6685C7BB43146C8423BA5B272AF1FF8007E715FC.getString2(threadContext.runtime, 32));
        file_6685C7BB43146C8423BA5B272AF1FF8007E715FC.getCallSite3().call(threadContext, rubyObject, rubyObject, file_6685C7BB43146C8423BA5B272AF1FF8007E715FC.getString3(threadContext.runtime, 32));
        file_6685C7BB43146C8423BA5B272AF1FF8007E715FC.getCallSite4().call(threadContext, rubyObject, rubyObject, file_6685C7BB43146C8423BA5B272AF1FF8007E715FC.getString4(threadContext.runtime, 32));
        file_6685C7BB43146C8423BA5B272AF1FF8007E715FC.getCallSite5().call(threadContext, rubyObject, rubyObject, file_6685C7BB43146C8423BA5B272AF1FF8007E715FC.getString5(threadContext.runtime, 32));
        file_6685C7BB43146C8423BA5B272AF1FF8007E715FC.getCallSite6().call(threadContext, rubyObject, rubyObject, file_6685C7BB43146C8423BA5B272AF1FF8007E715FC.getString6(threadContext.runtime, 32));
        return module__0$RUBY$Lister(file_6685C7BB43146C8423BA5B272AF1FF8007E715FC, threadContext, rubyObject, IRubyObject.NULL_ARRAY, Block.NULL_BLOCK);
    }
    
    @Override
    public IRubyObject __file__(final ThreadContext threadContext, final IRubyObject rubyObject, final IRubyObject[] array, final Block block) {
        return __file__(this, threadContext, rubyObject, array, block);
    }
    
    public static IRubyObject module__0$RUBY$Lister(final FILE_6685C7BB43146C8423BA5B272AF1FF8007E715FC p0, final ThreadContext p1, final IRubyObject p2, final Block p3) {
        // 
        // This method could not be decompiled.
        // 
        // Original Bytecode:
        // 
        //     0: aload_1        
        //     1: aload_1        
        //     2: getfield        org/jruby/runtime/ThreadContext.nil:Lorg/jruby/runtime/builtin/IRubyObject;
        //     5: invokestatic    org/jruby/javasupport/util/RuntimeHelpers.prepareClassNamespace:(Lorg/jruby/runtime/ThreadContext;Lorg/jruby/runtime/builtin/IRubyObject;)Lorg/jruby/RubyModule;
        //     8: ldc             "Lister"
        //    10: invokevirtual   org/jruby/RubyModule.defineOrGetModuleUnder:(Ljava/lang/String;)Lorg/jruby/RubyModule;
        //    13: dup            
        //    14: astore_2       
        //    15: aload_1        
        //    16: swap           
        //    17: aload_0        
        //    18: aload_1        
        //    19: ldc             ",0,0,-1"
        //    21: invokevirtual   ruby/jit/FILE_6685C7BB43146C8423BA5B272AF1FF8007E715FC.getScope0:(Lorg/jruby/runtime/ThreadContext;Ljava/lang/String;)Lorg/jruby/parser/StaticScope;
        //    24: invokevirtual   org/jruby/runtime/ThreadContext.preCompiledClassDummyScope:(Lorg/jruby/RubyModule;Lorg/jruby/parser/StaticScope;)V
        //    27: aload_0        
        //    28: aload_1        
        //    29: aload_2        
        //    30: getstatic       org/jruby/runtime/builtin/IRubyObject.NULL_ARRAY:[Lorg/jruby/runtime/builtin/IRubyObject;
        //    33: getstatic       org/jruby/runtime/Block.NULL_BLOCK:Lorg/jruby/runtime/Block;
        //    36: invokestatic    ruby/jit/FILE_6685C7BB43146C8423BA5B272AF1FF8007E715FC.module__1$RUBY$Measurements:(Lruby/jit/FILE_6685C7BB43146C8423BA5B272AF1FF8007E715FC;Lorg/jruby/runtime/ThreadContext;Lorg/jruby/runtime/builtin/IRubyObject;[Lorg/jruby/runtime/builtin/IRubyObject;Lorg/jruby/runtime/Block;)Lorg/jruby/runtime/builtin/IRubyObject;
        //    39: aload_1        
        //    40: getfield        org/jruby/runtime/ThreadContext.nil:Lorg/jruby/runtime/builtin/IRubyObject;
        //    43: goto            51
        //    46: aload_1        
        //    47: invokevirtual   org/jruby/runtime/ThreadContext.postCompiledClass:()V
        //    50: athrow         
        //    51: aload_1        
        //    52: invokevirtual   org/jruby/runtime/ThreadContext.postCompiledClass:()V
        //    55: areturn        
        //    Exceptions:
        //  Try           Handler
        //  Start  End    Start  End    Type
        //  -----  -----  -----  -----  ----
        //  27     43     46     51     Any
        // 
        // The error that occurred was:
        // 
        // java.lang.ArrayIndexOutOfBoundsException
        // 
        throw new IllegalStateException("An error occurred while decompiling this method.");
    }
    
    public static IRubyObject module__1$RUBY$Measurements(final FILE_6685C7BB43146C8423BA5B272AF1FF8007E715FC p0, final ThreadContext p1, final IRubyObject p2, final Block p3) {
        // 
        // This method could not be decompiled.
        // 
        // Original Bytecode:
        // 
        //     0: aload_1        
        //     1: aload_1        
        //     2: getfield        org/jruby/runtime/ThreadContext.nil:Lorg/jruby/runtime/builtin/IRubyObject;
        //     5: invokestatic    org/jruby/javasupport/util/RuntimeHelpers.prepareClassNamespace:(Lorg/jruby/runtime/ThreadContext;Lorg/jruby/runtime/builtin/IRubyObject;)Lorg/jruby/RubyModule;
        //     8: ldc             "Measurements"
        //    10: invokevirtual   org/jruby/RubyModule.defineOrGetModuleUnder:(Ljava/lang/String;)Lorg/jruby/RubyModule;
        //    13: dup            
        //    14: astore_2       
        //    15: aload_1        
        //    16: swap           
        //    17: aload_0        
        //    18: aload_1        
        //    19: ldc             ",0,0,-1"
        //    21: invokevirtual   ruby/jit/FILE_6685C7BB43146C8423BA5B272AF1FF8007E715FC.getScope1:(Lorg/jruby/runtime/ThreadContext;Ljava/lang/String;)Lorg/jruby/parser/StaticScope;
        //    24: invokevirtual   org/jruby/runtime/ThreadContext.preCompiledClassDummyScope:(Lorg/jruby/RubyModule;Lorg/jruby/parser/StaticScope;)V
        //    27: aload_0        
        //    28: aload_1        
        //    29: aload_0        
        //    30: aload_1        
        //    31: ldc_w           "Measurement"
        //    34: bipush          15
        //    36: invokevirtual   ruby/jit/FILE_6685C7BB43146C8423BA5B272AF1FF8007E715FC.getConstant:(Lorg/jruby/runtime/ThreadContext;Ljava/lang/String;I)Lorg/jruby/runtime/builtin/IRubyObject;
        //    39: getstatic       org/jruby/runtime/Block.NULL_BLOCK:Lorg/jruby/runtime/Block;
        //    42: invokestatic    ruby/jit/FILE_6685C7BB43146C8423BA5B272AF1FF8007E715FC.class_2$RUBY$AskEmail:(Lruby/jit/FILE_6685C7BB43146C8423BA5B272AF1FF8007E715FC;Lorg/jruby/runtime/ThreadContext;Lorg/jruby/runtime/builtin/IRubyObject;Lorg/jruby/runtime/Block;)Lorg/jruby/runtime/builtin/IRubyObject;
        //    45: aload_1        
        //    46: getfield        org/jruby/runtime/ThreadContext.nil:Lorg/jruby/runtime/builtin/IRubyObject;
        //    49: goto            57
        //    52: aload_1        
        //    53: invokevirtual   org/jruby/runtime/ThreadContext.postCompiledClass:()V
        //    56: athrow         
        //    57: aload_1        
        //    58: invokevirtual   org/jruby/runtime/ThreadContext.postCompiledClass:()V
        //    61: areturn        
        //    Exceptions:
        //  Try           Handler
        //  Start  End    Start  End    Type
        //  -----  -----  -----  -----  ----
        //  27     49     52     57     Any
        // 
        // The error that occurred was:
        // 
        // java.lang.ArrayIndexOutOfBoundsException
        // 
        throw new IllegalStateException("An error occurred while decompiling this method.");
    }
    
    public static IRubyObject class_2$RUBY$AskEmail(final FILE_6685C7BB43146C8423BA5B272AF1FF8007E715FC p0, final ThreadContext p1, final IRubyObject p2, final Block p3) {
        // 
        // This method could not be decompiled.
        // 
        // Original Bytecode:
        // 
        //     0: aload_1        
        //     1: getfield        org/jruby/runtime/ThreadContext.runtime:Lorg/jruby/Ruby;
        //     4: aload_2        
        //     5: invokestatic    org/jruby/javasupport/util/RuntimeHelpers.prepareSuperClass:(Lorg/jruby/Ruby;Lorg/jruby/runtime/builtin/IRubyObject;)Lorg/jruby/RubyClass;
        //     8: aload_1        
        //     9: aload_1        
        //    10: getfield        org/jruby/runtime/ThreadContext.nil:Lorg/jruby/runtime/builtin/IRubyObject;
        //    13: invokestatic    org/jruby/javasupport/util/RuntimeHelpers.prepareClassNamespace:(Lorg/jruby/runtime/ThreadContext;Lorg/jruby/runtime/builtin/IRubyObject;)Lorg/jruby/RubyModule;
        //    16: swap           
        //    17: ldc             "AskEmail"
        //    19: swap           
        //    20: invokevirtual   org/jruby/RubyModule.defineOrGetClassUnder:(Ljava/lang/String;Lorg/jruby/RubyClass;)Lorg/jruby/RubyClass;
        //    23: dup            
        //    24: astore_2       
        //    25: aload_1        
        //    26: swap           
        //    27: aload_0        
        //    28: aload_1        
        //    29: ldc             ",0,0,-1"
        //    31: invokevirtual   ruby/jit/FILE_6685C7BB43146C8423BA5B272AF1FF8007E715FC.getScope2:(Lorg/jruby/runtime/ThreadContext;Ljava/lang/String;)Lorg/jruby/parser/StaticScope;
        //    34: invokevirtual   org/jruby/runtime/ThreadContext.preCompiledClassDummyScope:(Lorg/jruby/RubyModule;Lorg/jruby/parser/StaticScope;)V
        //    37: aload_0        
        //    38: invokevirtual   ruby/jit/FILE_6685C7BB43146C8423BA5B272AF1FF8007E715FC.getCallSite7:()Lorg/jruby/runtime/CallSite;
        //    41: aload_1        
        //    42: aload_2        
        //    43: aload_2        
        //    44: aload_0        
        //    45: aload_1        
        //    46: ldc             "Questionnaire"
        //    48: invokevirtual   ruby/jit/FILE_6685C7BB43146C8423BA5B272AF1FF8007E715FC.getConstant0:(Lorg/jruby/runtime/ThreadContext;Ljava/lang/String;)Lorg/jruby/runtime/builtin/IRubyObject;
        //    51: invokestatic    org/jruby/javasupport/util/RuntimeHelpers.checkIsModule:(Lorg/jruby/runtime/builtin/IRubyObject;)Lorg/jruby/RubyModule;
        //    54: aload_0        
        //    55: swap           
        //    56: aload_1        
        //    57: ldc             "HasListeners"
        //    59: invokevirtual   ruby/jit/FILE_6685C7BB43146C8423BA5B272AF1FF8007E715FC.getConstantFrom1:(Lorg/jruby/RubyModule;Lorg/jruby/runtime/ThreadContext;Ljava/lang/String;)Lorg/jruby/runtime/builtin/IRubyObject;
        //    62: invokevirtual   org/jruby/runtime/CallSite.call:(Lorg/jruby/runtime/ThreadContext;Lorg/jruby/runtime/builtin/IRubyObject;Lorg/jruby/runtime/builtin/IRubyObject;Lorg/jruby/runtime/builtin/IRubyObject;)Lorg/jruby/runtime/builtin/IRubyObject;
        //    65: pop            
        //    66: aload_0        
        //    67: invokevirtual   ruby/jit/FILE_6685C7BB43146C8423BA5B272AF1FF8007E715FC.getCallSite8:()Lorg/jruby/runtime/CallSite;
        //    70: aload_1        
        //    71: aload_2        
        //    72: aload_2        
        //    73: aload_0        
        //    74: aload_1        
        //    75: getfield        org/jruby/runtime/ThreadContext.runtime:Lorg/jruby/Ruby;
        //    78: ldc             "questionnaire"
        //    80: invokevirtual   ruby/jit/FILE_6685C7BB43146C8423BA5B272AF1FF8007E715FC.getSymbol0:(Lorg/jruby/Ruby;Ljava/lang/String;)Lorg/jruby/RubySymbol;
        //    83: invokevirtual   org/jruby/runtime/CallSite.call:(Lorg/jruby/runtime/ThreadContext;Lorg/jruby/runtime/builtin/IRubyObject;Lorg/jruby/runtime/builtin/IRubyObject;Lorg/jruby/runtime/builtin/IRubyObject;)Lorg/jruby/runtime/builtin/IRubyObject;
        //    86: pop            
        //    87: aload_1        
        //    88: aload_2        
        //    89: aload_0        
        //    90: ldc             "description"
        //    92: ldc             "method__3$RUBY$description"
        //    94: ldc             ",0,0,-1"
        //    96: iconst_0       
        //    97: ldc             "./lib//lister/runner/measurements/ask_email.rb"
        //    99: ldc             20
        //   101: getstatic       org/jruby/internal/runtime/methods/CallConfiguration.FrameNoneScopeDummy:Lorg/jruby/internal/runtime/methods/CallConfiguration;
        //   104: ldc             "NONE"
        //   106: invokestatic    org/jruby/javasupport/util/RuntimeHelpers.def:(Lorg/jruby/runtime/ThreadContext;Lorg/jruby/runtime/builtin/IRubyObject;Ljava/lang/Object;Ljava/lang/String;Ljava/lang/String;Ljava/lang/String;ILjava/lang/String;ILorg/jruby/internal/runtime/methods/CallConfiguration;Ljava/lang/String;)Lorg/jruby/runtime/builtin/IRubyObject;
        //   109: pop            
        //   110: aload_1        
        //   111: aload_2        
        //   112: aload_0        
        //   113: ldc_w           "url_area"
        //   116: ldc_w           "method__4$RUBY$url_area"
        //   119: ldc_w           "a;ft,0,0,-1"
        //   122: iconst_0       
        //   123: ldc             "./lib//lister/runner/measurements/ask_email.rb"
        //   125: ldc_w           24
        //   128: getstatic       org/jruby/internal/runtime/methods/CallConfiguration.FrameFullScopeDummy:Lorg/jruby/internal/runtime/methods/CallConfiguration;
        //   131: ldc             "NONE"
        //   133: invokestatic    org/jruby/javasupport/util/RuntimeHelpers.def:(Lorg/jruby/runtime/ThreadContext;Lorg/jruby/runtime/builtin/IRubyObject;Ljava/lang/Object;Ljava/lang/String;Ljava/lang/String;Ljava/lang/String;ILjava/lang/String;ILorg/jruby/internal/runtime/methods/CallConfiguration;Ljava/lang/String;)Lorg/jruby/runtime/builtin/IRubyObject;
        //   136: pop            
        //   137: aload_1        
        //   138: aload_2        
        //   139: aload_0        
        //   140: ldc_w           "question"
        //   143: ldc_w           "method__5$RUBY$question"
        //   146: ldc_w           "q,0,0,-1"
        //   149: iconst_0       
        //   150: ldc             "./lib//lister/runner/measurements/ask_email.rb"
        //   152: ldc_w           32
        //   155: getstatic       org/jruby/internal/runtime/methods/CallConfiguration.FrameNoneScopeDummy:Lorg/jruby/internal/runtime/methods/CallConfiguration;
        //   158: ldc             "NONE"
        //   160: invokestatic    org/jruby/javasupport/util/RuntimeHelpers.def:(Lorg/jruby/runtime/ThreadContext;Lorg/jruby/runtime/builtin/IRubyObject;Ljava/lang/Object;Ljava/lang/String;Ljava/lang/String;Ljava/lang/String;ILjava/lang/String;ILorg/jruby/internal/runtime/methods/CallConfiguration;Ljava/lang/String;)Lorg/jruby/runtime/builtin/IRubyObject;
        //   163: pop            
        //   164: aload_1        
        //   165: aload_2        
        //   166: aload_0        
        //   167: ldc_w           "questions"
        //   170: ldc_w           "method__6$RUBY$questions"
        //   173: ldc             ",0,0,-1"
        //   175: iconst_0       
        //   176: ldc             "./lib//lister/runner/measurements/ask_email.rb"
        //   178: ldc_w           39
        //   181: getstatic       org/jruby/internal/runtime/methods/CallConfiguration.FrameNoneScopeNone:Lorg/jruby/internal/runtime/methods/CallConfiguration;
        //   184: ldc             "NONE"
        //   186: invokestatic    org/jruby/javasupport/util/RuntimeHelpers.def:(Lorg/jruby/runtime/ThreadContext;Lorg/jruby/runtime/builtin/IRubyObject;Ljava/lang/Object;Ljava/lang/String;Ljava/lang/String;Ljava/lang/String;ILjava/lang/String;ILorg/jruby/internal/runtime/methods/CallConfiguration;Ljava/lang/String;)Lorg/jruby/runtime/builtin/IRubyObject;
        //   189: pop            
        //   190: aload_1        
        //   191: aload_2        
        //   192: aload_0        
        //   193: ldc_w           "execute"
        //   196: ldc_w           "method__7$RUBY$execute"
        //   199: ldc             ",0,0,-1"
        //   201: iconst_0       
        //   202: ldc             "./lib//lister/runner/measurements/ask_email.rb"
        //   204: ldc_w           43
        //   207: getstatic       org/jruby/internal/runtime/methods/CallConfiguration.FrameFullScopeDummy:Lorg/jruby/internal/runtime/methods/CallConfiguration;
        //   210: ldc             "NONE"
        //   212: invokestatic    org/jruby/javasupport/util/RuntimeHelpers.def:(Lorg/jruby/runtime/ThreadContext;Lorg/jruby/runtime/builtin/IRubyObject;Ljava/lang/Object;Ljava/lang/String;Ljava/lang/String;Ljava/lang/String;ILjava/lang/String;ILorg/jruby/internal/runtime/methods/CallConfiguration;Ljava/lang/String;)Lorg/jruby/runtime/builtin/IRubyObject;
        //   215: pop            
        //   216: aload_1        
        //   217: aload_2        
        //   218: aload_0        
        //   219: ldc_w           "reports"
        //   222: ldc_w           "method__8$RUBY$reports"
        //   225: ldc             ",0,0,-1"
        //   227: iconst_0       
        //   228: ldc             "./lib//lister/runner/measurements/ask_email.rb"
        //   230: ldc_w           53
        //   233: getstatic       org/jruby/internal/runtime/methods/CallConfiguration.FrameNoneScopeNone:Lorg/jruby/internal/runtime/methods/CallConfiguration;
        //   236: ldc             "NONE"
        //   238: invokestatic    org/jruby/javasupport/util/RuntimeHelpers.def:(Lorg/jruby/runtime/ThreadContext;Lorg/jruby/runtime/builtin/IRubyObject;Ljava/lang/Object;Ljava/lang/String;Ljava/lang/String;Ljava/lang/String;ILjava/lang/String;ILorg/jruby/internal/runtime/methods/CallConfiguration;Ljava/lang/String;)Lorg/jruby/runtime/builtin/IRubyObject;
        //   241: aload_1        
        //   242: invokevirtual   org/jruby/runtime/ThreadContext.postCompiledClass:()V
        //   245: goto            253
        //   248: aload_1        
        //   249: invokevirtual   org/jruby/runtime/ThreadContext.postCompiledClass:()V
        //   252: athrow         
        //   253: areturn        
        //    Exceptions:
        //  Try           Handler
        //  Start  End    Start  End    Type
        //  -----  -----  -----  -----  ----
        //  37     241    248    253    Any
        // 
        // The error that occurred was:
        // 
        // java.lang.ArrayIndexOutOfBoundsException
        // 
        throw new IllegalStateException("An error occurred while decompiling this method.");
    }
    
    @JRubyMethod(name = "description", frame = true, required = 0, optional = 0, rest = -1)
    public static IRubyObject method__3$RUBY$description(final FILE_6685C7BB43146C8423BA5B272AF1FF8007E715FC file_6685C7BB43146C8423BA5B272AF1FF8007E715FC, final ThreadContext context, final IRubyObject rubyObject, final Block block) {
        return file_6685C7BB43146C8423BA5B272AF1FF8007E715FC.getCallSite9().call(context, rubyObject, file_6685C7BB43146C8423BA5B272AF1FF8007E715FC.getConstant2(context, "QuestionsList"));
    }
    
    @JRubyMethod(name = "url_area", frame = true, required = 0, optional = 0, rest = -1)
    public static IRubyObject method__4$RUBY$url_area(final FILE_6685C7BB43146C8423BA5B272AF1FF8007E715FC file_6685C7BB43146C8423BA5B272AF1FF8007E715FC, final ThreadContext threadContext, final IRubyObject rubyObject, final Block block) {
        IRubyObject ft = threadContext.nil;
        final IRubyObject call;
        final IRubyObject a = call = file_6685C7BB43146C8423BA5B272AF1FF8007E715FC.getCallSite(10).call(threadContext, rubyObject, file_6685C7BB43146C8423BA5B272AF1FF8007E715FC.getConstant3(threadContext, "JTextArea"), file_6685C7BB43146C8423BA5B272AF1FF8007E715FC.getCallSite(11).call(threadContext, rubyObject, file_6685C7BB43146C8423BA5B272AF1FF8007E715FC.getCallSite(12).call(threadContext, rubyObject, rubyObject)));
        final CallSite selectAttrAsgnCallSite = RuntimeHelpers.selectAttrAsgnCallSite(call, rubyObject, file_6685C7BB43146C8423BA5B272AF1FF8007E715FC.getCallSite(13), file_6685C7BB43146C8423BA5B272AF1FF8007E715FC.getCallSite(14));
        final RubyBoolean false = threadContext.runtime.getFalse();
        threadContext.pollThreadEvents();
        RuntimeHelpers.doAttrAsgn(call, selectAttrAsgnCallSite, false, threadContext, rubyObject);
        ft = file_6685C7BB43146C8423BA5B272AF1FF8007E715FC.getCallSite(15).call(threadContext, rubyObject, a);
        final IRubyObject rubyObject2 = a;
        RuntimeHelpers.doAttrAsgn(rubyObject2, RuntimeHelpers.selectAttrAsgnCallSite(rubyObject2, rubyObject, file_6685C7BB43146C8423BA5B272AF1FF8007E715FC.getCallSite(16), file_6685C7BB43146C8423BA5B272AF1FF8007E715FC.getCallSite(17)), file_6685C7BB43146C8423BA5B272AF1FF8007E715FC.getCallSite(18).call(threadContext, rubyObject, file_6685C7BB43146C8423BA5B272AF1FF8007E715FC.getConstant4(threadContext, "Font"), file_6685C7BB43146C8423BA5B272AF1FF8007E715FC.getCallSite(19).call(threadContext, rubyObject, ft), file_6685C7BB43146C8423BA5B272AF1FF8007E715FC.getConstantFrom6(RuntimeHelpers.checkIsModule(file_6685C7BB43146C8423BA5B272AF1FF8007E715FC.getConstant5(threadContext, "Font")), threadContext, "BOLD"), file_6685C7BB43146C8423BA5B272AF1FF8007E715FC.getCallSite(20).call(threadContext, rubyObject, file_6685C7BB43146C8423BA5B272AF1FF8007E715FC.getCallSite(21).call(threadContext, rubyObject, ft), 1L)), threadContext, rubyObject);
        return a;
    }
    
    @JRubyMethod(name = "question", frame = true, required = 0, optional = 0, rest = -1)
    public static IRubyObject method__5$RUBY$question(final FILE_6685C7BB43146C8423BA5B272AF1FF8007E715FC file_6685C7BB43146C8423BA5B272AF1FF8007E715FC, final ThreadContext threadContext, final IRubyObject rubyObject, final Block block) {
        IRubyObject q = threadContext.nil;
        q = file_6685C7BB43146C8423BA5B272AF1FF8007E715FC.getCallSite(22).call(threadContext, rubyObject, file_6685C7BB43146C8423BA5B272AF1FF8007E715FC.getConstantFrom8(RuntimeHelpers.checkIsModule(file_6685C7BB43146C8423BA5B272AF1FF8007E715FC.getConstant7(threadContext, "Questionnaire")), threadContext, "Questionnaire"), file_6685C7BB43146C8423BA5B272AF1FF8007E715FC.getCallSite(23).call(threadContext, rubyObject, rubyObject), file_6685C7BB43146C8423BA5B272AF1FF8007E715FC.getCallSite(24).call(threadContext, rubyObject, file_6685C7BB43146C8423BA5B272AF1FF8007E715FC.getCallSite(25).call(threadContext, rubyObject, rubyObject)));
        file_6685C7BB43146C8423BA5B272AF1FF8007E715FC.getCallSite(26).call(threadContext, rubyObject, q, file_6685C7BB43146C8423BA5B272AF1FF8007E715FC.getCallSite(27).call(threadContext, rubyObject, rubyObject), file_6685C7BB43146C8423BA5B272AF1FF8007E715FC.getConstantFrom(RuntimeHelpers.checkIsModule(file_6685C7BB43146C8423BA5B272AF1FF8007E715FC.getConstant9(threadContext, "BorderLayout")), threadContext, "SOUTH", 10));
        return q;
    }
    
    @JRubyMethod(name = "questions", frame = true, required = 0, optional = 0, rest = -1)
    public static IRubyObject method__6$RUBY$questions(final FILE_6685C7BB43146C8423BA5B272AF1FF8007E715FC file_6685C7BB43146C8423BA5B272AF1FF8007E715FC, final ThreadContext threadContext, final IRubyObject rubyObject, final Block block) {
        return RuntimeHelpers.constructRubyArray(threadContext.runtime, file_6685C7BB43146C8423BA5B272AF1FF8007E715FC.getCallSite(28).call(threadContext, rubyObject, rubyObject));
    }
    
    @JRubyMethod(name = "execute", frame = true, required = 0, optional = 0, rest = -1)
    public static IRubyObject method__7$RUBY$execute(final FILE_6685C7BB43146C8423BA5B272AF1FF8007E715FC file_6685C7BB43146C8423BA5B272AF1FF8007E715FC, final ThreadContext threadContext, final IRubyObject caller, final Block block) {
        file_6685C7BB43146C8423BA5B272AF1FF8007E715FC.setVariable0(threadContext.runtime, "@questionnaire", caller, file_6685C7BB43146C8423BA5B272AF1FF8007E715FC.getCallSite(29).call(threadContext, caller, file_6685C7BB43146C8423BA5B272AF1FF8007E715FC.getConstantFrom(RuntimeHelpers.checkIsModule(file_6685C7BB43146C8423BA5B272AF1FF8007E715FC.getConstant(threadContext, "Questionnaire", 11)), threadContext, "Questionnaire", 12), file_6685C7BB43146C8423BA5B272AF1FF8007E715FC.getCallSite(30).call(threadContext, caller, caller), file_6685C7BB43146C8423BA5B272AF1FF8007E715FC.getCallSite(31).call(threadContext, caller, file_6685C7BB43146C8423BA5B272AF1FF8007E715FC.getCallSite(32).call(threadContext, caller, caller))));
        file_6685C7BB43146C8423BA5B272AF1FF8007E715FC.getCallSite(33).call(threadContext, caller, file_6685C7BB43146C8423BA5B272AF1FF8007E715FC.getCallSite(34).call(threadContext, caller, caller));
        file_6685C7BB43146C8423BA5B272AF1FF8007E715FC.getCallSite(35).call(threadContext, caller, file_6685C7BB43146C8423BA5B272AF1FF8007E715FC.getCallSite(36).call(threadContext, caller, file_6685C7BB43146C8423BA5B272AF1FF8007E715FC.getCallSite(37).call(threadContext, caller, caller)), file_6685C7BB43146C8423BA5B272AF1FF8007E715FC.getCallSite(38).call(threadContext, caller, caller));
        final IRubyObject call = file_6685C7BB43146C8423BA5B272AF1FF8007E715FC.getCallSite(39).call(threadContext, caller, file_6685C7BB43146C8423BA5B272AF1FF8007E715FC.getCallSite(40).call(threadContext, caller, caller));
        final CallSite selectAttrAsgnCallSite = RuntimeHelpers.selectAttrAsgnCallSite(call, caller, file_6685C7BB43146C8423BA5B272AF1FF8007E715FC.getCallSite(41), file_6685C7BB43146C8423BA5B272AF1FF8007E715FC.getCallSite(42));
        final RubyBoolean true = threadContext.runtime.getTrue();
        threadContext.pollThreadEvents();
        RuntimeHelpers.doAttrAsgn(call, selectAttrAsgnCallSite, true, threadContext, caller);
        file_6685C7BB43146C8423BA5B272AF1FF8007E715FC.getCallSite(43).call(threadContext, caller, file_6685C7BB43146C8423BA5B272AF1FF8007E715FC.getConstantFrom(RuntimeHelpers.checkIsModule(file_6685C7BB43146C8423BA5B272AF1FF8007E715FC.getConstant(threadContext, "Questionnaire", 13)), threadContext, "ApplicationWorkFlow", 14), file_6685C7BB43146C8423BA5B272AF1FF8007E715FC.getCallSite(44).call(threadContext, caller, caller));
        final IRubyObject call2 = file_6685C7BB43146C8423BA5B272AF1FF8007E715FC.getCallSite(45).call(threadContext, caller, caller);
        final CallSite selectAttrAsgnCallSite2 = RuntimeHelpers.selectAttrAsgnCallSite(call2, caller, file_6685C7BB43146C8423BA5B272AF1FF8007E715FC.getCallSite(46), file_6685C7BB43146C8423BA5B272AF1FF8007E715FC.getCallSite(47));
        final RubyBoolean false = threadContext.runtime.getFalse();
        threadContext.pollThreadEvents();
        RuntimeHelpers.doAttrAsgn(call2, selectAttrAsgnCallSite2, false, threadContext, caller);
        return file_6685C7BB43146C8423BA5B272AF1FF8007E715FC.getCallSite(48).call(threadContext, caller, file_6685C7BB43146C8423BA5B272AF1FF8007E715FC.getCallSite(49).call(threadContext, caller, file_6685C7BB43146C8423BA5B272AF1FF8007E715FC.getCallSite(50).call(threadContext, caller, caller)), file_6685C7BB43146C8423BA5B272AF1FF8007E715FC.getCallSite(51).call(threadContext, caller, caller));
    }
    
    @JRubyMethod(name = "reports", frame = true, required = 0, optional = 0, rest = -1)
    public static IRubyObject method__8$RUBY$reports(final FILE_6685C7BB43146C8423BA5B272AF1FF8007E715FC file_6685C7BB43146C8423BA5B272AF1FF8007E715FC, final ThreadContext threadContext, final IRubyObject rubyObject, final Block block) {
        return file_6685C7BB43146C8423BA5B272AF1FF8007E715FC.getCallSite(52).call(threadContext, rubyObject, file_6685C7BB43146C8423BA5B272AF1FF8007E715FC.getCallSite(53).call(threadContext, rubyObject, rubyObject));
    }
    
    public static IRubyObject class_2$RUBY$AskEmail(final FILE_6685C7BB43146C8423BA5B272AF1FF8007E715FC file_6685C7BB43146C8423BA5B272AF1FF8007E715FC, final ThreadContext threadContext, final IRubyObject rubyObject, final IRubyObject[] args, final Block block) {
        Arity.checkArgumentCount(threadContext.getRuntime(), args, 0, 0);
        return class_2$RUBY$AskEmail(file_6685C7BB43146C8423BA5B272AF1FF8007E715FC, threadContext, rubyObject, block);
    }
    
    public static IRubyObject module__1$RUBY$Measurements(final FILE_6685C7BB43146C8423BA5B272AF1FF8007E715FC file_6685C7BB43146C8423BA5B272AF1FF8007E715FC, final ThreadContext threadContext, final IRubyObject rubyObject, final IRubyObject[] args, final Block block) {
        Arity.checkArgumentCount(threadContext.getRuntime(), args, 0, 0);
        return module__1$RUBY$Measurements(file_6685C7BB43146C8423BA5B272AF1FF8007E715FC, threadContext, rubyObject, block);
    }
    
    public static IRubyObject module__0$RUBY$Lister(final FILE_6685C7BB43146C8423BA5B272AF1FF8007E715FC file_6685C7BB43146C8423BA5B272AF1FF8007E715FC, final ThreadContext threadContext, final IRubyObject rubyObject, final IRubyObject[] args, final Block block) {
        Arity.checkArgumentCount(threadContext.getRuntime(), args, 0, 0);
        return module__0$RUBY$Lister(file_6685C7BB43146C8423BA5B272AF1FF8007E715FC, threadContext, rubyObject, block);
    }
    
    @Override
    public IRubyObject load(final ThreadContext context, final IRubyObject rubyObject, final IRubyObject[] array, final Block block) {
        try {
            RuntimeHelpers.preLoad(context, ",0,0,-2");
            final IRubyObject _file__ = __file__(this, context, rubyObject, array, block);
            RuntimeHelpers.postLoad(context);
            return _file__;
        }
        finally {
            RuntimeHelpers.postLoad(context);
        }
    }
    
    public static void main(final String[] argv) {
        final FILE_6685C7BB43146C8423BA5B272AF1FF8007E715FC file_6685C7BB43146C8423BA5B272AF1FF8007E715FC = new FILE_6685C7BB43146C8423BA5B272AF1FF8007E715FC();
        final String string = FILE_6685C7BB43146C8423BA5B272AF1FF8007E715FC.class.getClassLoader().getResource("ruby/jit/FILE_6685C7BB43146C8423BA5B272AF1FF8007E715FC.class").toString();
        file_6685C7BB43146C8423BA5B272AF1FF8007E715FC.setFilename(string);
        final RubyInstanceConfig config = new RubyInstanceConfig();
        config.setArgv(argv);
        config.setScriptFileName(string);
        final Ruby instance = Ruby.newInstance(config);
        file_6685C7BB43146C8423BA5B272AF1FF8007E715FC.load(instance.getCurrentContext(), instance.getTopSelf(), IRubyObject.NULL_ARRAY, Block.NULL_BLOCK);
    }
}
