// 
// Decompiled by Procyon v0.5.30
// 

package ruby.jit;

import org.jruby.Ruby;
import org.jruby.RubyInstanceConfig;
import org.jruby.runtime.Arity;
import org.jruby.javasupport.util.RuntimeHelpers;
import org.jruby.anno.JRubyMethod;
import org.jruby.runtime.Block;
import org.jruby.runtime.builtin.IRubyObject;
import org.jruby.ast.executable.RuntimeCache;
import org.jruby.runtime.ThreadContext;
import org.jruby.ast.executable.AbstractScript;

public class FILE_71957678BABDE3B4E4F91A6AC4CBFD3837C15D97 extends AbstractScript
{
    public FILE_71957678BABDE3B4E4F91A6AC4CBFD3837C15D97() {
        this.filename = "./lib//lister/measurements/lan_services.rb";
        super.runtimeCache = new RuntimeCache();
        this.initFromDescriptor("require\uffffF\uffffversion\uffffF\uffffold_versions\uffffF\uffffdescribe\uffffF\uffffdescribe\uffffF\uffffdescribe\uffffF\uffffdescribe\uffffF\uffffreport\uffffF\uffffdescribe\uffffF\uffffdescribe\uffffF\uffffreport\uffffF\uffffdescribe\uffffF\uffffdescribe\uffffF\uffff\u0003\u0002\u0000\u0000\u0001\u0000\u0000\u0000\u0000\u0002\u0000\u0000\u0014\u0001");
        this.setEncoding(0, "ASCII-8BIT");
        this.setByteList(8, "0.1.1", this.getEncoding0());
        this.setByteList(1, "0.1.2", this.getEncoding0());
        this.setByteList(7, "0.1.0", this.getEncoding0());
        this.setByteList(2, "dev", this.getEncoding0());
        this.setByteList(0, "lister/measurement", this.getEncoding0());
        this.setByteList(16, "The list of services found via UPnP", this.getEncoding0());
        this.setByteList(13, "English-HTML", this.getEncoding0());
        this.setByteList(12, "<p>This module scans the set of services provided by\nnetwork-enabled devices connected to your home network. We use Zeroconf and\nUPnP to test the set of services provided by network-enabled devices. We do not\ncollect the names of the services, but their type (for example, we will log\n\"music library\" instead of \"Jon Doe's ITune's playlist\"). \n      </p>", this.getEncoding0());
        this.setByteList(9, "List of network services", this.getEncoding0());
        this.setByteList(14, "Ce module cherche des services offerts par les autres appareils \n      connect\uffc3\uffa9s sur votre r\uffc3\uffa9seau. Nous testons \uffc3\uffa0 la fois Zeroconf et UPnP. Cela nous\n      donnera une id\uffc3\uffa9e de la proportion d'objets qui utilisent ces protocoles.\n      Nous ne prenons pas les noms des services, mais leur type.", this.getEncoding0());
        this.setByteList(11, "Fran\uffc3\uffa7ais", this.getEncoding0());
        this.setByteList(3, "0.0.1", this.getEncoding0());
        this.setByteList(19, "La liste des services trouv\uffc3\uffa9s par Zeroconf (Bonjour)", this.getEncoding0());
        this.setByteList(5, "0.0.3", this.getEncoding0());
        this.setByteList(4, "0.0.2", this.getEncoding0());
        this.setByteList(10, "Liste des services r\uffc3\uffa9seau", this.getEncoding0());
        this.setByteList(17, "La liste des services trouv\uffc3\uffa9s par UPnP", this.getEncoding0());
        this.setByteList(6, "0.0.4", this.getEncoding0());
        this.setByteList(15, "Fran\uffc3\uffa7ais-HTML", this.getEncoding0());
        this.setByteList(18, "The list of services found via Zeroconf (Bonjour)", this.getEncoding0());
    }
    
    @JRubyMethod(name = "__file__", frame = true, required = 0, optional = 0, rest = -2)
    public static IRubyObject __file__(final FILE_71957678BABDE3B4E4F91A6AC4CBFD3837C15D97 file_71957678BABDE3B4E4F91A6AC4CBFD3837C15D97, final ThreadContext threadContext, final IRubyObject rubyObject, final IRubyObject[] array, final Block block) {
        file_71957678BABDE3B4E4F91A6AC4CBFD3837C15D97.getCallSite0().call(threadContext, rubyObject, rubyObject, file_71957678BABDE3B4E4F91A6AC4CBFD3837C15D97.getString0(threadContext.runtime, 32));
        return module__0$RUBY$Lister(file_71957678BABDE3B4E4F91A6AC4CBFD3837C15D97, threadContext, rubyObject, IRubyObject.NULL_ARRAY, Block.NULL_BLOCK);
    }
    
    @Override
    public IRubyObject __file__(final ThreadContext threadContext, final IRubyObject rubyObject, final IRubyObject[] array, final Block block) {
        return __file__(this, threadContext, rubyObject, array, block);
    }
    
    public static IRubyObject module__0$RUBY$Lister(final FILE_71957678BABDE3B4E4F91A6AC4CBFD3837C15D97 p0, final ThreadContext p1, final IRubyObject p2, final Block p3) {
        // 
        // This method could not be decompiled.
        // 
        // Original Bytecode:
        // 
        //     0: aload_1        
        //     1: aload_1        
        //     2: getfield        org/jruby/runtime/ThreadContext.nil:Lorg/jruby/runtime/builtin/IRubyObject;
        //     5: invokestatic    org/jruby/javasupport/util/RuntimeHelpers.prepareClassNamespace:(Lorg/jruby/runtime/ThreadContext;Lorg/jruby/runtime/builtin/IRubyObject;)Lorg/jruby/RubyModule;
        //     8: ldc             "Lister"
        //    10: invokevirtual   org/jruby/RubyModule.defineOrGetModuleUnder:(Ljava/lang/String;)Lorg/jruby/RubyModule;
        //    13: dup            
        //    14: astore_2       
        //    15: aload_1        
        //    16: swap           
        //    17: aload_0        
        //    18: aload_1        
        //    19: ldc             ",0,0,-1"
        //    21: invokevirtual   ruby/jit/FILE_71957678BABDE3B4E4F91A6AC4CBFD3837C15D97.getScope0:(Lorg/jruby/runtime/ThreadContext;Ljava/lang/String;)Lorg/jruby/parser/StaticScope;
        //    24: invokevirtual   org/jruby/runtime/ThreadContext.preCompiledClassDummyScope:(Lorg/jruby/RubyModule;Lorg/jruby/parser/StaticScope;)V
        //    27: aload_0        
        //    28: aload_1        
        //    29: aload_2        
        //    30: getstatic       org/jruby/runtime/builtin/IRubyObject.NULL_ARRAY:[Lorg/jruby/runtime/builtin/IRubyObject;
        //    33: getstatic       org/jruby/runtime/Block.NULL_BLOCK:Lorg/jruby/runtime/Block;
        //    36: invokestatic    ruby/jit/FILE_71957678BABDE3B4E4F91A6AC4CBFD3837C15D97.module__1$RUBY$Measurements:(Lruby/jit/FILE_71957678BABDE3B4E4F91A6AC4CBFD3837C15D97;Lorg/jruby/runtime/ThreadContext;Lorg/jruby/runtime/builtin/IRubyObject;[Lorg/jruby/runtime/builtin/IRubyObject;Lorg/jruby/runtime/Block;)Lorg/jruby/runtime/builtin/IRubyObject;
        //    39: aload_1        
        //    40: getfield        org/jruby/runtime/ThreadContext.nil:Lorg/jruby/runtime/builtin/IRubyObject;
        //    43: goto            51
        //    46: aload_1        
        //    47: invokevirtual   org/jruby/runtime/ThreadContext.postCompiledClass:()V
        //    50: athrow         
        //    51: aload_1        
        //    52: invokevirtual   org/jruby/runtime/ThreadContext.postCompiledClass:()V
        //    55: areturn        
        //    Exceptions:
        //  Try           Handler
        //  Start  End    Start  End    Type
        //  -----  -----  -----  -----  ----
        //  27     43     46     51     Any
        // 
        // The error that occurred was:
        // 
        // java.lang.ArrayIndexOutOfBoundsException
        // 
        throw new IllegalStateException("An error occurred while decompiling this method.");
    }
    
    public static IRubyObject module__1$RUBY$Measurements(final FILE_71957678BABDE3B4E4F91A6AC4CBFD3837C15D97 p0, final ThreadContext p1, final IRubyObject p2, final Block p3) {
        // 
        // This method could not be decompiled.
        // 
        // Original Bytecode:
        // 
        //     0: aload_1        
        //     1: aload_1        
        //     2: getfield        org/jruby/runtime/ThreadContext.nil:Lorg/jruby/runtime/builtin/IRubyObject;
        //     5: invokestatic    org/jruby/javasupport/util/RuntimeHelpers.prepareClassNamespace:(Lorg/jruby/runtime/ThreadContext;Lorg/jruby/runtime/builtin/IRubyObject;)Lorg/jruby/RubyModule;
        //     8: ldc             "Measurements"
        //    10: invokevirtual   org/jruby/RubyModule.defineOrGetModuleUnder:(Ljava/lang/String;)Lorg/jruby/RubyModule;
        //    13: dup            
        //    14: astore_2       
        //    15: aload_1        
        //    16: swap           
        //    17: aload_0        
        //    18: aload_1        
        //    19: ldc             ",0,0,-1"
        //    21: invokevirtual   ruby/jit/FILE_71957678BABDE3B4E4F91A6AC4CBFD3837C15D97.getScope1:(Lorg/jruby/runtime/ThreadContext;Ljava/lang/String;)Lorg/jruby/parser/StaticScope;
        //    24: invokevirtual   org/jruby/runtime/ThreadContext.preCompiledClassDummyScope:(Lorg/jruby/RubyModule;Lorg/jruby/parser/StaticScope;)V
        //    27: aload_0        
        //    28: aload_1        
        //    29: aload_0        
        //    30: aload_1        
        //    31: ldc             "Measurement"
        //    33: invokevirtual   ruby/jit/FILE_71957678BABDE3B4E4F91A6AC4CBFD3837C15D97.getConstant0:(Lorg/jruby/runtime/ThreadContext;Ljava/lang/String;)Lorg/jruby/runtime/builtin/IRubyObject;
        //    36: getstatic       org/jruby/runtime/Block.NULL_BLOCK:Lorg/jruby/runtime/Block;
        //    39: invokestatic    ruby/jit/FILE_71957678BABDE3B4E4F91A6AC4CBFD3837C15D97.class_2$RUBY$NetworkServices:(Lruby/jit/FILE_71957678BABDE3B4E4F91A6AC4CBFD3837C15D97;Lorg/jruby/runtime/ThreadContext;Lorg/jruby/runtime/builtin/IRubyObject;Lorg/jruby/runtime/Block;)Lorg/jruby/runtime/builtin/IRubyObject;
        //    42: aload_1        
        //    43: getfield        org/jruby/runtime/ThreadContext.nil:Lorg/jruby/runtime/builtin/IRubyObject;
        //    46: goto            54
        //    49: aload_1        
        //    50: invokevirtual   org/jruby/runtime/ThreadContext.postCompiledClass:()V
        //    53: athrow         
        //    54: aload_1        
        //    55: invokevirtual   org/jruby/runtime/ThreadContext.postCompiledClass:()V
        //    58: areturn        
        //    Exceptions:
        //  Try           Handler
        //  Start  End    Start  End    Type
        //  -----  -----  -----  -----  ----
        //  27     46     49     54     Any
        // 
        // The error that occurred was:
        // 
        // java.lang.ArrayIndexOutOfBoundsException
        // 
        throw new IllegalStateException("An error occurred while decompiling this method.");
    }
    
    public static IRubyObject class_2$RUBY$NetworkServices(final FILE_71957678BABDE3B4E4F91A6AC4CBFD3837C15D97 p0, final ThreadContext p1, final IRubyObject p2, final Block p3) {
        // 
        // This method could not be decompiled.
        // 
        // Original Bytecode:
        // 
        //     0: aload_1        
        //     1: invokevirtual   org/jruby/runtime/ThreadContext.getCurrentScope:()Lorg/jruby/runtime/DynamicScope;
        //     4: dup            
        //     5: astore          4
        //     7: invokevirtual   org/jruby/runtime/DynamicScope.getValues:()[Lorg/jruby/runtime/builtin/IRubyObject;
        //    10: astore          5
        //    12: aload_1        
        //    13: getfield        org/jruby/runtime/ThreadContext.runtime:Lorg/jruby/Ruby;
        //    16: aload_2        
        //    17: invokestatic    org/jruby/javasupport/util/RuntimeHelpers.prepareSuperClass:(Lorg/jruby/Ruby;Lorg/jruby/runtime/builtin/IRubyObject;)Lorg/jruby/RubyClass;
        //    20: aload_1        
        //    21: aload_1        
        //    22: getfield        org/jruby/runtime/ThreadContext.nil:Lorg/jruby/runtime/builtin/IRubyObject;
        //    25: invokestatic    org/jruby/javasupport/util/RuntimeHelpers.prepareClassNamespace:(Lorg/jruby/runtime/ThreadContext;Lorg/jruby/runtime/builtin/IRubyObject;)Lorg/jruby/RubyModule;
        //    28: swap           
        //    29: ldc             "NetworkServices"
        //    31: swap           
        //    32: invokevirtual   org/jruby/RubyModule.defineOrGetClassUnder:(Ljava/lang/String;Lorg/jruby/RubyClass;)Lorg/jruby/RubyClass;
        //    35: dup            
        //    36: astore_2       
        //    37: aload_1        
        //    38: swap           
        //    39: aload_0        
        //    40: aload_1        
        //    41: ldc             ",0,0,-1"
        //    43: invokevirtual   ruby/jit/FILE_71957678BABDE3B4E4F91A6AC4CBFD3837C15D97.getScope2:(Lorg/jruby/runtime/ThreadContext;Ljava/lang/String;)Lorg/jruby/parser/StaticScope;
        //    46: invokevirtual   org/jruby/runtime/ThreadContext.preCompiledClass:(Lorg/jruby/RubyModule;Lorg/jruby/parser/StaticScope;)V
        //    49: aload_1        
        //    50: invokevirtual   org/jruby/runtime/ThreadContext.getCurrentScope:()Lorg/jruby/runtime/DynamicScope;
        //    53: astore          locals
        //    55: aload_0        
        //    56: invokevirtual   ruby/jit/FILE_71957678BABDE3B4E4F91A6AC4CBFD3837C15D97.getCallSite1:()Lorg/jruby/runtime/CallSite;
        //    59: aload_1        
        //    60: aload_2        
        //    61: aload_2        
        //    62: aload_0        
        //    63: aload_1        
        //    64: getfield        org/jruby/runtime/ThreadContext.runtime:Lorg/jruby/Ruby;
        //    67: bipush          32
        //    69: invokevirtual   ruby/jit/FILE_71957678BABDE3B4E4F91A6AC4CBFD3837C15D97.getString1:(Lorg/jruby/Ruby;I)Lorg/jruby/RubyString;
        //    72: invokevirtual   org/jruby/runtime/CallSite.call:(Lorg/jruby/runtime/ThreadContext;Lorg/jruby/runtime/builtin/IRubyObject;Lorg/jruby/runtime/builtin/IRubyObject;Lorg/jruby/runtime/builtin/IRubyObject;)Lorg/jruby/runtime/builtin/IRubyObject;
        //    75: pop            
        //    76: aload_0        
        //    77: invokevirtual   ruby/jit/FILE_71957678BABDE3B4E4F91A6AC4CBFD3837C15D97.getCallSite2:()Lorg/jruby/runtime/CallSite;
        //    80: aload_1        
        //    81: aload_2        
        //    82: aload_2        
        //    83: bipush          7
        //    85: anewarray       Lorg/jruby/runtime/builtin/IRubyObject;
        //    88: dup            
        //    89: iconst_0       
        //    90: aload_0        
        //    91: aload_1        
        //    92: getfield        org/jruby/runtime/ThreadContext.runtime:Lorg/jruby/Ruby;
        //    95: bipush          32
        //    97: invokevirtual   ruby/jit/FILE_71957678BABDE3B4E4F91A6AC4CBFD3837C15D97.getString2:(Lorg/jruby/Ruby;I)Lorg/jruby/RubyString;
        //   100: aastore        
        //   101: dup            
        //   102: iconst_1       
        //   103: aload_0        
        //   104: aload_1        
        //   105: getfield        org/jruby/runtime/ThreadContext.runtime:Lorg/jruby/Ruby;
        //   108: bipush          32
        //   110: invokevirtual   ruby/jit/FILE_71957678BABDE3B4E4F91A6AC4CBFD3837C15D97.getString3:(Lorg/jruby/Ruby;I)Lorg/jruby/RubyString;
        //   113: aastore        
        //   114: dup            
        //   115: iconst_2       
        //   116: aload_0        
        //   117: aload_1        
        //   118: getfield        org/jruby/runtime/ThreadContext.runtime:Lorg/jruby/Ruby;
        //   121: bipush          32
        //   123: invokevirtual   ruby/jit/FILE_71957678BABDE3B4E4F91A6AC4CBFD3837C15D97.getString4:(Lorg/jruby/Ruby;I)Lorg/jruby/RubyString;
        //   126: aastore        
        //   127: dup            
        //   128: iconst_3       
        //   129: aload_0        
        //   130: aload_1        
        //   131: getfield        org/jruby/runtime/ThreadContext.runtime:Lorg/jruby/Ruby;
        //   134: bipush          32
        //   136: invokevirtual   ruby/jit/FILE_71957678BABDE3B4E4F91A6AC4CBFD3837C15D97.getString5:(Lorg/jruby/Ruby;I)Lorg/jruby/RubyString;
        //   139: aastore        
        //   140: dup            
        //   141: iconst_4       
        //   142: aload_0        
        //   143: aload_1        
        //   144: getfield        org/jruby/runtime/ThreadContext.runtime:Lorg/jruby/Ruby;
        //   147: bipush          32
        //   149: invokevirtual   ruby/jit/FILE_71957678BABDE3B4E4F91A6AC4CBFD3837C15D97.getString6:(Lorg/jruby/Ruby;I)Lorg/jruby/RubyString;
        //   152: aastore        
        //   153: dup            
        //   154: iconst_5       
        //   155: aload_0        
        //   156: aload_1        
        //   157: getfield        org/jruby/runtime/ThreadContext.runtime:Lorg/jruby/Ruby;
        //   160: bipush          32
        //   162: invokevirtual   ruby/jit/FILE_71957678BABDE3B4E4F91A6AC4CBFD3837C15D97.getString7:(Lorg/jruby/Ruby;I)Lorg/jruby/RubyString;
        //   165: aastore        
        //   166: dup            
        //   167: bipush          6
        //   169: aload_0        
        //   170: aload_1        
        //   171: getfield        org/jruby/runtime/ThreadContext.runtime:Lorg/jruby/Ruby;
        //   174: bipush          32
        //   176: invokevirtual   ruby/jit/FILE_71957678BABDE3B4E4F91A6AC4CBFD3837C15D97.getString8:(Lorg/jruby/Ruby;I)Lorg/jruby/RubyString;
        //   179: aastore        
        //   180: invokevirtual   org/jruby/runtime/CallSite.call:(Lorg/jruby/runtime/ThreadContext;Lorg/jruby/runtime/builtin/IRubyObject;Lorg/jruby/runtime/builtin/IRubyObject;[Lorg/jruby/runtime/builtin/IRubyObject;)Lorg/jruby/runtime/builtin/IRubyObject;
        //   183: pop            
        //   184: aload_0        
        //   185: invokevirtual   ruby/jit/FILE_71957678BABDE3B4E4F91A6AC4CBFD3837C15D97.getCallSite3:()Lorg/jruby/runtime/CallSite;
        //   188: aload_1        
        //   189: aload_2        
        //   190: aload_2        
        //   191: aload_0        
        //   192: aload_1        
        //   193: getfield        org/jruby/runtime/ThreadContext.runtime:Lorg/jruby/Ruby;
        //   196: bipush          32
        //   198: invokevirtual   ruby/jit/FILE_71957678BABDE3B4E4F91A6AC4CBFD3837C15D97.getString9:(Lorg/jruby/Ruby;I)Lorg/jruby/RubyString;
        //   201: invokevirtual   org/jruby/runtime/CallSite.call:(Lorg/jruby/runtime/ThreadContext;Lorg/jruby/runtime/builtin/IRubyObject;Lorg/jruby/runtime/builtin/IRubyObject;Lorg/jruby/runtime/builtin/IRubyObject;)Lorg/jruby/runtime/builtin/IRubyObject;
        //   204: pop            
        //   205: aload_0        
        //   206: invokevirtual   ruby/jit/FILE_71957678BABDE3B4E4F91A6AC4CBFD3837C15D97.getCallSite4:()Lorg/jruby/runtime/CallSite;
        //   209: aload_1        
        //   210: aload_2        
        //   211: aload_2        
        //   212: aload_0        
        //   213: aload_1        
        //   214: getfield        org/jruby/runtime/ThreadContext.runtime:Lorg/jruby/Ruby;
        //   217: bipush          10
        //   219: bipush          64
        //   221: invokevirtual   ruby/jit/FILE_71957678BABDE3B4E4F91A6AC4CBFD3837C15D97.getString:(Lorg/jruby/Ruby;II)Lorg/jruby/RubyString;
        //   224: aload_0        
        //   225: aload_1        
        //   226: getfield        org/jruby/runtime/ThreadContext.runtime:Lorg/jruby/Ruby;
        //   229: bipush          11
        //   231: bipush          64
        //   233: invokevirtual   ruby/jit/FILE_71957678BABDE3B4E4F91A6AC4CBFD3837C15D97.getString:(Lorg/jruby/Ruby;II)Lorg/jruby/RubyString;
        //   236: invokevirtual   org/jruby/runtime/CallSite.call:(Lorg/jruby/runtime/ThreadContext;Lorg/jruby/runtime/builtin/IRubyObject;Lorg/jruby/runtime/builtin/IRubyObject;Lorg/jruby/runtime/builtin/IRubyObject;Lorg/jruby/runtime/builtin/IRubyObject;)Lorg/jruby/runtime/builtin/IRubyObject;
        //   239: pop            
        //   240: aload_0        
        //   241: invokevirtual   ruby/jit/FILE_71957678BABDE3B4E4F91A6AC4CBFD3837C15D97.getCallSite5:()Lorg/jruby/runtime/CallSite;
        //   244: aload_1        
        //   245: aload_2        
        //   246: aload_2        
        //   247: aload_0        
        //   248: aload_1        
        //   249: getfield        org/jruby/runtime/ThreadContext.runtime:Lorg/jruby/Ruby;
        //   252: bipush          12
        //   254: bipush          32
        //   256: invokevirtual   ruby/jit/FILE_71957678BABDE3B4E4F91A6AC4CBFD3837C15D97.getString:(Lorg/jruby/Ruby;II)Lorg/jruby/RubyString;
        //   259: aload_0        
        //   260: aload_1        
        //   261: getfield        org/jruby/runtime/ThreadContext.runtime:Lorg/jruby/Ruby;
        //   264: bipush          13
        //   266: bipush          32
        //   268: invokevirtual   ruby/jit/FILE_71957678BABDE3B4E4F91A6AC4CBFD3837C15D97.getString:(Lorg/jruby/Ruby;II)Lorg/jruby/RubyString;
        //   271: invokevirtual   org/jruby/runtime/CallSite.call:(Lorg/jruby/runtime/ThreadContext;Lorg/jruby/runtime/builtin/IRubyObject;Lorg/jruby/runtime/builtin/IRubyObject;Lorg/jruby/runtime/builtin/IRubyObject;Lorg/jruby/runtime/builtin/IRubyObject;)Lorg/jruby/runtime/builtin/IRubyObject;
        //   274: pop            
        //   275: aload_0        
        //   276: invokevirtual   ruby/jit/FILE_71957678BABDE3B4E4F91A6AC4CBFD3837C15D97.getCallSite6:()Lorg/jruby/runtime/CallSite;
        //   279: aload_1        
        //   280: aload_2        
        //   281: aload_2        
        //   282: aload_0        
        //   283: aload_1        
        //   284: getfield        org/jruby/runtime/ThreadContext.runtime:Lorg/jruby/Ruby;
        //   287: bipush          14
        //   289: bipush          64
        //   291: invokevirtual   ruby/jit/FILE_71957678BABDE3B4E4F91A6AC4CBFD3837C15D97.getString:(Lorg/jruby/Ruby;II)Lorg/jruby/RubyString;
        //   294: aload_0        
        //   295: aload_1        
        //   296: getfield        org/jruby/runtime/ThreadContext.runtime:Lorg/jruby/Ruby;
        //   299: bipush          15
        //   301: bipush          64
        //   303: invokevirtual   ruby/jit/FILE_71957678BABDE3B4E4F91A6AC4CBFD3837C15D97.getString:(Lorg/jruby/Ruby;II)Lorg/jruby/RubyString;
        //   306: invokevirtual   org/jruby/runtime/CallSite.call:(Lorg/jruby/runtime/ThreadContext;Lorg/jruby/runtime/builtin/IRubyObject;Lorg/jruby/runtime/builtin/IRubyObject;Lorg/jruby/runtime/builtin/IRubyObject;Lorg/jruby/runtime/builtin/IRubyObject;)Lorg/jruby/runtime/builtin/IRubyObject;
        //   309: pop            
        //   310: aload_0        
        //   311: invokevirtual   ruby/jit/FILE_71957678BABDE3B4E4F91A6AC4CBFD3837C15D97.getCallSite7:()Lorg/jruby/runtime/CallSite;
        //   314: aload_1        
        //   315: aload_2        
        //   316: aload_2        
        //   317: aload_0        
        //   318: aload_1        
        //   319: getfield        org/jruby/runtime/ThreadContext.runtime:Lorg/jruby/Ruby;
        //   322: ldc             "upnp"
        //   324: invokevirtual   ruby/jit/FILE_71957678BABDE3B4E4F91A6AC4CBFD3837C15D97.getSymbol0:(Lorg/jruby/Ruby;Ljava/lang/String;)Lorg/jruby/RubySymbol;
        //   327: aload_1        
        //   328: aload_2        
        //   329: aload_0        
        //   330: aload_1        
        //   331: ldc             "block_0$RUBY$NetworkServices,-1,,false,0,./lib//lister/measurements/lan_services.rb,30,true"
        //   333: invokevirtual   ruby/jit/FILE_71957678BABDE3B4E4F91A6AC4CBFD3837C15D97.getBlockBody0:(Lorg/jruby/runtime/ThreadContext;Ljava/lang/String;)Lorg/jruby/runtime/BlockBody;
        //   336: invokestatic    org/jruby/javasupport/util/RuntimeHelpers.createBlock:(Lorg/jruby/runtime/ThreadContext;Lorg/jruby/runtime/builtin/IRubyObject;Lorg/jruby/runtime/BlockBody;)Lorg/jruby/runtime/Block;
        //   339: invokevirtual   org/jruby/runtime/CallSite.callIter:(Lorg/jruby/runtime/ThreadContext;Lorg/jruby/runtime/builtin/IRubyObject;Lorg/jruby/runtime/builtin/IRubyObject;Lorg/jruby/runtime/builtin/IRubyObject;Lorg/jruby/runtime/Block;)Lorg/jruby/runtime/builtin/IRubyObject;
        //   342: pop            
        //   343: aload_0        
        //   344: bipush          10
        //   346: invokevirtual   ruby/jit/FILE_71957678BABDE3B4E4F91A6AC4CBFD3837C15D97.getCallSite:(I)Lorg/jruby/runtime/CallSite;
        //   349: aload_1        
        //   350: aload_2        
        //   351: aload_2        
        //   352: aload_0        
        //   353: aload_1        
        //   354: getfield        org/jruby/runtime/ThreadContext.runtime:Lorg/jruby/Ruby;
        //   357: ldc             "zeroconf"
        //   359: invokevirtual   ruby/jit/FILE_71957678BABDE3B4E4F91A6AC4CBFD3837C15D97.getSymbol1:(Lorg/jruby/Ruby;Ljava/lang/String;)Lorg/jruby/RubySymbol;
        //   362: aload_1        
        //   363: aload_2        
        //   364: aload_0        
        //   365: aload_1        
        //   366: ldc             "block_1$RUBY$NetworkServices,-1,,false,0,./lib//lister/measurements/lan_services.rb,36,true"
        //   368: invokevirtual   ruby/jit/FILE_71957678BABDE3B4E4F91A6AC4CBFD3837C15D97.getBlockBody1:(Lorg/jruby/runtime/ThreadContext;Ljava/lang/String;)Lorg/jruby/runtime/BlockBody;
        //   371: invokestatic    org/jruby/javasupport/util/RuntimeHelpers.createBlock:(Lorg/jruby/runtime/ThreadContext;Lorg/jruby/runtime/builtin/IRubyObject;Lorg/jruby/runtime/BlockBody;)Lorg/jruby/runtime/Block;
        //   374: invokevirtual   org/jruby/runtime/CallSite.callIter:(Lorg/jruby/runtime/ThreadContext;Lorg/jruby/runtime/builtin/IRubyObject;Lorg/jruby/runtime/builtin/IRubyObject;Lorg/jruby/runtime/builtin/IRubyObject;Lorg/jruby/runtime/Block;)Lorg/jruby/runtime/builtin/IRubyObject;
        //   377: aload_1        
        //   378: invokevirtual   org/jruby/runtime/ThreadContext.postCompiledClass:()V
        //   381: goto            389
        //   384: aload_1        
        //   385: invokevirtual   org/jruby/runtime/ThreadContext.postCompiledClass:()V
        //   388: athrow         
        //   389: areturn        
        //    LocalVariableTable:
        //  Start  Length  Slot  Name    Signature
        //  -----  ------  ----  ------  --------------------------------
        //  55     335     4     locals  Lorg/jruby/runtime/DynamicScope;
        //    Exceptions:
        //  Try           Handler
        //  Start  End    Start  End    Type
        //  -----  -----  -----  -----  ----
        //  55     377    384    389    Any
        // 
        // The error that occurred was:
        // 
        // java.lang.ArrayIndexOutOfBoundsException
        // 
        throw new IllegalStateException("An error occurred while decompiling this method.");
    }
    
    public static IRubyObject block_0$RUBY$NetworkServices(final FILE_71957678BABDE3B4E4F91A6AC4CBFD3837C15D97 file_71957678BABDE3B4E4F91A6AC4CBFD3837C15D97, final ThreadContext threadContext, final IRubyObject rubyObject, final IRubyObject rubyObject2, final Block block) {
        threadContext.getCurrentScope();
        RuntimeHelpers.processBlockArgument(threadContext.runtime, block);
        file_71957678BABDE3B4E4F91A6AC4CBFD3837C15D97.getCallSite8().call(threadContext, rubyObject, rubyObject, file_71957678BABDE3B4E4F91A6AC4CBFD3837C15D97.getString(threadContext.runtime, 16, 32));
        return file_71957678BABDE3B4E4F91A6AC4CBFD3837C15D97.getCallSite9().call(threadContext, rubyObject, rubyObject, file_71957678BABDE3B4E4F91A6AC4CBFD3837C15D97.getString(threadContext.runtime, 17, 64), file_71957678BABDE3B4E4F91A6AC4CBFD3837C15D97.getString(threadContext.runtime, 11, 64));
    }
    
    public static IRubyObject block_1$RUBY$NetworkServices(final FILE_71957678BABDE3B4E4F91A6AC4CBFD3837C15D97 file_71957678BABDE3B4E4F91A6AC4CBFD3837C15D97, final ThreadContext threadContext, final IRubyObject rubyObject, final IRubyObject rubyObject2, final Block block) {
        threadContext.getCurrentScope();
        RuntimeHelpers.processBlockArgument(threadContext.runtime, block);
        file_71957678BABDE3B4E4F91A6AC4CBFD3837C15D97.getCallSite(11).call(threadContext, rubyObject, rubyObject, file_71957678BABDE3B4E4F91A6AC4CBFD3837C15D97.getString(threadContext.runtime, 18, 32));
        return file_71957678BABDE3B4E4F91A6AC4CBFD3837C15D97.getCallSite(12).call(threadContext, rubyObject, rubyObject, file_71957678BABDE3B4E4F91A6AC4CBFD3837C15D97.getString(threadContext.runtime, 19, 64), file_71957678BABDE3B4E4F91A6AC4CBFD3837C15D97.getString(threadContext.runtime, 11, 64));
    }
    
    public static IRubyObject class_2$RUBY$NetworkServices(final FILE_71957678BABDE3B4E4F91A6AC4CBFD3837C15D97 file_71957678BABDE3B4E4F91A6AC4CBFD3837C15D97, final ThreadContext threadContext, final IRubyObject rubyObject, final IRubyObject[] args, final Block block) {
        Arity.checkArgumentCount(threadContext.getRuntime(), args, 0, 0);
        return class_2$RUBY$NetworkServices(file_71957678BABDE3B4E4F91A6AC4CBFD3837C15D97, threadContext, rubyObject, block);
    }
    
    public static IRubyObject module__1$RUBY$Measurements(final FILE_71957678BABDE3B4E4F91A6AC4CBFD3837C15D97 file_71957678BABDE3B4E4F91A6AC4CBFD3837C15D97, final ThreadContext threadContext, final IRubyObject rubyObject, final IRubyObject[] args, final Block block) {
        Arity.checkArgumentCount(threadContext.getRuntime(), args, 0, 0);
        return module__1$RUBY$Measurements(file_71957678BABDE3B4E4F91A6AC4CBFD3837C15D97, threadContext, rubyObject, block);
    }
    
    public static IRubyObject module__0$RUBY$Lister(final FILE_71957678BABDE3B4E4F91A6AC4CBFD3837C15D97 file_71957678BABDE3B4E4F91A6AC4CBFD3837C15D97, final ThreadContext threadContext, final IRubyObject rubyObject, final IRubyObject[] args, final Block block) {
        Arity.checkArgumentCount(threadContext.getRuntime(), args, 0, 0);
        return module__0$RUBY$Lister(file_71957678BABDE3B4E4F91A6AC4CBFD3837C15D97, threadContext, rubyObject, block);
    }
    
    @Override
    public IRubyObject load(final ThreadContext context, final IRubyObject rubyObject, final IRubyObject[] array, final Block block) {
        try {
            RuntimeHelpers.preLoad(context, ",0,0,-2");
            final IRubyObject _file__ = __file__(this, context, rubyObject, array, block);
            RuntimeHelpers.postLoad(context);
            return _file__;
        }
        finally {
            RuntimeHelpers.postLoad(context);
        }
    }
    
    public static void main(final String[] argv) {
        final FILE_71957678BABDE3B4E4F91A6AC4CBFD3837C15D97 file_71957678BABDE3B4E4F91A6AC4CBFD3837C15D97 = new FILE_71957678BABDE3B4E4F91A6AC4CBFD3837C15D97();
        final String string = FILE_71957678BABDE3B4E4F91A6AC4CBFD3837C15D97.class.getClassLoader().getResource("ruby/jit/FILE_71957678BABDE3B4E4F91A6AC4CBFD3837C15D97.class").toString();
        file_71957678BABDE3B4E4F91A6AC4CBFD3837C15D97.setFilename(string);
        final RubyInstanceConfig config = new RubyInstanceConfig();
        config.setArgv(argv);
        config.setScriptFileName(string);
        final Ruby instance = Ruby.newInstance(config);
        file_71957678BABDE3B4E4F91A6AC4CBFD3837C15D97.load(instance.getCurrentContext(), instance.getTopSelf(), IRubyObject.NULL_ARRAY, Block.NULL_BLOCK);
    }
}
