// 
// Decompiled by Procyon v0.5.30
// 

package ruby.jit;

import org.jruby.Ruby;
import org.jruby.RubyInstanceConfig;
import org.jruby.javasupport.util.RuntimeHelpers;
import org.jruby.runtime.Arity;
import org.jruby.anno.JRubyMethod;
import org.jruby.runtime.Block;
import org.jruby.runtime.builtin.IRubyObject;
import org.jruby.ast.executable.RuntimeCache;
import org.jruby.runtime.ThreadContext;
import org.jruby.ast.executable.AbstractScript;

public class FILE_F8838A427C202DEF6E61ABC70E0EB900C1039A19 extends AbstractScript
{
    public FILE_F8838A427C202DEF6E61ABC70E0EB900C1039A19() {
        this.filename = "./lib//lister/debug.rb";
        super.runtimeCache = new RuntimeCache();
        this.initFromDescriptor("\uffff\u0003\u0000\u0000\u0000\u0001\u0000\u0000\u0000\u0000\u0000\u0000\u0000\u0000\u0000");
    }
    
    @JRubyMethod(name = "__file__", frame = true, required = 0, optional = 0, rest = -2)
    public static IRubyObject __file__(final FILE_F8838A427C202DEF6E61ABC70E0EB900C1039A19 file_F8838A427C202DEF6E61ABC70E0EB900C1039A19, final ThreadContext threadContext, final IRubyObject rubyObject, final IRubyObject[] array, final Block block) {
        return module__0$RUBY$Lister(file_F8838A427C202DEF6E61ABC70E0EB900C1039A19, threadContext, rubyObject, IRubyObject.NULL_ARRAY, Block.NULL_BLOCK);
    }
    
    @Override
    public IRubyObject __file__(final ThreadContext threadContext, final IRubyObject rubyObject, final IRubyObject[] array, final Block block) {
        return __file__(this, threadContext, rubyObject, array, block);
    }
    
    public static IRubyObject module__0$RUBY$Lister(final FILE_F8838A427C202DEF6E61ABC70E0EB900C1039A19 p0, final ThreadContext p1, final IRubyObject p2, final Block p3) {
        // 
        // This method could not be decompiled.
        // 
        // Original Bytecode:
        // 
        //     0: aload_1        
        //     1: aload_1        
        //     2: getfield        org/jruby/runtime/ThreadContext.nil:Lorg/jruby/runtime/builtin/IRubyObject;
        //     5: invokestatic    org/jruby/javasupport/util/RuntimeHelpers.prepareClassNamespace:(Lorg/jruby/runtime/ThreadContext;Lorg/jruby/runtime/builtin/IRubyObject;)Lorg/jruby/RubyModule;
        //     8: ldc             "Lister"
        //    10: invokevirtual   org/jruby/RubyModule.defineOrGetModuleUnder:(Ljava/lang/String;)Lorg/jruby/RubyModule;
        //    13: dup            
        //    14: astore_2       
        //    15: aload_1        
        //    16: swap           
        //    17: aload_0        
        //    18: aload_1        
        //    19: ldc             ",0,0,-1"
        //    21: invokevirtual   ruby/jit/FILE_F8838A427C202DEF6E61ABC70E0EB900C1039A19.getScope0:(Lorg/jruby/runtime/ThreadContext;Ljava/lang/String;)Lorg/jruby/parser/StaticScope;
        //    24: invokevirtual   org/jruby/runtime/ThreadContext.preCompiledClassDummyScope:(Lorg/jruby/RubyModule;Lorg/jruby/parser/StaticScope;)V
        //    27: aload_0        
        //    28: aload_1        
        //    29: aload_2        
        //    30: getstatic       org/jruby/runtime/builtin/IRubyObject.NULL_ARRAY:[Lorg/jruby/runtime/builtin/IRubyObject;
        //    33: getstatic       org/jruby/runtime/Block.NULL_BLOCK:Lorg/jruby/runtime/Block;
        //    36: invokestatic    ruby/jit/FILE_F8838A427C202DEF6E61ABC70E0EB900C1039A19.module__1$RUBY$Debug:(Lruby/jit/FILE_F8838A427C202DEF6E61ABC70E0EB900C1039A19;Lorg/jruby/runtime/ThreadContext;Lorg/jruby/runtime/builtin/IRubyObject;[Lorg/jruby/runtime/builtin/IRubyObject;Lorg/jruby/runtime/Block;)Lorg/jruby/runtime/builtin/IRubyObject;
        //    39: aload_1        
        //    40: getfield        org/jruby/runtime/ThreadContext.nil:Lorg/jruby/runtime/builtin/IRubyObject;
        //    43: goto            51
        //    46: aload_1        
        //    47: invokevirtual   org/jruby/runtime/ThreadContext.postCompiledClass:()V
        //    50: athrow         
        //    51: aload_1        
        //    52: invokevirtual   org/jruby/runtime/ThreadContext.postCompiledClass:()V
        //    55: areturn        
        //    Exceptions:
        //  Try           Handler
        //  Start  End    Start  End    Type
        //  -----  -----  -----  -----  ----
        //  27     43     46     51     Any
        // 
        // The error that occurred was:
        // 
        // java.lang.ArrayIndexOutOfBoundsException
        // 
        throw new IllegalStateException("An error occurred while decompiling this method.");
    }
    
    public static IRubyObject module__1$RUBY$Debug(final FILE_F8838A427C202DEF6E61ABC70E0EB900C1039A19 p0, final ThreadContext p1, final IRubyObject p2, final Block p3) {
        // 
        // This method could not be decompiled.
        // 
        // Original Bytecode:
        // 
        //     0: aload_1        
        //     1: aload_1        
        //     2: getfield        org/jruby/runtime/ThreadContext.nil:Lorg/jruby/runtime/builtin/IRubyObject;
        //     5: invokestatic    org/jruby/javasupport/util/RuntimeHelpers.prepareClassNamespace:(Lorg/jruby/runtime/ThreadContext;Lorg/jruby/runtime/builtin/IRubyObject;)Lorg/jruby/RubyModule;
        //     8: ldc             "Debug"
        //    10: invokevirtual   org/jruby/RubyModule.defineOrGetModuleUnder:(Ljava/lang/String;)Lorg/jruby/RubyModule;
        //    13: dup            
        //    14: astore_2       
        //    15: aload_1        
        //    16: swap           
        //    17: aload_0        
        //    18: aload_1        
        //    19: ldc             ",0,0,-1"
        //    21: invokevirtual   ruby/jit/FILE_F8838A427C202DEF6E61ABC70E0EB900C1039A19.getScope1:(Lorg/jruby/runtime/ThreadContext;Ljava/lang/String;)Lorg/jruby/parser/StaticScope;
        //    24: invokevirtual   org/jruby/runtime/ThreadContext.preCompiledClassDummyScope:(Lorg/jruby/RubyModule;Lorg/jruby/parser/StaticScope;)V
        //    27: aload_0        
        //    28: aload_1        
        //    29: aload_0        
        //    30: aload_1        
        //    31: ldc             "StandardError"
        //    33: invokevirtual   ruby/jit/FILE_F8838A427C202DEF6E61ABC70E0EB900C1039A19.getConstant0:(Lorg/jruby/runtime/ThreadContext;Ljava/lang/String;)Lorg/jruby/runtime/builtin/IRubyObject;
        //    36: getstatic       org/jruby/runtime/Block.NULL_BLOCK:Lorg/jruby/runtime/Block;
        //    39: invokestatic    ruby/jit/FILE_F8838A427C202DEF6E61ABC70E0EB900C1039A19.class_2$RUBY$DebugException:(Lruby/jit/FILE_F8838A427C202DEF6E61ABC70E0EB900C1039A19;Lorg/jruby/runtime/ThreadContext;Lorg/jruby/runtime/builtin/IRubyObject;Lorg/jruby/runtime/Block;)Lorg/jruby/runtime/builtin/IRubyObject;
        //    42: aload_1        
        //    43: getfield        org/jruby/runtime/ThreadContext.nil:Lorg/jruby/runtime/builtin/IRubyObject;
        //    46: goto            54
        //    49: aload_1        
        //    50: invokevirtual   org/jruby/runtime/ThreadContext.postCompiledClass:()V
        //    53: athrow         
        //    54: aload_1        
        //    55: invokevirtual   org/jruby/runtime/ThreadContext.postCompiledClass:()V
        //    58: areturn        
        //    Exceptions:
        //  Try           Handler
        //  Start  End    Start  End    Type
        //  -----  -----  -----  -----  ----
        //  27     46     49     54     Any
        // 
        // The error that occurred was:
        // 
        // java.lang.ArrayIndexOutOfBoundsException
        // 
        throw new IllegalStateException("An error occurred while decompiling this method.");
    }
    
    public static IRubyObject class_2$RUBY$DebugException(final FILE_F8838A427C202DEF6E61ABC70E0EB900C1039A19 p0, final ThreadContext p1, final IRubyObject p2, final Block p3) {
        // 
        // This method could not be decompiled.
        // 
        // Original Bytecode:
        // 
        //     0: aload_1        
        //     1: getfield        org/jruby/runtime/ThreadContext.runtime:Lorg/jruby/Ruby;
        //     4: aload_2        
        //     5: invokestatic    org/jruby/javasupport/util/RuntimeHelpers.prepareSuperClass:(Lorg/jruby/Ruby;Lorg/jruby/runtime/builtin/IRubyObject;)Lorg/jruby/RubyClass;
        //     8: aload_1        
        //     9: aload_1        
        //    10: getfield        org/jruby/runtime/ThreadContext.nil:Lorg/jruby/runtime/builtin/IRubyObject;
        //    13: invokestatic    org/jruby/javasupport/util/RuntimeHelpers.prepareClassNamespace:(Lorg/jruby/runtime/ThreadContext;Lorg/jruby/runtime/builtin/IRubyObject;)Lorg/jruby/RubyModule;
        //    16: swap           
        //    17: ldc             "DebugException"
        //    19: swap           
        //    20: invokevirtual   org/jruby/RubyModule.defineOrGetClassUnder:(Ljava/lang/String;Lorg/jruby/RubyClass;)Lorg/jruby/RubyClass;
        //    23: dup            
        //    24: astore_2       
        //    25: aload_1        
        //    26: swap           
        //    27: aload_0        
        //    28: aload_1        
        //    29: ldc             ",0,0,-1"
        //    31: invokevirtual   ruby/jit/FILE_F8838A427C202DEF6E61ABC70E0EB900C1039A19.getScope2:(Lorg/jruby/runtime/ThreadContext;Ljava/lang/String;)Lorg/jruby/parser/StaticScope;
        //    34: invokevirtual   org/jruby/runtime/ThreadContext.preCompiledClassDummyScope:(Lorg/jruby/RubyModule;Lorg/jruby/parser/StaticScope;)V
        //    37: aload_1        
        //    38: getfield        org/jruby/runtime/ThreadContext.nil:Lorg/jruby/runtime/builtin/IRubyObject;
        //    41: aload_1        
        //    42: invokevirtual   org/jruby/runtime/ThreadContext.postCompiledClass:()V
        //    45: goto            53
        //    48: aload_1        
        //    49: invokevirtual   org/jruby/runtime/ThreadContext.postCompiledClass:()V
        //    52: athrow         
        //    53: areturn        
        //    Exceptions:
        //  Try           Handler
        //  Start  End    Start  End    Type
        //  -----  -----  -----  -----  ----
        //  37     41     48     53     Any
        // 
        // The error that occurred was:
        // 
        // java.lang.ArrayIndexOutOfBoundsException
        // 
        throw new IllegalStateException("An error occurred while decompiling this method.");
    }
    
    public static IRubyObject class_2$RUBY$DebugException(final FILE_F8838A427C202DEF6E61ABC70E0EB900C1039A19 file_F8838A427C202DEF6E61ABC70E0EB900C1039A19, final ThreadContext threadContext, final IRubyObject rubyObject, final IRubyObject[] args, final Block block) {
        Arity.checkArgumentCount(threadContext.getRuntime(), args, 0, 0);
        return class_2$RUBY$DebugException(file_F8838A427C202DEF6E61ABC70E0EB900C1039A19, threadContext, rubyObject, block);
    }
    
    public static IRubyObject module__1$RUBY$Debug(final FILE_F8838A427C202DEF6E61ABC70E0EB900C1039A19 file_F8838A427C202DEF6E61ABC70E0EB900C1039A19, final ThreadContext threadContext, final IRubyObject rubyObject, final IRubyObject[] args, final Block block) {
        Arity.checkArgumentCount(threadContext.getRuntime(), args, 0, 0);
        return module__1$RUBY$Debug(file_F8838A427C202DEF6E61ABC70E0EB900C1039A19, threadContext, rubyObject, block);
    }
    
    public static IRubyObject module__0$RUBY$Lister(final FILE_F8838A427C202DEF6E61ABC70E0EB900C1039A19 file_F8838A427C202DEF6E61ABC70E0EB900C1039A19, final ThreadContext threadContext, final IRubyObject rubyObject, final IRubyObject[] args, final Block block) {
        Arity.checkArgumentCount(threadContext.getRuntime(), args, 0, 0);
        return module__0$RUBY$Lister(file_F8838A427C202DEF6E61ABC70E0EB900C1039A19, threadContext, rubyObject, block);
    }
    
    @Override
    public IRubyObject load(final ThreadContext context, final IRubyObject rubyObject, final IRubyObject[] array, final Block block) {
        try {
            RuntimeHelpers.preLoad(context, ",0,0,-2");
            final IRubyObject _file__ = __file__(this, context, rubyObject, array, block);
            RuntimeHelpers.postLoad(context);
            return _file__;
        }
        finally {
            RuntimeHelpers.postLoad(context);
        }
    }
    
    public static void main(final String[] argv) {
        final FILE_F8838A427C202DEF6E61ABC70E0EB900C1039A19 file_F8838A427C202DEF6E61ABC70E0EB900C1039A19 = new FILE_F8838A427C202DEF6E61ABC70E0EB900C1039A19();
        final String string = FILE_F8838A427C202DEF6E61ABC70E0EB900C1039A19.class.getClassLoader().getResource("ruby/jit/FILE_F8838A427C202DEF6E61ABC70E0EB900C1039A19.class").toString();
        file_F8838A427C202DEF6E61ABC70E0EB900C1039A19.setFilename(string);
        final RubyInstanceConfig config = new RubyInstanceConfig();
        config.setArgv(argv);
        config.setScriptFileName(string);
        final Ruby instance = Ruby.newInstance(config);
        file_F8838A427C202DEF6E61ABC70E0EB900C1039A19.load(instance.getCurrentContext(), instance.getTopSelf(), IRubyObject.NULL_ARRAY, Block.NULL_BLOCK);
    }
}
