// 
// Decompiled by Procyon v0.5.30
// 

package ruby.jit;

import org.jruby.Ruby;
import org.jruby.RubyInstanceConfig;
import org.jruby.runtime.Arity;
import org.jruby.javasupport.util.RuntimeHelpers;
import org.jruby.anno.JRubyMethod;
import org.jruby.runtime.Block;
import org.jruby.runtime.builtin.IRubyObject;
import org.jruby.ast.executable.RuntimeCache;
import org.jruby.runtime.ThreadContext;
import org.jruby.ast.executable.AbstractScript;

public class FILE_3E9C726384588CD43F31AC32BB00ECBCEF6B3E49 extends AbstractScript
{
    public FILE_3E9C726384588CD43F31AC32BB00ECBCEF6B3E49() {
        this.filename = "./lib//lister/measurements/network_scan.rb";
        super.runtimeCache = new RuntimeCache();
        this.initFromDescriptor("require\uffffF\uffffversion\uffffF\uffffold_versions\uffffF\uffffdescribe\uffffF\uffffdescribe\uffffF\uffffdescribe\uffffF\uffffdescribe\uffffF\uffffreport\uffffF\uffffdescribe\uffffF\uffffdescribe\uffffF\uffffreport\uffffF\uffffdescribe\uffffF\uffffdescribe\uffffF\uffffreport\uffffF\uffffdescribe\uffffF\uffffdescribe\uffffF\uffffreport\uffffF\uffffdescribe\uffffF\uffffdescribe\uffffF\uffffreport\uffffF\uffffdescribe\uffffF\uffffdescribe\uffffF\uffff\u0003\u0005\u0000\u0000\u0001\u0000\u0000\u0000\u0000\u0005\u0000\u0000\u001a\u0001");
        this.setEncoding(0, "ASCII-8BIT");
        this.setByteList(2, "dev", this.getEncoding0());
        this.setByteList(20, "The hash digest of the MAC addresses. This allows us to\n        identify the cases where HNP runs from the same home but different\n        computers, and from the same computers but different homes.", this.getEncoding0());
        this.setByteList(0, "lister/measurement", this.getEncoding0());
        this.setByteList(18, "The names of the network interfaces cards of the devices present on the home network. Read from the vendor field of the MAC address part", this.getEncoding0());
        this.setByteList(19, "Le nom des constructeurs des cartes r\uffc3\uffa9seau des machines pr\uffc3\uffa9sentes sur le r\uffc3\uffa9seau. Lu depuis l'identifiant vendeur des adresses MAC", this.getEncoding0());
        this.setByteList(16, "The number of other devices, for ARP and Zeroconf", this.getEncoding0());
        this.setByteList(17, "Le nombre d'autres ordinateurs sur le r\uffc3\uffa9seau, pour ARP et Zeroconf", this.getEncoding0());
        this.setByteList(24, "Same as lan_nic_info, but for current computer", this.getEncoding0());
        this.setByteList(1, "0.1.0", this.getEncoding0());
        this.setByteList(14, "<p>Ce module scanne les ordinateurs et les objets connect\uffc3\uffa9s en\nr\uffc3\uffa9seau dans la maison.  Nous g\uffc3\uffa9n\uffc3\uffa9rons des paquets UDP vers le port 'discard'\n(9) vers chacune des machine du r\uffc3\uffa9seau local.  Cela remplira la table ARP et\nnous n'avons qu'\uffc3\uffa0 compter le nombre d'entr\uffc3\uffa9es. Ensuite, nous comptons avec\nZeroconf (ou Bonjour chez Apple) combien d'ordinateurs r\uffc3\uffa9pondent.  </p>", this.getEncoding0());
        this.setByteList(21, "Les hashes des addresses MAC. Cela nous permet d'identifier\n        les cas o\uffc3\uffb9 HNP tourne sur des machines diff\uffc3\uffa9rentes dans la m\uffc3\uffaame maison,\n        et de maisons diff\uffc3\uffa9rentes depuis la m\uffc3\uffaame machine.", this.getEncoding0());
        this.setByteList(13, "English-HTML", this.getEncoding0());
        this.setByteList(23, "La liste contenant, l'identifiant vendeur, la valeur hash\uffc3\uffa9e, et l'IP associ\uffc3\uffa9e (si elle est local) des addresses MAC trouv\uffc3\uffa9es dans le r\uffc3\uffa9seau local", this.getEncoding0());
        this.setByteList(11, "Fran\uffc3\uffa7ais", this.getEncoding0());
        this.setByteList(3, "0.0.1", this.getEncoding0());
        this.setByteList(22, "A list of values containing the vendor-id, hashed value, and associated IP (if local) of the MAC addresses found in the local network", this.getEncoding0());
        this.setByteList(5, "0.0.3", this.getEncoding0());
        this.setByteList(4, "0.0.2", this.getEncoding0());
        this.setByteList(7, "0.0.5", this.getEncoding0());
        this.setByteList(6, "0.0.4", this.getEncoding0());
        this.setByteList(10, "Nombre d'appareils connect\uffc3\uffa9s dans la maison", this.getEncoding0());
        this.setByteList(12, "<p> This module scans the set of computers and network devices\nin the home network.  We first generate UDP packets to the discard port (9) to all IPs of\nthe local network, this should trigger an ARP request, we then look at the\nnumber of ARP entries in the cache.  Then, we count with the Zeroconf (Apple's\nBonjour) protocol how many computers answer.\n      We also collect the vendor-ID of the MAC addresses and an anonymized\nversion of the MAC address.\n        </p>", this.getEncoding0());
        this.setByteList(9, "Number of other devices in the home network", this.getEncoding0());
        this.setByteList(8, "0.0.6", this.getEncoding0());
        this.setByteList(15, "Fran\uffc3\uffa7ais-HTML", this.getEncoding0());
        this.setByteList(25, "Pareil que lan_nic_info, mais pour l'ordinateur qui fait tourner HomeNet Profiler", this.getEncoding0());
    }
    
    @JRubyMethod(name = "__file__", frame = true, required = 0, optional = 0, rest = -2)
    public static IRubyObject __file__(final FILE_3E9C726384588CD43F31AC32BB00ECBCEF6B3E49 file_3E9C726384588CD43F31AC32BB00ECBCEF6B3E49, final ThreadContext threadContext, final IRubyObject rubyObject, final IRubyObject[] array, final Block block) {
        file_3E9C726384588CD43F31AC32BB00ECBCEF6B3E49.getCallSite0().call(threadContext, rubyObject, rubyObject, file_3E9C726384588CD43F31AC32BB00ECBCEF6B3E49.getString0(threadContext.runtime, 32));
        return module__0$RUBY$Lister(file_3E9C726384588CD43F31AC32BB00ECBCEF6B3E49, threadContext, rubyObject, IRubyObject.NULL_ARRAY, Block.NULL_BLOCK);
    }
    
    @Override
    public IRubyObject __file__(final ThreadContext threadContext, final IRubyObject rubyObject, final IRubyObject[] array, final Block block) {
        return __file__(this, threadContext, rubyObject, array, block);
    }
    
    public static IRubyObject module__0$RUBY$Lister(final FILE_3E9C726384588CD43F31AC32BB00ECBCEF6B3E49 p0, final ThreadContext p1, final IRubyObject p2, final Block p3) {
        // 
        // This method could not be decompiled.
        // 
        // Original Bytecode:
        // 
        //     0: aload_1        
        //     1: aload_1        
        //     2: getfield        org/jruby/runtime/ThreadContext.nil:Lorg/jruby/runtime/builtin/IRubyObject;
        //     5: invokestatic    org/jruby/javasupport/util/RuntimeHelpers.prepareClassNamespace:(Lorg/jruby/runtime/ThreadContext;Lorg/jruby/runtime/builtin/IRubyObject;)Lorg/jruby/RubyModule;
        //     8: ldc             "Lister"
        //    10: invokevirtual   org/jruby/RubyModule.defineOrGetModuleUnder:(Ljava/lang/String;)Lorg/jruby/RubyModule;
        //    13: dup            
        //    14: astore_2       
        //    15: aload_1        
        //    16: swap           
        //    17: aload_0        
        //    18: aload_1        
        //    19: ldc             ",0,0,-1"
        //    21: invokevirtual   ruby/jit/FILE_3E9C726384588CD43F31AC32BB00ECBCEF6B3E49.getScope0:(Lorg/jruby/runtime/ThreadContext;Ljava/lang/String;)Lorg/jruby/parser/StaticScope;
        //    24: invokevirtual   org/jruby/runtime/ThreadContext.preCompiledClassDummyScope:(Lorg/jruby/RubyModule;Lorg/jruby/parser/StaticScope;)V
        //    27: aload_0        
        //    28: aload_1        
        //    29: aload_2        
        //    30: getstatic       org/jruby/runtime/builtin/IRubyObject.NULL_ARRAY:[Lorg/jruby/runtime/builtin/IRubyObject;
        //    33: getstatic       org/jruby/runtime/Block.NULL_BLOCK:Lorg/jruby/runtime/Block;
        //    36: invokestatic    ruby/jit/FILE_3E9C726384588CD43F31AC32BB00ECBCEF6B3E49.module__1$RUBY$Measurements:(Lruby/jit/FILE_3E9C726384588CD43F31AC32BB00ECBCEF6B3E49;Lorg/jruby/runtime/ThreadContext;Lorg/jruby/runtime/builtin/IRubyObject;[Lorg/jruby/runtime/builtin/IRubyObject;Lorg/jruby/runtime/Block;)Lorg/jruby/runtime/builtin/IRubyObject;
        //    39: aload_1        
        //    40: getfield        org/jruby/runtime/ThreadContext.nil:Lorg/jruby/runtime/builtin/IRubyObject;
        //    43: goto            51
        //    46: aload_1        
        //    47: invokevirtual   org/jruby/runtime/ThreadContext.postCompiledClass:()V
        //    50: athrow         
        //    51: aload_1        
        //    52: invokevirtual   org/jruby/runtime/ThreadContext.postCompiledClass:()V
        //    55: areturn        
        //    Exceptions:
        //  Try           Handler
        //  Start  End    Start  End    Type
        //  -----  -----  -----  -----  ----
        //  27     43     46     51     Any
        // 
        // The error that occurred was:
        // 
        // java.lang.ArrayIndexOutOfBoundsException
        // 
        throw new IllegalStateException("An error occurred while decompiling this method.");
    }
    
    public static IRubyObject module__1$RUBY$Measurements(final FILE_3E9C726384588CD43F31AC32BB00ECBCEF6B3E49 p0, final ThreadContext p1, final IRubyObject p2, final Block p3) {
        // 
        // This method could not be decompiled.
        // 
        // Original Bytecode:
        // 
        //     0: aload_1        
        //     1: aload_1        
        //     2: getfield        org/jruby/runtime/ThreadContext.nil:Lorg/jruby/runtime/builtin/IRubyObject;
        //     5: invokestatic    org/jruby/javasupport/util/RuntimeHelpers.prepareClassNamespace:(Lorg/jruby/runtime/ThreadContext;Lorg/jruby/runtime/builtin/IRubyObject;)Lorg/jruby/RubyModule;
        //     8: ldc             "Measurements"
        //    10: invokevirtual   org/jruby/RubyModule.defineOrGetModuleUnder:(Ljava/lang/String;)Lorg/jruby/RubyModule;
        //    13: dup            
        //    14: astore_2       
        //    15: aload_1        
        //    16: swap           
        //    17: aload_0        
        //    18: aload_1        
        //    19: ldc             ",0,0,-1"
        //    21: invokevirtual   ruby/jit/FILE_3E9C726384588CD43F31AC32BB00ECBCEF6B3E49.getScope1:(Lorg/jruby/runtime/ThreadContext;Ljava/lang/String;)Lorg/jruby/parser/StaticScope;
        //    24: invokevirtual   org/jruby/runtime/ThreadContext.preCompiledClassDummyScope:(Lorg/jruby/RubyModule;Lorg/jruby/parser/StaticScope;)V
        //    27: aload_0        
        //    28: aload_1        
        //    29: aload_0        
        //    30: aload_1        
        //    31: ldc_w           "Measurement"
        //    34: invokevirtual   ruby/jit/FILE_3E9C726384588CD43F31AC32BB00ECBCEF6B3E49.getConstant0:(Lorg/jruby/runtime/ThreadContext;Ljava/lang/String;)Lorg/jruby/runtime/builtin/IRubyObject;
        //    37: getstatic       org/jruby/runtime/Block.NULL_BLOCK:Lorg/jruby/runtime/Block;
        //    40: invokestatic    ruby/jit/FILE_3E9C726384588CD43F31AC32BB00ECBCEF6B3E49.class_2$RUBY$NetworkScan:(Lruby/jit/FILE_3E9C726384588CD43F31AC32BB00ECBCEF6B3E49;Lorg/jruby/runtime/ThreadContext;Lorg/jruby/runtime/builtin/IRubyObject;Lorg/jruby/runtime/Block;)Lorg/jruby/runtime/builtin/IRubyObject;
        //    43: aload_1        
        //    44: getfield        org/jruby/runtime/ThreadContext.nil:Lorg/jruby/runtime/builtin/IRubyObject;
        //    47: goto            55
        //    50: aload_1        
        //    51: invokevirtual   org/jruby/runtime/ThreadContext.postCompiledClass:()V
        //    54: athrow         
        //    55: aload_1        
        //    56: invokevirtual   org/jruby/runtime/ThreadContext.postCompiledClass:()V
        //    59: areturn        
        //    Exceptions:
        //  Try           Handler
        //  Start  End    Start  End    Type
        //  -----  -----  -----  -----  ----
        //  27     47     50     55     Any
        // 
        // The error that occurred was:
        // 
        // java.lang.ArrayIndexOutOfBoundsException
        // 
        throw new IllegalStateException("An error occurred while decompiling this method.");
    }
    
    public static IRubyObject class_2$RUBY$NetworkScan(final FILE_3E9C726384588CD43F31AC32BB00ECBCEF6B3E49 p0, final ThreadContext p1, final IRubyObject p2, final Block p3) {
        // 
        // This method could not be decompiled.
        // 
        // Original Bytecode:
        // 
        //     0: aload_1        
        //     1: invokevirtual   org/jruby/runtime/ThreadContext.getCurrentScope:()Lorg/jruby/runtime/DynamicScope;
        //     4: dup            
        //     5: astore          4
        //     7: invokevirtual   org/jruby/runtime/DynamicScope.getValues:()[Lorg/jruby/runtime/builtin/IRubyObject;
        //    10: astore          5
        //    12: aload_1        
        //    13: getfield        org/jruby/runtime/ThreadContext.runtime:Lorg/jruby/Ruby;
        //    16: aload_2        
        //    17: invokestatic    org/jruby/javasupport/util/RuntimeHelpers.prepareSuperClass:(Lorg/jruby/Ruby;Lorg/jruby/runtime/builtin/IRubyObject;)Lorg/jruby/RubyClass;
        //    20: aload_1        
        //    21: aload_1        
        //    22: getfield        org/jruby/runtime/ThreadContext.nil:Lorg/jruby/runtime/builtin/IRubyObject;
        //    25: invokestatic    org/jruby/javasupport/util/RuntimeHelpers.prepareClassNamespace:(Lorg/jruby/runtime/ThreadContext;Lorg/jruby/runtime/builtin/IRubyObject;)Lorg/jruby/RubyModule;
        //    28: swap           
        //    29: ldc             "NetworkScan"
        //    31: swap           
        //    32: invokevirtual   org/jruby/RubyModule.defineOrGetClassUnder:(Ljava/lang/String;Lorg/jruby/RubyClass;)Lorg/jruby/RubyClass;
        //    35: dup            
        //    36: astore_2       
        //    37: aload_1        
        //    38: swap           
        //    39: aload_0        
        //    40: aload_1        
        //    41: ldc             ",0,0,-1"
        //    43: invokevirtual   ruby/jit/FILE_3E9C726384588CD43F31AC32BB00ECBCEF6B3E49.getScope2:(Lorg/jruby/runtime/ThreadContext;Ljava/lang/String;)Lorg/jruby/parser/StaticScope;
        //    46: invokevirtual   org/jruby/runtime/ThreadContext.preCompiledClass:(Lorg/jruby/RubyModule;Lorg/jruby/parser/StaticScope;)V
        //    49: aload_1        
        //    50: invokevirtual   org/jruby/runtime/ThreadContext.getCurrentScope:()Lorg/jruby/runtime/DynamicScope;
        //    53: astore          locals
        //    55: aload_0        
        //    56: invokevirtual   ruby/jit/FILE_3E9C726384588CD43F31AC32BB00ECBCEF6B3E49.getCallSite1:()Lorg/jruby/runtime/CallSite;
        //    59: aload_1        
        //    60: aload_2        
        //    61: aload_2        
        //    62: aload_0        
        //    63: aload_1        
        //    64: getfield        org/jruby/runtime/ThreadContext.runtime:Lorg/jruby/Ruby;
        //    67: bipush          32
        //    69: invokevirtual   ruby/jit/FILE_3E9C726384588CD43F31AC32BB00ECBCEF6B3E49.getString1:(Lorg/jruby/Ruby;I)Lorg/jruby/RubyString;
        //    72: invokevirtual   org/jruby/runtime/CallSite.call:(Lorg/jruby/runtime/ThreadContext;Lorg/jruby/runtime/builtin/IRubyObject;Lorg/jruby/runtime/builtin/IRubyObject;Lorg/jruby/runtime/builtin/IRubyObject;)Lorg/jruby/runtime/builtin/IRubyObject;
        //    75: pop            
        //    76: aload_0        
        //    77: invokevirtual   ruby/jit/FILE_3E9C726384588CD43F31AC32BB00ECBCEF6B3E49.getCallSite2:()Lorg/jruby/runtime/CallSite;
        //    80: aload_1        
        //    81: aload_2        
        //    82: aload_2        
        //    83: bipush          7
        //    85: anewarray       Lorg/jruby/runtime/builtin/IRubyObject;
        //    88: dup            
        //    89: iconst_0       
        //    90: aload_0        
        //    91: aload_1        
        //    92: getfield        org/jruby/runtime/ThreadContext.runtime:Lorg/jruby/Ruby;
        //    95: bipush          32
        //    97: invokevirtual   ruby/jit/FILE_3E9C726384588CD43F31AC32BB00ECBCEF6B3E49.getString2:(Lorg/jruby/Ruby;I)Lorg/jruby/RubyString;
        //   100: aastore        
        //   101: dup            
        //   102: iconst_1       
        //   103: aload_0        
        //   104: aload_1        
        //   105: getfield        org/jruby/runtime/ThreadContext.runtime:Lorg/jruby/Ruby;
        //   108: bipush          32
        //   110: invokevirtual   ruby/jit/FILE_3E9C726384588CD43F31AC32BB00ECBCEF6B3E49.getString3:(Lorg/jruby/Ruby;I)Lorg/jruby/RubyString;
        //   113: aastore        
        //   114: dup            
        //   115: iconst_2       
        //   116: aload_0        
        //   117: aload_1        
        //   118: getfield        org/jruby/runtime/ThreadContext.runtime:Lorg/jruby/Ruby;
        //   121: bipush          32
        //   123: invokevirtual   ruby/jit/FILE_3E9C726384588CD43F31AC32BB00ECBCEF6B3E49.getString4:(Lorg/jruby/Ruby;I)Lorg/jruby/RubyString;
        //   126: aastore        
        //   127: dup            
        //   128: iconst_3       
        //   129: aload_0        
        //   130: aload_1        
        //   131: getfield        org/jruby/runtime/ThreadContext.runtime:Lorg/jruby/Ruby;
        //   134: bipush          32
        //   136: invokevirtual   ruby/jit/FILE_3E9C726384588CD43F31AC32BB00ECBCEF6B3E49.getString5:(Lorg/jruby/Ruby;I)Lorg/jruby/RubyString;
        //   139: aastore        
        //   140: dup            
        //   141: iconst_4       
        //   142: aload_0        
        //   143: aload_1        
        //   144: getfield        org/jruby/runtime/ThreadContext.runtime:Lorg/jruby/Ruby;
        //   147: bipush          32
        //   149: invokevirtual   ruby/jit/FILE_3E9C726384588CD43F31AC32BB00ECBCEF6B3E49.getString6:(Lorg/jruby/Ruby;I)Lorg/jruby/RubyString;
        //   152: aastore        
        //   153: dup            
        //   154: iconst_5       
        //   155: aload_0        
        //   156: aload_1        
        //   157: getfield        org/jruby/runtime/ThreadContext.runtime:Lorg/jruby/Ruby;
        //   160: bipush          32
        //   162: invokevirtual   ruby/jit/FILE_3E9C726384588CD43F31AC32BB00ECBCEF6B3E49.getString7:(Lorg/jruby/Ruby;I)Lorg/jruby/RubyString;
        //   165: aastore        
        //   166: dup            
        //   167: bipush          6
        //   169: aload_0        
        //   170: aload_1        
        //   171: getfield        org/jruby/runtime/ThreadContext.runtime:Lorg/jruby/Ruby;
        //   174: bipush          32
        //   176: invokevirtual   ruby/jit/FILE_3E9C726384588CD43F31AC32BB00ECBCEF6B3E49.getString8:(Lorg/jruby/Ruby;I)Lorg/jruby/RubyString;
        //   179: aastore        
        //   180: invokevirtual   org/jruby/runtime/CallSite.call:(Lorg/jruby/runtime/ThreadContext;Lorg/jruby/runtime/builtin/IRubyObject;Lorg/jruby/runtime/builtin/IRubyObject;[Lorg/jruby/runtime/builtin/IRubyObject;)Lorg/jruby/runtime/builtin/IRubyObject;
        //   183: pop            
        //   184: aload_0        
        //   185: invokevirtual   ruby/jit/FILE_3E9C726384588CD43F31AC32BB00ECBCEF6B3E49.getCallSite3:()Lorg/jruby/runtime/CallSite;
        //   188: aload_1        
        //   189: aload_2        
        //   190: aload_2        
        //   191: aload_0        
        //   192: aload_1        
        //   193: getfield        org/jruby/runtime/ThreadContext.runtime:Lorg/jruby/Ruby;
        //   196: bipush          32
        //   198: invokevirtual   ruby/jit/FILE_3E9C726384588CD43F31AC32BB00ECBCEF6B3E49.getString9:(Lorg/jruby/Ruby;I)Lorg/jruby/RubyString;
        //   201: invokevirtual   org/jruby/runtime/CallSite.call:(Lorg/jruby/runtime/ThreadContext;Lorg/jruby/runtime/builtin/IRubyObject;Lorg/jruby/runtime/builtin/IRubyObject;Lorg/jruby/runtime/builtin/IRubyObject;)Lorg/jruby/runtime/builtin/IRubyObject;
        //   204: pop            
        //   205: aload_0        
        //   206: invokevirtual   ruby/jit/FILE_3E9C726384588CD43F31AC32BB00ECBCEF6B3E49.getCallSite4:()Lorg/jruby/runtime/CallSite;
        //   209: aload_1        
        //   210: aload_2        
        //   211: aload_2        
        //   212: aload_0        
        //   213: aload_1        
        //   214: getfield        org/jruby/runtime/ThreadContext.runtime:Lorg/jruby/Ruby;
        //   217: bipush          10
        //   219: bipush          64
        //   221: invokevirtual   ruby/jit/FILE_3E9C726384588CD43F31AC32BB00ECBCEF6B3E49.getString:(Lorg/jruby/Ruby;II)Lorg/jruby/RubyString;
        //   224: aload_0        
        //   225: aload_1        
        //   226: getfield        org/jruby/runtime/ThreadContext.runtime:Lorg/jruby/Ruby;
        //   229: bipush          11
        //   231: bipush          64
        //   233: invokevirtual   ruby/jit/FILE_3E9C726384588CD43F31AC32BB00ECBCEF6B3E49.getString:(Lorg/jruby/Ruby;II)Lorg/jruby/RubyString;
        //   236: invokevirtual   org/jruby/runtime/CallSite.call:(Lorg/jruby/runtime/ThreadContext;Lorg/jruby/runtime/builtin/IRubyObject;Lorg/jruby/runtime/builtin/IRubyObject;Lorg/jruby/runtime/builtin/IRubyObject;Lorg/jruby/runtime/builtin/IRubyObject;)Lorg/jruby/runtime/builtin/IRubyObject;
        //   239: pop            
        //   240: aload_0        
        //   241: invokevirtual   ruby/jit/FILE_3E9C726384588CD43F31AC32BB00ECBCEF6B3E49.getCallSite5:()Lorg/jruby/runtime/CallSite;
        //   244: aload_1        
        //   245: aload_2        
        //   246: aload_2        
        //   247: aload_0        
        //   248: aload_1        
        //   249: getfield        org/jruby/runtime/ThreadContext.runtime:Lorg/jruby/Ruby;
        //   252: bipush          12
        //   254: bipush          32
        //   256: invokevirtual   ruby/jit/FILE_3E9C726384588CD43F31AC32BB00ECBCEF6B3E49.getString:(Lorg/jruby/Ruby;II)Lorg/jruby/RubyString;
        //   259: aload_0        
        //   260: aload_1        
        //   261: getfield        org/jruby/runtime/ThreadContext.runtime:Lorg/jruby/Ruby;
        //   264: bipush          13
        //   266: bipush          32
        //   268: invokevirtual   ruby/jit/FILE_3E9C726384588CD43F31AC32BB00ECBCEF6B3E49.getString:(Lorg/jruby/Ruby;II)Lorg/jruby/RubyString;
        //   271: invokevirtual   org/jruby/runtime/CallSite.call:(Lorg/jruby/runtime/ThreadContext;Lorg/jruby/runtime/builtin/IRubyObject;Lorg/jruby/runtime/builtin/IRubyObject;Lorg/jruby/runtime/builtin/IRubyObject;Lorg/jruby/runtime/builtin/IRubyObject;)Lorg/jruby/runtime/builtin/IRubyObject;
        //   274: pop            
        //   275: aload_0        
        //   276: invokevirtual   ruby/jit/FILE_3E9C726384588CD43F31AC32BB00ECBCEF6B3E49.getCallSite6:()Lorg/jruby/runtime/CallSite;
        //   279: aload_1        
        //   280: aload_2        
        //   281: aload_2        
        //   282: aload_0        
        //   283: aload_1        
        //   284: getfield        org/jruby/runtime/ThreadContext.runtime:Lorg/jruby/Ruby;
        //   287: bipush          14
        //   289: bipush          64
        //   291: invokevirtual   ruby/jit/FILE_3E9C726384588CD43F31AC32BB00ECBCEF6B3E49.getString:(Lorg/jruby/Ruby;II)Lorg/jruby/RubyString;
        //   294: aload_0        
        //   295: aload_1        
        //   296: getfield        org/jruby/runtime/ThreadContext.runtime:Lorg/jruby/Ruby;
        //   299: bipush          15
        //   301: bipush          64
        //   303: invokevirtual   ruby/jit/FILE_3E9C726384588CD43F31AC32BB00ECBCEF6B3E49.getString:(Lorg/jruby/Ruby;II)Lorg/jruby/RubyString;
        //   306: invokevirtual   org/jruby/runtime/CallSite.call:(Lorg/jruby/runtime/ThreadContext;Lorg/jruby/runtime/builtin/IRubyObject;Lorg/jruby/runtime/builtin/IRubyObject;Lorg/jruby/runtime/builtin/IRubyObject;Lorg/jruby/runtime/builtin/IRubyObject;)Lorg/jruby/runtime/builtin/IRubyObject;
        //   309: pop            
        //   310: aload_0        
        //   311: invokevirtual   ruby/jit/FILE_3E9C726384588CD43F31AC32BB00ECBCEF6B3E49.getCallSite7:()Lorg/jruby/runtime/CallSite;
        //   314: aload_1        
        //   315: aload_2        
        //   316: aload_2        
        //   317: aload_0        
        //   318: aload_1        
        //   319: getfield        org/jruby/runtime/ThreadContext.runtime:Lorg/jruby/Ruby;
        //   322: ldc             "counts"
        //   324: invokevirtual   ruby/jit/FILE_3E9C726384588CD43F31AC32BB00ECBCEF6B3E49.getSymbol0:(Lorg/jruby/Ruby;Ljava/lang/String;)Lorg/jruby/RubySymbol;
        //   327: aload_1        
        //   328: aload_2        
        //   329: aload_0        
        //   330: aload_1        
        //   331: ldc             "block_0$RUBY$NetworkScan,-1,,false,0,./lib//lister/measurements/network_scan.rb,31,true"
        //   333: invokevirtual   ruby/jit/FILE_3E9C726384588CD43F31AC32BB00ECBCEF6B3E49.getBlockBody0:(Lorg/jruby/runtime/ThreadContext;Ljava/lang/String;)Lorg/jruby/runtime/BlockBody;
        //   336: invokestatic    org/jruby/javasupport/util/RuntimeHelpers.createBlock:(Lorg/jruby/runtime/ThreadContext;Lorg/jruby/runtime/builtin/IRubyObject;Lorg/jruby/runtime/BlockBody;)Lorg/jruby/runtime/Block;
        //   339: invokevirtual   org/jruby/runtime/CallSite.callIter:(Lorg/jruby/runtime/ThreadContext;Lorg/jruby/runtime/builtin/IRubyObject;Lorg/jruby/runtime/builtin/IRubyObject;Lorg/jruby/runtime/builtin/IRubyObject;Lorg/jruby/runtime/Block;)Lorg/jruby/runtime/builtin/IRubyObject;
        //   342: pop            
        //   343: aload_0        
        //   344: bipush          10
        //   346: invokevirtual   ruby/jit/FILE_3E9C726384588CD43F31AC32BB00ECBCEF6B3E49.getCallSite:(I)Lorg/jruby/runtime/CallSite;
        //   349: aload_1        
        //   350: aload_2        
        //   351: aload_2        
        //   352: aload_0        
        //   353: aload_1        
        //   354: getfield        org/jruby/runtime/ThreadContext.runtime:Lorg/jruby/Ruby;
        //   357: ldc             "mac_vendors"
        //   359: invokevirtual   ruby/jit/FILE_3E9C726384588CD43F31AC32BB00ECBCEF6B3E49.getSymbol1:(Lorg/jruby/Ruby;Ljava/lang/String;)Lorg/jruby/RubySymbol;
        //   362: aload_1        
        //   363: aload_2        
        //   364: aload_0        
        //   365: aload_1        
        //   366: ldc             "block_1$RUBY$NetworkScan,-1,,false,0,./lib//lister/measurements/network_scan.rb,37,true"
        //   368: invokevirtual   ruby/jit/FILE_3E9C726384588CD43F31AC32BB00ECBCEF6B3E49.getBlockBody1:(Lorg/jruby/runtime/ThreadContext;Ljava/lang/String;)Lorg/jruby/runtime/BlockBody;
        //   371: invokestatic    org/jruby/javasupport/util/RuntimeHelpers.createBlock:(Lorg/jruby/runtime/ThreadContext;Lorg/jruby/runtime/builtin/IRubyObject;Lorg/jruby/runtime/BlockBody;)Lorg/jruby/runtime/Block;
        //   374: invokevirtual   org/jruby/runtime/CallSite.callIter:(Lorg/jruby/runtime/ThreadContext;Lorg/jruby/runtime/builtin/IRubyObject;Lorg/jruby/runtime/builtin/IRubyObject;Lorg/jruby/runtime/builtin/IRubyObject;Lorg/jruby/runtime/Block;)Lorg/jruby/runtime/builtin/IRubyObject;
        //   377: pop            
        //   378: aload_0        
        //   379: bipush          13
        //   381: invokevirtual   ruby/jit/FILE_3E9C726384588CD43F31AC32BB00ECBCEF6B3E49.getCallSite:(I)Lorg/jruby/runtime/CallSite;
        //   384: aload_1        
        //   385: aload_2        
        //   386: aload_2        
        //   387: aload_0        
        //   388: aload_1        
        //   389: getfield        org/jruby/runtime/ThreadContext.runtime:Lorg/jruby/Ruby;
        //   392: ldc             "hashed_macs"
        //   394: invokevirtual   ruby/jit/FILE_3E9C726384588CD43F31AC32BB00ECBCEF6B3E49.getSymbol2:(Lorg/jruby/Ruby;Ljava/lang/String;)Lorg/jruby/RubySymbol;
        //   397: aload_1        
        //   398: aload_2        
        //   399: aload_0        
        //   400: aload_1        
        //   401: ldc             "block_2$RUBY$NetworkScan,-1,,false,0,./lib//lister/measurements/network_scan.rb,43,true"
        //   403: invokevirtual   ruby/jit/FILE_3E9C726384588CD43F31AC32BB00ECBCEF6B3E49.getBlockBody2:(Lorg/jruby/runtime/ThreadContext;Ljava/lang/String;)Lorg/jruby/runtime/BlockBody;
        //   406: invokestatic    org/jruby/javasupport/util/RuntimeHelpers.createBlock:(Lorg/jruby/runtime/ThreadContext;Lorg/jruby/runtime/builtin/IRubyObject;Lorg/jruby/runtime/BlockBody;)Lorg/jruby/runtime/Block;
        //   409: invokevirtual   org/jruby/runtime/CallSite.callIter:(Lorg/jruby/runtime/ThreadContext;Lorg/jruby/runtime/builtin/IRubyObject;Lorg/jruby/runtime/builtin/IRubyObject;Lorg/jruby/runtime/builtin/IRubyObject;Lorg/jruby/runtime/Block;)Lorg/jruby/runtime/builtin/IRubyObject;
        //   412: pop            
        //   413: aload_0        
        //   414: bipush          16
        //   416: invokevirtual   ruby/jit/FILE_3E9C726384588CD43F31AC32BB00ECBCEF6B3E49.getCallSite:(I)Lorg/jruby/runtime/CallSite;
        //   419: aload_1        
        //   420: aload_2        
        //   421: aload_2        
        //   422: aload_0        
        //   423: aload_1        
        //   424: getfield        org/jruby/runtime/ThreadContext.runtime:Lorg/jruby/Ruby;
        //   427: ldc             "lan_nic_info"
        //   429: invokevirtual   ruby/jit/FILE_3E9C726384588CD43F31AC32BB00ECBCEF6B3E49.getSymbol3:(Lorg/jruby/Ruby;Ljava/lang/String;)Lorg/jruby/RubySymbol;
        //   432: aload_1        
        //   433: aload_2        
        //   434: aload_0        
        //   435: aload_1        
        //   436: ldc             "block_3$RUBY$NetworkScan,-1,,false,0,./lib//lister/measurements/network_scan.rb,54,true"
        //   438: invokevirtual   ruby/jit/FILE_3E9C726384588CD43F31AC32BB00ECBCEF6B3E49.getBlockBody3:(Lorg/jruby/runtime/ThreadContext;Ljava/lang/String;)Lorg/jruby/runtime/BlockBody;
        //   441: invokestatic    org/jruby/javasupport/util/RuntimeHelpers.createBlock:(Lorg/jruby/runtime/ThreadContext;Lorg/jruby/runtime/builtin/IRubyObject;Lorg/jruby/runtime/BlockBody;)Lorg/jruby/runtime/Block;
        //   444: invokevirtual   org/jruby/runtime/CallSite.callIter:(Lorg/jruby/runtime/ThreadContext;Lorg/jruby/runtime/builtin/IRubyObject;Lorg/jruby/runtime/builtin/IRubyObject;Lorg/jruby/runtime/builtin/IRubyObject;Lorg/jruby/runtime/Block;)Lorg/jruby/runtime/builtin/IRubyObject;
        //   447: pop            
        //   448: aload_0        
        //   449: bipush          19
        //   451: invokevirtual   ruby/jit/FILE_3E9C726384588CD43F31AC32BB00ECBCEF6B3E49.getCallSite:(I)Lorg/jruby/runtime/CallSite;
        //   454: aload_1        
        //   455: aload_2        
        //   456: aload_2        
        //   457: aload_0        
        //   458: aload_1        
        //   459: getfield        org/jruby/runtime/ThreadContext.runtime:Lorg/jruby/Ruby;
        //   462: ldc             "computer_nic_info"
        //   464: invokevirtual   ruby/jit/FILE_3E9C726384588CD43F31AC32BB00ECBCEF6B3E49.getSymbol4:(Lorg/jruby/Ruby;Ljava/lang/String;)Lorg/jruby/RubySymbol;
        //   467: aload_1        
        //   468: aload_2        
        //   469: aload_0        
        //   470: aload_1        
        //   471: ldc             "block_4$RUBY$NetworkScan,-1,,false,0,./lib//lister/measurements/network_scan.rb,60,true"
        //   473: invokevirtual   ruby/jit/FILE_3E9C726384588CD43F31AC32BB00ECBCEF6B3E49.getBlockBody4:(Lorg/jruby/runtime/ThreadContext;Ljava/lang/String;)Lorg/jruby/runtime/BlockBody;
        //   476: invokestatic    org/jruby/javasupport/util/RuntimeHelpers.createBlock:(Lorg/jruby/runtime/ThreadContext;Lorg/jruby/runtime/builtin/IRubyObject;Lorg/jruby/runtime/BlockBody;)Lorg/jruby/runtime/Block;
        //   479: invokevirtual   org/jruby/runtime/CallSite.callIter:(Lorg/jruby/runtime/ThreadContext;Lorg/jruby/runtime/builtin/IRubyObject;Lorg/jruby/runtime/builtin/IRubyObject;Lorg/jruby/runtime/builtin/IRubyObject;Lorg/jruby/runtime/Block;)Lorg/jruby/runtime/builtin/IRubyObject;
        //   482: aload_1        
        //   483: invokevirtual   org/jruby/runtime/ThreadContext.postCompiledClass:()V
        //   486: goto            494
        //   489: aload_1        
        //   490: invokevirtual   org/jruby/runtime/ThreadContext.postCompiledClass:()V
        //   493: athrow         
        //   494: areturn        
        //    LocalVariableTable:
        //  Start  Length  Slot  Name    Signature
        //  -----  ------  ----  ------  --------------------------------
        //  55     440     4     locals  Lorg/jruby/runtime/DynamicScope;
        //    Exceptions:
        //  Try           Handler
        //  Start  End    Start  End    Type
        //  -----  -----  -----  -----  ----
        //  55     482    489    494    Any
        // 
        // The error that occurred was:
        // 
        // java.lang.ArrayIndexOutOfBoundsException
        // 
        throw new IllegalStateException("An error occurred while decompiling this method.");
    }
    
    public static IRubyObject block_0$RUBY$NetworkScan(final FILE_3E9C726384588CD43F31AC32BB00ECBCEF6B3E49 file_3E9C726384588CD43F31AC32BB00ECBCEF6B3E49, final ThreadContext threadContext, final IRubyObject rubyObject, final IRubyObject rubyObject2, final Block block) {
        threadContext.getCurrentScope();
        RuntimeHelpers.processBlockArgument(threadContext.runtime, block);
        file_3E9C726384588CD43F31AC32BB00ECBCEF6B3E49.getCallSite8().call(threadContext, rubyObject, rubyObject, file_3E9C726384588CD43F31AC32BB00ECBCEF6B3E49.getString(threadContext.runtime, 16, 32));
        return file_3E9C726384588CD43F31AC32BB00ECBCEF6B3E49.getCallSite9().call(threadContext, rubyObject, rubyObject, file_3E9C726384588CD43F31AC32BB00ECBCEF6B3E49.getString(threadContext.runtime, 17, 64), file_3E9C726384588CD43F31AC32BB00ECBCEF6B3E49.getString(threadContext.runtime, 11, 64));
    }
    
    public static IRubyObject block_1$RUBY$NetworkScan(final FILE_3E9C726384588CD43F31AC32BB00ECBCEF6B3E49 file_3E9C726384588CD43F31AC32BB00ECBCEF6B3E49, final ThreadContext threadContext, final IRubyObject rubyObject, final IRubyObject rubyObject2, final Block block) {
        threadContext.getCurrentScope();
        RuntimeHelpers.processBlockArgument(threadContext.runtime, block);
        file_3E9C726384588CD43F31AC32BB00ECBCEF6B3E49.getCallSite(11).call(threadContext, rubyObject, rubyObject, file_3E9C726384588CD43F31AC32BB00ECBCEF6B3E49.getString(threadContext.runtime, 18, 32));
        return file_3E9C726384588CD43F31AC32BB00ECBCEF6B3E49.getCallSite(12).call(threadContext, rubyObject, rubyObject, file_3E9C726384588CD43F31AC32BB00ECBCEF6B3E49.getString(threadContext.runtime, 19, 64), file_3E9C726384588CD43F31AC32BB00ECBCEF6B3E49.getString(threadContext.runtime, 11, 64));
    }
    
    public static IRubyObject block_2$RUBY$NetworkScan(final FILE_3E9C726384588CD43F31AC32BB00ECBCEF6B3E49 file_3E9C726384588CD43F31AC32BB00ECBCEF6B3E49, final ThreadContext threadContext, final IRubyObject rubyObject, final IRubyObject rubyObject2, final Block block) {
        threadContext.getCurrentScope();
        RuntimeHelpers.processBlockArgument(threadContext.runtime, block);
        file_3E9C726384588CD43F31AC32BB00ECBCEF6B3E49.getCallSite(14).call(threadContext, rubyObject, rubyObject, file_3E9C726384588CD43F31AC32BB00ECBCEF6B3E49.getString(threadContext.runtime, 20, 32));
        return file_3E9C726384588CD43F31AC32BB00ECBCEF6B3E49.getCallSite(15).call(threadContext, rubyObject, rubyObject, file_3E9C726384588CD43F31AC32BB00ECBCEF6B3E49.getString(threadContext.runtime, 21, 64), file_3E9C726384588CD43F31AC32BB00ECBCEF6B3E49.getString(threadContext.runtime, 11, 64));
    }
    
    public static IRubyObject block_3$RUBY$NetworkScan(final FILE_3E9C726384588CD43F31AC32BB00ECBCEF6B3E49 file_3E9C726384588CD43F31AC32BB00ECBCEF6B3E49, final ThreadContext threadContext, final IRubyObject rubyObject, final IRubyObject rubyObject2, final Block block) {
        threadContext.getCurrentScope();
        RuntimeHelpers.processBlockArgument(threadContext.runtime, block);
        file_3E9C726384588CD43F31AC32BB00ECBCEF6B3E49.getCallSite(17).call(threadContext, rubyObject, rubyObject, file_3E9C726384588CD43F31AC32BB00ECBCEF6B3E49.getString(threadContext.runtime, 22, 32));
        return file_3E9C726384588CD43F31AC32BB00ECBCEF6B3E49.getCallSite(18).call(threadContext, rubyObject, rubyObject, file_3E9C726384588CD43F31AC32BB00ECBCEF6B3E49.getString(threadContext.runtime, 23, 64), file_3E9C726384588CD43F31AC32BB00ECBCEF6B3E49.getString(threadContext.runtime, 11, 64));
    }
    
    public static IRubyObject block_4$RUBY$NetworkScan(final FILE_3E9C726384588CD43F31AC32BB00ECBCEF6B3E49 file_3E9C726384588CD43F31AC32BB00ECBCEF6B3E49, final ThreadContext threadContext, final IRubyObject rubyObject, final IRubyObject rubyObject2, final Block block) {
        threadContext.getCurrentScope();
        RuntimeHelpers.processBlockArgument(threadContext.runtime, block);
        file_3E9C726384588CD43F31AC32BB00ECBCEF6B3E49.getCallSite(20).call(threadContext, rubyObject, rubyObject, file_3E9C726384588CD43F31AC32BB00ECBCEF6B3E49.getString(threadContext.runtime, 24, 32));
        return file_3E9C726384588CD43F31AC32BB00ECBCEF6B3E49.getCallSite(21).call(threadContext, rubyObject, rubyObject, file_3E9C726384588CD43F31AC32BB00ECBCEF6B3E49.getString(threadContext.runtime, 25, 32), file_3E9C726384588CD43F31AC32BB00ECBCEF6B3E49.getString(threadContext.runtime, 11, 64));
    }
    
    public static IRubyObject class_2$RUBY$NetworkScan(final FILE_3E9C726384588CD43F31AC32BB00ECBCEF6B3E49 file_3E9C726384588CD43F31AC32BB00ECBCEF6B3E49, final ThreadContext threadContext, final IRubyObject rubyObject, final IRubyObject[] args, final Block block) {
        Arity.checkArgumentCount(threadContext.getRuntime(), args, 0, 0);
        return class_2$RUBY$NetworkScan(file_3E9C726384588CD43F31AC32BB00ECBCEF6B3E49, threadContext, rubyObject, block);
    }
    
    public static IRubyObject module__1$RUBY$Measurements(final FILE_3E9C726384588CD43F31AC32BB00ECBCEF6B3E49 file_3E9C726384588CD43F31AC32BB00ECBCEF6B3E49, final ThreadContext threadContext, final IRubyObject rubyObject, final IRubyObject[] args, final Block block) {
        Arity.checkArgumentCount(threadContext.getRuntime(), args, 0, 0);
        return module__1$RUBY$Measurements(file_3E9C726384588CD43F31AC32BB00ECBCEF6B3E49, threadContext, rubyObject, block);
    }
    
    public static IRubyObject module__0$RUBY$Lister(final FILE_3E9C726384588CD43F31AC32BB00ECBCEF6B3E49 file_3E9C726384588CD43F31AC32BB00ECBCEF6B3E49, final ThreadContext threadContext, final IRubyObject rubyObject, final IRubyObject[] args, final Block block) {
        Arity.checkArgumentCount(threadContext.getRuntime(), args, 0, 0);
        return module__0$RUBY$Lister(file_3E9C726384588CD43F31AC32BB00ECBCEF6B3E49, threadContext, rubyObject, block);
    }
    
    @Override
    public IRubyObject load(final ThreadContext context, final IRubyObject rubyObject, final IRubyObject[] array, final Block block) {
        try {
            RuntimeHelpers.preLoad(context, ",0,0,-2");
            final IRubyObject _file__ = __file__(this, context, rubyObject, array, block);
            RuntimeHelpers.postLoad(context);
            return _file__;
        }
        finally {
            RuntimeHelpers.postLoad(context);
        }
    }
    
    public static void main(final String[] argv) {
        final FILE_3E9C726384588CD43F31AC32BB00ECBCEF6B3E49 file_3E9C726384588CD43F31AC32BB00ECBCEF6B3E49 = new FILE_3E9C726384588CD43F31AC32BB00ECBCEF6B3E49();
        final String string = FILE_3E9C726384588CD43F31AC32BB00ECBCEF6B3E49.class.getClassLoader().getResource("ruby/jit/FILE_3E9C726384588CD43F31AC32BB00ECBCEF6B3E49.class").toString();
        file_3E9C726384588CD43F31AC32BB00ECBCEF6B3E49.setFilename(string);
        final RubyInstanceConfig config = new RubyInstanceConfig();
        config.setArgv(argv);
        config.setScriptFileName(string);
        final Ruby instance = Ruby.newInstance(config);
        file_3E9C726384588CD43F31AC32BB00ECBCEF6B3E49.load(instance.getCurrentContext(), instance.getTopSelf(), IRubyObject.NULL_ARRAY, Block.NULL_BLOCK);
    }
}
